Workbook

Sheet Summary
A2: NIKE: three-statement review
A3: FY2026 vs FY2025 actuals. Financial review, not a forecast.
A4: Metric | B4: FY2025 | C4: FY2026 | D4: Change
A5: Revenue | B5: =NKE_1_Analysis!B10 -> 46309 | C5: =NKE_1_Analysis!C10 -> 46398 | D5: =(C5-B5) -> 89
A6: Operating margin | B6: =NKE_2_Analysis!B11 -> 0.079941264 | C6: =NKE_2_Analysis!C11 -> 0.081835424 | D6: =(C6-B6)*100 -> 0.18941598
A7: Consolidated net income | B7: =NKE_3_Analysis!B12 -> 3219 | C7: =NKE_3_Analysis!C12 -> 3108 | D7: =(C7-B7) -> -111
A8: Operating cash flow | B8: =NKE_7_Analysis!B16 -> 3698 | C8: =NKE_7_Analysis!C16 -> 2868 | D8: =(C8-B8) -> -830
A9: Free cash flow | B9: =NKE_8_Analysis!B7 -> 3268 | C9: =NKE_8_Analysis!C7 -> 2184 | D9: =(C9-B9) -> -1084
A10: FCF after shareholder returns | B10: =NKE_8_Analysis!B13 -> -2017 | C10: =NKE_8_Analysis!C13 -> -369 | D10: =(C10-B10) -> 1648
A11: Net debt / (net cash) | B11: =NKE_6_Analysis!B13 -> -1190 | C11: =NKE_6_Analysis!C13 -> -1085 | D11: =(C11-B11) -> 105
A14: Revenue stabilised; cash conversion remained weak.
A16: Priorities: Direct sales, tariff-adjusted receivables and cash cover.
A18: Separate the tariff recovery from recurring trading performance.

Sheet NKE_1_Analysis
A2: 1. Revenue sources
A3: USD millions unless stated. Fiscal year ends 31 May.
A4: Metric | B4: FY2025 | C4: FY2026 | D4: Change
A5: NIKE Brand wholesale | B5: ='Reported inputs'!B51 -> 25883 | C5: ='Reported inputs'!C51 -> 27453 | D5: =C5-B5 -> 1570
A6: NIKE Direct | B6: ='Reported inputs'!B52 -> 18783 | C6: ='Reported inputs'!C52 -> 17720 | D6: =C6-B6 -> -1063
A7: Global Brand Divisions | B7: ='Reported inputs'!B53 -> 48 | C7: ='Reported inputs'!C53 -> 49 | D7: =C7-B7 -> 1
A8: Converse | B8: ='Reported inputs'!B54 -> 1692 | C8: ='Reported inputs'!C54 -> 1174 | D8: =C8-B8 -> -518
A9: Corporate | B9: ='Reported inputs'!B55 -> -97 | C9: ='Reported inputs'!C55 -> 2 | D9: =C9-B9 -> 99
A10: Total revenue | B10: =SUM(B5:B9) -> 46309 | C10: =SUM(C5:C9) -> 46398 | D10: =C10-B10 -> 89
A11: Revenue reconciliation | B11: =B10-'Reported inputs'!B5 -> 0 | C11: =C10-'Reported inputs'!C5 -> 0 | D11: =C11-B11 -> 0
A12: Revenue growth | C12: =C10/B10-1 -> 0.0019218726
A13: Currency-neutral growth | C13: ='Reported inputs'!C60 -> -0.02
A15: NIKE Brand channels reconcile with Converse and Corporate to group revenue. Currency-neutral growth is company-reported.

Sheet NKE_2_Analysis
A2: 2. Operating profitability
A3: USD millions unless stated. Fiscal year ends 31 May.
A4: Metric | B4: FY2025 | C4: FY2026 | D4: Change
A5: Revenue | B5: ='Reported inputs'!B5 -> 46309 | C5: ='Reported inputs'!C5 -> 46398 | D5: =C5-B5 -> 89
A6: Cost of sales | B6: ='Reported inputs'!B6 -> 26519 | C6: ='Reported inputs'!C6 -> 26487 | D6: =C6-B6 -> -32
A7: Gross profit | B7: =B5-B6 -> 19790 | C7: =C5-C6 -> 19911 | D7: =C7-B7 -> 121
A8: Gross margin | B8: =B7/B5 -> 0.42734674 | C8: =C7/C5 -> 0.42913488 | D8: =(C8-B8)*100 -> 0.17881404
A9: Selling and administrative expense | B9: ='Reported inputs'!B7 -> 16088 | C9: ='Reported inputs'!C7 -> 16114 | D9: =C9-B9 -> 26
A10: Operating profit before other income | B10: =B7-B9 -> 3702 | C10: =C7-C9 -> 3797 | D10: =C10-B10 -> 95
A11: Operating margin | B11: =B10/B5 -> 0.079941264 | C11: =C10/C5 -> 0.081835424 | D11: =(C11-B11)*100 -> 0.18941598
A12: SG&A / revenue | B12: =B9/B5 -> 0.34740547 | C12: =C9/C5 -> 0.34729945 | D12: =(C12-B12)*100 -> -0.010601938
A13: Demand creation expense | B13: ='Reported inputs'!B18 -> 4689 | C13: ='Reported inputs'!C18 -> 4754 | D13: =C13-B13 -> 65
A14: Other SG&A (derived) | B14: =B9-B13 -> 11399 | C14: =C9-C13 -> 11360 | D14: =C14-B14 -> -39
A15: Profit change: sales contribution | C15: ='Reported inputs'!C5-'Reported inputs'!B5 -> 89
A16: Profit change: cost-of-sales effect | C16: =-('Reported inputs'!C6-'Reported inputs'!B6) -> 32
A17: Profit change: SG&A effect | C17: =-('Reported inputs'!C7-'Reported inputs'!B7) -> -26
A18: Operating profit change | C18: =SUM(C15:C17) -> 95
A20: Operating profit = revenue - COGS - SG&A. NIKE-defined EBIT also includes other income. Tariff recovery is in reported COGS.

Sheet NKE_3_Analysis
A2: 3. Earnings quality
A3: USD millions unless stated. Fiscal year ends 31 May.
A4: Metric | B4: FY2025 | C4: FY2026 | D4: Change
A5: Operating profit before other income | B5: ='Reported inputs'!B8 -> 3702 | C5: ='Reported inputs'!C8 -> 3797 | D5: =C5-B5 -> 95
A6: Other non-operating income | B6: ='Reported inputs'!B16 -> 76 | C6: ='Reported inputs'!C16 -> 53 | D6: =C6-B6 -> -23
A7: Interest income | B7: ='Reported inputs'!B15 -> 0 | C7: ='Reported inputs'!C15 -> 0 | D7: =C7-B7 -> 0
A8: Interest expense / (interest income) | B8: ='Reported inputs'!B14 -> -107 | C8: ='Reported inputs'!C14 -> -50 | D8: =C8-B8 -> 57
A9: Profit before tax | B9: =B5+B6+B7-B8 -> 3885 | C9: =C5+C6+C7-C8 -> 3900 | D9: =C9-B9 -> 15
A10: Income tax expense | B10: ='Reported inputs'!B10 -> 666 | C10: ='Reported inputs'!C10 -> 792 | D10: =C10-B10 -> 126
A11: Effective tax rate | B11: =B10/B9 -> 0.17142857 | C11: =C10/C9 -> 0.20307692 | D11: =(C11-B11)*100 -> 3.1648352
A12: Consolidated net income | B12: =B9-B10 -> 3219 | C12: =C9-C10 -> 3108 | D12: =C12-B12 -> -111
A13: Noncontrolling interests | B13: ='Reported inputs'!B17 -> 0 | C13: ='Reported inputs'!C17 -> 0 | D13: =C13-B13 -> 0
A14: Parent net income | B14: =B12-B13 -> 3219 | C14: =C12-C13 -> 3108 | D14: =C14-B14 -> -111
A15: Diluted EPS | B15: ='Reported inputs'!B13 -> 2.16 | C15: ='Reported inputs'!C13 -> 2.1 | D15: =C15-B15 -> -0.06
A16: Net-income reconciliation | B16: =B12-'Reported inputs'!B11 -> 0 | C16: =C12-'Reported inputs'!C11 -> 0 | D16: =C16-B16 -> 0
A17: NIKE-defined EBIT | B17: =B5+B6 -> 3778 | C17: =C5+C6 -> 3850 | D17: =C17-B17 -> 72
A18: Tariff recovery benefit | B18: ='Reported inputs'!B57 -> 0 | C18: ='Reported inputs'!C57 -> 986 | D18: =C18-B18 -> 986
A19: Operating profit excluding recovery only | C19: =C5-C18 -> 2811
A21: Excluding only the $986m recovery is a sensitivity, not normalised profit: the related tariff costs remain in reported COGS.

Sheet NKE_4_Analysis
A2: 4. Short-term liquidity
A3: USD millions unless stated. Fiscal year ends 31 May.
A4: Metric | B4: FY2025 | C4: FY2026 | D4: Change
A5: Current assets | B5: ='Reported inputs'!B24 -> 23362 | C5: ='Reported inputs'!C24 -> 24603 | D5: =C5-B5 -> 1241
A6: Current liabilities | B6: ='Reported inputs'!B25 -> 10566 | C6: ='Reported inputs'!C25 -> 12547 | D6: =C6-B6 -> 1981
A7: Net current assets / (liabilities) | B7: =B5-B6 -> 12796 | C7: =C5-C6 -> 12056 | D7: =C7-B7 -> -740
A8: Current ratio | B8: =B5/B6 -> 2.2110543 | C8: =C5/C6 -> 1.9608671 | D8: =C8-B8 -> -0.25018719
A9: Cash and equivalents | B9: ='Reported inputs'!B19 -> 7464 | C9: ='Reported inputs'!C19 -> 7563 | D9: =C9-B9 -> 99
A10: Short-term investments | B10: ='Reported inputs'!B20 -> 1687 | C10: ='Reported inputs'!C20 -> 1464 | D10: =C10-B10 -> -223
A11: Cash and investments | B11: =B9+B10 -> 9151 | C11: =C9+C10 -> 9027 | D11: =C11-B11 -> -124
A12: Debt due within one year | B12: ='Reported inputs'!B29 -> 0 | C12: ='Reported inputs'!C29 -> 2000 | D12: =C12-B12 -> 2000
A13: Cash plus investments / current debt | C13: =C11/C12 -> 4.5135
A15: FY2025 current debt was zero, so its cash/debt ratio is not applicable. FY2026 includes $2bn of debt now due within one year.

Sheet NKE_5_Analysis
A2: 5. Working capital
A3: USD millions unless stated. Fiscal year ends 31 May.
A4: Metric | B4: FY2025 | C4: FY2026 | D4: Change
A5: Closing accounts receivable | B5: ='Reported inputs'!B21 -> 4717 | C5: ='Reported inputs'!C21 -> 5931 | D5: =C5-B5 -> 1214
A6: Closing inventory | B6: ='Reported inputs'!B22 -> 7489 | C6: ='Reported inputs'!C22 -> 7501 | D6: =C6-B6 -> 12
A7: Closing accounts payable | B7: ='Reported inputs'!B23 -> 3479 | C7: ='Reported inputs'!C23 -> 3600 | D7: =C7-B7 -> 121
A8: Operating working capital | B8: =B5+B6-B7 -> 8727 | C8: =C5+C6-C7 -> 9832 | D8: =C8-B8 -> 1105
A9: Average receivables | B9: =('Reported inputs'!B61+B5)/2 -> 4572 | C9: =('Reported inputs'!C61+C5)/2 -> 5324 | D9: =C9-B9 -> 752
A10: Average inventory | B10: =('Reported inputs'!B62+B6)/2 -> 7504 | C10: =('Reported inputs'!C62+C6)/2 -> 7495 | D10: =C10-B10 -> -9
A11: Average payables | B11: =('Reported inputs'!B63+B7)/2 -> 3165 | C11: =('Reported inputs'!C63+C7)/2 -> 3539.5 | D11: =C11-B11 -> 374.5
A12: Receivable days (proxy) | B12: =B9/'Reported inputs'!B5*'Reported inputs'!B64 -> 36.03576 | C12: =C9/'Reported inputs'!C5*'Reported inputs'!C64 -> 41.882409 | D12: =C12-B12 -> 5.8466489
A13: Inventory days | B13: =B10/'Reported inputs'!B6*'Reported inputs'!B64 -> 103.28293 | C13: =C10/'Reported inputs'!C6*'Reported inputs'!C64 -> 103.28369 | D13: =C13-B13 -> 0.00075711613
A14: Payable days (COGS proxy) | B14: =B11/'Reported inputs'!B6*'Reported inputs'!B64 -> 43.562163 | C14: =C11/'Reported inputs'!C6*'Reported inputs'!C64 -> 48.775531 | D14: =C14-B14 -> 5.2133684
A15: Cash conversion cycle (proxy) | B15: =B12+B13-B14 -> 95.756526 | C15: =C12+C13-C14 -> 96.390564 | D15: =C15-B15 -> 0.63403764
A16: Tariff receivable included in closing AR | B16: ='Reported inputs'!B58 -> 0 | C16: ='Reported inputs'!C58 -> 684 | D16: =C16-B16 -> 684
A17: Closing AR excluding tariff receivable | B17: =B5-B16 -> 4717 | C17: =C5-C16 -> 5247 | D17: =C17-B17 -> 530
A18: AR days excluding closing tariff effect | B18: =(('Reported inputs'!B61+B17)/2)/'Reported inputs'!B5*365 -> 36.03576 | C18: =(('Reported inputs'!C61+C17)/2)/'Reported inputs'!C5*365 -> 39.191991 | D18: =C18-B18 -> 3.1562312
A20: Days use average opening and closing balances; DSO uses total sales and DPO uses COGS. These are proxies, not ageing or contractual terms.

Sheet NKE_6_Analysis
A2: 6. Funding and asset quality
A3: USD millions unless stated. Fiscal year ends 31 May.
A4: Metric | B4: FY2025 | C4: FY2026 | D4: Change
A5: Total assets | B5: ='Reported inputs'!B26 -> 36579 | C5: ='Reported inputs'!C26 -> 38410 | D5: =C5-B5 -> 1831
A6: Total liabilities | B6: ='Reported inputs'!B27 -> 23366 | C6: ='Reported inputs'!C27 -> 23545 | D6: =C6-B6 -> 179
A7: Total equity including NCI | B7: ='Reported inputs'!B28 -> 13213 | C7: ='Reported inputs'!C28 -> 14865 | D7: =C7-B7 -> 1652
A8: Assets less liabilities and equity | B8: =B5-B6-B7 -> 0 | C8: =C5-C6-C7 -> 0 | D8: =C8-B8 -> 0
A9: Current debt | B9: ='Reported inputs'!B29 -> 0 | C9: ='Reported inputs'!C29 -> 2000 | D9: =C9-B9 -> 2000
A10: Long-term debt | B10: ='Reported inputs'!B30 -> 7961 | C10: ='Reported inputs'!C30 -> 5942 | D10: =C10-B10 -> -2019
A11: Total interest-bearing debt | B11: =B9+B10 -> 7961 | C11: =C9+C10 -> 7942 | D11: =C11-B11 -> -19
A12: Cash and short-term investments | B12: ='Reported inputs'!B19+'Reported inputs'!B20 -> 9151 | C12: ='Reported inputs'!C19+'Reported inputs'!C20 -> 9027 | D12: =C12-B12 -> -124
A13: Net debt / (net cash) | B13: =B11-B12 -> -1190 | C13: =C11-C12 -> -1085 | D13: =C13-B13 -> 105
A14: Current debt / total debt | B14: =B9/B11 -> 0 | C14: =C9/C11 -> 0.25182574 | D14: =(C14-B14)*100 -> 25.182574
A15: Goodwill and intangible assets | B15: ='Reported inputs'!B31+'Reported inputs'!B32 -> 499 | C15: ='Reported inputs'!C31+'Reported inputs'!C32 -> 499 | D15: =C15-B15 -> 0
A16: Goodwill and intangibles / assets | B16: =B15/B5 -> 0.013641707 | C16: =C15/C5 -> 0.012991408 | D16: =(C16-B16)*100 -> -0.06502985
A18: Net debt includes separately reported short-term investments and excludes leases. Net cash does not eliminate lease or marketing commitments.

Sheet NKE_7_Analysis
A2: 7. Profit to operating cash
A3: USD millions unless stated. Fiscal year ends 31 May.
A4: Metric | B4: FY2025 | C4: FY2026 | D4: Change
A5: Consolidated net income | B5: ='Reported inputs'!B11 -> 3219 | C5: ='Reported inputs'!C11 -> 3108 | D5: =C5-B5 -> -111
A6: Depreciation and amortisation | B6: ='Reported inputs'!B34 -> 775 | C6: ='Reported inputs'!C34 -> 747 | D6: =C6-B6 -> -28
A7: Share-based compensation | B7: ='Reported inputs'!B35 -> 709 | C7: ='Reported inputs'!C35 -> 715 | D7: =C7-B7 -> 6
A8: Deferred tax adjustment | B8: ='Reported inputs'!B36 -> -288 | C8: ='Reported inputs'!C36 -> -96 | D8: =C8-B8 -> 192
A9: Impairment and other | B9: ='Reported inputs'!B37 -> 33 | C9: ='Reported inputs'!C37 -> 50 | D9: =C9-B9 -> 17
A10: Noncash FX adjustment | B10: ='Reported inputs'!B38 -> 37 | C10: ='Reported inputs'!C38 -> 22 | D10: =C10-B10 -> -15
A11: Receivables cash effect | B11: ='Reported inputs'!B39 -> -257 | C11: ='Reported inputs'!C39 -> -1207 | D11: =C11-B11 -> -950
A12: Inventory cash effect | B12: ='Reported inputs'!B40 -> 120 | C12: ='Reported inputs'!C40 -> -31 | D12: =C12-B12 -> -151
A13: Other assets cash effect | B13: ='Reported inputs'!B41 -> -224 | C13: ='Reported inputs'!C41 -> 519 | D13: =C13-B13 -> 743
A14: Payables and other liabilities cash effect | B14: ='Reported inputs'!B42 -> -426 | C14: ='Reported inputs'!C42 -> -959 | D14: =C14-B14 -> -533
A15: Sum of disclosed components | B15: =SUM(B5:B14) -> 3698 | C15: =SUM(C5:C14) -> 2868 | D15: =C15-B15 -> -830
A16: Reported operating cash flow | B16: ='Reported inputs'!B33 -> 3698 | C16: ='Reported inputs'!C33 -> 2868 | D16: =C16-B16 -> -830
A17: Reported less component sum | B17: =B16-B15 -> 0 | C17: =C16-C15 -> 0 | D17: =C17-B17 -> 0
A18: CFO / consolidated net income | B18: =B16/B5 -> 1.148804 | C18: =C16/C5 -> 0.92277992 | D18: =(C18-B18)*100 -> -22.602405
A20: Cash-flow working-capital changes include non-trade balances. They need not equal balance-sheet changes because of FX and other effects.

Sheet NKE_8_Analysis
A2: 8. Cash available after investment
A3: USD millions unless stated. Fiscal year ends 31 May.
A4: Metric | B4: FY2025 | C4: FY2026 | D4: Change
A5: Operating cash flow | B5: ='Reported inputs'!B33 -> 3698 | C5: ='Reported inputs'!C33 -> 2868 | D5: =C5-B5 -> -830
A6: Capital expenditure paid | B6: ='Reported inputs'!B43 -> 430 | C6: ='Reported inputs'!C43 -> 684 | D6: =C6-B6 -> 254
A7: Free cash flow (CFO less capex) | B7: =B5-B6 -> 3268 | C7: =C5-C6 -> 2184 | D7: =C7-B7 -> -1084
A8: Free cash flow / revenue | B8: =B7/'Reported inputs'!B5 -> 0.070569436 | C8: =C7/'Reported inputs'!C5 -> 0.047070994 | D8: =(C8-B8)*100 -> -2.3498441
A9: Cash dividends paid | B9: ='Reported inputs'!B44 -> 2300 | C9: ='Reported inputs'!C44 -> 2407 | D9: =C9-B9 -> 107
A10: Cash used for share repurchases | B10: ='Reported inputs'!B45 -> 2985 | C10: ='Reported inputs'!C45 -> 146 | D10: =C10-B10 -> -2839
A11: Total shareholder cash returns | B11: =B9+B10 -> 5285 | C11: =C9+C10 -> 2553 | D11: =C11-B11 -> -2732
A12: FCF after dividends | B12: =B7-B9 -> 968 | C12: =C7-C9 -> -223 | D12: =C12-B12 -> -1191
A13: FCF after dividends and buybacks | B13: =B7-B11 -> -2017 | C13: =C7-C11 -> -369 | D13: =C13-B13 -> 1648
A14: Shareholder returns / FCF | B14: =B11/B7 -> 1.6171971 | C14: =C11/C7 -> 1.168956 | D14: =(C14-B14)*100 -> -44.824102
A15: Capex / depreciation | B15: =B6/'Reported inputs'!B34 -> 0.55483871 | C15: =C6/'Reported inputs'!C34 -> 0.91566265 | D15: =C15-B15 -> 0.36082394
A17: Cash repurchases use the cash-flow statement, not the narrower repurchase-program total. Funding needs also include other investing and financing.

Sheet NKE_9_Analysis
A2: 9. Cash reconciliation
A3: USD millions unless stated. Fiscal year ends 31 May.
A4: Metric | B4: FY2025 | C4: FY2026 | D4: Change
A5: Opening cash | B5: ='Reported inputs'!B49 -> 9860 | C5: ='Reported inputs'!C49 -> 7464 | D5: =C5-B5 -> -2396
A6: Operating cash flow | B6: ='Reported inputs'!B33 -> 3698 | C6: ='Reported inputs'!C33 -> 2868 | D6: =C6-B6 -> -830
A7: Investing cash flow | B7: ='Reported inputs'!B46 -> -275 | C7: ='Reported inputs'!C46 -> -488 | D7: =C7-B7 -> -213
A8: Financing cash flow | B8: ='Reported inputs'!B47 -> -5820 | C8: ='Reported inputs'!C47 -> -2292 | D8: =C8-B8 -> 3528
A9: FX effect on cash | B9: ='Reported inputs'!B48 -> 1 | C9: ='Reported inputs'!C48 -> 11 | D9: =C9-B9 -> 10
A10: Calculated cash change | B10: =SUM(B6:B9) -> -2396 | C10: =SUM(C6:C9) -> 99 | D10: =C10-B10 -> 2495
A11: Calculated closing cash | B11: =B5+B10 -> 7464 | C11: =C5+C10 -> 7563 | D11: =C11-B11 -> 99
A12: Reported closing cash | B12: ='Reported inputs'!B19 -> 7464 | C12: ='Reported inputs'!C19 -> 7563 | D12: =C12-B12 -> 99
A13: Closing cash reconciliation | B13: =B11-B12 -> 0 | C13: =C11-C12 -> 0 | D13: =C13-B13 -> 0
A15: Cash increased despite lower CFO because financing outflows fell. This is a historical reconciliation, not a forecast.

Sheet Reported inputs
A2: Reported inputs
A3: USD millions unless stated. Fiscal year ends 31 May.
A4: Metric | B4: FY2025 | C4: FY2026 | D4: Source / definition
A5: Revenue | B5: 46309 | C5: 46398 | D5: FY2026 annual report, PDF p. 58
A6: Cost of sales | B6: 26519 | C6: 26487 | D6: FY2026 annual report, PDF p. 58
A7: Selling and administrative expense | B7: 16088 | C7: 16114 | D7: FY2026 annual report, PDF p. 58
A8: Operating profit: sales less COGS and SG&A | B8: 3702 | C8: 3797 | D8: Calculated: revenue - cost of sales - SG&A; not NIKE-defined EBIT (PDF pp. 34, 58)
A9: Profit before tax | B9: 3885 | C9: 3900 | D9: FY2026 annual report, PDF p. 58
A10: Income tax expense | B10: 666 | C10: 792 | D10: FY2026 annual report, PDF p. 58
A11: Consolidated net income | B11: 3219 | C11: 3108 | D11: FY2026 annual report, PDF p. 58
A12: Net income attributable to parent | B12: 3219 | C12: 3108 | D12: FY2026 annual report, PDF p. 58
A13: Diluted EPS ($ per share) | B13: 2.16 | C13: 2.1 | D13: FY2026 annual report, PDF p. 58
A14: Interest expense / (net interest income) | B14: -107 | C14: -50 | D14: FY2026 annual report, PDF p. 58
A15: Interest income | B15: 0 | C15: 0 | D15: FY2026 annual report, PDF p. 58
A16: Other non-operating income | B16: 76 | C16: 53 | D16: FY2026 annual report, PDF p. 58
... A64: Days | B64: 365 | C64: 365 | D64: Analyst convention: 365 days for annual turnover ratios
