Workbook

Sheet Review
B2: P&G | Test before changing the forecast
B3: 17 quarters. Five business segments. Two information cutoffs.
B4: Decision: remove the unsupported sales cut; do not replace it with a weak coefficient.
B6: Global P&G volume vs US nondurables | C6: Quarters | D6: Slope (pp/pp) | E6: R-squared | F6: Forecast use
B7: ='Model tests'!B15 -> Beauty | C7: ='Model tests'!F15 -> 17 | D7: ='Model tests'!G15 -> 0.65647479 | E7: ='Model tests'!I15 -> 0.25966555 | F7: ='Model tests'!L15 -> Not approved
B8: ='Model tests'!B16 -> Grooming | C8: ='Model tests'!F16 -> 17 | D8: ='Model tests'!G16 -> 0.96197033 | E8: ='Model tests'!I16 -> 0.33991915 | F8: ='Model tests'!L16 -> Not approved
B9: ='Model tests'!B17 -> Health Care | C9: ='Model tests'!F17 -> 17 | D9: ='Model tests'!G17 -> 0.35381963 | E9: ='Model tests'!I17 -> 0.046203344 | F9: ='Model tests'!L17 -> Not approved
B10: ='Model tests'!B18 -> Fabric & Home Care | C10: ='Model tests'!F18 -> 17 | D10: ='Model tests'!G18 -> 1.3609605 | E10: ='Model tests'!I18 -> 0.59687268 | F10: ='Model tests'!L18 -> Not approved
B11: ='Model tests'!B19 -> Baby, Feminine & Family Care | C11: ='Model tests'!F19 -> 17 | D11: ='Model tests'!G19 -> 0.7705192 | E11: ='Model tests'!I19 -> 0.23188987 | F11: ='Model tests'!L19 -> Not approved
B13: Baby, Feminine & Family Care is a combined segment—not Baby Care alone.
B14: Slope measures historical association. It is not a causal sales elasticity.
B15: Market tests use one historical vintage per cutoff; they are not real-time backtests.
B17: New information by 15 May | C17: Period added | D17: Change vs prior month | E17: Action
B18: US personal care prices (NSA) | C18: 2026-04-01 | D18: 0.61655837 | E18: Review; no automatic sales cut
B19: US real nondurable spending (SA) | C19: 2026-03-01 | D19: 0.34757545 | E19: Review; no automatic sales cut
B20: US health/personal store sales (SA) | C20: 2026-04-01 | D20: -0.017453748 | E20: Review; no automatic sales cut
B22: Company actuals stop at March 2026; April–June results are excluded.
B23: April CPI = prices. Retail sales = money spent. Neither equals P&G unit volume.
B24: R-squared describes past co-movement, not forecast accuracy.
B26: Quarter | C26: US nondurable growth | D26: P&G segment volume
B27: ='Matched quarters'!F220 -> 2022-03-31 | C27: ='Matched quarters'!G220 -> 3.5989105 | D27: ='Matched quarters'!H220 -> 2
B28: ='Matched quarters'!F221 -> 2022-06-30 | C28: ='Matched quarters'!G221 -> -0.03796621 | D28: ='Matched quarters'!H221 -> 0
B29: ='Matched quarters'!F222 -> 2022-09-30 | C29: ='Matched quarters'!G222 -> -0.97428175 | D29: ='Matched quarters'!H222 -> -3
B30: ='Matched quarters'!F223 -> 2022-12-31 | C30: ='Matched quarters'!G223 -> -1.7083333 | D30: ='Matched quarters'!H223 -> -6
B31: ='Matched quarters'!F224 -> 2023-03-31 | C31: ='Matched quarters'!G224 -> -0.51383557 | D31: ='Matched quarters'!H224 -> -4
B32: ='Matched quarters'!F225 -> 2023-06-30 | C32: ='Matched quarters'!G225 -> -0.38380426 | D32: ='Matched quarters'!H225 -> 0
B33: ='Matched quarters'!F226 -> 2023-09-30 | C33: ='Matched quarters'!G226 -> 1.1893013 | D33: ='Matched quarters'!H226 -> -3
B34: ='Matched quarters'!F227 -> 2023-12-31 | C34: ='Matched quarters'!G227 -> 2.2255193 | D34: ='Matched quarters'!H227 -> -2
B35: ='Matched quarters'!F228 -> 2024-03-31 | C35: ='Matched quarters'!G228 -> 1.372616 | D35: ='Matched quarters'!H228 -> -3
B36: ='Matched quarters'!F229 -> 2024-06-30 | C36: ='Matched quarters'!G229 -> 2.2805944 | D36: ='Matched quarters'!H229 -> -1
B37: ='Matched quarters'!F230 -> 2024-09-30 | C37: ='Matched quarters'!G230 -> 2.6501995 | D37: ='Matched quarters'!H230 -> -1
B38: ='Matched quarters'!F231 -> 2024-12-31 | C38: ='Matched quarters'!G231 -> 2.7872397 | D38: ='Matched quarters'!H231 -> 4
... B43: ='Matched quarters'!F236 -> 2026-03-31 | C43: ='Matched quarters'!G236 -> 1.5477658 | D43: ='Matched quarters'!H236 -> 3

Sheet Product match
B2: Product matching | Use the right level
B3: Research 11 categories. Financial history covers five global reportable segments.
B5: Product line | C5: P&G reporting segment | D5: Market evidence collected / gap | E5: What it can tell us
B6: Hair Care | C6: Beauty | D6: Hair/dental/shaving CPI | E6: US prices; combined basket
B7: Personal Care | C7: Beauty | D7: Personal care products CPI | E7: US prices; broad basket
B8: Skin Care | C8: Beauty | D8: Cosmetics/bath CPI | E8: US prices; broader products
B9: Grooming | C9: Grooming | D9: Hair/dental/shaving CPI | E9: US prices; combined basket
B10: Oral Care | C10: Health Care | D10: Hair/dental/shaving CPI | E10: US prices; combined basket
B11: Personal Health Care | C11: Health Care | D11: Health/personal store sales | E11: Channel sales; includes other products
B12: Fabric Care | C12: Fabric & Home Care | D12: Household cleaning CPI | E12: US prices; not units sold
B13: Home Care | C13: Fabric & Home Care | D13: Household cleaning CPI | E13: US prices; not units sold
B14: Baby Care | C14: Baby, Feminine & Family Care | D14: No matched diaper quantity series | E14: Do not substitute baby food
B15: Feminine Care | C15: Baby, Feminine & Family Care | D15: No matched quantity series | E15: Do not infer from baby care
B16: Family Care | C16: Baby, Feminine & Family Care | D16: Household paper CPI | E16: US prices; not units sold
B19: Peers are optional: use them to test market vs company-specific explanations.
B20: No peer coefficient is used here. A future peer model must use the same history window.
B21: Match product, geography, units, accounting scope and publication dates first.

Sheet Model tests
B2: Sensitivity tests | Association is not causation
B3: US proxies vs global segments. No coefficient is approved for a sales adjustment.
B5: Segment | C5: P&G measure | D5: Market series | E5: Known by | F5: Quarters | G5: Slope (pp/pp) | H5: Intercept | I5: R-squared | J5: Fit RMSE (pp) | K5: Baseline RMSE | L5: Forecast use
B6: Beauty | C6: organic_volume_growth | D6: PCENDC96 | E6: 2026-04-24 | F6: =COUNT('Matched quarters'!G6:G21) -> 16 | G6: =(SUM('Matched quarters'!K6:K21)-SUM('Matched quarters'!G6:G21)*SUM('Matched quarters'!H6:H21)/F6)/(SUM('Matched quarters'!I6:I21)-SUM('Matched quarters'!G6:G21)^2/F6) -> 0.65552037 | H6: =SUM('Matched quarters'!H6:H21)/F6-G6*SUM('Matched quarters'!G6:G21)/F6 -> -0.94592874 | I6: =(SUM('Matched quarters'!K6:K21)-SUM('Matched quarters'!G6:G21)*SUM('Matched quarters'!H6:H21)/F6)^2/((SUM('Matched quarters'!I6:I21)-SUM('Matched quarters'!G6:G21)^2/F6)*(SUM('Matched quarters'!J6:J21)-SUM('Matched quarters'!H6:H21)^2/F6)) -> 0.37113095 | J6: =SQRT(AVERAGE('Matched quarters'!P14:P21)) -> 1.8329544 | K6: =SQRT(AVERAGE('Matched quarters'!Q14:Q21)) -> 1.5385667 | L6: Not approved
B7: Grooming | C7: organic_volume_growth | D7: PCENDC96 | E7: 2026-04-24 | F7: =COUNT('Matched quarters'!G22:G37) -> 16 | G7: =(SUM('Matched quarters'!K22:K37)-SUM('Matched quarters'!G22:G37)*SUM('Matched quarters'!H22:H37)/F7)/(SUM('Matched quarters'!I22:I37)-SUM('Matched quarters'!G22:G37)^2/F7) -> 0.96234707 | H7: =SUM('Matched quarters'!H22:H37)/F7-G7*SUM('Matched quarters'!G22:G37)/F7 -> -1.5429398 | I7: =(SUM('Matched quarters'!K22:K37)-SUM('Matched quarters'!G22:G37)*SUM('Matched quarters'!H22:H37)/F7)^2/((SUM('Matched quarters'!I22:I37)-SUM('Matched quarters'!G22:G37)^2/F7)*(SUM('Matched quarters'!J22:J37)-SUM('Matched quarters'!H22:H37)^2/F7)) -> 0.35012304 | J7: =SQRT(AVERAGE('Matched quarters'!P30:P37)) -> 2.3862366 | K7: =SQRT(AVERAGE('Matched quarters'!Q30:Q37)) -> 2.5814846 | L7: Not approved
B8: Health Care | C8: organic_volume_growth | D8: PCENDC96 | E8: 2026-04-24 | F8: =COUNT('Matched quarters'!G38:G53) -> 16 | G8: =(SUM('Matched quarters'!K38:K53)-SUM('Matched quarters'!G38:G53)*SUM('Matched quarters'!H38:H53)/F8)/(SUM('Matched quarters'!I38:I53)-SUM('Matched quarters'!G38:G53)^2/F8) -> 0.35409849 | H8: =SUM('Matched quarters'!H38:H53)/F8-G8*SUM('Matched quarters'!G38:G53)/F8 -> -1.1072323 | I8: =(SUM('Matched quarters'!K38:K53)-SUM('Matched quarters'!G38:G53)*SUM('Matched quarters'!H38:H53)/F8)^2/((SUM('Matched quarters'!I38:I53)-SUM('Matched quarters'!G38:G53)^2/F8)*(SUM('Matched quarters'!J38:J53)-SUM('Matched quarters'!H38:H53)^2/F8)) -> 0.047014203 | J8: =SQRT(AVERAGE('Matched quarters'!P46:P53)) -> 2.6781533 | K8: =SQRT(AVERAGE('Matched quarters'!Q46:Q53)) -> 1.8624581 | L8: Not approved
B9: Fabric & Home Care | C9: organic_volume_growth | D9: PCENDC96 | E9: 2026-04-24 | F9: =COUNT('Matched quarters'!G54:G69) -> 16 | G9: =(SUM('Matched quarters'!K54:K69)-SUM('Matched quarters'!G54:G69)*SUM('Matched quarters'!H54:H69)/F9)/(SUM('Matched quarters'!I54:I69)-SUM('Matched quarters'!G54:G69)^2/F9) -> 1.3604792 | H9: =SUM('Matched quarters'!H54:H69)/F9-G9*SUM('Matched quarters'!G54:G69)/F9 -> -2.5929118 | I9: =(SUM('Matched quarters'!K54:K69)-SUM('Matched quarters'!G54:G69)*SUM('Matched quarters'!H54:H69)/F9)^2/((SUM('Matched quarters'!I54:I69)-SUM('Matched quarters'!G54:G69)^2/F9)*(SUM('Matched quarters'!J54:J69)-SUM('Matched quarters'!H54:H69)^2/F9)) -> 0.62224742 | J9: =SQRT(AVERAGE('Matched quarters'!P62:P69)) -> 2.5548722 | K9: =SQRT(AVERAGE('Matched quarters'!Q62:Q69)) -> 1.8853879 | L9: Not approved
B10: Baby, Feminine & Family Care | C10: organic_volume_growth | D10: PCENDC96 | E10: 2026-04-24 | F10: =COUNT('Matched quarters'!G70:G85) -> 16 | G10: =(SUM('Matched quarters'!K70:K85)-SUM('Matched quarters'!G70:G85)*SUM('Matched quarters'!H70:H85)/F10)/(SUM('Matched quarters'!I70:I85)-SUM('Matched quarters'!G70:G85)^2/F10) -> 0.76964966 | H10: =SUM('Matched quarters'!H70:H85)/F10-G10*SUM('Matched quarters'!G70:G85)/F10 -> -2.6840011 | I10: =(SUM('Matched quarters'!K70:K85)-SUM('Matched quarters'!G70:G85)*SUM('Matched quarters'!H70:H85)/F10)^2/((SUM('Matched quarters'!I70:I85)-SUM('Matched quarters'!G70:G85)^2/F10)*(SUM('Matched quarters'!J70:J85)-SUM('Matched quarters'!H70:H85)^2/F10)) -> 0.27636199 | J10: =SQRT(AVERAGE('Matched quarters'!P78:P85)) -> 2.5805522 | K10: =SQRT(AVERAGE('Matched quarters'!Q78:Q85)) -> 2.9487815 | L10: Not approved
B11: Beauty | C11: price_contribution | D11: CUUR0000SEGB | E11: 2026-04-24 | F11: =COUNT('Matched quarters'!G86:G101) -> 16 | G11: =(SUM('Matched quarters'!K86:K101)-SUM('Matched quarters'!G86:G101)*SUM('Matched quarters'!H86:H101)/F11)/(SUM('Matched quarters'!I86:I101)-SUM('Matched quarters'!G86:G101)^2/F11) -> 0.96336109 | H11: =SUM('Matched quarters'!H86:H101)/F11-G11*SUM('Matched quarters'!G86:G101)/F11 -> 1.3471539 | I11: =(SUM('Matched quarters'!K86:K101)-SUM('Matched quarters'!G86:G101)*SUM('Matched quarters'!H86:H101)/F11)^2/((SUM('Matched quarters'!I86:I101)-SUM('Matched quarters'!G86:G101)^2/F11)*(SUM('Matched quarters'!J86:J101)-SUM('Matched quarters'!H86:H101)^2/F11)) -> 0.84290373 | J11: =SQRT(AVERAGE('Matched quarters'!P94:P101)) -> 1.3463739 | K11: =SQRT(AVERAGE('Matched quarters'!Q94:Q101)) -> 1.9764235 | L11: Not approved
B12: Grooming | C12: price_contribution | D12: CUUR0000SEGB | E12: 2026-04-24 | F12: =COUNT('Matched quarters'!G102:G117) -> 16 | G12: =(SUM('Matched quarters'!K102:K117)-SUM('Matched quarters'!G102:G117)*SUM('Matched quarters'!H102:H117)/F12)/(SUM('Matched quarters'!I102:I117)-SUM('Matched quarters'!G102:G117)^2/F12) -> 1.1270646 | H12: =SUM('Matched quarters'!H102:H117)/F12-G12*SUM('Matched quarters'!G102:G117)/F12 -> 2.4576334 | I12: =(SUM('Matched quarters'!K102:K117)-SUM('Matched quarters'!G102:G117)*SUM('Matched quarters'!H102:H117)/F12)^2/((SUM('Matched quarters'!I102:I117)-SUM('Matched quarters'!G102:G117)^2/F12)*(SUM('Matched quarters'!J102:J117)-SUM('Matched quarters'!H102:H117)^2/F12)) -> 0.80021182 | J12: =SQRT(AVERAGE('Matched quarters'!P110:P117)) -> 2.1749551 | K12: =SQRT(AVERAGE('Matched quarters'!Q110:Q117)) -> 3.4629738 | L12: Not approved
B13: Beauty | C13: organic_sales_growth | D13: RSHPCS | E13: 2026-04-24 | F13: =COUNT('Matched quarters'!G118:G134) -> 17 | G13: =(SUM('Matched quarters'!K118:K134)-SUM('Matched quarters'!G118:G134)*SUM('Matched quarters'!H118:H134)/F13)/(SUM('Matched quarters'!I118:I134)-SUM('Matched quarters'!G118:G134)^2/F13) -> 0.10895444 | H13: =SUM('Matched quarters'!H118:H134)/F13-G13*SUM('Matched quarters'!G118:G134)/F13 -> 2.9295212 | I13: =(SUM('Matched quarters'!K118:K134)-SUM('Matched quarters'!G118:G134)*SUM('Matched quarters'!H118:H134)/F13)^2/((SUM('Matched quarters'!I118:I134)-SUM('Matched quarters'!G118:G134)^2/F13)*(SUM('Matched quarters'!J118:J134)-SUM('Matched quarters'!H118:H134)^2/F13)) -> 0.0092390824 | J13: =SQRT(AVERAGE('Matched quarters'!P126:P134)) -> 3.0905804 | K13: =SQRT(AVERAGE('Matched quarters'!Q126:Q134)) -> 3.0196118 | L13: Not approved
B14: Health Care | C14: organic_sales_growth | D14: RSHPCS | E14: 2026-04-24 | F14: =COUNT('Matched quarters'!G135:G151) -> 17 | G14: =(SUM('Matched quarters'!K135:K151)-SUM('Matched quarters'!G135:G151)*SUM('Matched quarters'!H135:H151)/F14)/(SUM('Matched quarters'!I135:I151)-SUM('Matched quarters'!G135:G151)^2/F14) -> 0.062652357 | H14: =SUM('Matched quarters'!H135:H151)/F14-G14*SUM('Matched quarters'!G135:G151)/F14 -> 5.0668081 | I14: =(SUM('Matched quarters'!K135:K151)-SUM('Matched quarters'!G135:G151)*SUM('Matched quarters'!H135:H151)/F14)^2/((SUM('Matched quarters'!I135:I151)-SUM('Matched quarters'!G135:G151)^2/F14)*(SUM('Matched quarters'!J135:J151)-SUM('Matched quarters'!H135:H151)^2/F14)) -> 0.0017920341 | J14: =SQRT(AVERAGE('Matched quarters'!P143:P151)) -> 4.7260407 | K14: =SQRT(AVERAGE('Matched quarters'!Q143:Q151)) -> 1.8333333 | L14: Not approved
B15: Beauty | C15: organic_volume_growth | D15: PCENDC96 | E15: 2026-05-15 | F15: =COUNT('Matched quarters'!G152:G168) -> 17 | G15: =(SUM('Matched quarters'!K152:K168)-SUM('Matched quarters'!G152:G168)*SUM('Matched quarters'!H152:H168)/F15)/(SUM('Matched quarters'!I152:I168)-SUM('Matched quarters'!G152:G168)^2/F15) -> 0.65647479 | H15: =SUM('Matched quarters'!H152:H168)/F15-G15*SUM('Matched quarters'!G152:G168)/F15 -> -0.65731888 | I15: =(SUM('Matched quarters'!K152:K168)-SUM('Matched quarters'!G152:G168)*SUM('Matched quarters'!H152:H168)/F15)^2/((SUM('Matched quarters'!I152:I168)-SUM('Matched quarters'!G152:G168)^2/F15)*(SUM('Matched quarters'!J152:J168)-SUM('Matched quarters'!H152:H168)^2/F15)) -> 0.25966555 | J15: =SQRT(AVERAGE('Matched quarters'!P160:P168)) -> 2.3850427 | K15: =SQRT(AVERAGE('Matched quarters'!Q160:Q168)) -> 1.7159384 | L15: Not approved
B16: Grooming | C16: organic_volume_growth | D16: PCENDC96 | E16: 2026-05-15 | F16: =COUNT('Matched quarters'!G169:G185) -> 17 | G16: =(SUM('Matched quarters'!K169:K185)-SUM('Matched quarters'!G169:G185)*SUM('Matched quarters'!H169:H185)/F16)/(SUM('Matched quarters'!I169:I185)-SUM('Matched quarters'!G169:G185)^2/F16) -> 0.96197033 | H16: =SUM('Matched quarters'!H169:H185)/F16-G16*SUM('Matched quarters'!G169:G185)/F16 -> -1.6568629 | I16: =(SUM('Matched quarters'!K169:K185)-SUM('Matched quarters'!G169:G185)*SUM('Matched quarters'!H169:H185)/F16)^2/((SUM('Matched quarters'!I169:I185)-SUM('Matched quarters'!G169:G185)^2/F16)*(SUM('Matched quarters'!J169:J185)-SUM('Matched quarters'!H169:H185)^2/F16)) -> 0.33991915 | J16: =SQRT(AVERAGE('Matched quarters'!P177:P185)) -> 2.3414632 | K16: =SQRT(AVERAGE('Matched quarters'!Q177:Q185)) -> 2.5027762 | L16: Not approved
B17: Health Care | C17: organic_volume_growth | D17: PCENDC96 | E17: 2026-05-15 | F17: =COUNT('Matched quarters'!G186:G202) -> 17 | G17: =(SUM('Matched quarters'!K186:K202)-SUM('Matched quarters'!G186:G202)*SUM('Matched quarters'!H186:H202)/F17)/(SUM('Matched quarters'!I186:I202)-SUM('Matched quarters'!G186:G202)^2/F17) -> 0.35381963 | H17: =SUM('Matched quarters'!H186:H202)/F17-G17*SUM('Matched quarters'!G186:G202)/F17 -> -1.1915578 | I17: =(SUM('Matched quarters'!K186:K202)-SUM('Matched quarters'!G186:G202)*SUM('Matched quarters'!H186:H202)/F17)^2/((SUM('Matched quarters'!I186:I202)-SUM('Matched quarters'!G186:G202)^2/F17)*(SUM('Matched quarters'!J186:J202)-SUM('Matched quarters'!H186:H202)^2/F17)) -> 0.046203344 | J17: =SQRT(AVERAGE('Matched quarters'!P194:P202)) -> 2.5702578 | K17: =SQRT(AVERAGE('Matched quarters'!Q194:Q202)) -> 1.7638342 | L17: Not approved
B18: Fabric & Home Care | C18: organic_volume_growth | D18: PCENDC96 | E18: 2026-05-15 | F18: =COUNT('Matched quarters'!G203:G219) -> 17 | G18: =(SUM('Matched quarters'!K203:K219)-SUM('Matched quarters'!G203:G219)*SUM('Matched quarters'!H203:H219)/F18)/(SUM('Matched quarters'!I203:I219)-SUM('Matched quarters'!G203:G219)^2/F18) -> 1.3609605 | H18: =SUM('Matched quarters'!H203:H219)/F18-G18*SUM('Matched quarters'!G203:G219)/F18 -> -2.4473462 | I18: =(SUM('Matched quarters'!K203:K219)-SUM('Matched quarters'!G203:G219)*SUM('Matched quarters'!H203:H219)/F18)^2/((SUM('Matched quarters'!I203:I219)-SUM('Matched quarters'!G203:G219)^2/F18)*(SUM('Matched quarters'!J203:J219)-SUM('Matched quarters'!H203:H219)^2/F18)) -> 0.59687268 | J18: =SQRT(AVERAGE('Matched quarters'!P211:P219)) -> 2.5474428 | K18: =SQRT(AVERAGE('Matched quarters'!Q211:Q219)) -> 1.9632032 | L18: Not approved
B19: Baby, Feminine & Family Care | C19: organic_volume_growth | D19: PCENDC96 | E19: 2026-05-15 | F19: =COUNT('Matched quarters'!G220:G236) -> 17 | G19: =(SUM('Matched quarters'!K220:K236)-SUM('Matched quarters'!G220:G236)*SUM('Matched quarters'!H220:H236)/F19)/(SUM('Matched quarters'!I220:I236)-SUM('Matched quarters'!G220:G236)^2/F19) -> 0.7705192 | H19: =SUM('Matched quarters'!H220:H236)/F19-G19*SUM('Matched quarters'!G220:G236)/F19 -> -2.421059 | I19: =(SUM('Matched quarters'!K220:K236)-SUM('Matched quarters'!G220:G236)*SUM('Matched quarters'!H220:H236)/F19)^2/((SUM('Matched quarters'!I220:I236)-SUM('Matched quarters'!G220:G236)^2/F19)*(SUM('Matched quarters'!J220:J236)-SUM('Matched quarters'!H220:H236)^2/F19)) -> 0.23188987 | J19: =SQRT(AVERAGE('Matched quarters'!P228:P236)) -> 2.8569394 | K19: =SQRT(AVERAGE('Matched quarters'!Q228:Q236)) -> 3.1993923 | L19: Not approved
B20: Beauty | C20: price_contribution | D20: CUUR0000SEGB | E20: 2026-05-15 | F20: =COUNT('Matched quarters'!G237:G252) -> 16 | G20: =(SUM('Matched quarters'!K237:K252)-SUM('Matched quarters'!G237:G252)*SUM('Matched quarters'!H237:H252)/F20)/(SUM('Matched quarters'!I237:I252)-SUM('Matched quarters'!G237:G252)^2/F20) -> 0.96336109 | H20: =SUM('Matched quarters'!H237:H252)/F20-G20*SUM('Matched quarters'!G237:G252)/F20 -> 1.3471539 | I20: =(SUM('Matched quarters'!K237:K252)-SUM('Matched quarters'!G237:G252)*SUM('Matched quarters'!H237:H252)/F20)^2/((SUM('Matched quarters'!I237:I252)-SUM('Matched quarters'!G237:G252)^2/F20)*(SUM('Matched quarters'!J237:J252)-SUM('Matched quarters'!H237:H252)^2/F20)) -> 0.84290373 | J20: =SQRT(AVERAGE('Matched quarters'!P245:P252)) -> 1.3463739 | K20: =SQRT(AVERAGE('Matched quarters'!Q245:Q252)) -> 1.9764235 | L20: Not approved
B21: Grooming | C21: price_contribution | D21: CUUR0000SEGB | E21: 2026-05-15 | F21: =COUNT('Matched quarters'!G253:G268) -> 16 | G21: =(SUM('Matched quarters'!K253:K268)-SUM('Matched quarters'!G253:G268)*SUM('Matched quarters'!H253:H268)/F21)/(SUM('Matched quarters'!I253:I268)-SUM('Matched quarters'!G253:G268)^2/F21) -> 1.1270646 | H21: =SUM('Matched quarters'!H253:H268)/F21-G21*SUM('Matched quarters'!G253:G268)/F21 -> 2.4576334 | I21: =(SUM('Matched quarters'!K253:K268)-SUM('Matched quarters'!G253:G268)*SUM('Matched quarters'!H253:H268)/F21)^2/((SUM('Matched quarters'!I253:I268)-SUM('Matched quarters'!G253:G268)^2/F21)*(SUM('Matched quarters'!J253:J268)-SUM('Matched quarters'!H253:H268)^2/F21)) -> 0.80021182 | J21: =SQRT(AVERAGE('Matched quarters'!P261:P268)) -> 2.1749551 | K21: =SQRT(AVERAGE('Matched quarters'!Q261:Q268)) -> 3.4629738 | L21: Not approved
B22: Beauty | C22: organic_sales_growth | D22: RSHPCS | E22: 2026-05-15 | F22: =COUNT('Matched quarters'!G269:G285) -> 17 | G22: =(SUM('Matched quarters'!K269:K285)-SUM('Matched quarters'!G269:G285)*SUM('Matched quarters'!H269:H285)/F22)/(SUM('Matched quarters'!I269:I285)-SUM('Matched quarters'!G269:G285)^2/F22) -> 0.11163568 | H22: =SUM('Matched quarters'!H269:H285)/F22-G22*SUM('Matched quarters'!G269:G285)/F22 -> 2.9115216 | I22: =(SUM('Matched quarters'!K269:K285)-SUM('Matched quarters'!G269:G285)*SUM('Matched quarters'!H269:H285)/F22)^2/((SUM('Matched quarters'!I269:I285)-SUM('Matched quarters'!G269:G285)^2/F22)*(SUM('Matched quarters'!J269:J285)-SUM('Matched quarters'!H269:H285)^2/F22)) -> 0.0097007108 | J22: =SQRT(AVERAGE('Matched quarters'!P277:P285)) -> 3.0876523 | K22: =SQRT(AVERAGE('Matched quarters'!Q277:Q285)) -> 3.0196118 | L22: Not approved
B23: Health Care | C23: organic_sales_growth | D23: RSHPCS | E23: 2026-05-15 | F23: =COUNT('Matched quarters'!G286:G302) -> 17 | G23: =(SUM('Matched quarters'!K286:K302)-SUM('Matched quarters'!G286:G302)*SUM('Matched quarters'!H286:H302)/F23)/(SUM('Matched quarters'!I286:I302)-SUM('Matched quarters'!G286:G302)^2/F23) -> 0.047002303 | H23: =SUM('Matched quarters'!H286:H302)/F23-G23*SUM('Matched quarters'!G286:G302)/F23 -> 5.1516126 | I23: =(SUM('Matched quarters'!K286:K302)-SUM('Matched quarters'!G286:G302)*SUM('Matched quarters'!H286:H302)/F23)^2/((SUM('Matched quarters'!I286:I302)-SUM('Matched quarters'!G286:G302)^2/F23)*(SUM('Matched quarters'!J286:J302)-SUM('Matched quarters'!H286:H302)^2/F23)) -> 0.0010087144 | J23: =SQRT(AVERAGE('Matched quarters'!P294:P302)) -> 4.7316834 | K23: =SQRT(AVERAGE('Matched quarters'!Q294:Q302)) -> 1.8333333 | L23: Not approved

Sheet Matched quarters
B2: Quarterly pairs | Company and market
B5: Segment | C5: Company measure | D5: Market series | E5: Known by | F5: Quarter ended | G5: Market YoY % | H5: P&G % | I5: Market squared | J5: P&G squared | K5: Cross product | L5: Fitted P&G % | M5: Residual pp | N5: Rolling fit % | O5: Trailing-four % | P5: Fit error squared | Q5: Baseline error squared
B6: Beauty | C6: organic_volume_growth | D6: PCENDC96 | E6: 2026-04-24 | F6: 2022-03-31 | G6: ='Quarterly market'!G40 -> 3.5989105 | H6: ='PG history'!G6 -> -1 | I6: =G6*G6 -> 12.952157 | J6: =H6*H6 -> 1 | K6: =G6*H6 -> -3.5989105 | L6: ='Model tests'!H6+'Model tests'!G6*G6 -> 1.4132304 | M6: =H6-L6 -> -2.4132304
B7: Beauty | C7: organic_volume_growth | D7: PCENDC96 | E7: 2026-04-24 | F7: 2022-06-30 | G7: ='Quarterly market'!G41 -> -0.03796621 | H7: ='PG history'!G13 -> -2 | I7: =G7*G7 -> 0.0014414331 | J7: =H7*H7 -> 4 | K7: =G7*H7 -> 0.07593242 | L7: ='Model tests'!H6+'Model tests'!G6*G7 -> -0.97081637 | M7: =H7-L7 -> -1.0291836
B8: Beauty | C8: organic_volume_growth | D8: PCENDC96 | E8: 2026-04-24 | F8: 2022-09-30 | G8: ='Quarterly market'!G42 -> -0.97428175 | H8: ='PG history'!G20 -> -1 | I8: =G8*G8 -> 0.94922494 | J8: =H8*H8 -> 1 | K8: =G8*H8 -> 0.97428175 | L8: ='Model tests'!H6+'Model tests'!G6*G8 -> -1.5845903 | M8: =H8-L8 -> 0.58459028
B9: Beauty | C9: organic_volume_growth | D9: PCENDC96 | E9: 2026-04-24 | F9: 2022-12-31 | G9: ='Quarterly market'!G43 -> -1.7083333 | H9: ='PG history'!G27 -> -4 | I9: =G9*G9 -> 2.9184028 | J9: =H9*H9 -> 16 | K9: =G9*H9 -> 6.8333333 | L9: ='Model tests'!H6+'Model tests'!G6*G9 -> -2.065776 | M9: =H9-L9 -> -1.934224
B10: Beauty | C10: organic_volume_growth | D10: PCENDC96 | E10: 2026-04-24 | F10: 2023-03-31 | G10: ='Quarterly market'!G44 -> -0.51383557 | H10: ='PG history'!G34 -> 0 | I10: =G10*G10 -> 0.264027 | J10: =H10*H10 -> 0 | K10: =G10*H10 -> 0 | L10: ='Model tests'!H6+'Model tests'!G6*G10 -> -1.2827584 | M10: =H10-L10 -> 1.2827584
B11: Beauty | C11: organic_volume_growth | D11: PCENDC96 | E11: 2026-04-24 | F11: 2023-06-30 | G11: ='Quarterly market'!G45 -> -0.38380426 | H11: ='PG history'!G41 -> -1 | I11: =G11*G11 -> 0.14730571 | J11: =H11*H11 -> 1 | K11: =G11*H11 -> 0.38380426 | L11: ='Model tests'!H6+'Model tests'!G6*G11 -> -1.1975203 | M11: =H11-L11 -> 0.19752025
B12: Beauty | C12: organic_volume_growth | D12: PCENDC96 | E12: 2026-04-24 | F12: 2023-09-30 | G12: ='Quarterly market'!G46 -> 1.1893013 | H12: ='PG history'!G48 -> 0 | I12: =G12*G12 -> 1.4144376 | J12: =H12*H12 -> 0 | K12: =G12*H12 -> 0 | L12: ='Model tests'!H6+'Model tests'!G6*G12 -> -0.1663175 | M12: =H12-L12 -> 0.1663175
B13: Beauty | C13: organic_volume_growth | D13: PCENDC96 | E13: 2026-04-24 | F13: 2023-12-31 | G13: ='Quarterly market'!G47 -> 2.2255193 | H13: ='PG history'!G55 -> -1 | I13: =G13*G13 -> 4.9529361 | J13: =H13*H13 -> 1 | K13: =G13*H13 -> -2.2255193 | L13: ='Model tests'!H6+'Model tests'!G6*G13 -> 0.51294448 | M13: =H13-L13 -> -1.5129445
B14: Beauty | C14: organic_volume_growth | D14: PCENDC96 | E14: 2026-04-24 | F14: 2024-03-31 | G14: ='Quarterly market'!G48 -> 1.372616 | H14: ='PG history'!G62 -> 1 | I14: =G14*G14 -> 1.8840747 | J14: =H14*H14 -> 1 | K14: =G14*H14 -> 1.372616 | L14: ='Model tests'!H6+'Model tests'!G6*G14 -> -0.046150994 | M14: =H14-L14 -> 1.046151 | N14: =AVERAGE(H6:H13)+((SUM(K6:K13)-SUM(G6:G13)*SUM(H6:H13)/COUNT(G6:G13))/(SUM(I6:I13)-SUM(G6:G13)^2/COUNT(G6:G13)))*(G14-AVERAGE(G6:G13)) -> -0.96384867 | O14: =AVERAGE(H10:H13) -> -0.5 | P14: =(H14-N14)^2 -> 3.8567016 | Q14: =(H14-O14)^2 -> 2.25
B15: Beauty | C15: organic_volume_growth | D15: PCENDC96 | E15: 2026-04-24 | F15: 2024-06-30 | G15: ='Quarterly market'!G49 -> 2.2805944 | H15: ='PG history'!G69 -> 1 | I15: =G15*G15 -> 5.2011107 | J15: =H15*H15 -> 1 | K15: =G15*H15 -> 2.2805944 | L15: ='Model tests'!H6+'Model tests'!G6*G15 -> 0.54904732 | M15: =H15-L15 -> 0.45095268 | N15: =AVERAGE(H6:H14)+((SUM(K6:K14)-SUM(G6:G14)*SUM(H6:H14)/COUNT(G6:G14))/(SUM(I6:I14)-SUM(G6:G14)^2/COUNT(G6:G14)))*(G15-AVERAGE(G6:G14)) -> -0.34539719 | O15: =AVERAGE(H11:H14) -> -0.25 | P15: =(H15-N15)^2 -> 1.8100936 | Q15: =(H15-O15)^2 -> 1.5625
B16: Beauty | C16: organic_volume_growth | D16: PCENDC96 | E16: 2026-04-24 | F16: 2024-09-30 | G16: ='Quarterly market'!G50 -> 2.6501995 | H16: ='PG history'!G76 -> 0 | I16: =G16*G16 -> 7.0235576 | J16: =H16*H16 -> 0 | K16: =G16*H16 -> 0 | L16: ='Model tests'!H6+'Model tests'!G6*G16 -> 0.79133103 | M16: =H16-L16 -> -0.79133103 | N16: =AVERAGE(H6:H15)+((SUM(K6:K15)-SUM(G6:G15)*SUM(H6:H15)/COUNT(G6:G15))/(SUM(I6:I15)-SUM(G6:G15)^2/COUNT(G6:G15)))*(G16-AVERAGE(G6:G15)) -> 0.087697667 | O16: =AVERAGE(H12:H15) -> 0.25 | P16: =(H16-N16)^2 -> 0.0076908808 | Q16: =(H16-O16)^2 -> 0.0625
B17: Beauty | C17: organic_volume_growth | D17: PCENDC96 | E17: 2026-04-24 | F17: 2024-12-31 | G17: ='Quarterly market'!G51 -> 2.7872397 | H17: ='PG history'!G83 -> 0 | I17: =G17*G17 -> 7.7687052 | J17: =H17*H17 -> 0 | K17: =G17*H17 -> 0 | L17: ='Model tests'!H6+'Model tests'!G6*G17 -> 0.88116366 | M17: =H17-L17 -> -0.88116366 | N17: =AVERAGE(H6:H16)+((SUM(K6:K16)-SUM(G6:G16)*SUM(H6:H16)/COUNT(G6:G16))/(SUM(I6:I16)-SUM(G6:G16)^2/COUNT(G6:G16)))*(G17-AVERAGE(G6:G16)) -> 0.1321239 | O17: =AVERAGE(H13:H16) -> 0.25 | P17: =(H17-N17)^2 -> 0.017456725 | Q17: =(H17-O17)^2 -> 0.0625
B18: Beauty | C18: organic_volume_growth | D18: PCENDC96 | E18: 2026-04-24 | F18: 2025-03-31 | G18: ='Quarterly market'!G52 -> 3.7498513 | H18: ='PG history'!G90 -> 1 | I18: =G18*G18 -> 14.061385 | J18: =H18*H18 -> 1 | K18: =G18*H18 -> 3.7498513 | L18: ='Model tests'!H6+'Model tests'!G6*G18 -> 1.5121752 | M18: =H18-L18 -> -0.51217516 | N18: =AVERAGE(H6:H17)+((SUM(K6:K17)-SUM(G6:G17)*SUM(H6:H17)/COUNT(G6:G17))/(SUM(I6:I17)-SUM(G6:G17)^2/COUNT(G6:G17)))*(G18-AVERAGE(G6:G17)) -> 0.53600723 | O18: =AVERAGE(H14:H17) -> 0.5 | P18: =(H18-N18)^2 -> 0.21528929 | Q18: =(H18-O18)^2 -> 0.25
B19: Beauty | C19: organic_volume_growth | D19: PCENDC96 | E19: 2026-04-24 | F19: 2025-06-30 | G19: ='Quarterly market'!G53 -> 3.2332745 | H19: ='PG history'!G97 -> 1 | I19: =G19*G19 -> 10.454064 | J19: =H19*H19 -> 1 | K19: =G19*H19 -> 3.2332745 | L19: ='Model tests'!H6+'Model tests'!G6*G19 -> 1.1735485 | M19: =H19-L19 -> -0.17354853 | N19: =AVERAGE(H6:H18)+((SUM(K6:K18)-SUM(G6:G18)*SUM(H6:H18)/COUNT(G6:G18))/(SUM(I6:I18)-SUM(G6:G18)^2/COUNT(G6:G18)))*(G19-AVERAGE(G6:G18)) -> 0.40104061 | O19: =AVERAGE(H15:H18) -> 0.5 | P19: =(H19-N19)^2 -> 0.35875235 | Q19: =(H19-O19)^2 -> 0.25
B20: Beauty | C20: organic_volume_growth | D20: PCENDC96 | E20: 2026-04-24 | F20: 2025-09-30 | G20: ='Quarterly market'!G54 -> 2.9967231 | H20: ='PG history'!G104 -> 4 | I20: =G20*G20 -> 8.9803493 | J20: =H20*H20 -> 16 | K20: =G20*H20 -> 11.986892 | L20: ='Model tests'!H6+'Model tests'!G6*G20 -> 1.0184843 | M20: =H20-L20 -> 2.9815157 | N20: =AVERAGE(H6:H19)+((SUM(K6:K19)-SUM(G6:G19)*SUM(H6:H19)/COUNT(G6:G19))/(SUM(I6:I19)-SUM(G6:G19)^2/COUNT(G6:G19)))*(G20-AVERAGE(G6:G19)) -> 0.3731275 | O20: =AVERAGE(H16:H19) -> 0.5 | P20: =(H20-N20)^2 -> 13.154204 | Q20: =(H20-O20)^2 -> 12.25
B21: Beauty | C21: organic_volume_growth | D21: PCENDC96 | E21: 2026-04-24 | F21: 2025-12-31 | G21: ='Quarterly market'!G55 -> 2.1478109 | H21: ='PG history'!G111 -> 3 | I21: =G21*G21 -> 4.6130916 | J21: =H21*H21 -> 9 | K21: =G21*H21 -> 6.4434327 | L21: ='Model tests'!H6+'Model tests'!G6*G21 -> 0.46200503 | M21: =H21-L21 -> 2.537995 | N21: =AVERAGE(H6:H20)+((SUM(K6:K20)-SUM(G6:G20)*SUM(H6:H20)/COUNT(G6:G20))/(SUM(I6:I20)-SUM(G6:G20)^2/COUNT(G6:G20)))*(G21-AVERAGE(G6:G20)) -> 0.26914172 | O21: =AVERAGE(H17:H20) -> 1.5 | P21: =(H21-N21)^2 -> 7.457587 | Q21: =(H21-O21)^2 -> 2.25
B22: Grooming | C22: organic_volume_growth | D22: PCENDC96 | E22: 2026-04-24 | F22: 2022-03-31 | G22: ='Quarterly market'!G40 -> 3.5989105 | H22: ='PG history'!G7 -> 1 | I22: =G22*G22 -> 12.952157 | J22: =H22*H22 -> 1 | K22: =G22*H22 -> 3.5989105 | L22: ='Model tests'!H7+'Model tests'!G7*G22 -> 1.9204612 | M22: =H22-L22 -> -0.92046115
B23: Grooming | C23: organic_volume_growth | D23: PCENDC96 | E23: 2026-04-24 | F23: 2022-06-30 | G23: ='Quarterly market'!G41 -> -0.03796621 | H23: ='PG history'!G14 -> -2 | I23: =G23*G23 -> 0.0014414331 | J23: =H23*H23 -> 4 | K23: =G23*H23 -> 0.07593242 | L23: ='Model tests'!H7+'Model tests'!G7*G23 -> -1.5794765 | M23: =H23-L23 -> -0.42052352
B24: Grooming | C24: organic_volume_growth | D24: PCENDC96 | E24: 2026-04-24 | F24: 2022-09-30 | G24: ='Quarterly market'!G42 -> -0.97428175 | H24: ='PG history'!G21 -> 1 | I24: =G24*G24 -> 0.94922494 | J24: =H24*H24 -> 1 | K24: =G24*H24 -> -0.97428175 | L24: ='Model tests'!H7+'Model tests'!G7*G24 -> -2.480537 | M24: =H24-L24 -> 3.480537
B25: Grooming | C25: organic_volume_growth | D25: PCENDC96 | E25: 2026-04-24 | F25: 2022-12-31 | G25: ='Quarterly market'!G43 -> -1.7083333 | H25: ='PG history'!G28 -> -8 | I25: =G25*G25 -> 2.9184028 | J25: =H25*H25 -> 64 | K25: =G25*H25 -> 13.666667 | L25: ='Model tests'!H7+'Model tests'!G7*G25 -> -3.1869494 | M25: =H25-L25 -> -4.8130506
B26: Grooming | C26: organic_volume_growth | D26: PCENDC96 | E26: 2026-04-24 | F26: 2023-03-31 | G26: ='Quarterly market'!G44 -> -0.51383557 | H26: ='PG history'!G35 -> -1 | I26: =G26*G26 -> 0.264027 | J26: =H26*H26 -> 1 | K26: =G26*H26 -> 0.51383557 | L26: ='Model tests'!H7+'Model tests'!G7*G26 -> -2.037428 | M26: =H26-L26 -> 1.037428
B27: Grooming | C27: organic_volume_growth | D27: PCENDC96 | E27: 2026-04-24 | F27: 2023-06-30 | G27: ='Quarterly market'!G45 -> -0.38380426 | H27: ='PG history'!G42 -> -1 | I27: =G27*G27 -> 0.14730571 | J27: =H27*H27 -> 1 | K27: =G27*H27 -> 0.38380426 | L27: ='Model tests'!H7+'Model tests'!G7*G27 -> -1.9122927 | M27: =H27-L27 -> 0.91229271
B28: Grooming | C28: organic_volume_growth | D28: PCENDC96 | E28: 2026-04-24 | F28: 2023-09-30 | G28: ='Quarterly market'!G46 -> 1.1893013 | H28: ='PG history'!G49 -> -2 | I28: =G28*G28 -> 1.4144376 | J28: =H28*H28 -> 4 | K28: =G28*H28 -> -2.3786026 | L28: ='Model tests'!H7+'Model tests'!G7*G28 -> -0.39841917 | M28: =H28-L28 -> -1.6015808
B29: Grooming | C29: organic_volume_growth | D29: PCENDC96 | E29: 2026-04-24 | F29: 2023-12-31 | G29: ='Quarterly market'!G47 -> 2.2255193 | H29: ='PG history'!G56 -> 1 | I29: =G29*G29 -> 4.9529361 | J29: =H29*H29 -> 1 | K29: =G29*H29 -> 2.2255193 | L29: ='Model tests'!H7+'Model tests'!G7*G29 -> 0.59878216 | M29: =H29-L29 -> 0.40121784
B30: Grooming | C30: organic_volume_growth | D30: PCENDC96 | E30: 2026-04-24 | F30: 2024-03-31 | G30: ='Quarterly market'!G48 -> 1.372616 | H30: ='PG history'!G63 -> 2 | I30: =G30*G30 -> 1.8840747 | J30: =H30*H30 -> 4 | K30: =G30*H30 -> 2.745232 | L30: ='Model tests'!H7+'Model tests'!G7*G30 -> -0.22200682 | M30: =H30-L30 -> 2.2220068 | N30: =AVERAGE(H22:H29)+((SUM(K22:K29)-SUM(G22:G29)*SUM(H22:H29)/COUNT(G22:G29))/(SUM(I22:I29)-SUM(G22:G29)^2/COUNT(G22:G29)))*(G30-AVERAGE(G22:G29)) -> -0.44300324 | O30: =AVERAGE(H26:H29) -> -0.75 | P30: =(H30-N30)^2 -> 5.9682649 | Q30: =(H30-O30)^2 -> 7.5625
B31: Grooming | C31: organic_volume_growth | D31: PCENDC96 | E31: 2026-04-24 | F31: 2024-06-30 | G31: ='Quarterly market'!G49 -> 2.2805944 | H31: ='PG history'!G70 -> 2 | I31: =G31*G31 -> 5.2011107 | J31: =H31*H31 -> 4 | K31: =G31*H31 -> 4.5611888 | L31: ='Model tests'!H7+'Model tests'!G7*G31 -> 0.65178351 | M31: =H31-L31 -> 1.3482165 | N31: =AVERAGE(H22:H30)+((SUM(K22:K30)-SUM(G22:G30)*SUM(H22:H30)/COUNT(G22:G30))/(SUM(I22:I30)-SUM(G22:G30)^2/COUNT(G22:G30)))*(G31-AVERAGE(G22:G30)) -> 0.87794948 | O31: =AVERAGE(H27:H30) -> 0 | P31: =(H31-N31)^2 -> 1.2589974 | Q31: =(H31-O31)^2 -> 4
B32: Grooming | C32: organic_volume_growth | D32: PCENDC96 | E32: 2026-04-24 | F32: 2024-09-30 | G32: ='Quarterly market'!G50 -> 2.6501995 | H32: ='PG history'!G77 -> 5 | I32: =G32*G32 -> 7.0235576 | J32: =H32*H32 -> 25 | K32: =G32*H32 -> 13.250998 | L32: ='Model tests'!H7+'Model tests'!G7*G32 -> 1.0074719 | M32: =H32-L32 -> 3.9925281 | N32: =AVERAGE(H22:H31)+((SUM(K22:K31)-SUM(G22:G31)*SUM(H22:H31)/COUNT(G22:G31))/(SUM(I22:I31)-SUM(G22:G31)^2/COUNT(G22:G31)))*(G32-AVERAGE(G22:G31)) -> 1.5203439 | O32: =AVERAGE(H28:H31) -> 0.75 | P32: =(H32-N32)^2 -> 12.108007 | Q32: =(H32-O32)^2 -> 18.0625
B33: Grooming | C33: organic_volume_growth | D33: PCENDC96 | E33: 2026-04-24 | F33: 2024-12-31 | G33: ='Quarterly market'!G51 -> 2.7872397 | H33: ='PG history'!G84 -> 2 | I33: =G33*G33 -> 7.7687052 | J33: =H33*H33 -> 4 | K33: =G33*H33 -> 5.5744794 | L33: ='Model tests'!H7+'Model tests'!G7*G33 -> 1.1393522 | M33: =H33-L33 -> 0.86064784 | N33: =AVERAGE(H22:H32)+((SUM(K22:K32)-SUM(G22:G32)*SUM(H22:H32)/COUNT(G22:G32))/(SUM(I22:I32)-SUM(G22:G32)^2/COUNT(G22:G32)))*(G33-AVERAGE(G22:G32)) -> 2.3952585 | O33: =AVERAGE(H29:H32) -> 2.5 | P33: =(H33-N33)^2 -> 0.15622925 | Q33: =(H33-O33)^2 -> 0.25
B34: Grooming | C34: organic_volume_growth | D34: PCENDC96 | E34: 2026-04-24 | F34: 2025-03-31 | G34: ='Quarterly market'!G52 -> 3.7498513 | H34: ='PG history'!G91 -> 1 | I34: =G34*G34 -> 14.061385 | J34: =H34*H34 -> 1 | K34: =G34*H34 -> 3.7498513 | L34: ='Model tests'!H7+'Model tests'!G7*G34 -> 2.0657186 | M34: =H34-L34 -> -1.0657186 | N34: =AVERAGE(H22:H33)+((SUM(K22:K33)-SUM(G22:G33)*SUM(H22:H33)/COUNT(G22:G33))/(SUM(I22:I33)-SUM(G22:G33)^2/COUNT(G22:G33)))*(G34-AVERAGE(G22:G33)) -> 3.606601 | O34: =AVERAGE(H30:H33) -> 2.75 | P34: =(H34-N34)^2 -> 6.7943689 | Q34: =(H34-O34)^2 -> 3.0625
B35: Grooming | C35: organic_volume_growth | D35: PCENDC96 | E35: 2026-04-24 | F35: 2025-06-30 | G35: ='Quarterly market'!G53 -> 3.2332745 | H35: ='PG history'!G98 -> -1 | I35: =G35*G35 -> 10.454064 | J35: =H35*H35 -> 1 | K35: =G35*H35 -> -3.2332745 | L35: ='Model tests'!H7+'Model tests'!G7*G35 -> 1.5685924 | M35: =H35-L35 -> -2.5685924 | N35: =AVERAGE(H22:H34)+((SUM(K22:K34)-SUM(G22:G34)*SUM(H22:H34)/COUNT(G22:G34))/(SUM(I22:I34)-SUM(G22:G34)^2/COUNT(G22:G34)))*(G35-AVERAGE(G22:G34)) -> 2.3889586 | O35: =AVERAGE(H31:H34) -> 2.5 | P35: =(H35-N35)^2 -> 11.48504 | Q35: =(H35-O35)^2 -> 12.25
B36: Grooming | C36: organic_volume_growth | D36: PCENDC96 | E36: 2026-04-24 | F36: 2025-09-30 | G36: ='Quarterly market'!G54 -> 2.9967231 | H36: ='PG history'!G105 -> 1 | I36: =G36*G36 -> 8.9803493 | J36: =H36*H36 -> 1 | K36: =G36*H36 -> 2.9967231 | L36: ='Model tests'!H7+'Model tests'!G7*G36 -> 1.3409479 | M36: =H36-L36 -> -0.34094788 | N36: =AVERAGE(H22:H35)+((SUM(K22:K35)-SUM(G22:G35)*SUM(H22:H35)/COUNT(G22:G35))/(SUM(I22:I35)-SUM(G22:G35)^2/COUNT(G22:G35)))*(G36-AVERAGE(G22:G35)) -> 1.6375934 | O36: =AVERAGE(H32:H35) -> 1.75 | P36: =(H36-N36)^2 -> 0.40652536 | Q36: =(H36-O36)^2 -> 0.5625
B37: Grooming | C37: organic_volume_growth | D37: PCENDC96 | E37: 2026-04-24 | F37: 2025-12-31 | G37: ='Quarterly market'!G55 -> 2.1478109 | H37: ='PG history'!G112 -> -2 | I37: =G37*G37 -> 4.6130916 | J37: =H37*H37 -> 4 | K37: =G37*H37 -> -4.2956218 | L37: ='Model tests'!H7+'Model tests'!G7*G37 -> 0.5239997 | M37: =H37-L37 -> -2.5239997 | N37: =AVERAGE(H22:H36)+((SUM(K22:K36)-SUM(G22:G36)*SUM(H22:H36)/COUNT(G22:G36))/(SUM(I22:I36)-SUM(G22:G36)^2/COUNT(G22:G36)))*(G37-AVERAGE(G22:G36)) -> 0.71579951 | O37: =AVERAGE(H33:H36) -> 0.75 | P37: =(H37-N37)^2 -> 7.375567 | Q37: =(H37-O37)^2 -> 7.5625
B38: Health Care | C38: organic_volume_growth | D38: PCENDC96 | E38: 2026-04-24 | F38: 2022-03-31 | G38: ='Quarterly market'!G40 -> 3.5989105 | H38: ='PG history'!G8 -> 8 | I38: =G38*G38 -> 12.952157 | J38: =H38*H38 -> 64 | K38: =G38*H38 -> 28.791284 | L38: ='Model tests'!H8+'Model tests'!G8*G38 -> 0.1671365 | M38: =H38-L38 -> 7.8328635
B39: Health Care | C39: organic_volume_growth | D39: PCENDC96 | E39: 2026-04-24 | F39: 2022-06-30 | G39: ='Quarterly market'!G41 -> -0.03796621 | H39: ='PG history'!G15 -> 0 | I39: =G39*G39 -> 0.0014414331 | J39: =H39*H39 -> 0 | K39: =G39*H39 -> 0 | L39: ='Model tests'!H8+'Model tests'!G8*G39 -> -1.120676 | M39: =H39-L39 -> 1.120676
B40: Health Care | C40: organic_volume_growth | D40: PCENDC96 | E40: 2026-04-24 | F40: 2022-09-30 | G40: ='Quarterly market'!G42 -> -0.97428175 | H40: ='PG history'!G22 -> -2 | I40: =G40*G40 -> 0.94922494 | J40: =H40*H40 -> 4 | K40: =G40*H40 -> 1.9485635 | L40: ='Model tests'!H8+'Model tests'!G8*G40 -> -1.452224 | M40: =H40-L40 -> -0.54777604
B41: Health Care | C41: organic_volume_growth | D41: PCENDC96 | E41: 2026-04-24 | F41: 2022-12-31 | G41: ='Quarterly market'!G43 -> -1.7083333 | H41: ='PG history'!G29 -> -1 | I41: =G41*G41 -> 2.9184028 | J41: =H41*H41 -> 1 | K41: =G41*H41 -> 1.7083333 | L41: ='Model tests'!H8+'Model tests'!G8*G41 -> -1.7121505 | M41: =H41-L41 -> 0.71215051
B42: Health Care | C42: organic_volume_growth | D42: PCENDC96 | E42: 2026-04-24 | F42: 2023-03-31 | G42: ='Quarterly market'!G44 -> -0.51383557 | H42: ='PG history'!G36 -> 1 | I42: =G42*G42 -> 0.264027 | J42: =H42*H42 -> 1 | K42: =G42*H42 -> -0.51383557 | L42: ='Model tests'!H8+'Model tests'!G8*G42 -> -1.2891807 | M42: =H42-L42 -> 2.2891807
B43: Health Care | C43: organic_volume_growth | D43: PCENDC96 | E43: 2026-04-24 | F43: 2023-06-30 | G43: ='Quarterly market'!G45 -> -0.38380426 | H43: ='PG history'!G43 -> -3 | I43: =G43*G43 -> 0.14730571 | J43: =H43*H43 -> 9 | K43: =G43*H43 -> 1.1514128 | L43: ='Model tests'!H8+'Model tests'!G8*G43 -> -1.2431368 | M43: =H43-L43 -> -1.7568632
B44: Health Care | C44: organic_volume_growth | D44: PCENDC96 | E44: 2026-04-24 | F44: 2023-09-30 | G44: ='Quarterly market'!G46 -> 1.1893013 | H44: ='PG history'!G50 -> 2 | I44: =G44*G44 -> 1.4144376 | J44: =H44*H44 -> 4 | K44: =G44*H44 -> 2.3786026 | L44: ='Model tests'!H8+'Model tests'!G8*G44 -> -0.68610246 | M44: =H44-L44 -> 2.6861025
B45: Health Care | C45: organic_volume_growth | D45: PCENDC96 | E45: 2026-04-24 | F45: 2023-12-31 | G45: ='Quarterly market'!G47 -> 2.2255193 | H45: ='PG history'!G57 -> -4 | I45: =G45*G45 -> 4.9529361 | J45: =H45*H45 -> 16 | K45: =G45*H45 -> -8.9020772 | L45: ='Model tests'!H8+'Model tests'!G8*G45 -> -0.31917925 | M45: =H45-L45 -> -3.6808208
B46: Health Care | C46: organic_volume_growth | D46: PCENDC96 | E46: 2026-04-24 | F46: 2024-03-31 | G46: ='Quarterly market'!G48 -> 1.372616 | H46: ='PG history'!G64 -> -4 | I46: =G46*G46 -> 1.8840747 | J46: =H46*H46 -> 16 | K46: =G46*H46 -> -5.490464 | L46: ='Model tests'!H8+'Model tests'!G8*G46 -> -0.62119101 | M46: =H46-L46 -> -3.378809 | N46: =AVERAGE(H38:H45)+((SUM(K38:K45)-SUM(G38:G45)*SUM(H38:H45)/COUNT(G38:G45))/(SUM(I38:I45)-SUM(G38:G45)^2/COUNT(G38:G45)))*(G46-AVERAGE(G38:G45)) -> 1.2434437 | O46: =AVERAGE(H42:H45) -> -1 | P46: =(H46-N46)^2 -> 27.493702 | Q46: =(H46-O46)^2 -> 9
B47: Health Care | C47: organic_volume_growth | D47: PCENDC96 | E47: 2026-04-24 | F47: 2024-06-30 | G47: ='Quarterly market'!G49 -> 2.2805944 | H47: ='PG history'!G71 -> 1 | I47: =G47*G47 -> 5.2011107 | J47: =H47*H47 -> 1 | K47: =G47*H47 -> 2.2805944 | L47: ='Model tests'!H8+'Model tests'!G8*G47 -> -0.29967724 | M47: =H47-L47 -> 1.2996772 | N47: =AVERAGE(H38:H46)+((SUM(K38:K46)-SUM(G38:G46)*SUM(H38:H46)/COUNT(G38:G46))/(SUM(I38:I46)-SUM(G38:G46)^2/COUNT(G38:G46)))*(G47-AVERAGE(G38:G46)) -> 1.3948426 | O47: =AVERAGE(H43:H46) -> -2.25 | P47: =(H47-N47)^2 -> 0.15590069 | Q47: =(H47-O47)^2 -> 10.5625
B48: Health Care | C48: organic_volume_growth | D48: PCENDC96 | E48: 2026-04-24 | F48: 2024-09-30 | G48: ='Quarterly market'!G50 -> 2.6501995 | H48: ='PG history'!G78 -> -1 | I48: =G48*G48 -> 7.0235576 | J48: =H48*H48 -> 1 | K48: =G48*H48 -> -2.6501995 | L48: ='Model tests'!H8+'Model tests'!G8*G48 -> -0.16880062 | M48: =H48-L48 -> -0.83119938 | N48: =AVERAGE(H38:H47)+((SUM(K38:K47)-SUM(G38:G47)*SUM(H38:H47)/COUNT(G38:G47))/(SUM(I38:I47)-SUM(G38:G47)^2/COUNT(G38:G47)))*(G48-AVERAGE(G38:G47)) -> 1.6731237 | O48: =AVERAGE(H44:H47) -> -1.25 | P48: =(H48-N48)^2 -> 7.1455901 | Q48: =(H48-O48)^2 -> 0.0625
B49: Health Care | C49: organic_volume_growth | D49: PCENDC96 | E49: 2026-04-24 | F49: 2024-12-31 | G49: ='Quarterly market'!G51 -> 2.7872397 | H49: ='PG history'!G85 -> 0 | I49: =G49*G49 -> 7.7687052 | J49: =H49*H49 -> 0 | K49: =G49*H49 -> 0 | L49: ='Model tests'!H8+'Model tests'!G8*G49 -> -0.1202749 | M49: =H49-L49 -> 0.1202749 | N49: =AVERAGE(H38:H48)+((SUM(K38:K48)-SUM(G38:G48)*SUM(H38:H48)/COUNT(G38:G48))/(SUM(I38:I48)-SUM(G38:G48)^2/COUNT(G38:G48)))*(G49-AVERAGE(G38:G48)) -> 1.2531145 | O49: =AVERAGE(H45:H48) -> -2 | P49: =(H49-N49)^2 -> 1.5702959 | Q49: =(H49-O49)^2 -> 4
B50: Health Care | C50: organic_volume_growth | D50: PCENDC96 | E50: 2026-04-24 | F50: 2025-03-31 | G50: ='Quarterly market'!G52 -> 3.7498513 | H50: ='PG history'!G92 -> -1 | I50: =G50*G50 -> 14.061385 | J50: =H50*H50 -> 1 | K50: =G50*H50 -> -3.7498513 | L50: ='Model tests'!H8+'Model tests'!G8*G50 -> 0.22058442 | M50: =H50-L50 -> -1.2205844 | N50: =AVERAGE(H38:H49)+((SUM(K38:K49)-SUM(G38:G49)*SUM(H38:H49)/COUNT(G38:G49))/(SUM(I38:I49)-SUM(G38:G49)^2/COUNT(G38:G49)))*(G50-AVERAGE(G38:G49)) -> 1.736944 | O50: =AVERAGE(H46:H49) -> -1 | P50: =(H50-N50)^2 -> 7.4908626 | Q50: =(H50-O50)^2 -> 0
B51: Health Care | C51: organic_volume_growth | D51: PCENDC96 | E51: 2026-04-24 | F51: 2025-06-30 | G51: ='Quarterly market'!G53 -> 3.2332745 | H51: ='PG history'!G99 -> -2 | I51: =G51*G51 -> 10.454064 | J51: =H51*H51 -> 4 | K51: =G51*H51 -> -6.466549 | L51: ='Model tests'!H8+'Model tests'!G8*G51 -> 0.037665339 | M51: =H51-L51 -> -2.0376653 | N51: =AVERAGE(H38:H50)+((SUM(K38:K50)-SUM(G38:G50)*SUM(H38:H50)/COUNT(G38:G50))/(SUM(I38:I50)-SUM(G38:G50)^2/COUNT(G38:G50)))*(G51-AVERAGE(G38:G50)) -> 0.80161196 | O51: =AVERAGE(H47:H50) -> -0.25 | P51: =(H51-N51)^2 -> 7.8490296 | Q51: =(H51-O51)^2 -> 3.0625
B52: Health Care | C52: organic_volume_growth | D52: PCENDC96 | E52: 2026-04-24 | F52: 2025-09-30 | G52: ='Quarterly market'!G54 -> 2.9967231 | H52: ='PG history'!G106 -> -2 | I52: =G52*G52 -> 8.9803493 | J52: =H52*H52 -> 4 | K52: =G52*H52 -> -5.9934462 | L52: ='Model tests'!H8+'Model tests'!G8*G52 -> -0.046097148 | M52: =H52-L52 -> -1.9539029 | N52: =AVERAGE(H38:H51)+((SUM(K38:K51)-SUM(G38:G51)*SUM(H38:H51)/COUNT(G38:G51))/(SUM(I38:I51)-SUM(G38:G51)^2/COUNT(G38:G51)))*(G52-AVERAGE(G38:G51)) -> 0.27607581 | O52: =AVERAGE(H48:H51) -> -1 | P52: =(H52-N52)^2 -> 5.1805211 | Q52: =(H52-O52)^2 -> 1
B53: Health Care | C53: organic_volume_growth | D53: PCENDC96 | E53: 2026-04-24 | F53: 2025-12-31 | G53: ='Quarterly market'!G55 -> 2.1478109 | H53: ='PG history'!G113 -> -1 | I53: =G53*G53 -> 4.6130916 | J53: =H53*H53 -> 1 | K53: =G53*H53 -> -2.1478109 | L53: ='Model tests'!H8+'Model tests'!G8*G53 -> -0.34669568 | M53: =H53-L53 -> -0.65330432 | N53: =AVERAGE(H38:H52)+((SUM(K38:K52)-SUM(G38:G52)*SUM(H38:H52)/COUNT(G38:G52))/(SUM(I38:I52)-SUM(G38:G52)^2/COUNT(G38:G52)))*(G53-AVERAGE(G38:G52)) -> -0.2970508 | O53: =AVERAGE(H49:H52) -> -1.25 | P53: =(H53-N53)^2 -> 0.49413757 | Q53: =(H53-O53)^2 -> 0.0625
B54: Fabric & Home Care | C54: organic_volume_growth | D54: PCENDC96 | E54: 2026-04-24 | F54: 2022-03-31 | G54: ='Quarterly market'!G40 -> 3.5989105 | H54: ='PG history'!G9 -> 5 | I54: =G54*G54 -> 12.952157 | J54: =H54*H54 -> 25 | K54: =G54*H54 -> 17.994552 | L54: ='Model tests'!H9+'Model tests'!G9*G54 -> 2.3033309 | M54: =H54-L54 -> 2.6966691
B55: Fabric & Home Care | C55: organic_volume_growth | D55: PCENDC96 | E55: 2026-04-24 | F55: 2022-06-30 | G55: ='Quarterly market'!G41 -> -0.03796621 | H55: ='PG history'!G16 -> -1 | I55: =G55*G55 -> 0.0014414331 | J55: =H55*H55 -> 1 | K55: =G55*H55 -> 0.03796621 | L55: ='Model tests'!H9+'Model tests'!G9*G55 -> -2.644564 | M55: =H55-L55 -> 1.644564
B56: Fabric & Home Care | C56: organic_volume_growth | D56: PCENDC96 | E56: 2026-04-24 | F56: 2022-09-30 | G56: ='Quarterly market'!G42 -> -0.97428175 | H56: ='PG history'!G23 -> -4 | I56: =G56*G56 -> 0.94922494 | J56: =H56*H56 -> 16 | K56: =G56*H56 -> 3.897127 | L56: ='Model tests'!H9+'Model tests'!G9*G56 -> -3.9184018 | M56: =H56-L56 -> -0.08159821
B57: Fabric & Home Care | C57: organic_volume_growth | D57: PCENDC96 | E57: 2026-04-24 | F57: 2022-12-31 | G57: ='Quarterly market'!G43 -> -1.7083333 | H57: ='PG history'!G30 -> -7 | I57: =G57*G57 -> 2.9184028 | J57: =H57*H57 -> 49 | K57: =G57*H57 -> 11.958333 | L57: ='Model tests'!H9+'Model tests'!G9*G57 -> -4.9170637 | M57: =H57-L57 -> -2.0829363
B58: Fabric & Home Care | C58: organic_volume_growth | D58: PCENDC96 | E58: 2026-04-24 | F58: 2023-03-31 | G58: ='Quarterly market'!G44 -> -0.51383557 | H58: ='PG history'!G37 -> -5 | I58: =G58*G58 -> 0.264027 | J58: =H58*H58 -> 25 | K58: =G58*H58 -> 2.5691779 | L58: ='Model tests'!H9+'Model tests'!G9*G58 -> -3.2919744 | M58: =H58-L58 -> -1.7080256
B59: Fabric & Home Care | C59: organic_volume_growth | D59: PCENDC96 | E59: 2026-04-24 | F59: 2023-06-30 | G59: ='Quarterly market'!G45 -> -0.38380426 | H59: ='PG history'!G44 -> -2 | I59: =G59*G59 -> 0.14730571 | J59: =H59*H59 -> 4 | K59: =G59*H59 -> 0.76760852 | L59: ='Model tests'!H9+'Model tests'!G9*G59 -> -3.1150695 | M59: =H59-L59 -> 1.1150695
B60: Fabric & Home Care | C60: organic_volume_growth | D60: PCENDC96 | E60: 2026-04-24 | F60: 2023-09-30 | G60: ='Quarterly market'!G46 -> 1.1893013 | H60: ='PG history'!G51 -> 0 | I60: =G60*G60 -> 1.4144376 | J60: =H60*H60 -> 0 | K60: =G60*H60 -> 0 | L60: ='Model tests'!H9+'Model tests'!G9*G60 -> -0.9748921 | M60: =H60-L60 -> 0.9748921
B61: Fabric & Home Care | C61: organic_volume_growth | D61: PCENDC96 | E61: 2026-04-24 | F61: 2023-12-31 | G61: ='Quarterly market'!G47 -> 2.2255193 | H61: ='PG history'!G58 -> 1 | I61: =G61*G61 -> 4.9529361 | J61: =H61*H61 -> 1 | K61: =G61*H61 -> 2.2255193 | L61: ='Model tests'!H9+'Model tests'!G9*G61 -> 0.43486084 | M61: =H61-L61 -> 0.56513916
B62: Fabric & Home Care | C62: organic_volume_growth | D62: PCENDC96 | E62: 2026-04-24 | F62: 2024-03-31 | G62: ='Quarterly market'!G48 -> 1.372616 | H62: ='PG history'!G65 -> 1 | I62: =G62*G62 -> 1.8840747 | J62: =H62*H62 -> 1 | K62: =G62*H62 -> 1.372616 | L62: ='Model tests'!H9+'Model tests'!G9*G62 -> -0.72549629 | M62: =H62-L62 -> 1.7254963 | N62: =AVERAGE(H54:H61)+((SUM(K54:K61)-SUM(G54:G61)*SUM(H54:H61)/COUNT(G54:G61))/(SUM(I54:I61)-SUM(G54:G61)^2/COUNT(G54:G61)))*(G62-AVERAGE(G54:G61)) -> 0.29918937 | O62: =AVERAGE(H58:H61) -> -1.5 | P62: =(H62-N62)^2 -> 0.49113554 | Q62: =(H62-O62)^2 -> 6.25
B63: Fabric & Home Care | C63: organic_volume_growth | D63: PCENDC96 | E63: 2026-04-24 | F63: 2024-06-30 | G63: ='Quarterly market'!G49 -> 2.2805944 | H63: ='PG history'!G72 -> 3 | I63: =G63*G63 -> 5.2011107 | J63: =H63*H63 -> 9 | K63: =G63*H63 -> 6.8417831 | L63: ='Model tests'!H9+'Model tests'!G9*G63 -> 0.50978936 | M63: =H63-L63 -> 2.4902106 | N63: =AVERAGE(H54:H62)+((SUM(K54:K62)-SUM(G54:G62)*SUM(H54:H62)/COUNT(G54:G62))/(SUM(I54:I62)-SUM(G54:G62)^2/COUNT(G54:G62)))*(G63-AVERAGE(G54:G62)) -> 2.2647133 | O63: =AVERAGE(H59:H62) -> 0 | P63: =(H63-N63)^2 -> 0.54064648 | Q63: =(H63-O63)^2 -> 9
B64: Fabric & Home Care | C64: organic_volume_growth | D64: PCENDC96 | E64: 2026-04-24 | F64: 2024-09-30 | G64: ='Quarterly market'!G50 -> 2.6501995 | H64: ='PG history'!G79 -> 1 | I64: =G64*G64 -> 7.0235576 | J64: =H64*H64 -> 1 | K64: =G64*H64 -> 2.6501995 | L64: ='Model tests'!H9+'Model tests'!G9*G64 -> 1.0126295 | M64: =H64-L64 -> -0.012629469 | N64: =AVERAGE(H54:H63)+((SUM(K54:K63)-SUM(G54:G63)*SUM(H54:H63)/COUNT(G54:G63))/(SUM(I54:I63)-SUM(G54:G63)^2/COUNT(G54:G63)))*(G64-AVERAGE(G54:G63)) -> 3.1854541 | O64: =AVERAGE(H60:H63) -> 1.25 | P64: =(H64-N64)^2 -> 4.7762097 | Q64: =(H64-O64)^2 -> 0.0625
B65: Fabric & Home Care | C65: organic_volume_growth | D65: PCENDC96 | E65: 2026-04-24 | F65: 2024-12-31 | G65: ='Quarterly market'!G51 -> 2.7872397 | H65: ='PG history'!G86 -> 2 | I65: =G65*G65 -> 7.7687052 | J65: =H65*H65 -> 4 | K65: =G65*H65 -> 5.5744794 | L65: ='Model tests'!H9+'Model tests'!G9*G65 -> 1.1990698 | M65: =H65-L65 -> 0.80093022 | N65: =AVERAGE(H54:H64)+((SUM(K54:K64)-SUM(G54:G64)*SUM(H54:H64)/COUNT(G54:G64))/(SUM(I54:I64)-SUM(G54:G64)^2/COUNT(G54:G64)))*(G65-AVERAGE(G54:G64)) -> 3.0219913 | O65: =AVERAGE(H61:H64) -> 1.5 | P65: =(H65-N65)^2 -> 1.0444663 | Q65: =(H65-O65)^2 -> 0.25
B66: Fabric & Home Care | C66: organic_volume_growth | D66: PCENDC96 | E66: 2026-04-24 | F66: 2025-03-31 | G66: ='Quarterly market'!G52 -> 3.7498513 | H66: ='PG history'!G93 -> 0 | I66: =G66*G66 -> 14.061385 | J66: =H66*H66 -> 0 | K66: =G66*H66 -> 0 | L66: ='Model tests'!H9+'Model tests'!G9*G66 -> 2.5086828 | M66: =H66-L66 -> -2.5086828 | N66: =AVERAGE(H54:H65)+((SUM(K54:K65)-SUM(G54:G65)*SUM(H54:H65)/COUNT(G54:G65))/(SUM(I54:I65)-SUM(G54:G65)^2/COUNT(G54:G65)))*(G66-AVERAGE(G54:G65)) -> 4.6819577 | O66: =AVERAGE(H62:H65) -> 1.75 | P66: =(H66-N66)^2 -> 21.920728 | Q66: =(H66-O66)^2 -> 3.0625
B67: Fabric & Home Care | C67: organic_volume_growth | D67: PCENDC96 | E67: 2026-04-24 | F67: 2025-06-30 | G67: ='Quarterly market'!G53 -> 3.2332745 | H67: ='PG history'!G100 -> 0 | I67: =G67*G67 -> 10.454064 | J67: =H67*H67 -> 0 | K67: =G67*H67 -> 0 | L67: ='Model tests'!H9+'Model tests'!G9*G67 -> 1.8058908 | M67: =H67-L67 -> -1.8058908 | N67: =AVERAGE(H54:H66)+((SUM(K54:K66)-SUM(G54:G66)*SUM(H54:H66)/COUNT(G54:G66))/(SUM(I54:I66)-SUM(G54:G66)^2/COUNT(G54:G66)))*(G67-AVERAGE(G54:G66)) -> 2.7419762 | O67: =AVERAGE(H63:H66) -> 1.5 | P67: =(H67-N67)^2 -> 7.5184337 | Q67: =(H67-O67)^2 -> 2.25
B68: Fabric & Home Care | C68: organic_volume_growth | D68: PCENDC96 | E68: 2026-04-24 | F68: 2025-09-30 | G68: ='Quarterly market'!G54 -> 2.9967231 | H68: ='PG history'!G107 -> -2 | I68: =G68*G68 -> 8.9803493 | J68: =H68*H68 -> 4 | K68: =G68*H68 -> -5.9934462 | L68: ='Model tests'!H9+'Model tests'!G9*G68 -> 1.4840675 | M68: =H68-L68 -> -3.4840675 | N68: =AVERAGE(H54:H67)+((SUM(K54:K67)-SUM(G54:G67)*SUM(H54:H67)/COUNT(G54:G67))/(SUM(I54:I67)-SUM(G54:G67)^2/COUNT(G54:G67)))*(G68-AVERAGE(G54:G67)) -> 1.9751643 | O68: =AVERAGE(H64:H67) -> 0.75 | P68: =(H68-N68)^2 -> 15.801931 | Q68: =(H68-O68)^2 -> 7.5625
B69: Fabric & Home Care | C69: organic_volume_growth | D69: PCENDC96 | E69: 2026-04-24 | F69: 2025-12-31 | G69: ='Quarterly market'!G55 -> 2.1478109 | H69: ='PG history'!G114 -> 0 | I69: =G69*G69 -> 4.6130916 | J69: =H69*H69 -> 0 | K69: =G69*H69 -> 0 | L69: ='Model tests'!H9+'Model tests'!G9*G69 -> 0.32914018 | M69: =H69-L69 -> -0.32914018 | N69: =AVERAGE(H54:H68)+((SUM(K54:K68)-SUM(G54:G68)*SUM(H54:H68)/COUNT(G54:G68))/(SUM(I54:I68)-SUM(G54:G68)^2/COUNT(G54:G68)))*(G69-AVERAGE(G54:G68)) -> 0.35415168 | O69: =AVERAGE(H65:H68) -> 0 | P69: =(H69-N69)^2 -> 0.12542341 | Q69: =(H69-O69)^2 -> 0
B70: Baby, Feminine & Family Care | C70: organic_volume_growth | D70: PCENDC96 | E70: 2026-04-24 | F70: 2022-03-31 | G70: ='Quarterly market'!G40 -> 3.5989105 | H70: ='PG history'!G10 -> 2 | I70: =G70*G70 -> 12.952157 | J70: =H70*H70 -> 4 | K70: =G70*H70 -> 7.197821 | L70: ='Model tests'!H10+'Model tests'!G10*G70 -> 0.085899122 | M70: =H70-L70 -> 1.9141009
B71: Baby, Feminine & Family Care | C71: organic_volume_growth | D71: PCENDC96 | E71: 2026-04-24 | F71: 2022-06-30 | G71: ='Quarterly market'!G41 -> -0.03796621 | H71: ='PG history'!G17 -> 0 | I71: =G71*G71 -> 0.0014414331 | J71: =H71*H71 -> 0 | K71: =G71*H71 -> 0 | L71: ='Model tests'!H10+'Model tests'!G10*G71 -> -2.7132218 | M71: =H71-L71 -> 2.7132218
B72: Baby, Feminine & Family Care | C72: organic_volume_growth | D72: PCENDC96 | E72: 2026-04-24 | F72: 2022-09-30 | G72: ='Quarterly market'!G42 -> -0.97428175 | H72: ='PG history'!G24 -> -3 | I72: =G72*G72 -> 0.94922494 | J72: =H72*H72 -> 9 | K72: =G72*H72 -> 2.9228453 | L72: ='Model tests'!H10+'Model tests'!G10*G72 -> -3.4338567 | M72: =H72-L72 -> 0.43385672
B73: Baby, Feminine & Family Care | C73: organic_volume_growth | D73: PCENDC96 | E73: 2026-04-24 | F73: 2022-12-31 | G73: ='Quarterly market'!G43 -> -1.7083333 | H73: ='PG history'!G31 -> -6 | I73: =G73*G73 -> 2.9184028 | J73: =H73*H73 -> 36 | K73: =G73*H73 -> 10.25 | L73: ='Model tests'!H10+'Model tests'!G10*G73 -> -3.9988193 | M73: =H73-L73 -> -2.0011807
B74: Baby, Feminine & Family Care | C74: organic_volume_growth | D74: PCENDC96 | E74: 2026-04-24 | F74: 2023-03-31 | G74: ='Quarterly market'!G44 -> -0.51383557 | H74: ='PG history'!G38 -> -4 | I74: =G74*G74 -> 0.264027 | J74: =H74*H74 -> 16 | K74: =G74*H74 -> 2.0553423 | L74: ='Model tests'!H10+'Model tests'!G10*G74 -> -3.0794745 | M74: =H74-L74 -> -0.92052552
B75: Baby, Feminine & Family Care | C75: organic_volume_growth | D75: PCENDC96 | E75: 2026-04-24 | F75: 2023-06-30 | G75: ='Quarterly market'!G45 -> -0.38380426 | H75: ='PG history'!G45 -> 0 | I75: =G75*G75 -> 0.14730571 | J75: =H75*H75 -> 0 | K75: =G75*H75 -> 0 | L75: ='Model tests'!H10+'Model tests'!G10*G75 -> -2.9793959 | M75: =H75-L75 -> 2.9793959
B76: Baby, Feminine & Family Care | C76: organic_volume_growth | D76: PCENDC96 | E76: 2026-04-24 | F76: 2023-09-30 | G76: ='Quarterly market'!G46 -> 1.1893013 | H76: ='PG history'!G52 -> -3 | I76: =G76*G76 -> 1.4144376 | J76: =H76*H76 -> 9 | K76: =G76*H76 -> -3.567904 | L76: ='Model tests'!H10+'Model tests'!G10*G76 -> -1.7686557 | M76: =H76-L76 -> -1.2313443
B77: Baby, Feminine & Family Care | C77: organic_volume_growth | D77: PCENDC96 | E77: 2026-04-24 | F77: 2023-12-31 | G77: ='Quarterly market'!G47 -> 2.2255193 | H77: ='PG history'!G59 -> -2 | I77: =G77*G77 -> 4.9529361 | J77: =H77*H77 -> 4 | K77: =G77*H77 -> -4.4510386 | L77: ='Model tests'!H10+'Model tests'!G10*G77 -> -0.97113095 | M77: =H77-L77 -> -1.0288691
B78: Baby, Feminine & Family Care | C78: organic_volume_growth | D78: PCENDC96 | E78: 2026-04-24 | F78: 2024-03-31 | G78: ='Quarterly market'!G48 -> 1.372616 | H78: ='PG history'!G66 -> -3 | I78: =G78*G78 -> 1.8840747 | J78: =H78*H78 -> 9 | K78: =G78*H78 -> -4.117848 | L78: ='Model tests'!H10+'Model tests'!G10*G78 -> -1.6275677 | M78: =H78-L78 -> -1.3724323 | N78: =AVERAGE(H70:H77)+((SUM(K70:K77)-SUM(G70:G77)*SUM(H70:H77)/COUNT(G70:G77))/(SUM(I70:I77)-SUM(G70:G77)^2/COUNT(G70:G77)))*(G78-AVERAGE(G70:G77)) -> -1.0929296 | O78: =AVERAGE(H74:H77) -> -2.25 | P78: =(H78-N78)^2 -> 3.6369175 | Q78: =(H78-O78)^2 -> 0.5625
B79: Baby, Feminine & Family Care | C79: organic_volume_growth | D79: PCENDC96 | E79: 2026-04-24 | F79: 2024-06-30 | G79: ='Quarterly market'!G49 -> 2.2805944 | H79: ='PG history'!G73 -> -1 | I79: =G79*G79 -> 5.2011107 | J79: =H79*H79 -> 1 | K79: =G79*H79 -> -2.2805944 | L79: ='Model tests'!H10+'Model tests'!G10*G79 -> -0.92874242 | M79: =H79-L79 -> -0.07125758 | N79: =AVERAGE(H70:H78)+((SUM(K70:K78)-SUM(G70:G78)*SUM(H70:H78)/COUNT(G70:G78))/(SUM(I70:I78)-SUM(G70:G78)^2/COUNT(G70:G78)))*(G79-AVERAGE(G70:G78)) -> -0.55878899 | O79: =AVERAGE(H75:H78) -> -2 | P79: =(H79-N79)^2 -> 0.19466715 | Q79: =(H79-O79)^2 -> 1
B80: Baby, Feminine & Family Care | C80: organic_volume_growth | D80: PCENDC96 | E80: 2026-04-24 | F80: 2024-09-30 | G80: ='Quarterly market'!G50 -> 2.6501995 | H80: ='PG history'!G80 -> -1 | I80: =G80*G80 -> 7.0235576 | J80: =H80*H80 -> 1 | K80: =G80*H80 -> -2.6501995 | L80: ='Model tests'!H10+'Model tests'!G10*G80 -> -0.64427594 | M80: =H80-L80 -> -0.35572406 | N80: =AVERAGE(H70:H79)+((SUM(K70:K79)-SUM(G70:G79)*SUM(H70:H79)/COUNT(G70:G79))/(SUM(I70:I79)-SUM(G70:G79)^2/COUNT(G70:G79)))*(G80-AVERAGE(G70:G79)) -> -0.32779548 | O80: =AVERAGE(H76:H79) -> -2.25 | P80: =(H80-N80)^2 -> 0.45185891 | Q80: =(H80-O80)^2 -> 1.5625
B81: Baby, Feminine & Family Care | C81: organic_volume_growth | D81: PCENDC96 | E81: 2026-04-24 | F81: 2024-12-31 | G81: ='Quarterly market'!G51 -> 2.7872397 | H81: ='PG history'!G87 -> 4 | I81: =G81*G81 -> 7.7687052 | J81: =H81*H81 -> 16 | K81: =G81*H81 -> 11.148959 | L81: ='Model tests'!H10+'Model tests'!G10*G81 -> -0.53880301 | M81: =H81-L81 -> 4.538803 | N81: =AVERAGE(H70:H80)+((SUM(K70:K80)-SUM(G70:G80)*SUM(H70:H80)/COUNT(G70:G80))/(SUM(I70:I80)-SUM(G70:G80)^2/COUNT(G70:G80)))*(G81-AVERAGE(G70:G80)) -> -0.34879657 | O81: =AVERAGE(H77:H80) -> -1.75 | P81: =(H81-N81)^2 -> 18.912032 | Q81: =(H81-O81)^2 -> 33.0625
B82: Baby, Feminine & Family Care | C82: organic_volume_growth | D82: PCENDC96 | E82: 2026-04-24 | F82: 2025-03-31 | G82: ='Quarterly market'!G52 -> 3.7498513 | H82: ='PG history'!G94 -> -2 | I82: =G82*G82 -> 14.061385 | J82: =H82*H82 -> 4 | K82: =G82*H82 -> -7.4997026 | L82: ='Model tests'!H10+'Model tests'!G10*G82 -> 0.20207068 | M82: =H82-L82 -> -2.2020707 | N82: =AVERAGE(H70:H81)+((SUM(K70:K81)-SUM(G70:G81)*SUM(H70:H81)/COUNT(G70:G81))/(SUM(I70:I81)-SUM(G70:G81)^2/COUNT(G70:G81)))*(G82-AVERAGE(G70:G81)) -> 1.4353504 | O82: =AVERAGE(H78:H81) -> -0.25 | P82: =(H82-N82)^2 -> 11.801633 | Q82: =(H82-O82)^2 -> 3.0625
B83: Baby, Feminine & Family Care | C83: organic_volume_growth | D83: PCENDC96 | E83: 2026-04-24 | F83: 2025-06-30 | G83: ='Quarterly market'!G53 -> 3.2332745 | H83: ='PG history'!G101 -> 0 | I83: =G83*G83 -> 10.454064 | J83: =H83*H83 -> 0 | K83: =G83*H83 -> 0 | L83: ='Model tests'!H10+'Model tests'!G10*G83 -> -0.19551251 | M83: =H83-L83 -> 0.19551251 | N83: =AVERAGE(H70:H82)+((SUM(K70:K82)-SUM(G70:G82)*SUM(H70:H82)/COUNT(G70:G82))/(SUM(I70:I82)-SUM(G70:G82)^2/COUNT(G70:G82)))*(G83-AVERAGE(G70:G82)) -> 0.19307504 | O83: =AVERAGE(H79:H82) -> 0 | P83: =(H83-N83)^2 -> 0.037277973 | Q83: =(H83-O83)^2 -> 0
B84: Baby, Feminine & Family Care | C84: organic_volume_growth | D84: PCENDC96 | E84: 2026-04-24 | F84: 2025-09-30 | G84: ='Quarterly market'!G54 -> 2.9967231 | H84: ='PG history'!G108 -> 0 | I84: =G84*G84 -> 8.9803493 | J84: =H84*H84 -> 0 | K84: =G84*H84 -> 0 | L84: ='Model tests'!H10+'Model tests'!G10*G84 -> -0.3775742 | M84: =H84-L84 -> 0.3775742 | N84: =AVERAGE(H70:H83)+((SUM(K70:K83)-SUM(G70:G83)*SUM(H70:H83)/COUNT(G70:G83))/(SUM(I70:I83)-SUM(G70:G83)^2/COUNT(G70:G83)))*(G84-AVERAGE(G70:G83)) -> -0.031273276 | O84: =AVERAGE(H80:H83) -> 0.25 | P84: =(H84-N84)^2 -> 0.0009780178 | Q84: =(H84-O84)^2 -> 0.0625
B85: Baby, Feminine & Family Care | C85: organic_volume_growth | D85: PCENDC96 | E85: 2026-04-24 | F85: 2025-12-31 | G85: ='Quarterly market'!G55 -> 2.1478109 | H85: ='PG history'!G115 -> -5 | I85: =G85*G85 -> 4.6130916 | J85: =H85*H85 -> 25 | K85: =G85*H85 -> -10.739054 | L85: ='Model tests'!H10+'Model tests'!G10*G85 -> -1.0309392 | M85: =H85-L85 -> -3.9690608 | N85: =AVERAGE(H70:H84)+((SUM(K70:K84)-SUM(G70:G84)*SUM(H70:H84)/COUNT(G70:G84))/(SUM(I70:I84)-SUM(G70:G84)^2/COUNT(G70:G84)))*(G85-AVERAGE(G70:G84)) -> -0.72932857 | O85: =AVERAGE(H81:H84) -> 0.5 | P85: =(H85-N85)^2 -> 18.238634 | Q85: =(H85-O85)^2 -> 30.25
B86: Beauty | C86: price_contribution | D86: CUUR0000SEGB | E86: 2026-04-24 | F86: 2022-03-31 | G86: ='Quarterly market'!G73 -> 1.0280002 | H86: ='PG history'!H6 -> 4 | I86: =G86*G86 -> 1.0567844 | J86: =H86*H86 -> 16 | K86: =G86*H86 -> 4.1120008 | L86: ='Model tests'!H11+'Model tests'!G11*G86 -> 2.3374893 | M86: =H86-L86 -> 1.6625107
B87: Beauty | C87: price_contribution | D87: CUUR0000SEGB | E87: 2026-04-24 | F87: 2022-06-30 | G87: ='Quarterly market'!G74 -> 2.9122729 | H87: ='PG history'!H13 -> 6 | I87: =G87*G87 -> 8.4813337 | J87: =H87*H87 -> 36 | K87: =G87*H87 -> 17.473638 | L87: ='Model tests'!H11+'Model tests'!G11*G87 -> 4.1527243 | M87: =H87-L87 -> 1.8472757
B88: Beauty | C88: price_contribution | D88: CUUR0000SEGB | E88: 2026-04-24 | F88: 2022-09-30 | G88: ='Quarterly market'!G75 -> 5.8502773 | H88: ='PG history'!H20 -> 7 | I88: =G88*G88 -> 34.225745 | J88: =H88*H88 -> 49 | K88: =G88*H88 -> 40.951941 | L88: ='Model tests'!H11+'Model tests'!G11*G88 -> 6.9830835 | M88: =H88-L88 -> 0.016916545
B89: Beauty | C89: price_contribution | D89: CUUR0000SEGB | E89: 2026-04-24 | F89: 2022-12-31 | G89: ='Quarterly market'!G76 -> 7.2560335 | H89: ='PG history'!H27 -> 9 | I89: =G89*G89 -> 52.650022 | J89: =H89*H89 -> 81 | K89: =G89*H89 -> 65.304301 | L89: ='Model tests'!H11+'Model tests'!G11*G89 -> 8.3373342 | M89: =H89-L89 -> 0.66266581
B90: Beauty | C90: price_contribution | D90: CUUR0000SEGB | E90: 2026-04-24 | F90: 2023-03-31 | G90: ='Quarterly market'!G77 -> 6.772394 | H90: ='PG history'!H34 -> 8 | I90: =G90*G90 -> 45.865321 | J90: =H90*H90 -> 64 | K90: =G90*H90 -> 54.179152 | L90: ='Model tests'!H11+'Model tests'!G11*G90 -> 7.8714148 | M90: =H90-L90 -> 0.12858522
B91: Beauty | C91: price_contribution | D91: CUUR0000SEGB | E91: 2026-04-24 | F91: 2023-06-30 | G91: ='Quarterly market'!G78 -> 7.0582272 | H91: ='PG history'!H41 -> 8 | I91: =G91*G91 -> 49.818572 | J91: =H91*H91 -> 64 | K91: =G91*H91 -> 56.465818 | L91: ='Model tests'!H11+'Model tests'!G11*G91 -> 8.1467754 | M91: =H91-L91 -> -0.14677537
B92: Beauty | C92: price_contribution | D92: CUUR0000SEGB | E92: 2026-04-24 | F92: 2023-09-30 | G92: ='Quarterly market'!G79 -> 5.4935927 | H92: ='PG history'!H48 -> 7 | I92: =G92*G92 -> 30.179561 | J92: =H92*H92 -> 49 | K92: =G92*H92 -> 38.455149 | L92: ='Model tests'!H11+'Model tests'!G11*G92 -> 6.6394674 | M92: =H92-L92 -> 0.36053263
B93: Beauty | C93: price_contribution | D93: CUUR0000SEGB | E93: 2026-04-24 | F93: 2023-12-31 | G93: ='Quarterly market'!G80 -> 4.2122165 | H93: ='PG history'!H55 -> 4 | I93: =G93*G93 -> 17.742768 | J93: =H93*H93 -> 16 | K93: =G93*H93 -> 16.848866 | L93: ='Model tests'!H11+'Model tests'!G11*G93 -> 5.4050394 | M93: =H93-L93 -> -1.4050394
B94: Beauty | C94: price_contribution | D94: CUUR0000SEGB | E94: 2026-04-24 | F94: 2024-03-31 | G94: ='Quarterly market'!G81 -> 3.6368096 | H94: ='PG history'!H62 -> 4 | I94: =G94*G94 -> 13.226384 | J94: =H94*H94 -> 16 | K94: =G94*H94 -> 14.547239 | L94: ='Model tests'!H11+'Model tests'!G11*G94 -> 4.8507148 | M94: =H94-L94 -> -0.8507148 | N94: =AVERAGE(H86:H93)+((SUM(K86:K93)-SUM(G86:G93)*SUM(H86:H93)/COUNT(G86:G93))/(SUM(I86:I93)-SUM(G86:G93)^2/COUNT(G86:G93)))*(G94-AVERAGE(G86:G93)) -> 5.5766399 | O94: =AVERAGE(H90:H93) -> 6.75 | P94: =(H94-N94)^2 -> 2.4857932 | Q94: =(H94-O94)^2 -> 7.5625
B95: Beauty | C95: price_contribution | D95: CUUR0000SEGB | E95: 2026-04-24 | F95: 2024-06-30 | G95: ='Quarterly market'!G82 -> 1.654755 | H95: ='PG history'!H69 -> 3 | I95: =G95*G95 -> 2.7382141 | J95: =H95*H95 -> 9 | K95: =G95*H95 -> 4.964265 | L95: ='Model tests'!H11+'Model tests'!G11*G95 -> 2.9412805 | M95: =H95-L95 -> 0.058719499 | N95: =AVERAGE(H86:H94)+((SUM(K86:K94)-SUM(G86:G94)*SUM(H86:H94)/COUNT(G86:G94))/(SUM(I86:I94)-SUM(G86:G94)^2/COUNT(G86:G94)))*(G95-AVERAGE(G86:G94)) -> 3.7722463 | O95: =AVERAGE(H91:H94) -> 5.75 | P95: =(H95-N95)^2 -> 0.59636436 | Q95: =(H95-O95)^2 -> 7.5625
B96: Beauty | C96: price_contribution | D96: CUUR0000SEGB | E96: 2026-04-24 | F96: 2024-09-30 | G96: ='Quarterly market'!G83 -> 0.37330112 | H96: ='PG history'!H76 -> 1 | I96: =G96*G96 -> 0.13935372 | J96: =H96*H96 -> 1 | K96: =G96*H96 -> 0.37330112 | L96: ='Model tests'!H11+'Model tests'!G11*G96 -> 1.7067777 | M96: =H96-L96 -> -0.70677769 | N96: =AVERAGE(H86:H95)+((SUM(K86:K95)-SUM(G86:G95)*SUM(H86:H95)/COUNT(G86:G95))/(SUM(I86:I95)-SUM(G86:G95)^2/COUNT(G86:G95)))*(G96-AVERAGE(G86:G95)) -> 2.4782642 | O96: =AVERAGE(H92:H95) -> 4.5 | P96: =(H96-N96)^2 -> 2.1852652 | Q96: =(H96-O96)^2 -> 12.25
B97: Beauty | C97: price_contribution | D97: CUUR0000SEGB | E97: 2026-04-24 | F97: 2024-12-31 | G97: ='Quarterly market'!G84 -> 0.34106846 | H97: ='PG history'!H83 -> 2 | I97: =G97*G97 -> 0.11632769 | J97: =H97*H97 -> 4 | K97: =G97*H97 -> 0.68213691 | L97: ='Model tests'!H11+'Model tests'!G11*G97 -> 1.675726 | M97: =H97-L97 -> 0.324274 | N97: =AVERAGE(H86:H96)+((SUM(K86:K96)-SUM(G86:G96)*SUM(H86:H96)/COUNT(G86:G96))/(SUM(I86:I96)-SUM(G86:G96)^2/COUNT(G86:G96)))*(G97-AVERAGE(G86:G96)) -> 1.9622322 | O97: =AVERAGE(H93:H96) -> 3 | P97: =(H97-N97)^2 -> 0.0014264038 | Q97: =(H97-O97)^2 -> 1
B98: Beauty | C98: price_contribution | D98: CUUR0000SEGB | E98: 2026-04-24 | F98: 2025-03-31 | G98: ='Quarterly market'!G85 -> 0.2359462 | H98: ='PG history'!H90 -> 3 | I98: =G98*G98 -> 0.055670608 | J98: =H98*H98 -> 9 | K98: =G98*H98 -> 0.70783859 | L98: ='Model tests'!H11+'Model tests'!G11*G98 -> 1.5744553 | M98: =H98-L98 -> 1.4255447 | N98: =AVERAGE(H86:H97)+((SUM(K86:K97)-SUM(G86:G97)*SUM(H86:H97)/COUNT(G86:G97))/(SUM(I86:I97)-SUM(G86:G97)^2/COUNT(G86:G97)))*(G98-AVERAGE(G86:G97)) -> 1.8743494 | O98: =AVERAGE(H94:H97) -> 2.5 | P98: =(H98-N98)^2 -> 1.2670892 | Q98: =(H98-O98)^2 -> 0.25
B99: Beauty | C99: price_contribution | D99: CUUR0000SEGB | E99: 2026-04-24 | F99: 2025-06-30 | G99: ='Quarterly market'!G86 -> 0.5057825 | H99: ='PG history'!H97 -> 1 | I99: =G99*G99 -> 0.25581594 | J99: =H99*H99 -> 1 | K99: =G99*H99 -> 0.5057825 | L99: ='Model tests'!H11+'Model tests'!G11*G99 -> 1.8344051 | M99: =H99-L99 -> -0.8344051 | N99: =AVERAGE(H86:H98)+((SUM(K86:K98)-SUM(G86:G98)*SUM(H86:H98)/COUNT(G86:G98))/(SUM(I86:I98)-SUM(G86:G98)^2/COUNT(G86:G98)))*(G99-AVERAGE(G86:G98)) -> 2.3445928 | O99: =AVERAGE(H95:H98) -> 2.25 | P99: =(H99-N99)^2 -> 1.8079299 | Q99: =(H99-O99)^2 -> 1.5625
B100: Beauty | C100: price_contribution | D100: CUUR0000SEGB | E100: 2026-04-24 | F100: 2025-09-30 | G100: ='Quarterly market'!G87 -> 1.0082264 | H100: ='PG history'!H104 -> 2 | I100: =G100*G100 -> 1.0165205 | J100: =H100*H100 -> 4 | K100: =G100*H100 -> 2.0164529 | L100: ='Model tests'!H11+'Model tests'!G11*G100 -> 2.31844 | M100: =H100-L100 -> -0.31844003 | N100: =AVERAGE(H86:H99)+((SUM(K86:K99)-SUM(G86:G99)*SUM(H86:H99)/COUNT(G86:G99))/(SUM(I86:I99)-SUM(G86:G99)^2/COUNT(G86:G99)))*(G100-AVERAGE(G86:G99)) -> 2.5969526 | O100: =AVERAGE(H96:H99) -> 1.75 | P100: =(H100-N100)^2 -> 0.35635243 | Q100: =(H100-O100)^2 -> 0.0625
B101: Beauty | C101: price_contribution | D101: CUUR0000SEGB | E101: 2026-04-24 | F101: 2026-03-31 | G101: ='Quarterly market'!G88 -> 1.9491325 | H101: ='PG history'!H118 -> 1 | I101: =G101*G101 -> 3.7991176 | J101: =H101*H101 -> 1 | K101: =G101*H101 -> 1.9491325 | L101: ='Model tests'!H11+'Model tests'!G11*G101 -> 3.2248724 | M101: =H101-L101 -> -2.2248724 | N101: =AVERAGE(H86:H100)+((SUM(K86:K100)-SUM(G86:G100)*SUM(H86:H100)/COUNT(G86:G100))/(SUM(I86:I100)-SUM(G86:G100)^2/COUNT(G86:G100)))*(G101-AVERAGE(G86:G100)) -> 3.4086429 | O101: =AVERAGE(H97:H100) -> 2 | P101: =(H101-N101)^2 -> 5.8015606 | Q101: =(H101-O101)^2 -> 1
B102: Grooming | C102: price_contribution | D102: CUUR0000SEGB | E102: 2026-04-24 | F102: 2022-03-31 | G102: ='Quarterly market'!G73 -> 1.0280002 | H102: ='PG history'!H7 -> 6 | I102: =G102*G102 -> 1.0567844 | J102: =H102*H102 -> 36 | K102: =G102*H102 -> 6.1680012 | L102: ='Model tests'!H12+'Model tests'!G12*G102 -> 3.616256 | M102: =H102-L102 -> 2.383744
B103: Grooming | C103: price_contribution | D103: CUUR0000SEGB | E103: 2026-04-24 | F103: 2022-06-30 | G103: ='Quarterly market'!G74 -> 2.9122729 | H103: ='PG history'!H14 -> 6 | I103: =G103*G103 -> 8.4813337 | J103: =H103*H103 -> 36 | K103: =G103*H103 -> 17.473638 | L103: ='Model tests'!H12+'Model tests'!G12*G103 -> 5.7399531 | M103: =H103-L103 -> 0.26004686
...

Sheet Quarterly market
B2: Monthly to quarterly | Match periods first
B5: Series | C5: Known by | D5: Quarter ended | E5: Quarter level | F5: Prior-year level | G5: Year-on-year % | H5: Months
B6: RSHPCS | C6: 2026-04-24 | D6: 2022-03-31 | E6: =SUM('Monthly market'!E18,'Monthly market'!E19,'Monthly market'!E20) -> 97633 | F6: =SUM('Monthly market'!E6,'Monthly market'!E7,'Monthly market'!E8) -> 91538 | G6: =(E6/F6-1)*100 -> 6.6584369 | H6: 3
B7: RSHPCS | C7: 2026-04-24 | D7: 2022-06-30 | E7: =SUM('Monthly market'!E21,'Monthly market'!E22,'Monthly market'!E23) -> 98706 | F7: =SUM('Monthly market'!E9,'Monthly market'!E10,'Monthly market'!E11) -> 95612 | G7: =(E7/F7-1)*100 -> 3.2359955 | H7: 3
B8: RSHPCS | C8: 2026-04-24 | D8: 2022-09-30 | E8: =SUM('Monthly market'!E24,'Monthly market'!E25,'Monthly market'!E26) -> 100278 | F8: =SUM('Monthly market'!E12,'Monthly market'!E13,'Monthly market'!E14) -> 96837 | G8: =(E8/F8-1)*100 -> 3.5533938 | H8: 3
B9: RSHPCS | C9: 2026-04-24 | D9: 2022-12-31 | E9: =SUM('Monthly market'!E27,'Monthly market'!E28,'Monthly market'!E29) -> 100667 | F9: =SUM('Monthly market'!E15,'Monthly market'!E16,'Monthly market'!E17) -> 96979 | G9: =(E9/F9-1)*100 -> 3.8028852 | H9: 3
B10: RSHPCS | C10: 2026-04-24 | D10: 2023-03-31 | E10: =SUM('Monthly market'!E30,'Monthly market'!E31,'Monthly market'!E32) -> 104880 | F10: =SUM('Monthly market'!E18,'Monthly market'!E19,'Monthly market'!E20) -> 97633 | G10: =(E10/F10-1)*100 -> 7.4226952 | H10: 3
B11: RSHPCS | C11: 2026-04-24 | D11: 2023-06-30 | E11: =SUM('Monthly market'!E33,'Monthly market'!E34,'Monthly market'!E35) -> 106972 | F11: =SUM('Monthly market'!E21,'Monthly market'!E22,'Monthly market'!E23) -> 98706 | G11: =(E11/F11-1)*100 -> 8.3743643 | H11: 3
B12: RSHPCS | C12: 2026-04-24 | D12: 2023-09-30 | E12: =SUM('Monthly market'!E36,'Monthly market'!E37,'Monthly market'!E38) -> 107563 | F12: =SUM('Monthly market'!E24,'Monthly market'!E25,'Monthly market'!E26) -> 100278 | G12: =(E12/F12-1)*100 -> 7.2648038 | H12: 3
B13: RSHPCS | C13: 2026-04-24 | D13: 2023-12-31 | E13: =SUM('Monthly market'!E39,'Monthly market'!E40,'Monthly market'!E41) -> 110658 | F13: =SUM('Monthly market'!E27,'Monthly market'!E28,'Monthly market'!E29) -> 100667 | G13: =(E13/F13-1)*100 -> 9.9248016 | H13: 3
B14: RSHPCS | C14: 2026-04-24 | D14: 2024-03-31 | E14: =SUM('Monthly market'!E42,'Monthly market'!E43,'Monthly market'!E44) -> 107216 | F14: =SUM('Monthly market'!E30,'Monthly market'!E31,'Monthly market'!E32) -> 104880 | G14: =(E14/F14-1)*100 -> 2.2273074 | H14: 3
B15: RSHPCS | C15: 2026-04-24 | D15: 2024-06-30 | E15: =SUM('Monthly market'!E45,'Monthly market'!E46,'Monthly market'!E47) -> 107827 | F15: =SUM('Monthly market'!E33,'Monthly market'!E34,'Monthly market'!E35) -> 106972 | G15: =(E15/F15-1)*100 -> 0.79927458 | H15: 3
B16: RSHPCS | C16: 2026-04-24 | D16: 2024-09-30 | E16: =SUM('Monthly market'!E48,'Monthly market'!E49,'Monthly market'!E50) -> 113573 | F16: =SUM('Monthly market'!E36,'Monthly market'!E37,'Monthly market'!E38) -> 107563 | G16: =(E16/F16-1)*100 -> 5.5874232 | H16: 3
B17: RSHPCS | C17: 2026-04-24 | D17: 2024-12-31 | E17: =SUM('Monthly market'!E51,'Monthly market'!E52,'Monthly market'!E53) -> 114112 | F17: =SUM('Monthly market'!E39,'Monthly market'!E40,'Monthly market'!E41) -> 110658 | G17: =(E17/F17-1)*100 -> 3.1213288 | H17: 3
B18: RSHPCS | C18: 2026-04-24 | D18: 2025-03-31 | E18: =SUM('Monthly market'!E54,'Monthly market'!E55,'Monthly market'!E56) -> 115895 | F18: =SUM('Monthly market'!E42,'Monthly market'!E43,'Monthly market'!E44) -> 107216 | G18: =(E18/F18-1)*100 -> 8.0948739 | H18: 3
B19: RSHPCS | C19: 2026-04-24 | D19: 2025-06-30 | E19: =SUM('Monthly market'!E57,'Monthly market'!E58,'Monthly market'!E59) -> 117502 | F19: =SUM('Monthly market'!E45,'Monthly market'!E46,'Monthly market'!E47) -> 107827 | G19: =(E19/F19-1)*100 -> 8.9727063 | H19: 3
B20: RSHPCS | C20: 2026-04-24 | D20: 2025-09-30 | E20: =SUM('Monthly market'!E60,'Monthly market'!E61,'Monthly market'!E62) -> 120937 | F20: =SUM('Monthly market'!E48,'Monthly market'!E49,'Monthly market'!E50) -> 113573 | G20: =(E20/F20-1)*100 -> 6.4839354 | H20: 3
B21: RSHPCS | C21: 2026-04-24 | D21: 2025-12-31 | E21: =SUM('Monthly market'!E63,'Monthly market'!E64,'Monthly market'!E65) -> 120797 | F21: =SUM('Monthly market'!E51,'Monthly market'!E52,'Monthly market'!E53) -> 114112 | G21: =(E21/F21-1)*100 -> 5.8582796 | H21: 3
B22: RSHPCS | C22: 2026-04-24 | D22: 2026-03-31 | E22: =SUM('Monthly market'!E66,'Monthly market'!E67,'Monthly market'!E68) -> 118465 | F22: =SUM('Monthly market'!E54,'Monthly market'!E55,'Monthly market'!E56) -> 115895 | G22: =(E22/F22-1)*100 -> 2.2175245 | H22: 3
B23: RSHPCS | C23: 2026-05-15 | D23: 2022-03-31 | E23: =SUM('Monthly market'!E81,'Monthly market'!E82,'Monthly market'!E83) -> 97633 | F23: =SUM('Monthly market'!E69,'Monthly market'!E70,'Monthly market'!E71) -> 91538 | G23: =(E23/F23-1)*100 -> 6.6584369 | H23: 3
B24: RSHPCS | C24: 2026-05-15 | D24: 2022-06-30 | E24: =SUM('Monthly market'!E84,'Monthly market'!E85,'Monthly market'!E86) -> 98706 | F24: =SUM('Monthly market'!E72,'Monthly market'!E73,'Monthly market'!E74) -> 95612 | G24: =(E24/F24-1)*100 -> 3.2359955 | H24: 3
B25: RSHPCS | C25: 2026-05-15 | D25: 2022-09-30 | E25: =SUM('Monthly market'!E87,'Monthly market'!E88,'Monthly market'!E89) -> 100278 | F25: =SUM('Monthly market'!E75,'Monthly market'!E76,'Monthly market'!E77) -> 96837 | G25: =(E25/F25-1)*100 -> 3.5533938 | H25: 3
B26: RSHPCS | C26: 2026-05-15 | D26: 2022-12-31 | E26: =SUM('Monthly market'!E90,'Monthly market'!E91,'Monthly market'!E92) -> 100667 | F26: =SUM('Monthly market'!E78,'Monthly market'!E79,'Monthly market'!E80) -> 96979 | G26: =(E26/F26-1)*100 -> 3.8028852 | H26: 3
B27: RSHPCS | C27: 2026-05-15 | D27: 2023-03-31 | E27: =SUM('Monthly market'!E93,'Monthly market'!E94,'Monthly market'!E95) -> 104880 | F27: =SUM('Monthly market'!E81,'Monthly market'!E82,'Monthly market'!E83) -> 97633 | G27: =(E27/F27-1)*100 -> 7.4226952 | H27: 3
B28: RSHPCS | C28: 2026-05-15 | D28: 2023-06-30 | E28: =SUM('Monthly market'!E96,'Monthly market'!E97,'Monthly market'!E98) -> 106972 | F28: =SUM('Monthly market'!E84,'Monthly market'!E85,'Monthly market'!E86) -> 98706 | G28: =(E28/F28-1)*100 -> 8.3743643 | H28: 3
B29: RSHPCS | C29: 2026-05-15 | D29: 2023-09-30 | E29: =SUM('Monthly market'!E99,'Monthly market'!E100,'Monthly market'!E101) -> 107563 | F29: =SUM('Monthly market'!E87,'Monthly market'!E88,'Monthly market'!E89) -> 100278 | G29: =(E29/F29-1)*100 -> 7.2648038 | H29: 3
B30: RSHPCS | C30: 2026-05-15 | D30: 2023-12-31 | E30: =SUM('Monthly market'!E102,'Monthly market'!E103,'Monthly market'!E104) -> 110658 | F30: =SUM('Monthly market'!E90,'Monthly market'!E91,'Monthly market'!E92) -> 100667 | G30: =(E30/F30-1)*100 -> 9.9248016 | H30: 3
B31: RSHPCS | C31: 2026-05-15 | D31: 2024-03-31 | E31: =SUM('Monthly market'!E105,'Monthly market'!E106,'Monthly market'!E107) -> 107216 | F31: =SUM('Monthly market'!E93,'Monthly market'!E94,'Monthly market'!E95) -> 104880 | G31: =(E31/F31-1)*100 -> 2.2273074 | H31: 3
B32: RSHPCS | C32: 2026-05-15 | D32: 2024-06-30 | E32: =SUM('Monthly market'!E108,'Monthly market'!E109,'Monthly market'!E110) -> 107827 | F32: =SUM('Monthly market'!E96,'Monthly market'!E97,'Monthly market'!E98) -> 106972 | G32: =(E32/F32-1)*100 -> 0.79927458 | H32: 3
B33: RSHPCS | C33: 2026-05-15 | D33: 2024-09-30 | E33: =SUM('Monthly market'!E111,'Monthly market'!E112,'Monthly market'!E113) -> 113573 | F33: =SUM('Monthly market'!E99,'Monthly market'!E100,'Monthly market'!E101) -> 107563 | G33: =(E33/F33-1)*100 -> 5.5874232 | H33: 3
B34: RSHPCS | C34: 2026-05-15 | D34: 2024-12-31 | E34: =SUM('Monthly market'!E114,'Monthly market'!E115,'Monthly market'!E116) -> 114112 | F34: =SUM('Monthly market'!E102,'Monthly market'!E103,'Monthly market'!E104) -> 110658 | G34: =(E34/F34-1)*100 -> 3.1213288 | H34: 3
B35: RSHPCS | C35: 2026-05-15 | D35: 2025-03-31 | E35: =SUM('Monthly market'!E117,'Monthly market'!E118,'Monthly market'!E119) -> 115816 | F35: =SUM('Monthly market'!E105,'Monthly market'!E106,'Monthly market'!E107) -> 107216 | G35: =(E35/F35-1)*100 -> 8.0211909 | H35: 3
B36: RSHPCS | C36: 2026-05-15 | D36: 2025-06-30 | E36: =SUM('Monthly market'!E120,'Monthly market'!E121,'Monthly market'!E122) -> 117819 | F36: =SUM('Monthly market'!E108,'Monthly market'!E109,'Monthly market'!E110) -> 107827 | G36: =(E36/F36-1)*100 -> 9.2666957 | H36: 3
B37: RSHPCS | C37: 2026-05-15 | D37: 2025-09-30 | E37: =SUM('Monthly market'!E123,'Monthly market'!E124,'Monthly market'!E125) -> 120937 | F37: =SUM('Monthly market'!E111,'Monthly market'!E112,'Monthly market'!E113) -> 113573 | G37: =(E37/F37-1)*100 -> 6.4839354 | H37: 3
B38: RSHPCS | C38: 2026-05-15 | D38: 2025-12-31 | E38: =SUM('Monthly market'!E126,'Monthly market'!E127,'Monthly market'!E128) -> 120797 | F38: =SUM('Monthly market'!E114,'Monthly market'!E115,'Monthly market'!E116) -> 114112 | G38: =(E38/F38-1)*100 -> 5.8582796 | H38: 3
B39: RSHPCS | C39: 2026-05-15 | D39: 2026-03-31 | E39: =SUM('Monthly market'!E129,'Monthly market'!E130,'Monthly market'!E131) -> 118700 | F39: =SUM('Monthly market'!E117,'Monthly market'!E118,'Monthly market'!E119) -> 115816 | G39: =(E39/F39-1)*100 -> 2.4901568 | H39: 3
B40: PCENDC96 | C40: 2026-04-24 | D40: 2022-03-31 | E40: =AVERAGE('Monthly market'!E145,'Monthly market'!E146,'Monthly market'!E147) -> 3334.4 | F40: =AVERAGE('Monthly market'!E133,'Monthly market'!E134,'Monthly market'!E135) -> 3218.5667 | G40: =(E40/F40-1)*100 -> 3.5989105 | H40: 3
B41: PCENDC96 | C41: 2026-04-24 | D41: 2022-06-30 | E41: =AVERAGE('Monthly market'!E148,'Monthly market'!E149,'Monthly market'!E150) -> 3335.0333 | F41: =AVERAGE('Monthly market'!E136,'Monthly market'!E137,'Monthly market'!E138) -> 3336.3 | G41: =(E41/F41-1)*100 -> -0.03796621 | H41: 3
B42: PCENDC96 | C42: 2026-04-24 | D42: 2022-09-30 | E42: =AVERAGE('Monthly market'!E151,'Monthly market'!E152,'Monthly market'!E153) -> 3310.0667 | F42: =AVERAGE('Monthly market'!E139,'Monthly market'!E140,'Monthly market'!E141) -> 3342.6333 | G42: =(E42/F42-1)*100 -> -0.97428175 | H42: 3
B43: PCENDC96 | C43: 2026-04-24 | D43: 2022-12-31 | E43: =AVERAGE('Monthly market'!E154,'Monthly market'!E155,'Monthly market'!E156) -> 3302.6 | F43: =AVERAGE('Monthly market'!E142,'Monthly market'!E143,'Monthly market'!E144) -> 3360 | G43: =(E43/F43-1)*100 -> -1.7083333 | H43: 3
B44: PCENDC96 | C44: 2026-04-24 | D44: 2023-03-31 | E44: =AVERAGE('Monthly market'!E157,'Monthly market'!E158,'Monthly market'!E159) -> 3317.2667 | F44: =AVERAGE('Monthly market'!E145,'Monthly market'!E146,'Monthly market'!E147) -> 3334.4 | G44: =(E44/F44-1)*100 -> -0.51383557 | H44: 3
B45: PCENDC96 | C45: 2026-04-24 | D45: 2023-06-30 | E45: =AVERAGE('Monthly market'!E160,'Monthly market'!E161,'Monthly market'!E162) -> 3322.2333 | F45: =AVERAGE('Monthly market'!E148,'Monthly market'!E149,'Monthly market'!E150) -> 3335.0333 | G45: =(E45/F45-1)*100 -> -0.38380426 | H45: 3
B46: PCENDC96 | C46: 2026-04-24 | D46: 2023-09-30 | E46: =AVERAGE('Monthly market'!E163,'Monthly market'!E164,'Monthly market'!E165) -> 3349.4333 | F46: =AVERAGE('Monthly market'!E151,'Monthly market'!E152,'Monthly market'!E153) -> 3310.0667 | G46: =(E46/F46-1)*100 -> 1.1893013 | H46: 3
B47: PCENDC96 | C47: 2026-04-24 | D47: 2023-12-31 | E47: =AVERAGE('Monthly market'!E166,'Monthly market'!E167,'Monthly market'!E168) -> 3376.1 | F47: =AVERAGE('Monthly market'!E154,'Monthly market'!E155,'Monthly market'!E156) -> 3302.6 | G47: =(E47/F47-1)*100 -> 2.2255193 | H47: 3
B48: PCENDC96 | C48: 2026-04-24 | D48: 2024-03-31 | E48: =AVERAGE('Monthly market'!E169,'Monthly market'!E170,'Monthly market'!E171) -> 3362.8 | F48: =AVERAGE('Monthly market'!E157,'Monthly market'!E158,'Monthly market'!E159) -> 3317.2667 | G48: =(E48/F48-1)*100 -> 1.372616 | H48: 3
B49: PCENDC96 | C49: 2026-04-24 | D49: 2024-06-30 | E49: =AVERAGE('Monthly market'!E172,'Monthly market'!E173,'Monthly market'!E174) -> 3398 | F49: =AVERAGE('Monthly market'!E160,'Monthly market'!E161,'Monthly market'!E162) -> 3322.2333 | G49: =(E49/F49-1)*100 -> 2.2805944 | H49: 3
B50: PCENDC96 | C50: 2026-04-24 | D50: 2024-09-30 | E50: =AVERAGE('Monthly market'!E175,'Monthly market'!E176,'Monthly market'!E177) -> 3438.2 | F50: =AVERAGE('Monthly market'!E163,'Monthly market'!E164,'Monthly market'!E165) -> 3349.4333 | G50: =(E50/F50-1)*100 -> 2.6501995 | H50: 3
B51: PCENDC96 | C51: 2026-04-24 | D51: 2024-12-31 | E51: =AVERAGE('Monthly market'!E178,'Monthly market'!E179,'Monthly market'!E180) -> 3470.2 | F51: =AVERAGE('Monthly market'!E166,'Monthly market'!E167,'Monthly market'!E168) -> 3376.1 | G51: =(E51/F51-1)*100 -> 2.7872397 | H51: 3
B52: PCENDC96 | C52: 2026-04-24 | D52: 2025-03-31 | E52: =AVERAGE('Monthly market'!E181,'Monthly market'!E182,'Monthly market'!E183) -> 3488.9 | F52: =AVERAGE('Monthly market'!E169,'Monthly market'!E170,'Monthly market'!E171) -> 3362.8 | G52: =(E52/F52-1)*100 -> 3.7498513 | H52: 3
B53: PCENDC96 | C53: 2026-04-24 | D53: 2025-06-30 | E53: =AVERAGE('Monthly market'!E184,'Monthly market'!E185,'Monthly market'!E186) -> 3507.8667 | F53: =AVERAGE('Monthly market'!E172,'Monthly market'!E173,'Monthly market'!E174) -> 3398 | G53: =(E53/F53-1)*100 -> 3.2332745 | H53: 3
B54: PCENDC96 | C54: 2026-04-24 | D54: 2025-09-30 | E54: =AVERAGE('Monthly market'!E187,'Monthly market'!E188,'Monthly market'!E189) -> 3541.2333 | F54: =AVERAGE('Monthly market'!E175,'Monthly market'!E176,'Monthly market'!E177) -> 3438.2 | G54: =(E54/F54-1)*100 -> 2.9967231 | H54: 3
B55: PCENDC96 | C55: 2026-04-24 | D55: 2025-12-31 | E55: =AVERAGE('Monthly market'!E190,'Monthly market'!E191,'Monthly market'!E192) -> 3544.7333 | F55: =AVERAGE('Monthly market'!E178,'Monthly market'!E179,'Monthly market'!E180) -> 3470.2 | G55: =(E55/F55-1)*100 -> 2.1478109 | H55: 3
B56: PCENDC96 | C56: 2026-05-15 | D56: 2022-03-31 | E56: =AVERAGE('Monthly market'!E207,'Monthly market'!E208,'Monthly market'!E209) -> 3334.4 | F56: =AVERAGE('Monthly market'!E195,'Monthly market'!E196,'Monthly market'!E197) -> 3218.5667 | G56: =(E56/F56-1)*100 -> 3.5989105 | H56: 3
B57: PCENDC96 | C57: 2026-05-15 | D57: 2022-06-30 | E57: =AVERAGE('Monthly market'!E210,'Monthly market'!E211,'Monthly market'!E212) -> 3335.0333 | F57: =AVERAGE('Monthly market'!E198,'Monthly market'!E199,'Monthly market'!E200) -> 3336.3 | G57: =(E57/F57-1)*100 -> -0.03796621 | H57: 3
B58: PCENDC96 | C58: 2026-05-15 | D58: 2022-09-30 | E58: =AVERAGE('Monthly market'!E213,'Monthly market'!E214,'Monthly market'!E215) -> 3310.0667 | F58: =AVERAGE('Monthly market'!E201,'Monthly market'!E202,'Monthly market'!E203) -> 3342.6333 | G58: =(E58/F58-1)*100 -> -0.97428175 | H58: 3
B59: PCENDC96 | C59: 2026-05-15 | D59: 2022-12-31 | E59: =AVERAGE('Monthly market'!E216,'Monthly market'!E217,'Monthly market'!E218) -> 3302.6 | F59: =AVERAGE('Monthly market'!E204,'Monthly market'!E205,'Monthly market'!E206) -> 3360 | G59: =(E59/F59-1)*100 -> -1.7083333 | H59: 3
B60: PCENDC96 | C60: 2026-05-15 | D60: 2023-03-31 | E60: =AVERAGE('Monthly market'!E219,'Monthly market'!E220,'Monthly market'!E221) -> 3317.2667 | F60: =AVERAGE('Monthly market'!E207,'Monthly market'!E208,'Monthly market'!E209) -> 3334.4 | G60: =(E60/F60-1)*100 -> -0.51383557 | H60: 3
B61: PCENDC96 | C61: 2026-05-15 | D61: 2023-06-30 | E61: =AVERAGE('Monthly market'!E222,'Monthly market'!E223,'Monthly market'!E224) -> 3322.2333 | F61: =AVERAGE('Monthly market'!E210,'Monthly market'!E211,'Monthly market'!E212) -> 3335.0333 | G61: =(E61/F61-1)*100 -> -0.38380426 | H61: 3
B62: PCENDC96 | C62: 2026-05-15 | D62: 2023-09-30 | E62: =AVERAGE('Monthly market'!E225,'Monthly market'!E226,'Monthly market'!E227) -> 3349.4333 | F62: =AVERAGE('Monthly market'!E213,'Monthly market'!E214,'Monthly market'!E215) -> 3310.0667 | G62: =(E62/F62-1)*100 -> 1.1893013 | H62: 3
B63: PCENDC96 | C63: 2026-05-15 | D63: 2023-12-31 | E63: =AVERAGE('Monthly market'!E228,'Monthly market'!E229,'Monthly market'!E230) -> 3376.1 | F63: =AVERAGE('Monthly market'!E216,'Monthly market'!E217,'Monthly market'!E218) -> 3302.6 | G63: =(E63/F63-1)*100 -> 2.2255193 | H63: 3
B64: PCENDC96 | C64: 2026-05-15 | D64: 2024-03-31 | E64: =AVERAGE('Monthly market'!E231,'Monthly market'!E232,'Monthly market'!E233) -> 3362.8 | F64: =AVERAGE('Monthly market'!E219,'Monthly market'!E220,'Monthly market'!E221) -> 3317.2667 | G64: =(E64/F64-1)*100 -> 1.372616 | H64: 3
B65: PCENDC96 | C65: 2026-05-15 | D65: 2024-06-30 | E65: =AVERAGE('Monthly market'!E234,'Monthly market'!E235,'Monthly market'!E236) -> 3398 | F65: =AVERAGE('Monthly market'!E222,'Monthly market'!E223,'Monthly market'!E224) -> 3322.2333 | G65: =(E65/F65-1)*100 -> 2.2805944 | H65: 3
B66: PCENDC96 | C66: 2026-05-15 | D66: 2024-09-30 | E66: =AVERAGE('Monthly market'!E237,'Monthly market'!E238,'Monthly market'!E239) -> 3438.2 | F66: =AVERAGE('Monthly market'!E225,'Monthly market'!E226,'Monthly market'!E227) -> 3349.4333 | G66: =(E66/F66-1)*100 -> 2.6501995 | H66: 3
B67: PCENDC96 | C67: 2026-05-15 | D67: 2024-12-31 | E67: =AVERAGE('Monthly market'!E240,'Monthly market'!E241,'Monthly market'!E242) -> 3470.2 | F67: =AVERAGE('Monthly market'!E228,'Monthly market'!E229,'Monthly market'!E230) -> 3376.1 | G67: =(E67/F67-1)*100 -> 2.7872397 | H67: 3
B68: PCENDC96 | C68: 2026-05-15 | D68: 2025-03-31 | E68: =AVERAGE('Monthly market'!E243,'Monthly market'!E244,'Monthly market'!E245) -> 3488.9 | F68: =AVERAGE('Monthly market'!E231,'Monthly market'!E232,'Monthly market'!E233) -> 3362.8 | G68: =(E68/F68-1)*100 -> 3.7498513 | H68: 3
B69: PCENDC96 | C69: 2026-05-15 | D69: 2025-06-30 | E69: =AVERAGE('Monthly market'!E246,'Monthly market'!E247,'Monthly market'!E248) -> 3507.8667 | F69: =AVERAGE('Monthly market'!E234,'Monthly market'!E235,'Monthly market'!E236) -> 3398 | G69: =(E69/F69-1)*100 -> 3.2332745 | H69: 3
B70: PCENDC96 | C70: 2026-05-15 | D70: 2025-09-30 | E70: =AVERAGE('Monthly market'!E249,'Monthly market'!E250,'Monthly market'!E251) -> 3541.2333 | F70: =AVERAGE('Monthly market'!E237,'Monthly market'!E238,'Monthly market'!E239) -> 3438.2 | G70: =(E70/F70-1)*100 -> 2.9967231 | H70: 3
B71: PCENDC96 | C71: 2026-05-15 | D71: 2025-12-31 | E71: =AVERAGE('Monthly market'!E252,'Monthly market'!E253,'Monthly market'!E254) -> 3544.7333 | F71: =AVERAGE('Monthly market'!E240,'Monthly market'!E241,'Monthly market'!E242) -> 3470.2 | G71: =(E71/F71-1)*100 -> 2.1478109 | H71: 3
B72: PCENDC96 | C72: 2026-05-15 | D72: 2026-03-31 | E72: =AVERAGE('Monthly market'!E255,'Monthly market'!E256,'Monthly market'!E257) -> 3542.9 | F72: =AVERAGE('Monthly market'!E243,'Monthly market'!E244,'Monthly market'!E245) -> 3488.9 | G72: =(E72/F72-1)*100 -> 1.5477658 | H72: 3
B73: CUUR0000SEGB | C73: 2026-04-24 | D73: 2022-03-31 | E73: =AVERAGE('Monthly market'!E270,'Monthly market'!E271,'Monthly market'!E272) -> 161.63167 | F73: =AVERAGE('Monthly market'!E258,'Monthly market'!E259,'Monthly market'!E260) -> 159.987 | G73: =(E73/F73-1)*100 -> 1.0280002 | H73: 3
B74: CUUR0000SEGB | C74: 2026-04-24 | D74: 2022-06-30 | E74: =AVERAGE('Monthly market'!E273,'Monthly market'!E274,'Monthly market'!E275) -> 164.41333 | F74: =AVERAGE('Monthly market'!E261,'Monthly market'!E262,'Monthly market'!E263) -> 159.76067 | G74: =(E74/F74-1)*100 -> 2.9122729 | H74: 3
B75: CUUR0000SEGB | C75: 2026-04-24 | D75: 2022-09-30 | E75: =AVERAGE('Monthly market'!E276,'Monthly market'!E277,'Monthly market'!E278) -> 168.94833 | F75: =AVERAGE('Monthly market'!E264,'Monthly market'!E265,'Monthly market'!E266) -> 159.61067 | G75: =(E75/F75-1)*100 -> 5.8502773 | H75: 3
B76: CUUR0000SEGB | C76: 2026-04-24 | D76: 2022-12-31 | E76: =AVERAGE('Monthly market'!E279,'Monthly market'!E280,'Monthly market'!E281) -> 171.058 | F76: =AVERAGE('Monthly market'!E267,'Monthly market'!E268,'Monthly market'!E269) -> 159.48567 | G76: =(E76/F76-1)*100 -> 7.2560335 | H76: 3
B77: CUUR0000SEGB | C77: 2026-04-24 | D77: 2023-03-31 | E77: =AVERAGE('Monthly market'!E282,'Monthly market'!E283,'Monthly market'!E284) -> 172.578 | F77: =AVERAGE('Monthly market'!E270,'Monthly market'!E271,'Monthly market'!E272) -> 161.63167 | G77: =(E77/F77-1)*100 -> 6.772394 | H77: 3
B78: CUUR0000SEGB | C78: 2026-04-24 | D78: 2023-06-30 | E78: =AVERAGE('Monthly market'!E285,'Monthly market'!E286,'Monthly market'!E287) -> 176.018 | F78: =AVERAGE('Monthly market'!E273,'Monthly market'!E274,'Monthly market'!E275) -> 164.41333 | G78: =(E78/F78-1)*100 -> 7.0582272 | H78: 3
B79: CUUR0000SEGB | C79: 2026-04-24 | D79: 2023-09-30 | E79: =AVERAGE('Monthly market'!E288,'Monthly market'!E289,'Monthly market'!E290) -> 178.22967 | F79: =AVERAGE('Monthly market'!E276,'Monthly market'!E277,'Monthly market'!E278) -> 168.94833 | G79: =(E79/F79-1)*100 -> 5.4935927 | H79: 3
B80: CUUR0000SEGB | C80: 2026-04-24 | D80: 2023-12-31 | E80: =AVERAGE('Monthly market'!E291,'Monthly market'!E292,'Monthly market'!E293) -> 178.26333 | F80: =AVERAGE('Monthly market'!E279,'Monthly market'!E280,'Monthly market'!E281) -> 171.058 | G80: =(E80/F80-1)*100 -> 4.2122165 | H80: 3
B81: CUUR0000SEGB | C81: 2026-04-24 | D81: 2024-03-31 | E81: =AVERAGE('Monthly market'!E294,'Monthly market'!E295,'Monthly market'!E296) -> 178.85433 | F81: =AVERAGE('Monthly market'!E282,'Monthly market'!E283,'Monthly market'!E284) -> 172.578 | G81: =(E81/F81-1)*100 -> 3.6368096 | H81: 3
B82: CUUR0000SEGB | C82: 2026-04-24 | D82: 2024-06-30 | E82: =AVERAGE('Monthly market'!E297,'Monthly market'!E298,'Monthly market'!E299) -> 178.93067 | F82: =AVERAGE('Monthly market'!E285,'Monthly market'!E286,'Monthly market'!E287) -> 176.018 | G82: =(E82/F82-1)*100 -> 1.654755 | H82: 3
B83: CUUR0000SEGB | C83: 2026-04-24 | D83: 2024-09-30 | E83: =AVERAGE('Monthly market'!E300,'Monthly market'!E301,'Monthly market'!E302) -> 178.895 | F83: =AVERAGE('Monthly market'!E288,'Monthly market'!E289,'Monthly market'!E290) -> 178.22967 | G83: =(E83/F83-1)*100 -> 0.37330112 | H83: 3
B84: CUUR0000SEGB | C84: 2026-04-24 | D84: 2024-12-31 | E84: =AVERAGE('Monthly market'!E303,'Monthly market'!E304,'Monthly market'!E305) -> 178.87133 | F84: =AVERAGE('Monthly market'!E291,'Monthly market'!E292,'Monthly market'!E293) -> 178.26333 | G84: =(E84/F84-1)*100 -> 0.34106846 | H84: 3
B85: CUUR0000SEGB | C85: 2026-04-24 | D85: 2025-03-31 | E85: =AVERAGE('Monthly market'!E306,'Monthly market'!E307,'Monthly market'!E308) -> 179.27633 | F85: =AVERAGE('Monthly market'!E294,'Monthly market'!E295,'Monthly market'!E296) -> 178.85433 | G85: =(E85/F85-1)*100 -> 0.2359462 | H85: 3
B86: CUUR0000SEGB | C86: 2026-04-24 | D86: 2025-06-30 | E86: =AVERAGE('Monthly market'!E309,'Monthly market'!E310,'Monthly market'!E311) -> 179.83567 | F86: =AVERAGE('Monthly market'!E297,'Monthly market'!E298,'Monthly market'!E299) -> 178.93067 | G86: =(E86/F86-1)*100 -> 0.5057825 | H86: 3
B87: CUUR0000SEGB | C87: 2026-04-24 | D87: 2025-09-30 | E87: =AVERAGE('Monthly market'!E312,'Monthly market'!E313,'Monthly market'!E314) -> 180.69867 | F87: =AVERAGE('Monthly market'!E300,'Monthly market'!E301,'Monthly market'!E302) -> 178.895 | G87: =(E87/F87-1)*100 -> 1.0082264 | H87: 3
B88: CUUR0000SEGB | C88: 2026-04-24 | D88: 2026-03-31 | E88: =AVERAGE('Monthly market'!E317,'Monthly market'!E318,'Monthly market'!E319) -> 182.77067 | F88: =AVERAGE('Monthly market'!E306,'Monthly market'!E307,'Monthly market'!E308) -> 179.27633 | G88: =(E88/F88-1)*100 -> 1.9491325 | H88: 3
B89: CUUR0000SEGB | C89: 2026-05-15 | D89: 2022-03-31 | E89: =AVERAGE('Monthly market'!E332,'Monthly market'!E333,'Monthly market'!E334) -> 161.63167 | F89: =AVERAGE('Monthly market'!E320,'Monthly market'!E321,'Monthly market'!E322) -> 159.987 | G89: =(E89/F89-1)*100 -> 1.0280002 | H89: 3
B90: CUUR0000SEGB | C90: 2026-05-15 | D90: 2022-06-30 | E90: =AVERAGE('Monthly market'!E335,'Monthly market'!E336,'Monthly market'!E337) -> 164.41333 | F90: =AVERAGE('Monthly market'!E323,'Monthly market'!E324,'Monthly market'!E325) -> 159.76067 | G90: =(E90/F90-1)*100 -> 2.9122729 | H90: 3
B91: CUUR0000SEGB | C91: 2026-05-15 | D91: 2022-09-30 | E91: =AVERAGE('Monthly market'!E338,'Monthly market'!E339,'Monthly market'!E340) -> 168.94833 | F91: =AVERAGE('Monthly market'!E326,'Monthly market'!E327,'Monthly market'!E328) -> 159.61067 | G91: =(E91/F91-1)*100 -> 5.8502773 | H91: 3
B92: CUUR0000SEGB | C92: 2026-05-15 | D92: 2022-12-31 | E92: =AVERAGE('Monthly market'!E341,'Monthly market'!E342,'Monthly market'!E343) -> 171.058 | F92: =AVERAGE('Monthly market'!E329,'Monthly market'!E330,'Monthly market'!E331) -> 159.48567 | G92: =(E92/F92-1)*100 -> 7.2560335 | H92: 3
B93: CUUR0000SEGB | C93: 2026-05-15 | D93: 2023-03-31 | E93: =AVERAGE('Monthly market'!E344,'Monthly market'!E345,'Monthly market'!E346) -> 172.578 | F93: =AVERAGE('Monthly market'!E332,'Monthly market'!E333,'Monthly market'!E334) -> 161.63167 | G93: =(E93/F93-1)*100 -> 6.772394 | H93: 3
B94: CUUR0000SEGB | C94: 2026-05-15 | D94: 2023-06-30 | E94: =AVERAGE('Monthly market'!E347,'Monthly market'!E348,'Monthly market'!E349) -> 176.018 | F94: =AVERAGE('Monthly market'!E335,'Monthly market'!E336,'Monthly market'!E337) -> 164.41333 | G94: =(E94/F94-1)*100 -> 7.0582272 | H94: 3
B95: CUUR0000SEGB | C95: 2026-05-15 | D95: 2023-09-30 | E95: =AVERAGE('Monthly market'!E350,'Monthly market'!E351,'Monthly market'!E352) -> 178.22967 | F95: =AVERAGE('Monthly market'!E338,'Monthly market'!E339,'Monthly market'!E340) -> 168.94833 | G95: =(E95/F95-1)*100 -> 5.4935927 | H95: 3
B96: CUUR0000SEGB | C96: 2026-05-15 | D96: 2023-12-31 | E96: =AVERAGE('Monthly market'!E353,'Monthly market'!E354,'Monthly market'!E355) -> 178.26333 | F96: =AVERAGE('Monthly market'!E341,'Monthly market'!E342,'Monthly market'!E343) -> 171.058 | G96: =(E96/F96-1)*100 -> 4.2122165 | H96: 3
B97: CUUR0000SEGB | C97: 2026-05-15 | D97: 2024-03-31 | E97: =AVERAGE('Monthly market'!E356,'Monthly market'!E357,'Monthly market'!E358) -> 178.85433 | F97: =AVERAGE('Monthly market'!E344,'Monthly market'!E345,'Monthly market'!E346) -> 172.578 | G97: =(E97/F97-1)*100 -> 3.6368096 | H97: 3
B98: CUUR0000SEGB | C98: 2026-05-15 | D98: 2024-06-30 | E98: =AVERAGE('Monthly market'!E359,'Monthly market'!E360,'Monthly market'!E361) -> 178.93067 | F98: =AVERAGE('Monthly market'!E347,'Monthly market'!E348,'Monthly market'!E349) -> 176.018 | G98: =(E98/F98-1)*100 -> 1.654755 | H98: 3
B99: CUUR0000SEGB | C99: 2026-05-15 | D99: 2024-09-30 | E99: =AVERAGE('Monthly market'!E362,'Monthly market'!E363,'Monthly market'!E364) -> 178.895 | F99: =AVERAGE('Monthly market'!E350,'Monthly market'!E351,'Monthly market'!E352) -> 178.22967 | G99: =(E99/F99-1)*100 -> 0.37330112 | H99: 3
B100: CUUR0000SEGB | C100: 2026-05-15 | D100: 2024-12-31 | E100: =AVERAGE('Monthly market'!E365,'Monthly market'!E366,'Monthly market'!E367) -> 178.87133 | F100: =AVERAGE('Monthly market'!E353,'Monthly market'!E354,'Monthly market'!E355) -> 178.26333 | G100: =(E100/F100-1)*100 -> 0.34106846 | H100: 3
B101: CUUR0000SEGB | C101: 2026-05-15 | D101: 2025-03-31 | E101: =AVERAGE('Monthly market'!E368,'Monthly market'!E369,'Monthly market'!E370) -> 179.27633 | F101: =AVERAGE('Monthly market'!E356,'Monthly market'!E357,'Monthly market'!E358) -> 178.85433 | G101: =(E101/F101-1)*100 -> 0.2359462 | H101: 3
B102: CUUR0000SEGB | C102: 2026-05-15 | D102: 2025-06-30 | E102: =AVERAGE('Monthly market'!E371,'Monthly market'!E372,'Monthly market'!E373) -> 179.83567 | F102: =AVERAGE('Monthly market'!E359,'Monthly market'!E360,'Monthly market'!E361) -> 178.93067 | G102: =(E102/F102-1)*100 -> 0.5057825 | H102: 3
B103: CUUR0000SEGB | C103: 2026-05-15 | D103: 2025-09-30 | E103: =AVERAGE('Monthly market'!E374,'Monthly market'!E375,'Monthly market'!E376) -> 180.69867 | F103: =AVERAGE('Monthly market'!E362,'Monthly market'!E363,'Monthly market'!E364) -> 178.895 | G103: =(E103/F103-1)*100 -> 1.0082264 | H103: 3
...

Sheet PG history
B2: P&G | Quarterly facts
B3: January 2022–March 2026. Sales in USD millions; growth and contributions in %.
B5: Quarter ended | C5: Business segment | D5: Net sales | E5: Sales growth | F5: Organic growth | G5: Organic volume | H5: Pricing | I5: Mix | J5: FX | K5: Published
B6: 2022-03-31 | C6: Beauty | D6: 3389 | E6: 2 | F6: 3 | G6: -1 | H6: 4 | I6: 0 | J6: -2 | K6: 2022-04-20
B7: 2022-03-31 | C7: Grooming | D7: 1481 | E7: 3 | F7: 8 | G7: 1 | H7: 6 | I7: 1 | J7: -5 | K7: 2022-04-20
B8: 2022-03-31 | C8: Health Care | D8: 2662 | E8: 13 | F8: 16 | G8: 8 | H8: 3 | I8: 5 | J8: -3 | K8: 2022-04-20
B9: 2022-03-31 | C9: Fabric & Home Care | D9: 6699 | E9: 7 | F9: 10 | G9: 5 | H9: 5 | I9: 1 | J9: -3 | K9: 2022-04-20
B10: 2022-03-31 | C10: Baby, Feminine & Family Care | D10: 4935 | E10: 7 | F10: 10 | G10: 2 | H10: 5 | I10: 2 | J10: -3 | K10: 2022-04-20
B11: 2022-03-31 | C11: Corporate | D11: 215 | K11: 2022-04-20
B12: 2022-03-31 | C12: Total Company | D12: 19381 | E12: 7 | F12: 10 | G12: 3 | H12: 5 | I12: 2 | J12: -3 | K12: 2022-04-20
B13: 2022-06-30 | C13: Beauty | D13: 3461 | E13: -1 | F13: 0 | G13: -2 | H13: 6 | I13: -4 | J13: -3 | K13: 2022-07-29
B14: 2022-06-30 | C14: Grooming | D14: 1608 | E14: -3 | F14: 3 | G14: -2 | H14: 6 | I14: -1 | J14: -6 | K14: 2022-07-29
B15: 2022-06-30 | C15: Health Care | D15: 2510 | E15: 5 | F15: 9 | G15: 0 | H15: 5 | I15: 4 | J15: -4 | K15: 2022-07-29
B16: 2022-06-30 | C16: Fabric & Home Care | D16: 6876 | E16: 4 | F16: 9 | G16: -1 | H16: 10 | I16: 0 | J16: -5 | K16: 2022-07-29
B17: 2022-06-30 | C17: Baby, Feminine & Family Care | D17: 4821 | E17: 3 | F17: 7 | G17: 0 | H17: 6 | I17: 1 | J17: -3 | K17: 2022-07-29
B18: 2022-06-30 | C18: Corporate | D18: 239 | K18: 2022-07-29
B19: 2022-06-30 | C19: Total Company | D19: 19515 | E19: 3 | F19: 7 | G19: -1 | H19: 8 | I19: 0 | J19: -4 | K19: 2022-07-29
B20: 2022-09-30 | C20: Beauty | D20: 3961 | E20: 0 | F20: 4 | G20: -1 | H20: 7 | I20: -2 | J20: -6 | K20: 2022-10-19
B21: 2022-09-30 | C21: Grooming | D21: 1625 | E21: -4 | F21: 5 | G21: 1 | H21: 8 | I21: -4 | J21: -8 | K21: 2022-10-19
B22: 2022-09-30 | C22: Health Care | D22: 2757 | E22: 3 | F22: 8 | G22: -2 | H22: 6 | I22: 4 | J22: -5 | K22: 2022-10-19
B23: 2022-09-30 | C23: Fabric & Home Care | D23: 7082 | E23: 1 | F23: 8 | G23: -4 | H23: 11 | I23: 1 | J23: -6 | K23: 2022-10-19
B24: 2022-09-30 | C24: Baby, Feminine & Family Care | D24: 4934 | E24: 1 | F24: 6 | G24: -3 | H24: 8 | I24: 1 | J24: -5 | K24: 2022-10-19
B25: 2022-09-30 | C25: Corporate | D25: 253 | K25: 2022-10-19
B26: 2022-09-30 | C26: Total Company | D26: 20612 | E26: 1 | F26: 7 | G26: -3 | H26: 9 | I26: 1 | J26: -6 | K26: 2022-10-19
B27: 2022-12-31 | C27: Beauty | D27: 3807 | E27: -3 | F27: 3 | G27: -4 | H27: 9 | I27: -2 | J27: -8 | K27: 2023-01-19
B28: 2022-12-31 | C28: Grooming | D28: 1643 | E28: -9 | F28: 0 | G28: -8 | H28: 11 | I28: -3 | J28: -9 | K28: 2023-01-19
B29: 2022-12-31 | C29: Health Care | D29: 3051 | E29: 2 | F29: 8 | G29: -1 | H29: 5 | I29: 4 | J29: -6 | K29: 2023-01-19
B30: 2022-12-31 | C30: Fabric & Home Care | D30: 7032 | E30: 1 | F30: 8 | G30: -7 | H30: 13 | I30: 2 | J30: -7 | K30: 2023-01-19
B31: 2022-12-31 | C31: Baby, Feminine & Family Care | D31: 5065 | E31: -1 | F31: 4 | G31: -6 | H31: 8 | I31: 2 | J31: -5 | K31: 2023-01-19
B32: 2022-12-31 | C32: Corporate | D32: 175 | K32: 2023-01-19
B33: 2022-12-31 | C33: Total Company | D33: 20773 | E33: -1 | F33: 5 | G33: -6 | H33: 10 | I33: 1 | J33: -6 | K33: 2023-01-19
B34: 2023-03-31 | C34: Beauty | D34: 3494 | E34: 3 | F34: 7 | G34: 0 | H34: 8 | I34: -1 | J34: -5 | K34: 2023-04-21
B35: 2023-03-31 | C35: Grooming | D35: 1495 | E35: 1 | F35: 7 | G35: -1 | H35: 10 | I35: -2 | J35: -6 | K35: 2023-04-21
B36: 2023-03-31 | C36: Health Care | D36: 2828 | E36: 6 | F36: 9 | G36: 1 | H36: 6 | I36: 3 | J36: -3 | K36: 2023-04-21
B37: 2023-03-31 | C37: Fabric & Home Care | D37: 7016 | E37: 5 | F37: 9 | G37: -5 | H37: 13 | I37: 1 | J37: -4 | K37: 2023-04-21
B38: 2023-03-31 | C38: Baby, Feminine & Family Care | D38: 5062 | E38: 3 | F38: 6 | G38: -4 | H38: 8 | I38: 2 | J38: -3 | K38: 2023-04-21
B39: 2023-03-31 | C39: Corporate | D39: 173 | K39: 2023-04-21
B40: 2023-03-31 | C40: Total Company | D40: 20068 | E40: 4 | F40: 7 | G40: -3 | H40: 10 | I40: 1 | J40: -4 | K40: 2023-04-21
B41: 2023-06-30 | C41: Beauty | D41: 3746 | E41: 8 | F41: 11 | G41: -1 | H41: 8 | I41: 4 | J41: -4 | K41: 2023-07-28
B42: 2023-06-30 | C42: Grooming | D42: 1656 | E42: 3 | F42: 8 | G42: -1 | H42: 9 | I42: 0 | J42: -5 | K42: 2023-07-28
B43: 2023-06-30 | C43: Health Care | D43: 2590 | E43: 3 | F43: 5 | G43: -3 | H43: 6 | I43: 2 | J43: -2 | K43: 2023-07-28
B44: 2023-06-30 | C44: Fabric & Home Care | D44: 7241 | E44: 5 | F44: 8 | G44: -2 | H44: 6 | I44: 3 | J44: -2 | K44: 2023-07-28
B45: 2023-06-30 | C45: Baby, Feminine & Family Care | D45: 5156 | E45: 7 | F45: 9 | G45: 0 | H45: 8 | I45: 2 | J45: -3 | K45: 2023-07-28
B46: 2023-06-30 | C46: Corporate | D46: 164 | K46: 2023-07-28
B47: 2023-06-30 | C47: Total Company | D47: 20553 | E47: 5 | F47: 8 | G47: -1 | H47: 7 | I47: 2 | J47: -3 | K47: 2023-07-28
B48: 2023-09-30 | C48: Beauty | D48: 4097 | E48: 3 | F48: 5 | G48: 0 | H48: 7 | I48: -2 | J48: -3 | K48: 2023-10-18
B49: 2023-09-30 | C49: Grooming | D49: 1724 | E49: 6 | F49: 9 | G49: -2 | H49: 9 | I49: 1 | J49: -3 | K49: 2023-10-18
B50: 2023-09-30 | C50: Health Care | D50: 3074 | E50: 11 | F50: 10 | G50: 2 | H50: 6 | I50: 2 | J50: 1 | K50: 2023-10-18
B51: 2023-09-30 | C51: Fabric & Home Care | D51: 7646 | E51: 8 | F51: 9 | G51: 0 | H51: 8 | I51: 1 | J51: -1 | K51: 2023-10-18
B52: 2023-09-30 | C52: Baby, Feminine & Family Care | D52: 5186 | E52: 5 | F52: 7 | G52: -3 | H52: 8 | I52: 2 | J52: -2 | K52: 2023-10-18
B53: 2023-09-30 | C53: Corporate | D53: 144 | K53: 2023-10-18
B54: 2023-09-30 | C54: Total Company | D54: 21871 | E54: 6 | F54: 7 | G54: -1 | H54: 7 | I54: 1 | J54: -1 | K54: 2023-10-18
B55: 2023-12-31 | C55: Beauty | D55: 3849 | E55: 1 | F55: 1 | G55: -1 | H55: 4 | I55: -3 | J55: -1 | K55: 2024-01-23
B56: 2023-12-31 | C56: Grooming | D56: 1734 | E56: 6 | F56: 9 | G56: 1 | H56: 7 | I56: 1 | J56: -3 | K56: 2024-01-23
B57: 2023-12-31 | C57: Health Care | D57: 3172 | E57: 4 | F57: 2 | G57: -4 | H57: 5 | I57: 1 | J57: 2 | K57: 2024-01-23
B58: 2023-12-31 | C58: Fabric & Home Care | D58: 7415 | E58: 5 | F58: 6 | G58: 1 | H58: 4 | I58: 1 | J58: 0 | K58: 2024-01-23
B59: 2023-12-31 | C59: Baby, Feminine & Family Care | D59: 5146 | E59: 2 | F59: 3 | G59: -2 | H59: 4 | I59: 1 | J59: -1 | K59: 2024-01-23
B60: 2023-12-31 | C60: Corporate | D60: 126 | K60: 2024-01-23
B61: 2023-12-31 | C61: Total Company | D61: 21441 | E61: 3 | F61: 4 | G61: -1 | H61: 4 | I61: 0 | J61: -1 | K61: 2024-01-23
B62: 2024-03-31 | C62: Beauty | D62: 3550 | E62: 2 | F62: 3 | G62: 1 | H62: 4 | I62: -1 | J62: -3 | K62: 2024-04-19
B63: 2024-03-31 | C63: Grooming | D63: 1539 | E63: 3 | F63: 10 | G63: 2 | H63: 10 | I63: -1 | J63: -7 | K63: 2024-04-19
B64: 2024-03-31 | C64: Health Care | D64: 2873 | E64: 2 | F64: 2 | G64: -4 | H64: 4 | I64: 3 | J64: -1 | K64: 2024-04-19
B65: 2024-03-31 | C65: Fabric & Home Care | D65: 7169 | E65: 2 | F65: 3 | G65: 1 | H65: 2 | I65: 0 | J65: -1 | K65: 2024-04-19
B66: 2024-03-31 | C66: Baby, Feminine & Family Care | D66: 4936 | E66: -2 | F66: 0 | G66: -3 | H66: 2 | I66: 1 | J66: -2 | K66: 2024-04-19
B67: 2024-03-31 | C67: Corporate | D67: 128 | K67: 2024-04-19
B68: 2024-03-31 | C68: Total Company | D68: 20195 | E68: 1 | F68: 3 | G68: 0 | H68: 3 | I68: 0 | J68: -2 | K68: 2024-04-19
B69: 2024-06-30 | C69: Beauty | D69: 3724 | E69: -1 | F69: 3 | G69: 1 | H69: 3 | I69: 0 | J69: -3 | K69: 2024-07-30
B70: 2024-06-30 | C70: Grooming | D70: 1657 | E70: 0 | F70: 7 | G70: 2 | H70: 5 | I70: 0 | J70: -7 | K70: 2024-07-30
B71: 2024-06-30 | C71: Health Care | D71: 2674 | E71: 3 | F71: 4 | G71: 1 | H71: 2 | I71: 1 | J71: -1 | K71: 2024-07-30
B72: 2024-06-30 | C72: Fabric & Home Care | D72: 7265 | E72: 0 | F72: 2 | G72: 3 | H72: -1 | I72: 1 | J72: -1 | K72: 2024-07-30
B73: 2024-06-30 | C73: Baby, Feminine & Family Care | D73: 5009 | E73: -3 | F73: -1 | G73: -1 | H73: 0 | I73: 0 | J73: -2 | K73: 2024-07-30
B74: 2024-06-30 | C74: Corporate | D74: 202 | K74: 2024-07-30
B75: 2024-06-30 | C75: Total Company | D75: 20532 | E75: 0 | F75: 2 | G75: 2 | H75: 1 | I75: 0 | J75: -2 | K75: 2024-07-30
B76: 2024-09-30 | C76: Beauty | D76: 3892 | E76: -5 | F76: -2 | G76: 0 | H76: 1 | I76: -3 | J76: -1 | K76: 2024-10-18
B77: 2024-09-30 | C77: Grooming | D77: 1723 | E77: 0 | F77: 3 | G77: 5 | H77: 1 | I77: -3 | J77: -2 | K77: 2024-10-18
B78: 2024-09-30 | C78: Health Care | D78: 3147 | E78: 2 | F78: 4 | G78: -1 | H78: 1 | I78: 4 | J78: -1 | K78: 2024-10-18
B79: 2024-09-30 | C79: Fabric & Home Care | D79: 7710 | E79: 1 | F79: 3 | G79: 1 | H79: 0 | I79: 1 | J79: -1 | K79: 2024-10-18
B80: 2024-09-30 | C80: Baby, Feminine & Family Care | D80: 5102 | E80: -2 | F80: 0 | G80: -1 | H80: 0 | I80: 0 | J80: -1 | K80: 2024-10-18
B81: 2024-09-30 | C81: Corporate | D81: 163 | K81: 2024-10-18
B82: 2024-09-30 | C82: Total Company | D82: 21737 | E82: -1 | F82: 2 | G82: 1 | H82: 1 | I82: 0 | J82: -1 | K82: 2024-10-18
B83: 2024-12-31 | C83: Beauty | D83: 3848 | E83: 0 | F83: 2 | G83: 0 | H83: 2 | I83: 0 | J83: -1 | K83: 2025-01-22
B84: 2024-12-31 | C84: Grooming | D84: 1752 | E84: 1 | F84: 2 | G84: 2 | H84: 1 | I84: -1 | J84: -1 | K84: 2025-01-22
B85: 2024-12-31 | C85: Health Care | D85: 3249 | E85: 2 | F85: 3 | G85: 0 | H85: 1 | I85: 2 | J85: 0 | K85: 2025-01-22
B86: 2024-12-31 | C86: Fabric & Home Care | D86: 7575 | E86: 2 | F86: 3 | G86: 2 | H86: 0 | I86: 1 | J86: 0 | K86: 2025-01-22
B87: 2024-12-31 | C87: Baby, Feminine & Family Care | D87: 5298 | E87: 3 | F87: 4 | G87: 4 | H87: -1 | I87: 0 | J87: 0 | K87: 2025-01-22
B88: 2024-12-31 | C88: Corporate | D88: 159 | K88: 2025-01-22
B89: 2024-12-31 | C89: Total Company | D89: 21882 | E89: 2 | F89: 3 | G89: 2 | H89: 0 | I89: 1 | J89: 0 | K89: 2025-01-22
B90: 2025-03-31 | C90: Beauty | D90: 3490 | E90: -2 | F90: 2 | G90: 1 | H90: 3 | I90: -2 | J90: -3 | K90: 2025-04-24
B91: 2025-03-31 | C91: Grooming | D91: 1505 | E91: -2 | F91: 3 | G91: 1 | H91: 2 | I91: 0 | J91: -4 | K91: 2025-04-24
B92: 2025-03-31 | C92: Health Care | D92: 2880 | E92: 0 | F92: 4 | G92: -1 | H92: 1 | I92: 3 | J92: -3 | K92: 2025-04-24
B93: 2025-03-31 | C93: Fabric & Home Care | D93: 6948 | E93: -3 | F93: 0 | G93: 0 | H93: 0 | I93: 0 | J93: -2 | K93: 2025-04-24
B94: 2025-03-31 | C94: Baby, Feminine & Family Care | D94: 4755 | E94: -4 | F94: -1 | G94: -2 | H94: 0 | I94: 1 | J94: -2 | K94: 2025-04-24
B95: 2025-03-31 | C95: Corporate | D95: 198 | K95: 2025-04-24
B96: 2025-03-31 | C96: Total Company | D96: 19776 | E96: -2 | F96: 1 | G96: 0 | H96: 1 | I96: 0 | J96: -2 | K96: 2025-04-24
B97: 2025-06-30 | C97: Beauty | D97: 3733 | E97: 0 | F97: 1 | G97: 1 | H97: 1 | I97: -1 | J97: -1 | K97: 2025-07-29
B98: 2025-06-30 | C98: Grooming | D98: 1683 | E98: 2 | F98: 1 | G98: -1 | H98: 4 | I98: -1 | J98: 0 | K98: 2025-07-29
B99: 2025-06-30 | C99: Health Care | D99: 2722 | E99: 2 | F99: 2 | G99: -2 | H99: 1 | I99: 3 | J99: 0 | K99: 2025-07-29
B100: 2025-06-30 | C100: Fabric & Home Care | D100: 7385 | E100: 2 | F100: 1 | G100: 0 | H100: 1 | I100: 0 | J100: 1 | K100: 2025-07-29
B101: 2025-06-30 | C101: Baby, Feminine & Family Care | D101: 5093 | E101: 2 | F101: 1 | G101: 0 | H101: 1 | I101: 0 | J101: 1 | K101: 2025-07-29
B102: 2025-06-30 | C102: Corporate | D102: 274 | K102: 2025-07-29
...

Sheet Monthly market
B2: Monthly market | Date-frozen inputs
B5: Series | C5: Known by | D5: Month | E5: Value | F5: Units | G5: Source
B6: RSHPCS | C6: 2026-04-24 | D6: 2021-01-01 | E6: 29812 | F6: USD million, monthly flow, seasonally adjusted | G6: https://alfred.stlouisfed.org/graph/alfredgraph.csv?id=RSHPCS&cosd=2021-01-01&coed=2026-04-01&vintage_date=2026-04-24
B7: RSHPCS | C7: 2026-04-24 | D7: 2021-02-01 | E7: 29636 | F7: USD million, monthly flow, seasonally adjusted | G7: https://alfred.stlouisfed.org/graph/alfredgraph.csv?id=RSHPCS&cosd=2021-01-01&coed=2026-04-01&vintage_date=2026-04-24
B8: RSHPCS | C8: 2026-04-24 | D8: 2021-03-01 | E8: 32090 | F8: USD million, monthly flow, seasonally adjusted | G8: https://alfred.stlouisfed.org/graph/alfredgraph.csv?id=RSHPCS&cosd=2021-01-01&coed=2026-04-01&vintage_date=2026-04-24
B9: RSHPCS | C9: 2026-04-24 | D9: 2021-04-01 | E9: 31957 | F9: USD million, monthly flow, seasonally adjusted | G9: https://alfred.stlouisfed.org/graph/alfredgraph.csv?id=RSHPCS&cosd=2021-01-01&coed=2026-04-01&vintage_date=2026-04-24
B10: RSHPCS | C10: 2026-04-24 | D10: 2021-05-01 | E10: 31321 | F10: USD million, monthly flow, seasonally adjusted | G10: https://alfred.stlouisfed.org/graph/alfredgraph.csv?id=RSHPCS&cosd=2021-01-01&coed=2026-04-01&vintage_date=2026-04-24
B11: RSHPCS | C11: 2026-04-24 | D11: 2021-06-01 | E11: 32334 | F11: USD million, monthly flow, seasonally adjusted | G11: https://alfred.stlouisfed.org/graph/alfredgraph.csv?id=RSHPCS&cosd=2021-01-01&coed=2026-04-01&vintage_date=2026-04-24
B12: RSHPCS | C12: 2026-04-24 | D12: 2021-07-01 | E12: 32225 | F12: USD million, monthly flow, seasonally adjusted | G12: https://alfred.stlouisfed.org/graph/alfredgraph.csv?id=RSHPCS&cosd=2021-01-01&coed=2026-04-01&vintage_date=2026-04-24
B13: RSHPCS | C13: 2026-04-24 | D13: 2021-08-01 | E13: 32429 | F13: USD million, monthly flow, seasonally adjusted | G13: https://alfred.stlouisfed.org/graph/alfredgraph.csv?id=RSHPCS&cosd=2021-01-01&coed=2026-04-01&vintage_date=2026-04-24
B14: RSHPCS | C14: 2026-04-24 | D14: 2021-09-01 | E14: 32183 | F14: USD million, monthly flow, seasonally adjusted | G14: https://alfred.stlouisfed.org/graph/alfredgraph.csv?id=RSHPCS&cosd=2021-01-01&coed=2026-04-01&vintage_date=2026-04-24
B15: RSHPCS | C15: 2026-04-24 | D15: 2021-10-01 | E15: 32099 | F15: USD million, monthly flow, seasonally adjusted | G15: https://alfred.stlouisfed.org/graph/alfredgraph.csv?id=RSHPCS&cosd=2021-01-01&coed=2026-04-01&vintage_date=2026-04-24
B16: RSHPCS | C16: 2026-04-24 | D16: 2021-11-01 | E16: 32490 | F16: USD million, monthly flow, seasonally adjusted | G16: https://alfred.stlouisfed.org/graph/alfredgraph.csv?id=RSHPCS&cosd=2021-01-01&coed=2026-04-01&vintage_date=2026-04-24
B17: RSHPCS | C17: 2026-04-24 | D17: 2021-12-01 | E17: 32390 | F17: USD million, monthly flow, seasonally adjusted | G17: https://alfred.stlouisfed.org/graph/alfredgraph.csv?id=RSHPCS&cosd=2021-01-01&coed=2026-04-01&vintage_date=2026-04-24
... B382: CUUR0000SEGB | C382: 2026-05-15 | D382: 2026-04-01 | E382: 184.895 | F382: Index 1982-84=100, not seasonally adjusted | G382: https://alfred.stlouisfed.org/graph/alfredgraph.csv?id=CUUR0000SEGB&cosd=2021-01-01&coed=2026-04-01&vintage_date=2026-05-15

Sheet Product prices
B2: Product prices | Research only
B3: Current-vintage BLS history. Not used in April/May forecast calculations.
B5: Series | C5: Product group | D5: Month | E5: Price index | F5: Vintage status
B6: CUUR0000SEGB01 | C6: Hair, dental, shaving and miscellaneous personal care products | D6: 2021-01-01 | E6: 103.209 | F6: Retrieved 2026-10-05; historical vintage not verified
B7: CUUR0000SEGB01 | C7: Hair, dental, shaving and miscellaneous personal care products | D7: 2021-02-01 | E7: 103.459 | F7: Retrieved 2026-10-05; historical vintage not verified
B8: CUUR0000SEGB01 | C8: Hair, dental, shaving and miscellaneous personal care products | D8: 2021-03-01 | E8: 103.394 | F8: Retrieved 2026-10-05; historical vintage not verified
B9: CUUR0000SEGB01 | C9: Hair, dental, shaving and miscellaneous personal care products | D9: 2021-04-01 | E9: 103.675 | F9: Retrieved 2026-10-05; historical vintage not verified
B10: CUUR0000SEGB01 | C10: Hair, dental, shaving and miscellaneous personal care products | D10: 2021-05-01 | E10: 103.926 | F10: Retrieved 2026-10-05; historical vintage not verified
B11: CUUR0000SEGB01 | C11: Hair, dental, shaving and miscellaneous personal care products | D11: 2021-06-01 | E11: 103.538 | F11: Retrieved 2026-10-05; historical vintage not verified
B12: CUUR0000SEGB01 | C12: Hair, dental, shaving and miscellaneous personal care products | D12: 2021-07-01 | E12: 104.221 | F12: Retrieved 2026-10-05; historical vintage not verified
B13: CUUR0000SEGB01 | C13: Hair, dental, shaving and miscellaneous personal care products | D13: 2021-08-01 | E13: 104.098 | F13: Retrieved 2026-10-05; historical vintage not verified
B14: CUUR0000SEGB01 | C14: Hair, dental, shaving and miscellaneous personal care products | D14: 2021-09-01 | E14: 103.769 | F14: Retrieved 2026-10-05; historical vintage not verified
B15: CUUR0000SEGB01 | C15: Hair, dental, shaving and miscellaneous personal care products | D15: 2021-10-01 | E15: 104.304 | F15: Retrieved 2026-10-05; historical vintage not verified
B16: CUUR0000SEGB01 | C16: Hair, dental, shaving and miscellaneous personal care products | D16: 2021-11-01 | E16: 104.136 | F16: Retrieved 2026-10-05; historical vintage not verified
B17: CUUR0000SEGB01 | C17: Hair, dental, shaving and miscellaneous personal care products | D17: 2021-12-01 | E17: 104.129 | F17: Retrieved 2026-10-05; historical vintage not verified
... B62: CUUR0000SEGB01 | C62: Hair, dental, shaving and miscellaneous personal care products | D62: 2025-09-01 | E62: 124.066 | F62: Retrieved 2026-10-05; historical vintage not verified
B63: CUUR0000SEGB01 | C63: Hair, dental, shaving and miscellaneous personal care products | D63: 2025-10-01 | F63: Retrieved 2026-10-05; historical vintage not verified
B64: CUUR0000SEGB01 | C64: Hair, dental, shaving and miscellaneous personal care products | D64: 2025-11-01 | E64: 124.059 | F64: Retrieved 2026-10-05; historical vintage not verified
B65: CUUR0000SEGB01 | C65: Hair, dental, shaving and miscellaneous personal care products | D65: 2025-12-01 | E65: 124.018 | F65: Retrieved 2026-10-05; historical vintage not verified
B66: CUUR0000SEGB01 | C66: Hair, dental, shaving and miscellaneous personal care products | D66: 2026-01-01 | E66: 124.317 | F66: Retrieved 2026-10-05; historical vintage not verified
B67: CUUR0000SEGB01 | C67: Hair, dental, shaving and miscellaneous personal care products | D67: 2026-02-01 | E67: 125.749 | F67: Retrieved 2026-10-05; historical vintage not verified
B68: CUUR0000SEGB01 | C68: Hair, dental, shaving and miscellaneous personal care products | D68: 2026-03-01 | E68: 126.219 | F68: Retrieved 2026-10-05; historical vintage not verified
B69: CUUR0000SEGB01 | C69: Hair, dental, shaving and miscellaneous personal care products | D69: 2026-04-01 | E69: 126.078 | F69: Retrieved 2026-10-05; historical vintage not verified
B70: CUUR0000SEGB02 | C70: Cosmetics, perfume, bath, nail preparations and implements | D70: 2021-01-01 | E70: 179.952 | F70: Retrieved 2026-10-05; historical vintage not verified
B71: CUUR0000SEGB02 | C71: Cosmetics, perfume, bath, nail preparations and implements | D71: 2021-02-01 | E71: 180.497 | F71: Retrieved 2026-10-05; historical vintage not verified
B72: CUUR0000SEGB02 | C72: Cosmetics, perfume, bath, nail preparations and implements | D72: 2021-03-01 | E72: 180.006 | F72: Retrieved 2026-10-05; historical vintage not verified
B73: CUUR0000SEGB02 | C73: Cosmetics, perfume, bath, nail preparations and implements | D73: 2021-04-01 | E73: 180.289 | F73: Retrieved 2026-10-05; historical vintage not verified
B74: CUUR0000SEGB02 | C74: Cosmetics, perfume, bath, nail preparations and implements | D74: 2021-05-01 | E74: 178.222 | F74: Retrieved 2026-10-05; historical vintage not verified
B75: CUUR0000SEGB02 | C75: Cosmetics, perfume, bath, nail preparations and implements | D75: 2021-06-01 | E75: 178.072 | F75: Retrieved 2026-10-05; historical vintage not verified
... B126: CUUR0000SEGB02 | C126: Cosmetics, perfume, bath, nail preparations and implements | D126: 2025-09-01 | E126: 192.368 | F126: Retrieved 2026-10-05; historical vintage not verified
B127: CUUR0000SEGB02 | C127: Cosmetics, perfume, bath, nail preparations and implements | D127: 2025-10-01 | F127: Retrieved 2026-10-05; historical vintage not verified
B128: CUUR0000SEGB02 | C128: Cosmetics, perfume, bath, nail preparations and implements | D128: 2025-11-01 | E128: 190.307 | F128: Retrieved 2026-10-05; historical vintage not verified
B129: CUUR0000SEGB02 | C129: Cosmetics, perfume, bath, nail preparations and implements | D129: 2025-12-01 | E129: 189.36 | F129: Retrieved 2026-10-05; historical vintage not verified
B130: CUUR0000SEGB02 | C130: Cosmetics, perfume, bath, nail preparations and implements | D130: 2026-01-01 | E130: 191.697 | F130: Retrieved 2026-10-05; historical vintage not verified
B131: CUUR0000SEGB02 | C131: Cosmetics, perfume, bath, nail preparations and implements | D131: 2026-02-01 | E131: 192.404 | F131: Retrieved 2026-10-05; historical vintage not verified
B132: CUUR0000SEGB02 | C132: Cosmetics, perfume, bath, nail preparations and implements | D132: 2026-03-01 | E132: 193.373 | F132: Retrieved 2026-10-05; historical vintage not verified
B133: CUUR0000SEGB02 | C133: Cosmetics, perfume, bath, nail preparations and implements | D133: 2026-04-01 | E133: 195.913 | F133: Retrieved 2026-10-05; historical vintage not verified
B134: CUUR0000SEHN01 | C134: Household cleaning products | D134: 2021-01-01 | E134: 128.551 | F134: Retrieved 2026-10-05; historical vintage not verified
B135: CUUR0000SEHN01 | C135: Household cleaning products | D135: 2021-02-01 | E135: 127.847 | F135: Retrieved 2026-10-05; historical vintage not verified
B136: CUUR0000SEHN01 | C136: Household cleaning products | D136: 2021-03-01 | E136: 125.942 | F136: Retrieved 2026-10-05; historical vintage not verified
B137: CUUR0000SEHN01 | C137: Household cleaning products | D137: 2021-04-01 | E137: 126.442 | F137: Retrieved 2026-10-05; historical vintage not verified
B138: CUUR0000SEHN01 | C138: Household cleaning products | D138: 2021-05-01 | E138: 126.961 | F138: Retrieved 2026-10-05; historical vintage not verified
B139: CUUR0000SEHN01 | C139: Household cleaning products | D139: 2021-06-01 | E139: 125.977 | F139: Retrieved 2026-10-05; historical vintage not verified
... B190: CUUR0000SEHN01 | C190: Household cleaning products | D190: 2025-09-01 | E190: 152.491 | F190: Retrieved 2026-10-05; historical vintage not verified
B191: CUUR0000SEHN01 | C191: Household cleaning products | D191: 2025-10-01 | F191: Retrieved 2026-10-05; historical vintage not verified
B192: CUUR0000SEHN01 | C192: Household cleaning products | D192: 2025-11-01 | E192: 152.567 | F192: Retrieved 2026-10-05; historical vintage not verified
B193: CUUR0000SEHN01 | C193: Household cleaning products | D193: 2025-12-01 | E193: 153.908 | F193: Retrieved 2026-10-05; historical vintage not verified
B194: CUUR0000SEHN01 | C194: Household cleaning products | D194: 2026-01-01 | E194: 154.013 | F194: Retrieved 2026-10-05; historical vintage not verified
B195: CUUR0000SEHN01 | C195: Household cleaning products | D195: 2026-02-01 | E195: 153.87 | F195: Retrieved 2026-10-05; historical vintage not verified
B196: CUUR0000SEHN01 | C196: Household cleaning products | D196: 2026-03-01 | E196: 153.443 | F196: Retrieved 2026-10-05; historical vintage not verified
B197: CUUR0000SEHN01 | C197: Household cleaning products | D197: 2026-04-01 | E197: 152.377 | F197: Retrieved 2026-10-05; historical vintage not verified
B198: CUUR0000SEHN02 | C198: Household paper products | D198: 2021-01-01 | E198: 193.185 | F198: Retrieved 2026-10-05; historical vintage not verified
B199: CUUR0000SEHN02 | C199: Household paper products | D199: 2021-02-01 | E199: 192.919 | F199: Retrieved 2026-10-05; historical vintage not verified
B200: CUUR0000SEHN02 | C200: Household paper products | D200: 2021-03-01 | E200: 191.804 | F200: Retrieved 2026-10-05; historical vintage not verified
B201: CUUR0000SEHN02 | C201: Household paper products | D201: 2021-04-01 | E201: 191.563 | F201: Retrieved 2026-10-05; historical vintage not verified
B202: CUUR0000SEHN02 | C202: Household paper products | D202: 2021-05-01 | E202: 192.733 | F202: Retrieved 2026-10-05; historical vintage not verified
B203: CUUR0000SEHN02 | C203: Household paper products | D203: 2021-06-01 | E203: 193.138 | F203: Retrieved 2026-10-05; historical vintage not verified
... B254: CUUR0000SEHN02 | C254: Household paper products | D254: 2025-09-01 | E254: 243.179 | F254: Retrieved 2026-10-05; historical vintage not verified
B255: CUUR0000SEHN02 | C255: Household paper products | D255: 2025-10-01 | F255: Retrieved 2026-10-05; historical vintage not verified
B256: CUUR0000SEHN02 | C256: Household paper products | D256: 2025-11-01 | E256: 240.845 | F256: Retrieved 2026-10-05; historical vintage not verified
B257: CUUR0000SEHN02 | C257: Household paper products | D257: 2025-12-01 | E257: 237.062 | F257: Retrieved 2026-10-05; historical vintage not verified
B258: CUUR0000SEHN02 | C258: Household paper products | D258: 2026-01-01 | E258: 238.354 | F258: Retrieved 2026-10-05; historical vintage not verified
B259: CUUR0000SEHN02 | C259: Household paper products | D259: 2026-02-01 | E259: 237.696 | F259: Retrieved 2026-10-05; historical vintage not verified
B260: CUUR0000SEHN02 | C260: Household paper products | D260: 2026-03-01 | E260: 238.037 | F260: Retrieved 2026-10-05; historical vintage not verified
B261: CUUR0000SEHN02 | C261: Household paper products | D261: 2026-04-01 | E261: 240.878 | F261: Retrieved 2026-10-05; historical vintage not verified

Sheet Source evidence
B2: Source evidence | Trace each P&G input
B5: Quarter | C5: Segment | D5: Measure | E5: Value | F5: Published | G5: Table / row | H5: Original report | I5: Original row
B6: 2022-03-31 | C6: Beauty | D6: reported_volume_growth | E6: 0 | F6: 2022-04-20 | G6: table 32, row 3 (zero-based) | H6: https://www.sec.gov/Archives/edgar/data/80424/000008042422000035/pg-20220331.htm | I6: Beauty | —% | (1)% | (2)% | 4% | —% | —% | 2%
B7: 2022-03-31 | C7: Beauty | D7: organic_volume_growth | E7: -1 | F7: 2022-04-20 | G7: table 32, row 3 (zero-based) | H7: https://www.sec.gov/Archives/edgar/data/80424/000008042422000035/pg-20220331.htm | I7: Beauty | —% | (1)% | (2)% | 4% | —% | —% | 2%
B8: 2022-03-31 | C8: Beauty | D8: fx_contribution | E8: -2 | F8: 2022-04-20 | G8: table 32, row 3 (zero-based) | H8: https://www.sec.gov/Archives/edgar/data/80424/000008042422000035/pg-20220331.htm | I8: Beauty | —% | (1)% | (2)% | 4% | —% | —% | 2%
B9: 2022-03-31 | C9: Beauty | D9: price_contribution | E9: 4 | F9: 2022-04-20 | G9: table 32, row 3 (zero-based) | H9: https://www.sec.gov/Archives/edgar/data/80424/000008042422000035/pg-20220331.htm | I9: Beauty | —% | (1)% | (2)% | 4% | —% | —% | 2%
B10: 2022-03-31 | C10: Beauty | D10: mix_contribution | E10: 0 | F10: 2022-04-20 | G10: table 32, row 3 (zero-based) | H10: https://www.sec.gov/Archives/edgar/data/80424/000008042422000035/pg-20220331.htm | I10: Beauty | —% | (1)% | (2)% | 4% | —% | —% | 2%
B11: 2022-03-31 | C11: Beauty | D11: other_contribution | E11: 0 | F11: 2022-04-20 | G11: table 32, row 3 (zero-based) | H11: https://www.sec.gov/Archives/edgar/data/80424/000008042422000035/pg-20220331.htm | I11: Beauty | —% | (1)% | (2)% | 4% | —% | —% | 2%
B12: 2022-03-31 | C12: Beauty | D12: reported_sales_growth | E12: 2 | F12: 2022-04-20 | G12: table 32, row 3 (zero-based) | H12: https://www.sec.gov/Archives/edgar/data/80424/000008042422000035/pg-20220331.htm | I12: Beauty | —% | (1)% | (2)% | 4% | —% | —% | 2%
B13: 2022-03-31 | C13: Grooming | D13: reported_volume_growth | E13: 1 | F13: 2022-04-20 | G13: table 32, row 4 (zero-based) | H13: https://www.sec.gov/Archives/edgar/data/80424/000008042422000035/pg-20220331.htm | I13: Grooming | 1% | 1% | (5)% | 6% | 1% | —% | 3%
B14: 2022-03-31 | C14: Grooming | D14: organic_volume_growth | E14: 1 | F14: 2022-04-20 | G14: table 32, row 4 (zero-based) | H14: https://www.sec.gov/Archives/edgar/data/80424/000008042422000035/pg-20220331.htm | I14: Grooming | 1% | 1% | (5)% | 6% | 1% | —% | 3%
B15: 2022-03-31 | C15: Grooming | D15: fx_contribution | E15: -5 | F15: 2022-04-20 | G15: table 32, row 4 (zero-based) | H15: https://www.sec.gov/Archives/edgar/data/80424/000008042422000035/pg-20220331.htm | I15: Grooming | 1% | 1% | (5)% | 6% | 1% | —% | 3%
B16: 2022-03-31 | C16: Grooming | D16: price_contribution | E16: 6 | F16: 2022-04-20 | G16: table 32, row 4 (zero-based) | H16: https://www.sec.gov/Archives/edgar/data/80424/000008042422000035/pg-20220331.htm | I16: Grooming | 1% | 1% | (5)% | 6% | 1% | —% | 3%
B17: 2022-03-31 | C17: Grooming | D17: mix_contribution | E17: 1 | F17: 2022-04-20 | G17: table 32, row 4 (zero-based) | H17: https://www.sec.gov/Archives/edgar/data/80424/000008042422000035/pg-20220331.htm | I17: Grooming | 1% | 1% | (5)% | 6% | 1% | —% | 3%
... B940: 2026-03-31 | C940: Total Company | D940: organic_sales_growth | E940: 3 | F940: 2026-04-24 | G940: table 42, row 7 (zero-based) | H940: https://www.sec.gov/Archives/edgar/data/80424/000008042426000060/pg-20260331.htm | I940: Total Company | 7 | % | (4) | % | — | % | 3 | %
