Workbook

Sheet Review
B2: P&G release-aware backtest
B3: Eight test quarters: April-June 2024 through January-March 2026. Errors in percentage points.
B5: Business segment | C5: Measure | D5: Market RMSE | E5: Four-quarter mean | F5: Last actual | G5: Test quarters
B6: =Scorecard!B22 -> Beauty | C6: Volume growth | D6: =Scorecard!G22 -> 2.4262494 | E6: =Scorecard!H22 -> 1.7410485 | F6: =Scorecard!I22 -> 1.4142136 | G6: =Scorecard!F22 -> 8
B7: =Scorecard!B41 -> Grooming | C7: Volume growth | D7: =Scorecard!G41 -> 2.4544843 | E7: =Scorecard!H41 -> 2.4701341 | F7: =Scorecard!I41 -> 2.1213203 | G7: =Scorecard!F41 -> 8
B8: =Scorecard!B60 -> Health Care | C8: Volume growth | D8: =Scorecard!G60 -> 1.8544294 | E8: =Scorecard!H60 -> 1.5411035 | F8: =Scorecard!I60 -> 2.0615528 | G8: =Scorecard!F60 -> 8
B9: =Scorecard!B79 -> Fabric & Home Care | C9: Volume growth | D9: =Scorecard!G79 -> 2.5796899 | E9: =Scorecard!H79 -> 1.8853879 | F9: =Scorecard!I79 -> 1.767767 | G9: =Scorecard!F79 -> 8
B10: =Scorecard!B98 -> Baby, Feminine & Family Care | C10: Volume growth | D10: =Scorecard!G98 -> 3.0408744 | E10: =Scorecard!H98 -> 3.3830922 | F10: =Scorecard!I98 -> 4.4440972 | G10: =Scorecard!F98 -> 8
B11: =Scorecard!B117 -> Beauty | C11: Pricing contribution | D11: =Scorecard!G117 -> 1.2373816 | E11: =Scorecard!H117 -> 1.7207375 | F11: =Scorecard!I117 -> 1.2747549 | G11: =Scorecard!F117 -> 8
B12: =Scorecard!B136 -> Grooming | C12: Pricing contribution | D12: =Scorecard!G136 -> 2.0552154 | E12: =Scorecard!H136 -> 3.4437443 | F12: =Scorecard!I136 -> 2.5248762 | G12: =Scorecard!F136 -> 8
B13: =Scorecard!B155 -> Beauty | C13: Organic sales growth | D13: =Scorecard!G155 -> 3.0969202 | E13: =Scorecard!H155 -> 3.0220544 | F13: =Scorecard!I155 -> 3.1622777 | G13: =Scorecard!F155 -> 8
B14: =Scorecard!B174 -> Health Care | C14: Organic sales growth | D14: =Scorecard!G174 -> 3.8101096 | E14: =Scorecard!H174 -> 1.118034 | F14: =Scorecard!I174 -> 1.4142136 | G14: =Scorecard!F174 -> 8
B17: Grooming pricing remains a candidate; Beauty barely beats the last-actual rule.
B18: No model is approved for automatic scenario changes from eight test quarters.
B21: Pricing model | C21: Market-only RMSE | D21: 50/50 blend RMSE | E21: Conclusion
B22: Beauty | C22: =Scorecard!G117 -> 1.2373816 | D22: =Scorecard!G119 -> 1.3644921 | E22: =IF(D22<C22,"Blend improved","Blend worsened") -> Blend worsened
B23: Grooming | C23: =Scorecard!G136 -> 2.0552154 | D23: =Scorecard!G138 -> 2.683222 | E23: =IF(D23<C23,"Blend improved","Blend worsened") -> Blend worsened
B26: 50/50 blending is tested, not assumed to fix weak data. No regional weights were invented.
B27: Frozen inputs preserve historical availability. A rerun is required to add new releases.
B28: This is retrospective model development, not an untouched prospective test.

Sheet Quarter example
B2: Grooming pricing: January-March 2026
B3: Updates can worsen a forecast. Actual pricing contribution: 3pp, published 24 April.
B5: Forecast date | C5: Observed months | D5: Last actual rule | E5: Market model | F5: Actual (later) | G5: Model error pp | J5: Date label
B6: ='Forecast log'!F446 -> 46023 | C6: ='Forecast log'!G446 -> 0 | D6: ='Forecast log'!I446 -> 4 | E6: ='Forecast log'!N446 -> 3.8752792 | F6: ='PG facts'!E119 -> 3 | G6: =E6-F6 -> 0.8752792 | J6: =TEXT(B6,"dd-mmm") -> 01-Jan
B7: ='Forecast log'!F447 -> 46035 | C7: ='Forecast log'!G447 -> 0 | D7: ='Forecast log'!I447 -> 4 | E7: ='Forecast log'!N447 -> 4.0143577 | F7: ='PG facts'!E119 -> 3 | G7: =E7-F7 -> 1.0143577 | J7: =TEXT(B7,"dd-mmm") -> 13-Jan
B8: ='Forecast log'!F448 -> 46045 | C8: ='Forecast log'!G448 -> 0 | D8: ='Forecast log'!I448 -> 2 | E8: ='Forecast log'!N448 -> 4.0143577 | F8: ='PG facts'!E119 -> 3 | G8: =E8-F8 -> 1.0143577 | J8: =TEXT(B8,"dd-mmm") -> 23-Jan
B9: ='Forecast log'!F449 -> 46066 | C9: ='Forecast log'!G449 -> 1 | D9: ='Forecast log'!I449 -> 2 | E9: ='Forecast log'!N449 -> 4.3390568 | F9: ='PG facts'!E119 -> 3 | G9: =E9-F9 -> 1.3390568 | J9: =TEXT(B9,"dd-mmm") -> 13-Feb
B10: ='Forecast log'!F450 -> 46092 | C10: ='Forecast log'!G450 -> 2 | D10: ='Forecast log'!I450 -> 2 | E10: ='Forecast log'!N450 -> 4.59835 | F10: ='PG facts'!E119 -> 3 | G10: =E10-F10 -> 1.59835 | J10: =TEXT(B10,"dd-mmm") -> 11-Mar
B11: ='Forecast log'!F451 -> 46122 | C11: ='Forecast log'!G451 -> 3 | D11: ='Forecast log'!I451 -> 2 | E11: ='Forecast log'!N451 -> 4.7910848 | F11: ='PG facts'!E119 -> 3 | G11: =E11-F11 -> 1.7910848 | J11: =TEXT(B11,"dd-mmm") -> 10-Apr
B12: ='Forecast log'!F452 -> 46135 | C12: ='Forecast log'!G452 -> 3 | D12: ='Forecast log'!I452 -> 2 | E12: ='Forecast log'!N452 -> 4.7910848 | F12: ='PG facts'!E119 -> 3 | G12: =E12-F12 -> 1.7910848 | J12: =TEXT(B12,"dd-mmm") -> 23-Apr
B14: Actuals are shown for evaluation only; they do not feed earlier forecasts.

Sheet Scorecard
B2: Model errors on comparable quarters
B5: Segment | C5: Measure | D5: Stage | E5: Method | F5: Quarters | G5: RMSE pp | H5: Mean RMSE pp | I5: Last actual RMSE pp | J5: MAE pp | K5: Bias pp | L5: Wins vs mean
B6: Beauty | C6: organic_volume_growth | D6: Origin | E6: baseline | F6: =COUNTIFS('Scored quarters'!$C$6:$C$1367,B6,'Scored quarters'!$D$6:$D$1367,C6,'Scored quarters'!$F$6:$F$1367,D6,'Scored quarters'!$G$6:$G$1367,E6) -> 8 | G6: =SQRT(SUMIFS('Scored quarters'!$K$6:$K$1367,'Scored quarters'!$C$6:$C$1367,B6,'Scored quarters'!$D$6:$D$1367,C6,'Scored quarters'!$F$6:$F$1367,D6,'Scored quarters'!$G$6:$G$1367,E6)/F6) -> 2.0596571 | H6: =SQRT(SUMIFS('Scored quarters'!$L$6:$L$1367,'Scored quarters'!$C$6:$C$1367,B6,'Scored quarters'!$D$6:$D$1367,C6,'Scored quarters'!$F$6:$F$1367,D6,'Scored quarters'!$G$6:$G$1367,E6)/F6) -> 2.0596571 | I6: =SQRT(SUMIFS('Scored quarters'!$M$6:$M$1367,'Scored quarters'!$C$6:$C$1367,B6,'Scored quarters'!$D$6:$D$1367,C6,'Scored quarters'!$F$6:$F$1367,D6,'Scored quarters'!$G$6:$G$1367,E6)/F6) -> 1.6583124 | J6: =SUMIFS('Scored quarters'!$O$6:$O$1367,'Scored quarters'!$C$6:$C$1367,B6,'Scored quarters'!$D$6:$D$1367,C6,'Scored quarters'!$F$6:$F$1367,D6,'Scored quarters'!$G$6:$G$1367,E6)/F6 -> 1.59375 | K6: =SUMIFS('Scored quarters'!$J$6:$J$1367,'Scored quarters'!$C$6:$C$1367,B6,'Scored quarters'!$D$6:$D$1367,C6,'Scored quarters'!$F$6:$F$1367,D6,'Scored quarters'!$G$6:$G$1367,E6)/F6 -> -1.53125 | L6: =SUMIFS('Scored quarters'!$N$6:$N$1367,'Scored quarters'!$C$6:$C$1367,B6,'Scored quarters'!$D$6:$D$1367,C6,'Scored quarters'!$F$6:$F$1367,D6,'Scored quarters'!$G$6:$G$1367,E6) -> 0
B7: Beauty | C7: organic_volume_growth | D7: Origin | E7: last_actual | F7: =COUNTIFS('Scored quarters'!$C$6:$C$1367,B7,'Scored quarters'!$D$6:$D$1367,C7,'Scored quarters'!$F$6:$F$1367,D7,'Scored quarters'!$G$6:$G$1367,E7) -> 8 | G7: =SQRT(SUMIFS('Scored quarters'!$K$6:$K$1367,'Scored quarters'!$C$6:$C$1367,B7,'Scored quarters'!$D$6:$D$1367,C7,'Scored quarters'!$F$6:$F$1367,D7,'Scored quarters'!$G$6:$G$1367,E7)/F7) -> 1.6583124 | H7: =SQRT(SUMIFS('Scored quarters'!$L$6:$L$1367,'Scored quarters'!$C$6:$C$1367,B7,'Scored quarters'!$D$6:$D$1367,C7,'Scored quarters'!$F$6:$F$1367,D7,'Scored quarters'!$G$6:$G$1367,E7)/F7) -> 2.0596571 | I7: =SQRT(SUMIFS('Scored quarters'!$M$6:$M$1367,'Scored quarters'!$C$6:$C$1367,B7,'Scored quarters'!$D$6:$D$1367,C7,'Scored quarters'!$F$6:$F$1367,D7,'Scored quarters'!$G$6:$G$1367,E7)/F7) -> 1.6583124 | J7: =SUMIFS('Scored quarters'!$O$6:$O$1367,'Scored quarters'!$C$6:$C$1367,B7,'Scored quarters'!$D$6:$D$1367,C7,'Scored quarters'!$F$6:$F$1367,D7,'Scored quarters'!$G$6:$G$1367,E7)/F7 -> 1.5 | K7: =SUMIFS('Scored quarters'!$J$6:$J$1367,'Scored quarters'!$C$6:$C$1367,B7,'Scored quarters'!$D$6:$D$1367,C7,'Scored quarters'!$F$6:$F$1367,D7,'Scored quarters'!$G$6:$G$1367,E7)/F7 -> -1 | L7: =SUMIFS('Scored quarters'!$N$6:$N$1367,'Scored quarters'!$C$6:$C$1367,B7,'Scored quarters'!$D$6:$D$1367,C7,'Scored quarters'!$F$6:$F$1367,D7,'Scored quarters'!$G$6:$G$1367,E7) -> 3
B8: Beauty | C8: organic_volume_growth | D8: Origin | E8: bridge | F8: =COUNTIFS('Scored quarters'!$C$6:$C$1367,B8,'Scored quarters'!$D$6:$D$1367,C8,'Scored quarters'!$F$6:$F$1367,D8,'Scored quarters'!$G$6:$G$1367,E8) -> 8 | G8: =SQRT(SUMIFS('Scored quarters'!$K$6:$K$1367,'Scored quarters'!$C$6:$C$1367,B8,'Scored quarters'!$D$6:$D$1367,C8,'Scored quarters'!$F$6:$F$1367,D8,'Scored quarters'!$G$6:$G$1367,E8)/F8) -> 2.3099248 | H8: =SQRT(SUMIFS('Scored quarters'!$L$6:$L$1367,'Scored quarters'!$C$6:$C$1367,B8,'Scored quarters'!$D$6:$D$1367,C8,'Scored quarters'!$F$6:$F$1367,D8,'Scored quarters'!$G$6:$G$1367,E8)/F8) -> 2.0596571 | I8: =SQRT(SUMIFS('Scored quarters'!$M$6:$M$1367,'Scored quarters'!$C$6:$C$1367,B8,'Scored quarters'!$D$6:$D$1367,C8,'Scored quarters'!$F$6:$F$1367,D8,'Scored quarters'!$G$6:$G$1367,E8)/F8) -> 1.6583124 | J8: =SUMIFS('Scored quarters'!$O$6:$O$1367,'Scored quarters'!$C$6:$C$1367,B8,'Scored quarters'!$D$6:$D$1367,C8,'Scored quarters'!$F$6:$F$1367,D8,'Scored quarters'!$G$6:$G$1367,E8)/F8 -> 1.8495023 | K8: =SUMIFS('Scored quarters'!$J$6:$J$1367,'Scored quarters'!$C$6:$C$1367,B8,'Scored quarters'!$D$6:$D$1367,C8,'Scored quarters'!$F$6:$F$1367,D8,'Scored quarters'!$G$6:$G$1367,E8)/F8 -> -1.8495023 | L8: =SUMIFS('Scored quarters'!$N$6:$N$1367,'Scored quarters'!$C$6:$C$1367,B8,'Scored quarters'!$D$6:$D$1367,C8,'Scored quarters'!$F$6:$F$1367,D8,'Scored quarters'!$G$6:$G$1367,E8) -> 2
B9: Beauty | C9: organic_volume_growth | D9: Origin | E9: blend | F9: =COUNTIFS('Scored quarters'!$C$6:$C$1367,B9,'Scored quarters'!$D$6:$D$1367,C9,'Scored quarters'!$F$6:$F$1367,D9,'Scored quarters'!$G$6:$G$1367,E9) -> 8 | G9: =SQRT(SUMIFS('Scored quarters'!$K$6:$K$1367,'Scored quarters'!$C$6:$C$1367,B9,'Scored quarters'!$D$6:$D$1367,C9,'Scored quarters'!$F$6:$F$1367,D9,'Scored quarters'!$G$6:$G$1367,E9)/F9) -> 2.1801357 | H9: =SQRT(SUMIFS('Scored quarters'!$L$6:$L$1367,'Scored quarters'!$C$6:$C$1367,B9,'Scored quarters'!$D$6:$D$1367,C9,'Scored quarters'!$F$6:$F$1367,D9,'Scored quarters'!$G$6:$G$1367,E9)/F9) -> 2.0596571 | I9: =SQRT(SUMIFS('Scored quarters'!$M$6:$M$1367,'Scored quarters'!$C$6:$C$1367,B9,'Scored quarters'!$D$6:$D$1367,C9,'Scored quarters'!$F$6:$F$1367,D9,'Scored quarters'!$G$6:$G$1367,E9)/F9) -> 1.6583124 | J9: =SUMIFS('Scored quarters'!$O$6:$O$1367,'Scored quarters'!$C$6:$C$1367,B9,'Scored quarters'!$D$6:$D$1367,C9,'Scored quarters'!$F$6:$F$1367,D9,'Scored quarters'!$G$6:$G$1367,E9)/F9 -> 1.7148431 | K9: =SUMIFS('Scored quarters'!$J$6:$J$1367,'Scored quarters'!$C$6:$C$1367,B9,'Scored quarters'!$D$6:$D$1367,C9,'Scored quarters'!$F$6:$F$1367,D9,'Scored quarters'!$G$6:$G$1367,E9)/F9 -> -1.6903762 | L9: =SUMIFS('Scored quarters'!$N$6:$N$1367,'Scored quarters'!$C$6:$C$1367,B9,'Scored quarters'!$D$6:$D$1367,C9,'Scored quarters'!$F$6:$F$1367,D9,'Scored quarters'!$G$6:$G$1367,E9) -> 2
B10: Beauty | C10: organic_volume_growth | D10: First month | E10: baseline | F10: =COUNTIFS('Scored quarters'!$C$6:$C$1367,B10,'Scored quarters'!$D$6:$D$1367,C10,'Scored quarters'!$F$6:$F$1367,D10,'Scored quarters'!$G$6:$G$1367,E10) -> 8 | G10: =SQRT(SUMIFS('Scored quarters'!$K$6:$K$1367,'Scored quarters'!$C$6:$C$1367,B10,'Scored quarters'!$D$6:$D$1367,C10,'Scored quarters'!$F$6:$F$1367,D10,'Scored quarters'!$G$6:$G$1367,E10)/F10) -> 1.7410485 | H10: =SQRT(SUMIFS('Scored quarters'!$L$6:$L$1367,'Scored quarters'!$C$6:$C$1367,B10,'Scored quarters'!$D$6:$D$1367,C10,'Scored quarters'!$F$6:$F$1367,D10,'Scored quarters'!$G$6:$G$1367,E10)/F10) -> 1.7410485 | I10: =SQRT(SUMIFS('Scored quarters'!$M$6:$M$1367,'Scored quarters'!$C$6:$C$1367,B10,'Scored quarters'!$D$6:$D$1367,C10,'Scored quarters'!$F$6:$F$1367,D10,'Scored quarters'!$G$6:$G$1367,E10)/F10) -> 1.4142136 | J10: =SUMIFS('Scored quarters'!$O$6:$O$1367,'Scored quarters'!$C$6:$C$1367,B10,'Scored quarters'!$D$6:$D$1367,C10,'Scored quarters'!$F$6:$F$1367,D10,'Scored quarters'!$G$6:$G$1367,E10)/F10 -> 1.3125 | K10: =SUMIFS('Scored quarters'!$J$6:$J$1367,'Scored quarters'!$C$6:$C$1367,B10,'Scored quarters'!$D$6:$D$1367,C10,'Scored quarters'!$F$6:$F$1367,D10,'Scored quarters'!$G$6:$G$1367,E10)/F10 -> -1.1875 | L10: =SUMIFS('Scored quarters'!$N$6:$N$1367,'Scored quarters'!$C$6:$C$1367,B10,'Scored quarters'!$D$6:$D$1367,C10,'Scored quarters'!$F$6:$F$1367,D10,'Scored quarters'!$G$6:$G$1367,E10) -> 0
B11: Beauty | C11: organic_volume_growth | D11: First month | E11: last_actual | F11: =COUNTIFS('Scored quarters'!$C$6:$C$1367,B11,'Scored quarters'!$D$6:$D$1367,C11,'Scored quarters'!$F$6:$F$1367,D11,'Scored quarters'!$G$6:$G$1367,E11) -> 8 | G11: =SQRT(SUMIFS('Scored quarters'!$K$6:$K$1367,'Scored quarters'!$C$6:$C$1367,B11,'Scored quarters'!$D$6:$D$1367,C11,'Scored quarters'!$F$6:$F$1367,D11,'Scored quarters'!$G$6:$G$1367,E11)/F11) -> 1.4142136 | H11: =SQRT(SUMIFS('Scored quarters'!$L$6:$L$1367,'Scored quarters'!$C$6:$C$1367,B11,'Scored quarters'!$D$6:$D$1367,C11,'Scored quarters'!$F$6:$F$1367,D11,'Scored quarters'!$G$6:$G$1367,E11)/F11) -> 1.7410485 | I11: =SQRT(SUMIFS('Scored quarters'!$M$6:$M$1367,'Scored quarters'!$C$6:$C$1367,B11,'Scored quarters'!$D$6:$D$1367,C11,'Scored quarters'!$F$6:$F$1367,D11,'Scored quarters'!$G$6:$G$1367,E11)/F11) -> 1.4142136 | J11: =SUMIFS('Scored quarters'!$O$6:$O$1367,'Scored quarters'!$C$6:$C$1367,B11,'Scored quarters'!$D$6:$D$1367,C11,'Scored quarters'!$F$6:$F$1367,D11,'Scored quarters'!$G$6:$G$1367,E11)/F11 -> 1 | K11: =SUMIFS('Scored quarters'!$J$6:$J$1367,'Scored quarters'!$C$6:$C$1367,B11,'Scored quarters'!$D$6:$D$1367,C11,'Scored quarters'!$F$6:$F$1367,D11,'Scored quarters'!$G$6:$G$1367,E11)/F11 -> -0.5 | L11: =SUMIFS('Scored quarters'!$N$6:$N$1367,'Scored quarters'!$C$6:$C$1367,B11,'Scored quarters'!$D$6:$D$1367,C11,'Scored quarters'!$F$6:$F$1367,D11,'Scored quarters'!$G$6:$G$1367,E11) -> 6
B12: Beauty | C12: organic_volume_growth | D12: First month | E12: bridge | F12: =COUNTIFS('Scored quarters'!$C$6:$C$1367,B12,'Scored quarters'!$D$6:$D$1367,C12,'Scored quarters'!$F$6:$F$1367,D12,'Scored quarters'!$G$6:$G$1367,E12) -> 8 | G12: =SQRT(SUMIFS('Scored quarters'!$K$6:$K$1367,'Scored quarters'!$C$6:$C$1367,B12,'Scored quarters'!$D$6:$D$1367,C12,'Scored quarters'!$F$6:$F$1367,D12,'Scored quarters'!$G$6:$G$1367,E12)/F12) -> 2.3158154 | H12: =SQRT(SUMIFS('Scored quarters'!$L$6:$L$1367,'Scored quarters'!$C$6:$C$1367,B12,'Scored quarters'!$D$6:$D$1367,C12,'Scored quarters'!$F$6:$F$1367,D12,'Scored quarters'!$G$6:$G$1367,E12)/F12) -> 1.7410485 | I12: =SQRT(SUMIFS('Scored quarters'!$M$6:$M$1367,'Scored quarters'!$C$6:$C$1367,B12,'Scored quarters'!$D$6:$D$1367,C12,'Scored quarters'!$F$6:$F$1367,D12,'Scored quarters'!$G$6:$G$1367,E12)/F12) -> 1.4142136 | J12: =SUMIFS('Scored quarters'!$O$6:$O$1367,'Scored quarters'!$C$6:$C$1367,B12,'Scored quarters'!$D$6:$D$1367,C12,'Scored quarters'!$F$6:$F$1367,D12,'Scored quarters'!$G$6:$G$1367,E12)/F12 -> 1.7398249 | K12: =SUMIFS('Scored quarters'!$J$6:$J$1367,'Scored quarters'!$C$6:$C$1367,B12,'Scored quarters'!$D$6:$D$1367,C12,'Scored quarters'!$F$6:$F$1367,D12,'Scored quarters'!$G$6:$G$1367,E12)/F12 -> -1.7398249 | L12: =SUMIFS('Scored quarters'!$N$6:$N$1367,'Scored quarters'!$C$6:$C$1367,B12,'Scored quarters'!$D$6:$D$1367,C12,'Scored quarters'!$F$6:$F$1367,D12,'Scored quarters'!$G$6:$G$1367,E12) -> 2
B13: Beauty | C13: organic_volume_growth | D13: First month | E13: lagged | F13: =COUNTIFS('Scored quarters'!$C$6:$C$1367,B13,'Scored quarters'!$D$6:$D$1367,C13,'Scored quarters'!$F$6:$F$1367,D13,'Scored quarters'!$G$6:$G$1367,E13) -> 8 | G13: =SQRT(SUMIFS('Scored quarters'!$K$6:$K$1367,'Scored quarters'!$C$6:$C$1367,B13,'Scored quarters'!$D$6:$D$1367,C13,'Scored quarters'!$F$6:$F$1367,D13,'Scored quarters'!$G$6:$G$1367,E13)/F13) -> 2.4015705 | H13: =SQRT(SUMIFS('Scored quarters'!$L$6:$L$1367,'Scored quarters'!$C$6:$C$1367,B13,'Scored quarters'!$D$6:$D$1367,C13,'Scored quarters'!$F$6:$F$1367,D13,'Scored quarters'!$G$6:$G$1367,E13)/F13) -> 1.7410485 | I13: =SQRT(SUMIFS('Scored quarters'!$M$6:$M$1367,'Scored quarters'!$C$6:$C$1367,B13,'Scored quarters'!$D$6:$D$1367,C13,'Scored quarters'!$F$6:$F$1367,D13,'Scored quarters'!$G$6:$G$1367,E13)/F13) -> 1.4142136 | J13: =SUMIFS('Scored quarters'!$O$6:$O$1367,'Scored quarters'!$C$6:$C$1367,B13,'Scored quarters'!$D$6:$D$1367,C13,'Scored quarters'!$F$6:$F$1367,D13,'Scored quarters'!$G$6:$G$1367,E13)/F13 -> 1.9642891 | K13: =SUMIFS('Scored quarters'!$J$6:$J$1367,'Scored quarters'!$C$6:$C$1367,B13,'Scored quarters'!$D$6:$D$1367,C13,'Scored quarters'!$F$6:$F$1367,D13,'Scored quarters'!$G$6:$G$1367,E13)/F13 -> -1.9642891 | L13: =SUMIFS('Scored quarters'!$N$6:$N$1367,'Scored quarters'!$C$6:$C$1367,B13,'Scored quarters'!$D$6:$D$1367,C13,'Scored quarters'!$F$6:$F$1367,D13,'Scored quarters'!$G$6:$G$1367,E13) -> 0
B14: Beauty | C14: organic_volume_growth | D14: First month | E14: blend | F14: =COUNTIFS('Scored quarters'!$C$6:$C$1367,B14,'Scored quarters'!$D$6:$D$1367,C14,'Scored quarters'!$F$6:$F$1367,D14,'Scored quarters'!$G$6:$G$1367,E14) -> 8 | G14: =SQRT(SUMIFS('Scored quarters'!$K$6:$K$1367,'Scored quarters'!$C$6:$C$1367,B14,'Scored quarters'!$D$6:$D$1367,C14,'Scored quarters'!$F$6:$F$1367,D14,'Scored quarters'!$G$6:$G$1367,E14)/F14) -> 2.0101564 | H14: =SQRT(SUMIFS('Scored quarters'!$L$6:$L$1367,'Scored quarters'!$C$6:$C$1367,B14,'Scored quarters'!$D$6:$D$1367,C14,'Scored quarters'!$F$6:$F$1367,D14,'Scored quarters'!$G$6:$G$1367,E14)/F14) -> 1.7410485 | I14: =SQRT(SUMIFS('Scored quarters'!$M$6:$M$1367,'Scored quarters'!$C$6:$C$1367,B14,'Scored quarters'!$D$6:$D$1367,C14,'Scored quarters'!$F$6:$F$1367,D14,'Scored quarters'!$G$6:$G$1367,E14)/F14) -> 1.4142136 | J14: =SUMIFS('Scored quarters'!$O$6:$O$1367,'Scored quarters'!$C$6:$C$1367,B14,'Scored quarters'!$D$6:$D$1367,C14,'Scored quarters'!$F$6:$F$1367,D14,'Scored quarters'!$G$6:$G$1367,E14)/F14 -> 1.4908202 | K14: =SUMIFS('Scored quarters'!$J$6:$J$1367,'Scored quarters'!$C$6:$C$1367,B14,'Scored quarters'!$D$6:$D$1367,C14,'Scored quarters'!$F$6:$F$1367,D14,'Scored quarters'!$G$6:$G$1367,E14)/F14 -> -1.4636625 | L14: =SUMIFS('Scored quarters'!$N$6:$N$1367,'Scored quarters'!$C$6:$C$1367,B14,'Scored quarters'!$D$6:$D$1367,C14,'Scored quarters'!$F$6:$F$1367,D14,'Scored quarters'!$G$6:$G$1367,E14) -> 3
B15: Beauty | C15: organic_volume_growth | D15: Second month | E15: baseline | F15: =COUNTIFS('Scored quarters'!$C$6:$C$1367,B15,'Scored quarters'!$D$6:$D$1367,C15,'Scored quarters'!$F$6:$F$1367,D15,'Scored quarters'!$G$6:$G$1367,E15) -> 8 | G15: =SQRT(SUMIFS('Scored quarters'!$K$6:$K$1367,'Scored quarters'!$C$6:$C$1367,B15,'Scored quarters'!$D$6:$D$1367,C15,'Scored quarters'!$F$6:$F$1367,D15,'Scored quarters'!$G$6:$G$1367,E15)/F15) -> 1.7410485 | H15: =SQRT(SUMIFS('Scored quarters'!$L$6:$L$1367,'Scored quarters'!$C$6:$C$1367,B15,'Scored quarters'!$D$6:$D$1367,C15,'Scored quarters'!$F$6:$F$1367,D15,'Scored quarters'!$G$6:$G$1367,E15)/F15) -> 1.7410485 | I15: =SQRT(SUMIFS('Scored quarters'!$M$6:$M$1367,'Scored quarters'!$C$6:$C$1367,B15,'Scored quarters'!$D$6:$D$1367,C15,'Scored quarters'!$F$6:$F$1367,D15,'Scored quarters'!$G$6:$G$1367,E15)/F15) -> 1.4142136 | J15: =SUMIFS('Scored quarters'!$O$6:$O$1367,'Scored quarters'!$C$6:$C$1367,B15,'Scored quarters'!$D$6:$D$1367,C15,'Scored quarters'!$F$6:$F$1367,D15,'Scored quarters'!$G$6:$G$1367,E15)/F15 -> 1.3125 | K15: =SUMIFS('Scored quarters'!$J$6:$J$1367,'Scored quarters'!$C$6:$C$1367,B15,'Scored quarters'!$D$6:$D$1367,C15,'Scored quarters'!$F$6:$F$1367,D15,'Scored quarters'!$G$6:$G$1367,E15)/F15 -> -1.1875 | L15: =SUMIFS('Scored quarters'!$N$6:$N$1367,'Scored quarters'!$C$6:$C$1367,B15,'Scored quarters'!$D$6:$D$1367,C15,'Scored quarters'!$F$6:$F$1367,D15,'Scored quarters'!$G$6:$G$1367,E15) -> 0
B16: Beauty | C16: organic_volume_growth | D16: Second month | E16: last_actual | F16: =COUNTIFS('Scored quarters'!$C$6:$C$1367,B16,'Scored quarters'!$D$6:$D$1367,C16,'Scored quarters'!$F$6:$F$1367,D16,'Scored quarters'!$G$6:$G$1367,E16) -> 8 | G16: =SQRT(SUMIFS('Scored quarters'!$K$6:$K$1367,'Scored quarters'!$C$6:$C$1367,B16,'Scored quarters'!$D$6:$D$1367,C16,'Scored quarters'!$F$6:$F$1367,D16,'Scored quarters'!$G$6:$G$1367,E16)/F16) -> 1.4142136 | H16: =SQRT(SUMIFS('Scored quarters'!$L$6:$L$1367,'Scored quarters'!$C$6:$C$1367,B16,'Scored quarters'!$D$6:$D$1367,C16,'Scored quarters'!$F$6:$F$1367,D16,'Scored quarters'!$G$6:$G$1367,E16)/F16) -> 1.7410485 | I16: =SQRT(SUMIFS('Scored quarters'!$M$6:$M$1367,'Scored quarters'!$C$6:$C$1367,B16,'Scored quarters'!$D$6:$D$1367,C16,'Scored quarters'!$F$6:$F$1367,D16,'Scored quarters'!$G$6:$G$1367,E16)/F16) -> 1.4142136 | J16: =SUMIFS('Scored quarters'!$O$6:$O$1367,'Scored quarters'!$C$6:$C$1367,B16,'Scored quarters'!$D$6:$D$1367,C16,'Scored quarters'!$F$6:$F$1367,D16,'Scored quarters'!$G$6:$G$1367,E16)/F16 -> 1 | K16: =SUMIFS('Scored quarters'!$J$6:$J$1367,'Scored quarters'!$C$6:$C$1367,B16,'Scored quarters'!$D$6:$D$1367,C16,'Scored quarters'!$F$6:$F$1367,D16,'Scored quarters'!$G$6:$G$1367,E16)/F16 -> -0.5 | L16: =SUMIFS('Scored quarters'!$N$6:$N$1367,'Scored quarters'!$C$6:$C$1367,B16,'Scored quarters'!$D$6:$D$1367,C16,'Scored quarters'!$F$6:$F$1367,D16,'Scored quarters'!$G$6:$G$1367,E16) -> 6
B17: Beauty | C17: organic_volume_growth | D17: Second month | E17: bridge | F17: =COUNTIFS('Scored quarters'!$C$6:$C$1367,B17,'Scored quarters'!$D$6:$D$1367,C17,'Scored quarters'!$F$6:$F$1367,D17,'Scored quarters'!$G$6:$G$1367,E17) -> 8 | G17: =SQRT(SUMIFS('Scored quarters'!$K$6:$K$1367,'Scored quarters'!$C$6:$C$1367,B17,'Scored quarters'!$D$6:$D$1367,C17,'Scored quarters'!$F$6:$F$1367,D17,'Scored quarters'!$G$6:$G$1367,E17)/F17) -> 2.432074 | H17: =SQRT(SUMIFS('Scored quarters'!$L$6:$L$1367,'Scored quarters'!$C$6:$C$1367,B17,'Scored quarters'!$D$6:$D$1367,C17,'Scored quarters'!$F$6:$F$1367,D17,'Scored quarters'!$G$6:$G$1367,E17)/F17) -> 1.7410485 | I17: =SQRT(SUMIFS('Scored quarters'!$M$6:$M$1367,'Scored quarters'!$C$6:$C$1367,B17,'Scored quarters'!$D$6:$D$1367,C17,'Scored quarters'!$F$6:$F$1367,D17,'Scored quarters'!$G$6:$G$1367,E17)/F17) -> 1.4142136 | J17: =SUMIFS('Scored quarters'!$O$6:$O$1367,'Scored quarters'!$C$6:$C$1367,B17,'Scored quarters'!$D$6:$D$1367,C17,'Scored quarters'!$F$6:$F$1367,D17,'Scored quarters'!$G$6:$G$1367,E17)/F17 -> 1.7611425 | K17: =SUMIFS('Scored quarters'!$J$6:$J$1367,'Scored quarters'!$C$6:$C$1367,B17,'Scored quarters'!$D$6:$D$1367,C17,'Scored quarters'!$F$6:$F$1367,D17,'Scored quarters'!$G$6:$G$1367,E17)/F17 -> -1.7611425 | L17: =SUMIFS('Scored quarters'!$N$6:$N$1367,'Scored quarters'!$C$6:$C$1367,B17,'Scored quarters'!$D$6:$D$1367,C17,'Scored quarters'!$F$6:$F$1367,D17,'Scored quarters'!$G$6:$G$1367,E17) -> 3
... B176: Health Care | C176: organic_sales_growth | D176: Pre-earnings | E176: blend | F176: =COUNTIFS('Scored quarters'!$C$6:$C$1367,B176,'Scored quarters'!$D$6:$D$1367,C176,'Scored quarters'!$F$6:$F$1367,D176,'Scored quarters'!$G$6:$G$1367,E176) -> 8 | G176: =SQRT(SUMIFS('Scored quarters'!$K$6:$K$1367,'Scored quarters'!$C$6:$C$1367,B176,'Scored quarters'!$D$6:$D$1367,C176,'Scored quarters'!$F$6:$F$1367,D176,'Scored quarters'!$G$6:$G$1367,E176)/F176) -> 2.3169169 | H176: =SQRT(SUMIFS('Scored quarters'!$L$6:$L$1367,'Scored quarters'!$C$6:$C$1367,B176,'Scored quarters'!$D$6:$D$1367,C176,'Scored quarters'!$F$6:$F$1367,D176,'Scored quarters'!$G$6:$G$1367,E176)/F176) -> 1.118034 | I176: =SQRT(SUMIFS('Scored quarters'!$M$6:$M$1367,'Scored quarters'!$C$6:$C$1367,B176,'Scored quarters'!$D$6:$D$1367,C176,'Scored quarters'!$F$6:$F$1367,D176,'Scored quarters'!$G$6:$G$1367,E176)/F176) -> 1.4142136 | J176: =SUMIFS('Scored quarters'!$O$6:$O$1367,'Scored quarters'!$C$6:$C$1367,B176,'Scored quarters'!$D$6:$D$1367,C176,'Scored quarters'!$F$6:$F$1367,D176,'Scored quarters'!$G$6:$G$1367,E176)/F176 -> 2.1402169 | K176: =SUMIFS('Scored quarters'!$J$6:$J$1367,'Scored quarters'!$C$6:$C$1367,B176,'Scored quarters'!$D$6:$D$1367,C176,'Scored quarters'!$F$6:$F$1367,D176,'Scored quarters'!$G$6:$G$1367,E176)/F176 -> 2.1402169 | L176: =SUMIFS('Scored quarters'!$N$6:$N$1367,'Scored quarters'!$C$6:$C$1367,B176,'Scored quarters'!$D$6:$D$1367,C176,'Scored quarters'!$F$6:$F$1367,D176,'Scored quarters'!$G$6:$G$1367,E176) -> 0

Sheet Scored quarters
B2: Score only after P&G publishes actuals
B5: Forecast ID | C5: Segment | D5: Measure | E5: Quarter | F5: Stage | G5: Method | H5: Prediction | I5: Actual | J5: Error pp | K5: Squared error | L5: Mean error squared | M5: Last actual error squared | N5: Beats mean? | O5: Absolute error
B6: 1 | C6: Beauty | D6: organic_volume_growth | E6: 45473 | F6: Origin | G6: baseline | H6: ='Forecast log'!H6 -> -0.5 | I6: ='PG facts'!D69 -> 1 | J6: =H6-I6 -> -1.5 | K6: =J6^2 -> 2.25 | L6: =('Forecast log'!H6-I6)^2 -> 2.25 | M6: =('Forecast log'!I6-I6)^2 -> 4 | N6: =IF(ABS(J6)<SQRT(L6),1,0) -> 0 | O6: =ABS(J6) -> 1.5
B7: 1 | C7: Beauty | D7: organic_volume_growth | E7: 45473 | F7: Origin | G7: last_actual | H7: ='Forecast log'!I6 -> -1 | I7: ='PG facts'!D69 -> 1 | J7: =H7-I7 -> -2 | K7: =J7^2 -> 4 | L7: =('Forecast log'!H6-I7)^2 -> 2.25 | M7: =('Forecast log'!I6-I7)^2 -> 4 | N7: =IF(ABS(J7)<SQRT(L7),1,0) -> 0 | O7: =ABS(J7) -> 2
B8: 1 | C8: Beauty | D8: organic_volume_growth | E8: 45473 | F8: Origin | G8: bridge | H8: ='Forecast log'!N6 -> -0.95439473 | I8: ='PG facts'!D69 -> 1 | J8: =H8-I8 -> -1.9543947 | K8: =J8^2 -> 3.8196588 | L8: =('Forecast log'!H6-I8)^2 -> 2.25 | M8: =('Forecast log'!I6-I8)^2 -> 4 | N8: =IF(ABS(J8)<SQRT(L8),1,0) -> 0 | O8: =ABS(J8) -> 1.9543947
B9: 1 | C9: Beauty | D9: organic_volume_growth | E9: 45473 | F9: Origin | G9: blend | H9: ='Forecast log'!T6 -> -0.72719737 | I9: ='PG facts'!D69 -> 1 | J9: =H9-I9 -> -1.7271974 | K9: =J9^2 -> 2.9832107 | L9: =('Forecast log'!H6-I9)^2 -> 2.25 | M9: =('Forecast log'!I6-I9)^2 -> 4 | N9: =IF(ABS(J9)<SQRT(L9),1,0) -> 0 | O9: =ABS(J9) -> 1.7271974
B10: 7 | C10: Beauty | D10: organic_volume_growth | E10: 45473 | F10: Pre-earnings | G10: baseline | H10: ='Forecast log'!H12 -> -0.25 | I10: ='PG facts'!D69 -> 1 | J10: =H10-I10 -> -1.25 | K10: =J10^2 -> 1.5625 | L10: =('Forecast log'!H12-I10)^2 -> 1.5625 | M10: =('Forecast log'!I12-I10)^2 -> 0 | N10: =IF(ABS(J10)<SQRT(L10),1,0) -> 0 | O10: =ABS(J10) -> 1.25
B11: 7 | C11: Beauty | D11: organic_volume_growth | E11: 45473 | F11: Pre-earnings | G11: last_actual | H11: ='Forecast log'!I12 -> 1 | I11: ='PG facts'!D69 -> 1 | J11: =H11-I11 -> 0 | K11: =J11^2 -> 0 | L11: =('Forecast log'!H12-I11)^2 -> 1.5625 | M11: =('Forecast log'!I12-I11)^2 -> 0 | N11: =IF(ABS(J11)<SQRT(L11),1,0) -> 1 | O11: =ABS(J11) -> 0
B12: 7 | C12: Beauty | D12: organic_volume_growth | E12: 45473 | F12: Pre-earnings | G12: bridge | H12: ='Forecast log'!N12 -> -0.63217368 | I12: ='PG facts'!D69 -> 1 | J12: =H12-I12 -> -1.6321737 | K12: =J12^2 -> 2.6639909 | L12: =('Forecast log'!H12-I12)^2 -> 1.5625 | M12: =('Forecast log'!I12-I12)^2 -> 0 | N12: =IF(ABS(J12)<SQRT(L12),1,0) -> 0 | O12: =ABS(J12) -> 1.6321737
B13: 7 | C13: Beauty | D13: organic_volume_growth | E13: 45473 | F13: Pre-earnings | G13: lagged | H13: ='Forecast log'!S12 -> -0.9593244 | I13: ='PG facts'!D69 -> 1 | J13: =H13-I13 -> -1.9593244 | K13: =J13^2 -> 3.8389521 | L13: =('Forecast log'!H12-I13)^2 -> 1.5625 | M13: =('Forecast log'!I12-I13)^2 -> 0 | N13: =IF(ABS(J13)<SQRT(L13),1,0) -> 0 | O13: =ABS(J13) -> 1.9593244
B14: 7 | C14: Beauty | D14: organic_volume_growth | E14: 45473 | F14: Pre-earnings | G14: blend | H14: ='Forecast log'!T12 -> -0.44108684 | I14: ='PG facts'!D69 -> 1 | J14: =H14-I14 -> -1.4410868 | K14: =J14^2 -> 2.0767313 | L14: =('Forecast log'!H12-I14)^2 -> 1.5625 | M14: =('Forecast log'!I12-I14)^2 -> 0 | N14: =IF(ABS(J14)<SQRT(L14),1,0) -> 0 | O14: =ABS(J14) -> 1.4410868
B15: 4 | C15: Beauty | D15: organic_volume_growth | E15: 45473 | F15: First month | G15: baseline | H15: ='Forecast log'!H9 -> -0.25 | I15: ='PG facts'!D69 -> 1 | J15: =H15-I15 -> -1.25 | K15: =J15^2 -> 1.5625 | L15: =('Forecast log'!H9-I15)^2 -> 1.5625 | M15: =('Forecast log'!I9-I15)^2 -> 0 | N15: =IF(ABS(J15)<SQRT(L15),1,0) -> 0 | O15: =ABS(J15) -> 1.25
B16: 4 | C16: Beauty | D16: organic_volume_growth | E16: 45473 | F16: First month | G16: last_actual | H16: ='Forecast log'!I9 -> 1 | I16: ='PG facts'!D69 -> 1 | J16: =H16-I16 -> 0 | K16: =J16^2 -> 0 | L16: =('Forecast log'!H9-I16)^2 -> 1.5625 | M16: =('Forecast log'!I9-I16)^2 -> 0 | N16: =IF(ABS(J16)<SQRT(L16),1,0) -> 1 | O16: =ABS(J16) -> 0
B17: 4 | C17: Beauty | D17: organic_volume_growth | E17: 45473 | F17: First month | G17: bridge | H17: ='Forecast log'!N9 -> -0.61787849 | I17: ='PG facts'!D69 -> 1 | J17: =H17-I17 -> -1.6178785 | K17: =J17^2 -> 2.6175308 | L17: =('Forecast log'!H9-I17)^2 -> 1.5625 | M17: =('Forecast log'!I9-I17)^2 -> 0 | N17: =IF(ABS(J17)<SQRT(L17),1,0) -> 0 | O17: =ABS(J17) -> 1.6178785
B18: 4 | C18: Beauty | D18: organic_volume_growth | E18: 45473 | F18: First month | G18: lagged | H18: ='Forecast log'!S9 -> -0.9542201 | I18: ='PG facts'!D69 -> 1 | J18: =H18-I18 -> -1.9542201 | K18: =J18^2 -> 3.8189762 | L18: =('Forecast log'!H9-I18)^2 -> 1.5625 | M18: =('Forecast log'!I9-I18)^2 -> 0 | N18: =IF(ABS(J18)<SQRT(L18),1,0) -> 0 | O18: =ABS(J18) -> 1.9542201
B19: 4 | C19: Beauty | D19: organic_volume_growth | E19: 45473 | F19: First month | G19: blend | H19: ='Forecast log'!T9 -> -0.43393925 | I19: ='PG facts'!D69 -> 1 | J19: =H19-I19 -> -1.4339392 | K19: =J19^2 -> 2.0561818 | L19: =('Forecast log'!H9-I19)^2 -> 1.5625 | M19: =('Forecast log'!I9-I19)^2 -> 0 | N19: =IF(ABS(J19)<SQRT(L19),1,0) -> 0 | O19: =ABS(J19) -> 1.4339392
B20: 5 | C20: Beauty | D20: organic_volume_growth | E20: 45473 | F20: Second month | G20: baseline | H20: ='Forecast log'!H10 -> -0.25 | I20: ='PG facts'!D69 -> 1 | J20: =H20-I20 -> -1.25 | K20: =J20^2 -> 1.5625 | L20: =('Forecast log'!H10-I20)^2 -> 1.5625 | M20: =('Forecast log'!I10-I20)^2 -> 0 | N20: =IF(ABS(J20)<SQRT(L20),1,0) -> 0 | O20: =ABS(J20) -> 1.25
B21: 5 | C21: Beauty | D21: organic_volume_growth | E21: 45473 | F21: Second month | G21: last_actual | H21: ='Forecast log'!I10 -> 1 | I21: ='PG facts'!D69 -> 1 | J21: =H21-I21 -> 0 | K21: =J21^2 -> 0 | L21: =('Forecast log'!H10-I21)^2 -> 1.5625 | M21: =('Forecast log'!I10-I21)^2 -> 0 | N21: =IF(ABS(J21)<SQRT(L21),1,0) -> 1 | O21: =ABS(J21) -> 0
B22: 5 | C22: Beauty | D22: organic_volume_growth | E22: 45473 | F22: Second month | G22: bridge | H22: ='Forecast log'!N10 -> -0.70010948 | I22: ='PG facts'!D69 -> 1 | J22: =H22-I22 -> -1.7001095 | K22: =J22^2 -> 2.8903722 | L22: =('Forecast log'!H10-I22)^2 -> 1.5625 | M22: =('Forecast log'!I10-I22)^2 -> 0 | N22: =IF(ABS(J22)<SQRT(L22),1,0) -> 0 | O22: =ABS(J22) -> 1.7001095
B23: 5 | C23: Beauty | D23: organic_volume_growth | E23: 45473 | F23: Second month | G23: lagged | H23: ='Forecast log'!S10 -> -0.9593244 | I23: ='PG facts'!D69 -> 1 | J23: =H23-I23 -> -1.9593244 | K23: =J23^2 -> 3.8389521 | L23: =('Forecast log'!H10-I23)^2 -> 1.5625 | M23: =('Forecast log'!I10-I23)^2 -> 0 | N23: =IF(ABS(J23)<SQRT(L23),1,0) -> 0 | O23: =ABS(J23) -> 1.9593244
B24: 5 | C24: Beauty | D24: organic_volume_growth | E24: 45473 | F24: Second month | G24: blend | H24: ='Forecast log'!T10 -> -0.47505474 | I24: ='PG facts'!D69 -> 1 | J24: =H24-I24 -> -1.4750547 | K24: =J24^2 -> 2.1757865 | L24: =('Forecast log'!H10-I24)^2 -> 1.5625 | M24: =('Forecast log'!I10-I24)^2 -> 0 | N24: =IF(ABS(J24)<SQRT(L24),1,0) -> 0 | O24: =ABS(J24) -> 1.4750547
B25: 66 | C25: Beauty | D25: organic_volume_growth | E25: 45565 | F25: Origin | G25: baseline | H25: ='Forecast log'!H71 -> -0.25 | I25: ='PG facts'!D76 -> 0 | J25: =H25-I25 -> -0.25 | K25: =J25^2 -> 0.0625 | L25: =('Forecast log'!H71-I25)^2 -> 0.0625 | M25: =('Forecast log'!I71-I25)^2 -> 1 | N25: =IF(ABS(J25)<SQRT(L25),1,0) -> 0 | O25: =ABS(J25) -> 0.25
B26: 66 | C26: Beauty | D26: organic_volume_growth | E26: 45565 | F26: Origin | G26: last_actual | H26: ='Forecast log'!I71 -> 1 | I26: ='PG facts'!D76 -> 0 | J26: =H26-I26 -> 1 | K26: =J26^2 -> 1 | L26: =('Forecast log'!H71-I26)^2 -> 0.0625 | M26: =('Forecast log'!I71-I26)^2 -> 1 | N26: =IF(ABS(J26)<SQRT(L26),1,0) -> 0 | O26: =ABS(J26) -> 1
B27: 66 | C27: Beauty | D27: organic_volume_growth | E27: 45565 | F27: Origin | G27: bridge | H27: ='Forecast log'!N71 -> -0.6071972 | I27: ='PG facts'!D76 -> 0 | J27: =H27-I27 -> -0.6071972 | K27: =J27^2 -> 0.36868844 | L27: =('Forecast log'!H71-I27)^2 -> 0.0625 | M27: =('Forecast log'!I71-I27)^2 -> 1 | N27: =IF(ABS(J27)<SQRT(L27),1,0) -> 0 | O27: =ABS(J27) -> 0.6071972
B28: 66 | C28: Beauty | D28: organic_volume_growth | E28: 45565 | F28: Origin | G28: blend | H28: ='Forecast log'!T71 -> -0.4285986 | I28: ='PG facts'!D76 -> 0 | J28: =H28-I28 -> -0.4285986 | K28: =J28^2 -> 0.18369676 | L28: =('Forecast log'!H71-I28)^2 -> 0.0625 | M28: =('Forecast log'!I71-I28)^2 -> 1 | N28: =IF(ABS(J28)<SQRT(L28),1,0) -> 0 | O28: =ABS(J28) -> 0.4285986
B29: 71 | C29: Beauty | D29: organic_volume_growth | E29: 45565 | F29: Pre-earnings | G29: baseline | H29: ='Forecast log'!H76 -> 0.25 | I29: ='PG facts'!D76 -> 0 | J29: =H29-I29 -> 0.25 | K29: =J29^2 -> 0.0625 | L29: =('Forecast log'!H76-I29)^2 -> 0.0625 | M29: =('Forecast log'!I76-I29)^2 -> 1 | N29: =IF(ABS(J29)<SQRT(L29),1,0) -> 0 | O29: =ABS(J29) -> 0.25
B30: 71 | C30: Beauty | D30: organic_volume_growth | E30: 45565 | F30: Pre-earnings | G30: last_actual | H30: ='Forecast log'!I76 -> 1 | I30: ='PG facts'!D76 -> 0 | J30: =H30-I30 -> 1 | K30: =J30^2 -> 1 | L30: =('Forecast log'!H76-I30)^2 -> 0.0625 | M30: =('Forecast log'!I76-I30)^2 -> 1 | N30: =IF(ABS(J30)<SQRT(L30),1,0) -> 0 | O30: =ABS(J30) -> 1
B31: 71 | C31: Beauty | D31: organic_volume_growth | E31: 45565 | F31: Pre-earnings | G31: bridge | H31: ='Forecast log'!N76 -> -0.051498095 | I31: ='PG facts'!D76 -> 0 | J31: =H31-I31 -> -0.051498095 | K31: =J31^2 -> 0.0026520538 | L31: =('Forecast log'!H76-I31)^2 -> 0.0625 | M31: =('Forecast log'!I76-I31)^2 -> 1 | N31: =IF(ABS(J31)<SQRT(L31),1,0) -> 1 | O31: =ABS(J31) -> 0.051498095
B32: 71 | C32: Beauty | D32: organic_volume_growth | E32: 45565 | F32: Pre-earnings | G32: lagged | H32: ='Forecast log'!S76 -> -0.53242653 | I32: ='PG facts'!D76 -> 0 | J32: =H32-I32 -> -0.53242653 | K32: =J32^2 -> 0.28347801 | L32: =('Forecast log'!H76-I32)^2 -> 0.0625 | M32: =('Forecast log'!I76-I32)^2 -> 1 | N32: =IF(ABS(J32)<SQRT(L32),1,0) -> 0 | O32: =ABS(J32) -> 0.53242653
B33: 71 | C33: Beauty | D33: organic_volume_growth | E33: 45565 | F33: Pre-earnings | G33: blend | H33: ='Forecast log'!T76 -> 0.099250953 | I33: ='PG facts'!D76 -> 0 | J33: =H33-I33 -> 0.099250953 | K33: =J33^2 -> 0.0098507516 | L33: =('Forecast log'!H76-I33)^2 -> 0.0625 | M33: =('Forecast log'!I76-I33)^2 -> 1 | N33: =IF(ABS(J33)<SQRT(L33),1,0) -> 1 | O33: =ABS(J33) -> 0.099250953
B34: 69 | C34: Beauty | D34: organic_volume_growth | E34: 45565 | F34: First month | G34: baseline | H34: ='Forecast log'!H74 -> 0.25 | I34: ='PG facts'!D76 -> 0 | J34: =H34-I34 -> 0.25 | K34: =J34^2 -> 0.0625 | L34: =('Forecast log'!H74-I34)^2 -> 0.0625 | M34: =('Forecast log'!I74-I34)^2 -> 1 | N34: =IF(ABS(J34)<SQRT(L34),1,0) -> 0 | O34: =ABS(J34) -> 0.25
B35: 69 | C35: Beauty | D35: organic_volume_growth | E35: 45565 | F35: First month | G35: last_actual | H35: ='Forecast log'!I74 -> 1 | I35: ='PG facts'!D76 -> 0 | J35: =H35-I35 -> 1 | K35: =J35^2 -> 1 | L35: =('Forecast log'!H74-I35)^2 -> 0.0625 | M35: =('Forecast log'!I74-I35)^2 -> 1 | N35: =IF(ABS(J35)<SQRT(L35),1,0) -> 0 | O35: =ABS(J35) -> 1
B36: 69 | C36: Beauty | D36: organic_volume_growth | E36: 45565 | F36: First month | G36: bridge | H36: ='Forecast log'!N74 -> -0.34776572 | I36: ='PG facts'!D76 -> 0 | J36: =H36-I36 -> -0.34776572 | K36: =J36^2 -> 0.12094099 | L36: =('Forecast log'!H74-I36)^2 -> 0.0625 | M36: =('Forecast log'!I74-I36)^2 -> 1 | N36: =IF(ABS(J36)<SQRT(L36),1,0) -> 0 | O36: =ABS(J36) -> 0.34776572
B37: 69 | C37: Beauty | D37: organic_volume_growth | E37: 45565 | F37: First month | G37: lagged | H37: ='Forecast log'!S74 -> -0.63678505 | I37: ='PG facts'!D76 -> 0 | J37: =H37-I37 -> -0.63678505 | K37: =J37^2 -> 0.4054952 | L37: =('Forecast log'!H74-I37)^2 -> 0.0625 | M37: =('Forecast log'!I74-I37)^2 -> 1 | N37: =IF(ABS(J37)<SQRT(L37),1,0) -> 0 | O37: =ABS(J37) -> 0.63678505
B38: 69 | C38: Beauty | D38: organic_volume_growth | E38: 45565 | F38: First month | G38: blend | H38: ='Forecast log'!T74 -> -0.048882858 | I38: ='PG facts'!D76 -> 0 | J38: =H38-I38 -> -0.048882858 | K38: =J38^2 -> 0.0023895338 | L38: =('Forecast log'!H74-I38)^2 -> 0.0625 | M38: =('Forecast log'!I74-I38)^2 -> 1 | N38: =IF(ABS(J38)<SQRT(L38),1,0) -> 1 | O38: =ABS(J38) -> 0.048882858
B39: 70 | C39: Beauty | D39: organic_volume_growth | E39: 45565 | F39: Second month | G39: baseline | H39: ='Forecast log'!H75 -> 0.25 | I39: ='PG facts'!D76 -> 0 | J39: =H39-I39 -> 0.25 | K39: =J39^2 -> 0.0625 | L39: =('Forecast log'!H75-I39)^2 -> 0.0625 | M39: =('Forecast log'!I75-I39)^2 -> 1 | N39: =IF(ABS(J39)<SQRT(L39),1,0) -> 0 | O39: =ABS(J39) -> 0.25
B40: 70 | C40: Beauty | D40: organic_volume_growth | E40: 45565 | F40: Second month | G40: last_actual | H40: ='Forecast log'!I75 -> 1 | I40: ='PG facts'!D76 -> 0 | J40: =H40-I40 -> 1 | K40: =J40^2 -> 1 | L40: =('Forecast log'!H75-I40)^2 -> 0.0625 | M40: =('Forecast log'!I75-I40)^2 -> 1 | N40: =IF(ABS(J40)<SQRT(L40),1,0) -> 0 | O40: =ABS(J40) -> 1
B41: 70 | C41: Beauty | D41: organic_volume_growth | E41: 45565 | F41: Second month | G41: bridge | H41: ='Forecast log'!N75 -> -0.051498095 | I41: ='PG facts'!D76 -> 0 | J41: =H41-I41 -> -0.051498095 | K41: =J41^2 -> 0.0026520538 | L41: =('Forecast log'!H75-I41)^2 -> 0.0625 | M41: =('Forecast log'!I75-I41)^2 -> 1 | N41: =IF(ABS(J41)<SQRT(L41),1,0) -> 1 | O41: =ABS(J41) -> 0.051498095
B42: 70 | C42: Beauty | D42: organic_volume_growth | E42: 45565 | F42: Second month | G42: lagged | H42: ='Forecast log'!S75 -> -0.53242653 | I42: ='PG facts'!D76 -> 0 | J42: =H42-I42 -> -0.53242653 | K42: =J42^2 -> 0.28347801 | L42: =('Forecast log'!H75-I42)^2 -> 0.0625 | M42: =('Forecast log'!I75-I42)^2 -> 1 | N42: =IF(ABS(J42)<SQRT(L42),1,0) -> 0 | O42: =ABS(J42) -> 0.53242653
B43: 70 | C43: Beauty | D43: organic_volume_growth | E43: 45565 | F43: Second month | G43: blend | H43: ='Forecast log'!T75 -> 0.099250953 | I43: ='PG facts'!D76 -> 0 | J43: =H43-I43 -> 0.099250953 | K43: =J43^2 -> 0.0098507516 | L43: =('Forecast log'!H75-I43)^2 -> 0.0625 | M43: =('Forecast log'!I75-I43)^2 -> 1 | N43: =IF(ABS(J43)<SQRT(L43),1,0) -> 1 | O43: =ABS(J43) -> 0.099250953
B44: 122 | C44: Beauty | D44: organic_volume_growth | E44: 45657 | F44: Origin | G44: baseline | H44: ='Forecast log'!H127 -> 0.25 | I44: ='PG facts'!D83 -> 0 | J44: =H44-I44 -> 0.25 | K44: =J44^2 -> 0.0625 | L44: =('Forecast log'!H127-I44)^2 -> 0.0625 | M44: =('Forecast log'!I127-I44)^2 -> 1 | N44: =IF(ABS(J44)<SQRT(L44),1,0) -> 0 | O44: =ABS(J44) -> 0.25
B45: 122 | C45: Beauty | D45: organic_volume_growth | E45: 45657 | F45: Origin | G45: last_actual | H45: ='Forecast log'!I127 -> 1 | I45: ='PG facts'!D83 -> 0 | J45: =H45-I45 -> 1 | K45: =J45^2 -> 1 | L45: =('Forecast log'!H127-I45)^2 -> 0.0625 | M45: =('Forecast log'!I127-I45)^2 -> 1 | N45: =IF(ABS(J45)<SQRT(L45),1,0) -> 0 | O45: =ABS(J45) -> 1
B46: 122 | C46: Beauty | D46: organic_volume_growth | E46: 45657 | F46: Origin | G46: bridge | H46: ='Forecast log'!N127 -> -0.054264674 | I46: ='PG facts'!D83 -> 0 | J46: =H46-I46 -> -0.054264674 | K46: =J46^2 -> 0.0029446549 | L46: =('Forecast log'!H127-I46)^2 -> 0.0625 | M46: =('Forecast log'!I127-I46)^2 -> 1 | N46: =IF(ABS(J46)<SQRT(L46),1,0) -> 1 | O46: =ABS(J46) -> 0.054264674
B47: 122 | C47: Beauty | D47: organic_volume_growth | E47: 45657 | F47: Origin | G47: blend | H47: ='Forecast log'!T127 -> 0.097867663 | I47: ='PG facts'!D83 -> 0 | J47: =H47-I47 -> 0.097867663 | K47: =J47^2 -> 0.0095780795 | L47: =('Forecast log'!H127-I47)^2 -> 0.0625 | M47: =('Forecast log'!I127-I47)^2 -> 1 | N47: =IF(ABS(J47)<SQRT(L47),1,0) -> 1 | O47: =ABS(J47) -> 0.097867663
B48: 127 | C48: Beauty | D48: organic_volume_growth | E48: 45657 | F48: Pre-earnings | G48: baseline | H48: ='Forecast log'!H132 -> 0.25 | I48: ='PG facts'!D83 -> 0 | J48: =H48-I48 -> 0.25 | K48: =J48^2 -> 0.0625 | L48: =('Forecast log'!H132-I48)^2 -> 0.0625 | M48: =('Forecast log'!I132-I48)^2 -> 0 | N48: =IF(ABS(J48)<SQRT(L48),1,0) -> 0 | O48: =ABS(J48) -> 0.25
B49: 127 | C49: Beauty | D49: organic_volume_growth | E49: 45657 | F49: Pre-earnings | G49: last_actual | H49: ='Forecast log'!I132 -> 0 | I49: ='PG facts'!D83 -> 0 | J49: =H49-I49 -> 0 | K49: =J49^2 -> 0 | L49: =('Forecast log'!H132-I49)^2 -> 0.0625 | M49: =('Forecast log'!I132-I49)^2 -> 0 | N49: =IF(ABS(J49)<SQRT(L49),1,0) -> 1 | O49: =ABS(J49) -> 0
B50: 127 | C50: Beauty | D50: organic_volume_growth | E50: 45657 | F50: Pre-earnings | G50: bridge | H50: ='Forecast log'!N132 -> -0.042655672 | I50: ='PG facts'!D83 -> 0 | J50: =H50-I50 -> -0.042655672 | K50: =J50^2 -> 0.0018195064 | L50: =('Forecast log'!H132-I50)^2 -> 0.0625 | M50: =('Forecast log'!I132-I50)^2 -> 0 | N50: =IF(ABS(J50)<SQRT(L50),1,0) -> 1 | O50: =ABS(J50) -> 0.042655672
B51: 127 | C51: Beauty | D51: organic_volume_growth | E51: 45657 | F51: Pre-earnings | G51: lagged | H51: ='Forecast log'!S132 -> -0.36532959 | I51: ='PG facts'!D83 -> 0 | J51: =H51-I51 -> -0.36532959 | K51: =J51^2 -> 0.13346571 | L51: =('Forecast log'!H132-I51)^2 -> 0.0625 | M51: =('Forecast log'!I132-I51)^2 -> 0 | N51: =IF(ABS(J51)<SQRT(L51),1,0) -> 0 | O51: =ABS(J51) -> 0.36532959
B52: 127 | C52: Beauty | D52: organic_volume_growth | E52: 45657 | F52: Pre-earnings | G52: blend | H52: ='Forecast log'!T132 -> 0.10367216 | I52: ='PG facts'!D83 -> 0 | J52: =H52-I52 -> 0.10367216 | K52: =J52^2 -> 0.010747918 | L52: =('Forecast log'!H132-I52)^2 -> 0.0625 | M52: =('Forecast log'!I132-I52)^2 -> 0 | N52: =IF(ABS(J52)<SQRT(L52),1,0) -> 1 | O52: =ABS(J52) -> 0.10367216
B53: 125 | C53: Beauty | D53: organic_volume_growth | E53: 45657 | F53: First month | G53: baseline | H53: ='Forecast log'!H130 -> 0.25 | I53: ='PG facts'!D83 -> 0 | J53: =H53-I53 -> 0.25 | K53: =J53^2 -> 0.0625 | L53: =('Forecast log'!H130-I53)^2 -> 0.0625 | M53: =('Forecast log'!I130-I53)^2 -> 0 | N53: =IF(ABS(J53)<SQRT(L53),1,0) -> 0 | O53: =ABS(J53) -> 0.25
B54: 125 | C54: Beauty | D54: organic_volume_growth | E54: 45657 | F54: First month | G54: last_actual | H54: ='Forecast log'!I130 -> 0 | I54: ='PG facts'!D83 -> 0 | J54: =H54-I54 -> 0 | K54: =J54^2 -> 0 | L54: =('Forecast log'!H130-I54)^2 -> 0.0625 | M54: =('Forecast log'!I130-I54)^2 -> 0 | N54: =IF(ABS(J54)<SQRT(L54),1,0) -> 1 | O54: =ABS(J54) -> 0
B55: 125 | C55: Beauty | D55: organic_volume_growth | E55: 45657 | F55: First month | G55: bridge | H55: ='Forecast log'!N130 -> -0.032738261 | I55: ='PG facts'!D83 -> 0 | J55: =H55-I55 -> -0.032738261 | K55: =J55^2 -> 0.0010717938 | L55: =('Forecast log'!H130-I55)^2 -> 0.0625 | M55: =('Forecast log'!I130-I55)^2 -> 0 | N55: =IF(ABS(J55)<SQRT(L55),1,0) -> 1 | O55: =ABS(J55) -> 0.032738261
B56: 125 | C56: Beauty | D56: organic_volume_growth | E56: 45657 | F56: First month | G56: lagged | H56: ='Forecast log'!S130 -> -0.36812334 | I56: ='PG facts'!D83 -> 0 | J56: =H56-I56 -> -0.36812334 | K56: =J56^2 -> 0.13551479 | L56: =('Forecast log'!H130-I56)^2 -> 0.0625 | M56: =('Forecast log'!I130-I56)^2 -> 0 | N56: =IF(ABS(J56)<SQRT(L56),1,0) -> 0 | O56: =ABS(J56) -> 0.36812334
B57: 125 | C57: Beauty | D57: organic_volume_growth | E57: 45657 | F57: First month | G57: blend | H57: ='Forecast log'!T130 -> 0.10863087 | I57: ='PG facts'!D83 -> 0 | J57: =H57-I57 -> 0.10863087 | K57: =J57^2 -> 0.011800666 | L57: =('Forecast log'!H130-I57)^2 -> 0.0625 | M57: =('Forecast log'!I130-I57)^2 -> 0 | N57: =IF(ABS(J57)<SQRT(L57),1,0) -> 1 | O57: =ABS(J57) -> 0.10863087
B58: 126 | C58: Beauty | D58: organic_volume_growth | E58: 45657 | F58: Second month | G58: baseline | H58: ='Forecast log'!H131 -> 0.25 | I58: ='PG facts'!D83 -> 0 | J58: =H58-I58 -> 0.25 | K58: =J58^2 -> 0.0625 | L58: =('Forecast log'!H131-I58)^2 -> 0.0625 | M58: =('Forecast log'!I131-I58)^2 -> 0 | N58: =IF(ABS(J58)<SQRT(L58),1,0) -> 0 | O58: =ABS(J58) -> 0.25
B59: 126 | C59: Beauty | D59: organic_volume_growth | E59: 45657 | F59: Second month | G59: last_actual | H59: ='Forecast log'!I131 -> 0 | I59: ='PG facts'!D83 -> 0 | J59: =H59-I59 -> 0 | K59: =J59^2 -> 0 | L59: =('Forecast log'!H131-I59)^2 -> 0.0625 | M59: =('Forecast log'!I131-I59)^2 -> 0 | N59: =IF(ABS(J59)<SQRT(L59),1,0) -> 1 | O59: =ABS(J59) -> 0
B60: 126 | C60: Beauty | D60: organic_volume_growth | E60: 45657 | F60: Second month | G60: bridge | H60: ='Forecast log'!N131 -> -0.042655672 | I60: ='PG facts'!D83 -> 0 | J60: =H60-I60 -> -0.042655672 | K60: =J60^2 -> 0.0018195064 | L60: =('Forecast log'!H131-I60)^2 -> 0.0625 | M60: =('Forecast log'!I131-I60)^2 -> 0 | N60: =IF(ABS(J60)<SQRT(L60),1,0) -> 1 | O60: =ABS(J60) -> 0.042655672
B61: 126 | C61: Beauty | D61: organic_volume_growth | E61: 45657 | F61: Second month | G61: lagged | H61: ='Forecast log'!S131 -> -0.36532959 | I61: ='PG facts'!D83 -> 0 | J61: =H61-I61 -> -0.36532959 | K61: =J61^2 -> 0.13346571 | L61: =('Forecast log'!H131-I61)^2 -> 0.0625 | M61: =('Forecast log'!I131-I61)^2 -> 0 | N61: =IF(ABS(J61)<SQRT(L61),1,0) -> 0 | O61: =ABS(J61) -> 0.36532959
B62: 126 | C62: Beauty | D62: organic_volume_growth | E62: 45657 | F62: Second month | G62: blend | H62: ='Forecast log'!T131 -> 0.10367216 | I62: ='PG facts'!D83 -> 0 | J62: =H62-I62 -> 0.10367216 | K62: =J62^2 -> 0.010747918 | L62: =('Forecast log'!H131-I62)^2 -> 0.0625 | M62: =('Forecast log'!I131-I62)^2 -> 0 | N62: =IF(ABS(J62)<SQRT(L62),1,0) -> 1 | O62: =ABS(J62) -> 0.10367216
B63: 180 | C63: Beauty | D63: organic_volume_growth | E63: 45747 | F63: Origin | G63: baseline | H63: ='Forecast log'!H185 -> 0.25 | I63: ='PG facts'!D90 -> 1 | J63: =H63-I63 -> -0.75 | K63: =J63^2 -> 0.5625 | L63: =('Forecast log'!H185-I63)^2 -> 0.5625 | M63: =('Forecast log'!I185-I63)^2 -> 1 | N63: =IF(ABS(J63)<SQRT(L63),1,0) -> 0 | O63: =ABS(J63) -> 0.75
B64: 180 | C64: Beauty | D64: organic_volume_growth | E64: 45747 | F64: Origin | G64: last_actual | H64: ='Forecast log'!I185 -> 0 | I64: ='PG facts'!D90 -> 1 | J64: =H64-I64 -> -1 | K64: =J64^2 -> 1 | L64: =('Forecast log'!H185-I64)^2 -> 0.5625 | M64: =('Forecast log'!I185-I64)^2 -> 1 | N64: =IF(ABS(J64)<SQRT(L64),1,0) -> 0 | O64: =ABS(J64) -> 1
B65: 180 | C65: Beauty | D65: organic_volume_growth | E65: 45747 | F65: Origin | G65: bridge | H65: ='Forecast log'!N185 -> 0.0088004278 | I65: ='PG facts'!D90 -> 1 | J65: =H65-I65 -> -0.99119957 | K65: =J65^2 -> 0.98247659 | L65: =('Forecast log'!H185-I65)^2 -> 0.5625 | M65: =('Forecast log'!I185-I65)^2 -> 1 | N65: =IF(ABS(J65)<SQRT(L65),1,0) -> 0 | O65: =ABS(J65) -> 0.99119957
B66: 180 | C66: Beauty | D66: organic_volume_growth | E66: 45747 | F66: Origin | G66: blend | H66: ='Forecast log'!T185 -> 0.12940021 | I66: ='PG facts'!D90 -> 1 | J66: =H66-I66 -> -0.87059979 | K66: =J66^2 -> 0.75794399 | L66: =('Forecast log'!H185-I66)^2 -> 0.5625 | M66: =('Forecast log'!I185-I66)^2 -> 1 | N66: =IF(ABS(J66)<SQRT(L66),1,0) -> 0 | O66: =ABS(J66) -> 0.87059979
B67: 185 | C67: Beauty | D67: organic_volume_growth | E67: 45747 | F67: Pre-earnings | G67: baseline | H67: ='Forecast log'!H190 -> 0.5 | I67: ='PG facts'!D90 -> 1 | J67: =H67-I67 -> -0.5 | K67: =J67^2 -> 0.25 | L67: =('Forecast log'!H190-I67)^2 -> 0.25 | M67: =('Forecast log'!I190-I67)^2 -> 1 | N67: =IF(ABS(J67)<SQRT(L67),1,0) -> 0 | O67: =ABS(J67) -> 0.5
B68: 185 | C68: Beauty | D68: organic_volume_growth | E68: 45747 | F68: Pre-earnings | G68: last_actual | H68: ='Forecast log'!I190 -> 0 | I68: ='PG facts'!D90 -> 1 | J68: =H68-I68 -> -1 | K68: =J68^2 -> 1 | L68: =('Forecast log'!H190-I68)^2 -> 0.25 | M68: =('Forecast log'!I190-I68)^2 -> 1 | N68: =IF(ABS(J68)<SQRT(L68),1,0) -> 0 | O68: =ABS(J68) -> 1
B69: 185 | C69: Beauty | D69: organic_volume_growth | E69: 45747 | F69: Pre-earnings | G69: bridge | H69: ='Forecast log'!N190 -> 0.1296734 | I69: ='PG facts'!D90 -> 1 | J69: =H69-I69 -> -0.8703266 | K69: =J69^2 -> 0.75746838 | L69: =('Forecast log'!H190-I69)^2 -> 0.25 | M69: =('Forecast log'!I190-I69)^2 -> 1 | N69: =IF(ABS(J69)<SQRT(L69),1,0) -> 0 | O69: =ABS(J69) -> 0.8703266
B70: 185 | C70: Beauty | D70: organic_volume_growth | E70: 45747 | F70: Pre-earnings | G70: lagged | H70: ='Forecast log'!S190 -> -0.33498588 | I70: ='PG facts'!D90 -> 1 | J70: =H70-I70 -> -1.3349859 | K70: =J70^2 -> 1.7821873 | L70: =('Forecast log'!H190-I70)^2 -> 0.25 | M70: =('Forecast log'!I190-I70)^2 -> 1 | N70: =IF(ABS(J70)<SQRT(L70),1,0) -> 0 | O70: =ABS(J70) -> 1.3349859
B71: 185 | C71: Beauty | D71: organic_volume_growth | E71: 45747 | F71: Pre-earnings | G71: blend | H71: ='Forecast log'!T190 -> 0.3148367 | I71: ='PG facts'!D90 -> 1 | J71: =H71-I71 -> -0.6851633 | K71: =J71^2 -> 0.46944874 | L71: =('Forecast log'!H190-I71)^2 -> 0.25 | M71: =('Forecast log'!I190-I71)^2 -> 1 | N71: =IF(ABS(J71)<SQRT(L71),1,0) -> 0 | O71: =ABS(J71) -> 0.6851633
B72: 183 | C72: Beauty | D72: organic_volume_growth | E72: 45747 | F72: First month | G72: baseline | H72: ='Forecast log'!H188 -> 0.5 | I72: ='PG facts'!D90 -> 1 | J72: =H72-I72 -> -0.5 | K72: =J72^2 -> 0.25 | L72: =('Forecast log'!H188-I72)^2 -> 0.25 | M72: =('Forecast log'!I188-I72)^2 -> 1 | N72: =IF(ABS(J72)<SQRT(L72),1,0) -> 0 | O72: =ABS(J72) -> 0.5
B73: 183 | C73: Beauty | D73: organic_volume_growth | E73: 45747 | F73: First month | G73: last_actual | H73: ='Forecast log'!I188 -> 0 | I73: ='PG facts'!D90 -> 1 | J73: =H73-I73 -> -1 | K73: =J73^2 -> 1 | L73: =('Forecast log'!H188-I73)^2 -> 0.25 | M73: =('Forecast log'!I188-I73)^2 -> 1 | N73: =IF(ABS(J73)<SQRT(L73),1,0) -> 0 | O73: =ABS(J73) -> 1
B74: 183 | C74: Beauty | D74: organic_volume_growth | E74: 45747 | F74: First month | G74: bridge | H74: ='Forecast log'!N188 -> -0.12678592 | I74: ='PG facts'!D90 -> 1 | J74: =H74-I74 -> -1.1267859 | K74: =J74^2 -> 1.2696465 | L74: =('Forecast log'!H188-I74)^2 -> 0.25 | M74: =('Forecast log'!I188-I74)^2 -> 1 | N74: =IF(ABS(J74)<SQRT(L74),1,0) -> 0 | O74: =ABS(J74) -> 1.1267859
B75: 183 | C75: Beauty | D75: organic_volume_growth | E75: 45747 | F75: First month | G75: lagged | H75: ='Forecast log'!S188 -> -0.34083037 | I75: ='PG facts'!D90 -> 1 | J75: =H75-I75 -> -1.3408304 | K75: =J75^2 -> 1.7978261 | L75: =('Forecast log'!H188-I75)^2 -> 0.25 | M75: =('Forecast log'!I188-I75)^2 -> 1 | N75: =IF(ABS(J75)<SQRT(L75),1,0) -> 0 | O75: =ABS(J75) -> 1.3408304
B76: 183 | C76: Beauty | D76: organic_volume_growth | E76: 45747 | F76: First month | G76: blend | H76: ='Forecast log'!T188 -> 0.18660704 | I76: ='PG facts'!D90 -> 1 | J76: =H76-I76 -> -0.81339296 | K76: =J76^2 -> 0.66160811 | L76: =('Forecast log'!H188-I76)^2 -> 0.25 | M76: =('Forecast log'!I188-I76)^2 -> 1 | N76: =IF(ABS(J76)<SQRT(L76),1,0) -> 0 | O76: =ABS(J76) -> 0.81339296
B77: 184 | C77: Beauty | D77: organic_volume_growth | E77: 45747 | F77: Second month | G77: baseline | H77: ='Forecast log'!H189 -> 0.5 | I77: ='PG facts'!D90 -> 1 | J77: =H77-I77 -> -0.5 | K77: =J77^2 -> 0.25 | L77: =('Forecast log'!H189-I77)^2 -> 0.25 | M77: =('Forecast log'!I189-I77)^2 -> 1 | N77: =IF(ABS(J77)<SQRT(L77),1,0) -> 0 | O77: =ABS(J77) -> 0.5
B78: 184 | C78: Beauty | D78: organic_volume_growth | E78: 45747 | F78: Second month | G78: last_actual | H78: ='Forecast log'!I189 -> 0 | I78: ='PG facts'!D90 -> 1 | J78: =H78-I78 -> -1 | K78: =J78^2 -> 1 | L78: =('Forecast log'!H189-I78)^2 -> 0.25 | M78: =('Forecast log'!I189-I78)^2 -> 1 | N78: =IF(ABS(J78)<SQRT(L78),1,0) -> 0 | O78: =ABS(J78) -> 1
B79: 184 | C79: Beauty | D79: organic_volume_growth | E79: 45747 | F79: Second month | G79: bridge | H79: ='Forecast log'!N189 -> 0.1296734 | I79: ='PG facts'!D90 -> 1 | J79: =H79-I79 -> -0.8703266 | K79: =J79^2 -> 0.75746838 | L79: =('Forecast log'!H189-I79)^2 -> 0.25 | M79: =('Forecast log'!I189-I79)^2 -> 1 | N79: =IF(ABS(J79)<SQRT(L79),1,0) -> 0 | O79: =ABS(J79) -> 0.8703266
B80: 184 | C80: Beauty | D80: organic_volume_growth | E80: 45747 | F80: Second month | G80: lagged | H80: ='Forecast log'!S189 -> -0.33498588 | I80: ='PG facts'!D90 -> 1 | J80: =H80-I80 -> -1.3349859 | K80: =J80^2 -> 1.7821873 | L80: =('Forecast log'!H189-I80)^2 -> 0.25 | M80: =('Forecast log'!I189-I80)^2 -> 1 | N80: =IF(ABS(J80)<SQRT(L80),1,0) -> 0 | O80: =ABS(J80) -> 1.3349859
B81: 184 | C81: Beauty | D81: organic_volume_growth | E81: 45747 | F81: Second month | G81: blend | H81: ='Forecast log'!T189 -> 0.3148367 | I81: ='PG facts'!D90 -> 1 | J81: =H81-I81 -> -0.6851633 | K81: =J81^2 -> 0.46944874 | L81: =('Forecast log'!H189-I81)^2 -> 0.25 | M81: =('Forecast log'!I189-I81)^2 -> 1 | N81: =IF(ABS(J81)<SQRT(L81),1,0) -> 0 | O81: =ABS(J81) -> 0.6851633
B82: 238 | C82: Beauty | D82: organic_volume_growth | E82: 45838 | F82: Origin | G82: baseline | H82: ='Forecast log'!H243 -> 0.5 | I82: ='PG facts'!D97 -> 1 | J82: =H82-I82 -> -0.5 | K82: =J82^2 -> 0.25 | L82: =('Forecast log'!H243-I82)^2 -> 0.25 | M82: =('Forecast log'!I243-I82)^2 -> 1 | N82: =IF(ABS(J82)<SQRT(L82),1,0) -> 0 | O82: =ABS(J82) -> 0.5
B83: 238 | C83: Beauty | D83: organic_volume_growth | E83: 45838 | F83: Origin | G83: last_actual | H83: ='Forecast log'!I243 -> 0 | I83: ='PG facts'!D97 -> 1 | J83: =H83-I83 -> -1 | K83: =J83^2 -> 1 | L83: =('Forecast log'!H243-I83)^2 -> 0.25 | M83: =('Forecast log'!I243-I83)^2 -> 1 | N83: =IF(ABS(J83)<SQRT(L83),1,0) -> 0 | O83: =ABS(J83) -> 1
B84: 238 | C84: Beauty | D84: organic_volume_growth | E84: 45838 | F84: Origin | G84: bridge | H84: ='Forecast log'!N243 -> 0.079052164 | I84: ='PG facts'!D97 -> 1 | J84: =H84-I84 -> -0.92094784 | K84: =J84^2 -> 0.84814492 | L84: =('Forecast log'!H243-I84)^2 -> 0.25 | M84: =('Forecast log'!I243-I84)^2 -> 1 | N84: =IF(ABS(J84)<SQRT(L84),1,0) -> 0 | O84: =ABS(J84) -> 0.92094784
B85: 238 | C85: Beauty | D85: organic_volume_growth | E85: 45838 | F85: Origin | G85: blend | H85: ='Forecast log'!T243 -> 0.28952608 | I85: ='PG facts'!D97 -> 1 | J85: =H85-I85 -> -0.71047392 | K85: =J85^2 -> 0.50477319 | L85: =('Forecast log'!H243-I85)^2 -> 0.25 | M85: =('Forecast log'!I243-I85)^2 -> 1 | N85: =IF(ABS(J85)<SQRT(L85),1,0) -> 0 | O85: =ABS(J85) -> 0.71047392
B86: 243 | C86: Beauty | D86: organic_volume_growth | E86: 45838 | F86: Pre-earnings | G86: baseline | H86: ='Forecast log'!H248 -> 0.5 | I86: ='PG facts'!D97 -> 1 | J86: =H86-I86 -> -0.5 | K86: =J86^2 -> 0.25 | L86: =('Forecast log'!H248-I86)^2 -> 0.25 | M86: =('Forecast log'!I248-I86)^2 -> 0 | N86: =IF(ABS(J86)<SQRT(L86),1,0) -> 0 | O86: =ABS(J86) -> 0.5
B87: 243 | C87: Beauty | D87: organic_volume_growth | E87: 45838 | F87: Pre-earnings | G87: last_actual | H87: ='Forecast log'!I248 -> 1 | I87: ='PG facts'!D97 -> 1 | J87: =H87-I87 -> 0 | K87: =J87^2 -> 0 | L87: =('Forecast log'!H248-I87)^2 -> 0.25 | M87: =('Forecast log'!I248-I87)^2 -> 0 | N87: =IF(ABS(J87)<SQRT(L87),1,0) -> 1 | O87: =ABS(J87) -> 0
B88: 243 | C88: Beauty | D88: organic_volume_growth | E88: 45838 | F88: Pre-earnings | G88: bridge | H88: ='Forecast log'!N248 -> 0.42260038 | I88: ='PG facts'!D97 -> 1 | J88: =H88-I88 -> -0.57739962 | K88: =J88^2 -> 0.33339032 | L88: =('Forecast log'!H248-I88)^2 -> 0.25 | M88: =('Forecast log'!I248-I88)^2 -> 0 | N88: =IF(ABS(J88)<SQRT(L88),1,0) -> 0 | O88: =ABS(J88) -> 0.57739962
B89: 243 | C89: Beauty | D89: organic_volume_growth | E89: 45838 | F89: Pre-earnings | G89: lagged | H89: ='Forecast log'!S248 -> 0.071965113 | I89: ='PG facts'!D97 -> 1 | J89: =H89-I89 -> -0.92803489 | K89: =J89^2 -> 0.86124875 | L89: =('Forecast log'!H248-I89)^2 -> 0.25 | M89: =('Forecast log'!I248-I89)^2 -> 0 | N89: =IF(ABS(J89)<SQRT(L89),1,0) -> 0 | O89: =ABS(J89) -> 0.92803489
B90: 243 | C90: Beauty | D90: organic_volume_growth | E90: 45838 | F90: Pre-earnings | G90: blend | H90: ='Forecast log'!T248 -> 0.46130019 | I90: ='PG facts'!D97 -> 1 | J90: =H90-I90 -> -0.53869981 | K90: =J90^2 -> 0.29019749 | L90: =('Forecast log'!H248-I90)^2 -> 0.25 | M90: =('Forecast log'!I248-I90)^2 -> 0 | N90: =IF(ABS(J90)<SQRT(L90),1,0) -> 0 | O90: =ABS(J90) -> 0.53869981
B91: 241 | C91: Beauty | D91: organic_volume_growth | E91: 45838 | F91: First month | G91: baseline | H91: ='Forecast log'!H246 -> 0.5 | I91: ='PG facts'!D97 -> 1 | J91: =H91-I91 -> -0.5 | K91: =J91^2 -> 0.25 | L91: =('Forecast log'!H246-I91)^2 -> 0.25 | M91: =('Forecast log'!I246-I91)^2 -> 0 | N91: =IF(ABS(J91)<SQRT(L91),1,0) -> 0 | O91: =ABS(J91) -> 0.5
B92: 241 | C92: Beauty | D92: organic_volume_growth | E92: 45838 | F92: First month | G92: last_actual | H92: ='Forecast log'!I246 -> 1 | I92: ='PG facts'!D97 -> 1 | J92: =H92-I92 -> 0 | K92: =J92^2 -> 0 | L92: =('Forecast log'!H246-I92)^2 -> 0.25 | M92: =('Forecast log'!I246-I92)^2 -> 0 | N92: =IF(ABS(J92)<SQRT(L92),1,0) -> 1 | O92: =ABS(J92) -> 0
B93: 241 | C93: Beauty | D93: organic_volume_growth | E93: 45838 | F93: First month | G93: bridge | H93: ='Forecast log'!N246 -> 0.59074415 | I93: ='PG facts'!D97 -> 1 | J93: =H93-I93 -> -0.40925585 | K93: =J93^2 -> 0.16749035 | L93: =('Forecast log'!H246-I93)^2 -> 0.25 | M93: =('Forecast log'!I246-I93)^2 -> 0 | N93: =IF(ABS(J93)<SQRT(L93),1,0) -> 1 | O93: =ABS(J93) -> 0.40925585
B94: 241 | C94: Beauty | D94: organic_volume_growth | E94: 45838 | F94: First month | G94: lagged | H94: ='Forecast log'!S246 -> 0.076957221 | I94: ='PG facts'!D97 -> 1 | J94: =H94-I94 -> -0.92304278 | K94: =J94^2 -> 0.85200797 | L94: =('Forecast log'!H246-I94)^2 -> 0.25 | M94: =('Forecast log'!I246-I94)^2 -> 0 | N94: =IF(ABS(J94)<SQRT(L94),1,0) -> 0 | O94: =ABS(J94) -> 0.92304278
B95: 241 | C95: Beauty | D95: organic_volume_growth | E95: 45838 | F95: First month | G95: blend | H95: ='Forecast log'!T246 -> 0.54537207 | I95: ='PG facts'!D97 -> 1 | J95: =H95-I95 -> -0.45462793 | K95: =J95^2 -> 0.20668655 | L95: =('Forecast log'!H246-I95)^2 -> 0.25 | M95: =('Forecast log'!I246-I95)^2 -> 0 | N95: =IF(ABS(J95)<SQRT(L95),1,0) -> 1 | O95: =ABS(J95) -> 0.45462793
B96: 242 | C96: Beauty | D96: organic_volume_growth | E96: 45838 | F96: Second month | G96: baseline | H96: ='Forecast log'!H247 -> 0.5 | I96: ='PG facts'!D97 -> 1 | J96: =H96-I96 -> -0.5 | K96: =J96^2 -> 0.25 | L96: =('Forecast log'!H247-I96)^2 -> 0.25 | M96: =('Forecast log'!I247-I96)^2 -> 0 | N96: =IF(ABS(J96)<SQRT(L96),1,0) -> 0 | O96: =ABS(J96) -> 0.5
B97: 242 | C97: Beauty | D97: organic_volume_growth | E97: 45838 | F97: Second month | G97: last_actual | H97: ='Forecast log'!I247 -> 1 | I97: ='PG facts'!D97 -> 1 | J97: =H97-I97 -> 0 | K97: =J97^2 -> 0 | L97: =('Forecast log'!H247-I97)^2 -> 0.25 | M97: =('Forecast log'!I247-I97)^2 -> 0 | N97: =IF(ABS(J97)<SQRT(L97),1,0) -> 1 | O97: =ABS(J97) -> 0
B98: 242 | C98: Beauty | D98: organic_volume_growth | E98: 45838 | F98: Second month | G98: bridge | H98: ='Forecast log'!N247 -> 0.42260038 | I98: ='PG facts'!D97 -> 1 | J98: =H98-I98 -> -0.57739962 | K98: =J98^2 -> 0.33339032 | L98: =('Forecast log'!H247-I98)^2 -> 0.25 | M98: =('Forecast log'!I247-I98)^2 -> 0 | N98: =IF(ABS(J98)<SQRT(L98),1,0) -> 0 | O98: =ABS(J98) -> 0.57739962
B99: 242 | C99: Beauty | D99: organic_volume_growth | E99: 45838 | F99: Second month | G99: lagged | H99: ='Forecast log'!S247 -> 0.071965113 | I99: ='PG facts'!D97 -> 1 | J99: =H99-I99 -> -0.92803489 | K99: =J99^2 -> 0.86124875 | L99: =('Forecast log'!H247-I99)^2 -> 0.25 | M99: =('Forecast log'!I247-I99)^2 -> 0 | N99: =IF(ABS(J99)<SQRT(L99),1,0) -> 0 | O99: =ABS(J99) -> 0.92803489
B100: 242 | C100: Beauty | D100: organic_volume_growth | E100: 45838 | F100: Second month | G100: blend | H100: ='Forecast log'!T247 -> 0.46130019 | I100: ='PG facts'!D97 -> 1 | J100: =H100-I100 -> -0.53869981 | K100: =J100^2 -> 0.29019749 | L100: =('Forecast log'!H247-I100)^2 -> 0.25 | M100: =('Forecast log'!I247-I100)^2 -> 0 | N100: =IF(ABS(J100)<SQRT(L100),1,0) -> 0 | O100: =ABS(J100) -> 0.53869981
B101: 298 | C101: Beauty | D101: organic_volume_growth | E101: 45930 | F101: Origin | G101: baseline | H101: ='Forecast log'!H303 -> 0.5 | I101: ='PG facts'!D104 -> 4 | J101: =H101-I101 -> -3.5 | K101: =J101^2 -> 12.25 | L101: =('Forecast log'!H303-I101)^2 -> 12.25 | M101: =('Forecast log'!I303-I101)^2 -> 9 | N101: =IF(ABS(J101)<SQRT(L101),1,0) -> 0 | O101: =ABS(J101) -> 3.5
B102: 298 | C102: Beauty | D102: organic_volume_growth | E102: 45930 | F102: Origin | G102: last_actual | H102: ='Forecast log'!I303 -> 1 | I102: ='PG facts'!D104 -> 4 | J102: =H102-I102 -> -3 | K102: =J102^2 -> 9 | L102: =('Forecast log'!H303-I102)^2 -> 12.25 | M102: =('Forecast log'!I303-I102)^2 -> 9 | N102: =IF(ABS(J102)<SQRT(L102),1,0) -> 1 | O102: =ABS(J102) -> 3
B103: 298 | C103: Beauty | D103: organic_volume_growth | E103: 45930 | F103: Origin | G103: bridge | H103: ='Forecast log'!N303 -> 0.39943299 | I103: ='PG facts'!D104 -> 4 | J103: =H103-I103 -> -3.600567 | K103: =J103^2 -> 12.964083 | L103: =('Forecast log'!H303-I103)^2 -> 12.25 | M103: =('Forecast log'!I303-I103)^2 -> 9 | N103: =IF(ABS(J103)<SQRT(L103),1,0) -> 0 | O103: =ABS(J103) -> 3.600567
...

Sheet Forecast log
B2: Release-by-release forecast calculations
B3: Download / calendar alignment runs in Python. Excel recalculates fitted coefficients, forecasts and scores.
B5: ID | C5: Segment | D5: Measure | E5: Target quarter | F5: Known by | G5: Observed months | H5: Four-quarter mean | I5: Last actual | J5: Bridge n | K5: Bridge slope | L5: Bridge intercept | M5: Market nowcast % | N5: Bridge result | O5: Lag n | P5: Lag slope | Q5: Lag intercept | R5: Prior-quarter market % | S5: Lag result | T5: 50/50 blend | U5: Market version | V5: Latest P&G publication | W5: Market source
B6: 1 | C6: Beauty | D6: organic_volume_growth | E6: 45473 | F6: 45383 | G6: 0 | H6: =AVERAGE('PG facts'!D34,'PG facts'!D41,'PG facts'!D48,'PG facts'!D55) -> -0.5 | I6: ='PG facts'!D55 -> -1 | J6: =COUNT('Training pairs'!F6:F13) -> 8 | K6: =(SUM('Training pairs'!I6:I13)-SUM('Training pairs'!F6:F13)*SUM('Training pairs'!G6:G13)/COUNT('Training pairs'!F6:F13))/(SUM('Training pairs'!H6:H13)-SUM('Training pairs'!F6:F13)^2/COUNT('Training pairs'!F6:F13)) -> 0.31709936 | L6: =AVERAGE('Training pairs'!G6:G13)-K6*AVERAGE('Training pairs'!F6:F13) -> -1.4839268 | M6: =(SUM('Target months'!H6:H8)/SUM('Target months'!F6:F8)-1)*100 -> 1.6699249 | N6: =L6+K6*M6 -> -0.95439473 | O6: ="n.a." -> n.a. | P6: ="n.a." -> n.a. | Q6: ="n.a." -> n.a. | R6: n.a. | S6: ="n.a." -> n.a. | T6: =(H6+N6)/2 -> -0.72719737 | U6: 45383 | V6: 45314 | W6: https://alfred.stlouisfed.org/graph/alfredgraph.csv?id=PCENDC96&cosd=2021-01-01&coed=2026-04-01&vintage_date=2024-04-01
B7: 2 | C7: Beauty | D7: organic_volume_growth | E7: 45473 | F7: 45401 | G7: 0 | H7: =AVERAGE('PG facts'!D41,'PG facts'!D48,'PG facts'!D55,'PG facts'!D62) -> -0.25 | I7: ='PG facts'!D62 -> 1 | J7: =COUNT('Training pairs'!F21:F28) -> 8 | K7: =(SUM('Training pairs'!I21:I28)-SUM('Training pairs'!F21:F28)*SUM('Training pairs'!G21:G28)/COUNT('Training pairs'!F21:F28))/(SUM('Training pairs'!H21:H28)-SUM('Training pairs'!F21:F28)^2/COUNT('Training pairs'!F21:F28)) -> 0.31709936 | L7: =AVERAGE('Training pairs'!G21:G28)-K7*AVERAGE('Training pairs'!F21:F28) -> -1.4839268 | M7: =(SUM('Target months'!H9:H11)/SUM('Target months'!F9:F11)-1)*100 -> 1.6699249 | N7: =L7+K7*M7 -> -0.95439473 | O7: =COUNT('Training pairs'!F29:F36) -> 8 | P7: =(SUM('Training pairs'!I29:I36)-SUM('Training pairs'!F29:F36)*SUM('Training pairs'!G29:G36)/COUNT('Training pairs'!F29:F36))/(SUM('Training pairs'!H29:H36)-SUM('Training pairs'!F29:F36)^2/COUNT('Training pairs'!F29:F36)) -> 0.045498424 | Q7: =AVERAGE('Training pairs'!G29:G36)-P7*AVERAGE('Training pairs'!F29:F36) -> -1.0335646 | R7: n.a. | S7: ="n.a." -> n.a. | T7: =(H7+N7)/2 -> -0.60219737 | U7: 45383 | V7: 45401 | W7: https://alfred.stlouisfed.org/graph/alfredgraph.csv?id=PCENDC96&cosd=2021-01-01&coed=2026-04-01&vintage_date=2024-04-01
B8: 3 | C8: Beauty | D8: organic_volume_growth | E8: 45473 | F8: 45408 | G8: 0 | H8: =AVERAGE('PG facts'!D41,'PG facts'!D48,'PG facts'!D55,'PG facts'!D62) -> -0.25 | I8: ='PG facts'!D62 -> 1 | J8: =COUNT('Training pairs'!F37:F45) -> 9 | K8: =(SUM('Training pairs'!I37:I45)-SUM('Training pairs'!F37:F45)*SUM('Training pairs'!G37:G45)/COUNT('Training pairs'!F37:F45))/(SUM('Training pairs'!H37:H45)-SUM('Training pairs'!F37:F45)^2/COUNT('Training pairs'!F37:F45)) -> 0.42335534 | L8: =AVERAGE('Training pairs'!G37:G45)-K8*AVERAGE('Training pairs'!F37:F45) -> -1.367135 | M8: =(SUM('Target months'!H12:H14)/SUM('Target months'!F12:F14)-1)*100 -> 1.9054357 | N8: =L8+K8*M8 -> -0.56045861 | O8: =COUNT('Training pairs'!F46:F53) -> 8 | P8: =(SUM('Training pairs'!I46:I53)-SUM('Training pairs'!F46:F53)*SUM('Training pairs'!G46:G53)/COUNT('Training pairs'!F46:F53))/(SUM('Training pairs'!H46:H53)-SUM('Training pairs'!F46:F53)^2/COUNT('Training pairs'!F46:F53)) -> 0.045498424 | Q8: =AVERAGE('Training pairs'!G46:G53)-P8*AVERAGE('Training pairs'!F46:F53) -> -1.0335646 | R8: 1.9031592 | S8: =Q8+P8*R8 -> -0.94697382 | T8: =(H8+N8)/2 -> -0.40522931 | U8: 45408 | V8: 45401 | W8: https://alfred.stlouisfed.org/graph/alfredgraph.csv?id=PCENDC96&cosd=2021-01-01&coed=2026-04-01&vintage_date=2024-04-26
B9: 4 | C9: Beauty | D9: organic_volume_growth | E9: 45473 | F9: 45443 | G9: 1 | H9: =AVERAGE('PG facts'!D41,'PG facts'!D48,'PG facts'!D55,'PG facts'!D62) -> -0.25 | I9: ='PG facts'!D62 -> 1 | J9: =COUNT('Training pairs'!F54:F62) -> 9 | K9: =(SUM('Training pairs'!I54:I62)-SUM('Training pairs'!F54:F62)*SUM('Training pairs'!G54:G62)/COUNT('Training pairs'!F54:F62))/(SUM('Training pairs'!H54:H62)-SUM('Training pairs'!F54:F62)^2/COUNT('Training pairs'!F54:F62)) -> 0.41290525 | L9: =AVERAGE('Training pairs'!G54:G62)-K9*AVERAGE('Training pairs'!F54:F62) -> -1.3507658 | M9: =(SUM('Target months'!H15:H17)/SUM('Target months'!F15:F17)-1)*100 -> 1.7749528 | N9: =L9+K9*M9 -> -0.61787849 | O9: =COUNT('Training pairs'!F63:F70) -> 8 | P9: =(SUM('Training pairs'!I63:I70)-SUM('Training pairs'!F63:F70)*SUM('Training pairs'!G63:G70)/COUNT('Training pairs'!F63:F70))/(SUM('Training pairs'!H63:H70)-SUM('Training pairs'!F63:F70)^2/COUNT('Training pairs'!F63:F70)) -> 0.045498424 | Q9: =AVERAGE('Training pairs'!G63:G70)-P9*AVERAGE('Training pairs'!F63:F70) -> -1.0335646 | R9: 1.7438949 | S9: =Q9+P9*R9 -> -0.9542201 | T9: =(H9+N9)/2 -> -0.43393925 | U9: 45443 | V9: 45401 | W9: https://alfred.stlouisfed.org/graph/alfredgraph.csv?id=PCENDC96&cosd=2021-01-01&coed=2026-04-01&vintage_date=2024-05-31
B10: 5 | C10: Beauty | D10: organic_volume_growth | E10: 45473 | F10: 45471 | G10: 2 | H10: =AVERAGE('PG facts'!D41,'PG facts'!D48,'PG facts'!D55,'PG facts'!D62) -> -0.25 | I10: ='PG facts'!D62 -> 1 | J10: =COUNT('Training pairs'!F71:F79) -> 9 | K10: =(SUM('Training pairs'!I71:I79)-SUM('Training pairs'!F71:F79)*SUM('Training pairs'!G71:G79)/COUNT('Training pairs'!F71:F79))/(SUM('Training pairs'!H71:H79)-SUM('Training pairs'!F71:F79)^2/COUNT('Training pairs'!F71:F79)) -> 0.40471248 | L10: =AVERAGE('Training pairs'!G71:G79)-K10*AVERAGE('Training pairs'!F71:F79) -> -1.3387612 | M10: =(SUM('Target months'!H18:H20)/SUM('Target months'!F18:F20)-1)*100 -> 1.5780382 | N10: =L10+K10*M10 -> -0.70010948 | O10: =COUNT('Training pairs'!F80:F87) -> 8 | P10: =(SUM('Training pairs'!I80:I87)-SUM('Training pairs'!F80:F87)*SUM('Training pairs'!G80:G87)/COUNT('Training pairs'!F80:F87))/(SUM('Training pairs'!H80:H87)-SUM('Training pairs'!F80:F87)^2/COUNT('Training pairs'!F80:F87)) -> 0.045498424 | Q10: =AVERAGE('Training pairs'!G80:G87)-P10*AVERAGE('Training pairs'!F80:F87) -> -1.0335646 | R10: 1.6317086 | S10: =Q10+P10*R10 -> -0.9593244 | T10: =(H10+N10)/2 -> -0.47505474 | U10: 45471 | V10: 45401 | W10: https://alfred.stlouisfed.org/graph/alfredgraph.csv?id=PCENDC96&cosd=2021-01-01&coed=2026-04-01&vintage_date=2024-06-28
B11: 6 | C11: Beauty | D11: organic_volume_growth | E11: 45473 | F11: 45499 | G11: 3 | H11: =AVERAGE('PG facts'!D41,'PG facts'!D48,'PG facts'!D55,'PG facts'!D62) -> -0.25 | I11: ='PG facts'!D62 -> 1 | J11: =COUNT('Training pairs'!F88:F96) -> 9 | K11: =(SUM('Training pairs'!I88:I96)-SUM('Training pairs'!F88:F96)*SUM('Training pairs'!G88:G96)/COUNT('Training pairs'!F88:F96))/(SUM('Training pairs'!H88:H96)-SUM('Training pairs'!F88:F96)^2/COUNT('Training pairs'!F88:F96)) -> 0.40471248 | L11: =AVERAGE('Training pairs'!G88:G96)-K11*AVERAGE('Training pairs'!F88:F96) -> -1.3387612 | M11: =(SUM('Target months'!H21:H23)/SUM('Target months'!F21:F23)-1)*100 -> 1.7459001 | N11: =L11+K11*M11 -> -0.63217368 | O11: =COUNT('Training pairs'!F97:F104) -> 8 | P11: =(SUM('Training pairs'!I97:I104)-SUM('Training pairs'!F97:F104)*SUM('Training pairs'!G97:G104)/COUNT('Training pairs'!F97:F104))/(SUM('Training pairs'!H97:H104)-SUM('Training pairs'!F97:F104)^2/COUNT('Training pairs'!F97:F104)) -> 0.045498424 | Q11: =AVERAGE('Training pairs'!G97:G104)-P11*AVERAGE('Training pairs'!F97:F104) -> -1.0335646 | R11: 1.6317086 | S11: =Q11+P11*R11 -> -0.9593244 | T11: =(H11+N11)/2 -> -0.44108684 | U11: 45499 | V11: 45401 | W11: https://alfred.stlouisfed.org/graph/alfredgraph.csv?id=PCENDC96&cosd=2021-01-01&coed=2026-04-01&vintage_date=2024-07-26
B12: 7 | C12: Beauty | D12: organic_volume_growth | E12: 45473 | F12: 45502 | G12: 3 | H12: =AVERAGE('PG facts'!D41,'PG facts'!D48,'PG facts'!D55,'PG facts'!D62) -> -0.25 | I12: ='PG facts'!D62 -> 1 | J12: =COUNT('Training pairs'!F105:F113) -> 9 | K12: =(SUM('Training pairs'!I105:I113)-SUM('Training pairs'!F105:F113)*SUM('Training pairs'!G105:G113)/COUNT('Training pairs'!F105:F113))/(SUM('Training pairs'!H105:H113)-SUM('Training pairs'!F105:F113)^2/COUNT('Training pairs'!F105:F113)) -> 0.40471248 | L12: =AVERAGE('Training pairs'!G105:G113)-K12*AVERAGE('Training pairs'!F105:F113) -> -1.3387612 | M12: =(SUM('Target months'!H24:H26)/SUM('Target months'!F24:F26)-1)*100 -> 1.7459001 | N12: =L12+K12*M12 -> -0.63217368 | O12: =COUNT('Training pairs'!F114:F121) -> 8 | P12: =(SUM('Training pairs'!I114:I121)-SUM('Training pairs'!F114:F121)*SUM('Training pairs'!G114:G121)/COUNT('Training pairs'!F114:F121))/(SUM('Training pairs'!H114:H121)-SUM('Training pairs'!F114:F121)^2/COUNT('Training pairs'!F114:F121)) -> 0.045498424 | Q12: =AVERAGE('Training pairs'!G114:G121)-P12*AVERAGE('Training pairs'!F114:F121) -> -1.0335646 | R12: 1.6317086 | S12: =Q12+P12*R12 -> -0.9593244 | T12: =(H12+N12)/2 -> -0.44108684 | U12: 45499 | V12: 45401 | W12: https://alfred.stlouisfed.org/graph/alfredgraph.csv?id=PCENDC96&cosd=2021-01-01&coed=2026-04-01&vintage_date=2024-07-26
B13: 8 | C13: Grooming | D13: organic_volume_growth | E13: 45473 | F13: 45383 | G13: 0 | H13: =AVERAGE('PG facts'!D35,'PG facts'!D42,'PG facts'!D49,'PG facts'!D56) -> -0.75 | I13: ='PG facts'!D56 -> 1 | J13: =COUNT('Training pairs'!F122:F129) -> 8 | K13: =(SUM('Training pairs'!I122:I129)-SUM('Training pairs'!F122:F129)*SUM('Training pairs'!G122:G129)/COUNT('Training pairs'!F122:F129))/(SUM('Training pairs'!H122:H129)-SUM('Training pairs'!F122:F129)^2/COUNT('Training pairs'!F122:F129)) -> 1.0507367 | L13: =AVERAGE('Training pairs'!G122:G129)-K13*AVERAGE('Training pairs'!F122:F129) -> -2.1501372 | M13: =(SUM('Target months'!H27:H29)/SUM('Target months'!F27:F29)-1)*100 -> 1.6699249 | N13: =L13+K13*M13 -> -0.39548585 | O13: ="n.a." -> n.a. | P13: ="n.a." -> n.a. | Q13: ="n.a." -> n.a. | R13: n.a. | S13: ="n.a." -> n.a. | T13: =(H13+N13)/2 -> -0.57274293 | U13: 45383 | V13: 45314 | W13: https://alfred.stlouisfed.org/graph/alfredgraph.csv?id=PCENDC96&cosd=2021-01-01&coed=2026-04-01&vintage_date=2024-04-01
B14: 9 | C14: Grooming | D14: organic_volume_growth | E14: 45473 | F14: 45401 | G14: 0 | H14: =AVERAGE('PG facts'!D42,'PG facts'!D49,'PG facts'!D56,'PG facts'!D63) -> 0 | I14: ='PG facts'!D63 -> 2 | J14: =COUNT('Training pairs'!F137:F144) -> 8 | K14: =(SUM('Training pairs'!I137:I144)-SUM('Training pairs'!F137:F144)*SUM('Training pairs'!G137:G144)/COUNT('Training pairs'!F137:F144))/(SUM('Training pairs'!H137:H144)-SUM('Training pairs'!F137:F144)^2/COUNT('Training pairs'!F137:F144)) -> 1.0507367 | L14: =AVERAGE('Training pairs'!G137:G144)-K14*AVERAGE('Training pairs'!F137:F144) -> -2.1501372 | M14: =(SUM('Target months'!H30:H32)/SUM('Target months'!F30:F32)-1)*100 -> 1.6699249 | N14: =L14+K14*M14 -> -0.39548585 | O14: =COUNT('Training pairs'!F145:F152) -> 8 | P14: =(SUM('Training pairs'!I145:I152)-SUM('Training pairs'!F145:F152)*SUM('Training pairs'!G145:G152)/COUNT('Training pairs'!F145:F152))/(SUM('Training pairs'!H145:H152)-SUM('Training pairs'!F145:F152)^2/COUNT('Training pairs'!F145:F152)) -> 0.60069365 | Q14: =AVERAGE('Training pairs'!G145:G152)-P14*AVERAGE('Training pairs'!F145:F152) -> -1.6931367 | R14: n.a. | S14: ="n.a." -> n.a. | T14: =(H14+N14)/2 -> -0.19774293 | U14: 45383 | V14: 45401 | W14: https://alfred.stlouisfed.org/graph/alfredgraph.csv?id=PCENDC96&cosd=2021-01-01&coed=2026-04-01&vintage_date=2024-04-01
B15: 10 | C15: Grooming | D15: organic_volume_growth | E15: 45473 | F15: 45408 | G15: 0 | H15: =AVERAGE('PG facts'!D42,'PG facts'!D49,'PG facts'!D56,'PG facts'!D63) -> 0 | I15: ='PG facts'!D63 -> 2 | J15: =COUNT('Training pairs'!F153:F161) -> 9 | K15: =(SUM('Training pairs'!I153:I161)-SUM('Training pairs'!F153:F161)*SUM('Training pairs'!G153:G161)/COUNT('Training pairs'!F153:F161))/(SUM('Training pairs'!H153:H161)-SUM('Training pairs'!F153:F161)^2/COUNT('Training pairs'!F153:F161)) -> 1.1722483 | L15: =AVERAGE('Training pairs'!G153:G161)-K15*AVERAGE('Training pairs'!F153:F161) -> -2.0165771 | M15: =(SUM('Target months'!H33:H35)/SUM('Target months'!F33:F35)-1)*100 -> 1.9054357 | N15: =L15+K15*M15 -> 0.2170666 | O15: =COUNT('Training pairs'!F162:F169) -> 8 | P15: =(SUM('Training pairs'!I162:I169)-SUM('Training pairs'!F162:F169)*SUM('Training pairs'!G162:G169)/COUNT('Training pairs'!F162:F169))/(SUM('Training pairs'!H162:H169)-SUM('Training pairs'!F162:F169)^2/COUNT('Training pairs'!F162:F169)) -> 0.60069365 | Q15: =AVERAGE('Training pairs'!G162:G169)-P15*AVERAGE('Training pairs'!F162:F169) -> -1.6931367 | R15: 1.9031592 | S15: =Q15+P15*R15 -> -0.54992105 | T15: =(H15+N15)/2 -> 0.1085333 | U15: 45408 | V15: 45401 | W15: https://alfred.stlouisfed.org/graph/alfredgraph.csv?id=PCENDC96&cosd=2021-01-01&coed=2026-04-01&vintage_date=2024-04-26
B16: 11 | C16: Grooming | D16: organic_volume_growth | E16: 45473 | F16: 45443 | G16: 1 | H16: =AVERAGE('PG facts'!D42,'PG facts'!D49,'PG facts'!D56,'PG facts'!D63) -> 0 | I16: ='PG facts'!D63 -> 2 | J16: =COUNT('Training pairs'!F170:F178) -> 9 | K16: =(SUM('Training pairs'!I170:I178)-SUM('Training pairs'!F170:F178)*SUM('Training pairs'!G170:G178)/COUNT('Training pairs'!F170:F178))/(SUM('Training pairs'!H170:H178)-SUM('Training pairs'!F170:F178)^2/COUNT('Training pairs'!F170:F178)) -> 1.1657354 | L16: =AVERAGE('Training pairs'!G170:G178)-K16*AVERAGE('Training pairs'!F170:F178) -> -1.9903002 | M16: =(SUM('Target months'!H36:H38)/SUM('Target months'!F36:F38)-1)*100 -> 1.7749528 | N16: =L16+K16*M16 -> 0.0788251 | O16: =COUNT('Training pairs'!F179:F186) -> 8 | P16: =(SUM('Training pairs'!I179:I186)-SUM('Training pairs'!F179:F186)*SUM('Training pairs'!G179:G186)/COUNT('Training pairs'!F179:F186))/(SUM('Training pairs'!H179:H186)-SUM('Training pairs'!F179:F186)^2/COUNT('Training pairs'!F179:F186)) -> 0.60069365 | Q16: =AVERAGE('Training pairs'!G179:G186)-P16*AVERAGE('Training pairs'!F179:F186) -> -1.6931367 | R16: 1.7438949 | S16: =Q16+P16*R16 -> -0.64559015 | T16: =(H16+N16)/2 -> 0.03941255 | U16: 45443 | V16: 45401 | W16: https://alfred.stlouisfed.org/graph/alfredgraph.csv?id=PCENDC96&cosd=2021-01-01&coed=2026-04-01&vintage_date=2024-05-31
B17: 12 | C17: Grooming | D17: organic_volume_growth | E17: 45473 | F17: 45471 | G17: 2 | H17: =AVERAGE('PG facts'!D42,'PG facts'!D49,'PG facts'!D56,'PG facts'!D63) -> 0 | I17: ='PG facts'!D63 -> 2 | J17: =COUNT('Training pairs'!F187:F195) -> 9 | K17: =(SUM('Training pairs'!I187:I195)-SUM('Training pairs'!F187:F195)*SUM('Training pairs'!G187:G195)/COUNT('Training pairs'!F187:F195))/(SUM('Training pairs'!H187:H195)-SUM('Training pairs'!F187:F195)^2/COUNT('Training pairs'!F187:F195)) -> 1.1592507 | L17: =AVERAGE('Training pairs'!G187:G195)-K17*AVERAGE('Training pairs'!F187:F195) -> -1.9703412 | M17: =(SUM('Target months'!H39:H41)/SUM('Target months'!F39:F41)-1)*100 -> 1.5780382 | N17: =L17+K17*M17 -> -0.14099933 | O17: =COUNT('Training pairs'!F196:F203) -> 8 | P17: =(SUM('Training pairs'!I196:I203)-SUM('Training pairs'!F196:F203)*SUM('Training pairs'!G196:G203)/COUNT('Training pairs'!F196:F203))/(SUM('Training pairs'!H196:H203)-SUM('Training pairs'!F196:F203)^2/COUNT('Training pairs'!F196:F203)) -> 0.60069365 | Q17: =AVERAGE('Training pairs'!G196:G203)-P17*AVERAGE('Training pairs'!F196:F203) -> -1.6931367 | R17: 1.6317086 | S17: =Q17+P17*R17 -> -0.7129797 | T17: =(H17+N17)/2 -> -0.070499663 | U17: 45471 | V17: 45401 | W17: https://alfred.stlouisfed.org/graph/alfredgraph.csv?id=PCENDC96&cosd=2021-01-01&coed=2026-04-01&vintage_date=2024-06-28
B18: 13 | C18: Grooming | D18: organic_volume_growth | E18: 45473 | F18: 45499 | G18: 3 | H18: =AVERAGE('PG facts'!D42,'PG facts'!D49,'PG facts'!D56,'PG facts'!D63) -> 0 | I18: ='PG facts'!D63 -> 2 | J18: =COUNT('Training pairs'!F204:F212) -> 9 | K18: =(SUM('Training pairs'!I204:I212)-SUM('Training pairs'!F204:F212)*SUM('Training pairs'!G204:G212)/COUNT('Training pairs'!F204:F212))/(SUM('Training pairs'!H204:H212)-SUM('Training pairs'!F204:F212)^2/COUNT('Training pairs'!F204:F212)) -> 1.1592507 | L18: =AVERAGE('Training pairs'!G204:G212)-K18*AVERAGE('Training pairs'!F204:F212) -> -1.9703412 | M18: =(SUM('Target months'!H42:H44)/SUM('Target months'!F42:F44)-1)*100 -> 1.7459001 | N18: =L18+K18*M18 -> 0.053594674 | O18: =COUNT('Training pairs'!F213:F220) -> 8 | P18: =(SUM('Training pairs'!I213:I220)-SUM('Training pairs'!F213:F220)*SUM('Training pairs'!G213:G220)/COUNT('Training pairs'!F213:F220))/(SUM('Training pairs'!H213:H220)-SUM('Training pairs'!F213:F220)^2/COUNT('Training pairs'!F213:F220)) -> 0.60069365 | Q18: =AVERAGE('Training pairs'!G213:G220)-P18*AVERAGE('Training pairs'!F213:F220) -> -1.6931367 | R18: 1.6317086 | S18: =Q18+P18*R18 -> -0.7129797 | T18: =(H18+N18)/2 -> 0.026797337 | U18: 45499 | V18: 45401 | W18: https://alfred.stlouisfed.org/graph/alfredgraph.csv?id=PCENDC96&cosd=2021-01-01&coed=2026-04-01&vintage_date=2024-07-26
B19: 14 | C19: Grooming | D19: organic_volume_growth | E19: 45473 | F19: 45502 | G19: 3 | H19: =AVERAGE('PG facts'!D42,'PG facts'!D49,'PG facts'!D56,'PG facts'!D63) -> 0 | I19: ='PG facts'!D63 -> 2 | J19: =COUNT('Training pairs'!F221:F229) -> 9 | K19: =(SUM('Training pairs'!I221:I229)-SUM('Training pairs'!F221:F229)*SUM('Training pairs'!G221:G229)/COUNT('Training pairs'!F221:F229))/(SUM('Training pairs'!H221:H229)-SUM('Training pairs'!F221:F229)^2/COUNT('Training pairs'!F221:F229)) -> 1.1592507 | L19: =AVERAGE('Training pairs'!G221:G229)-K19*AVERAGE('Training pairs'!F221:F229) -> -1.9703412 | M19: =(SUM('Target months'!H45:H47)/SUM('Target months'!F45:F47)-1)*100 -> 1.7459001 | N19: =L19+K19*M19 -> 0.053594674 | O19: =COUNT('Training pairs'!F230:F237) -> 8 | P19: =(SUM('Training pairs'!I230:I237)-SUM('Training pairs'!F230:F237)*SUM('Training pairs'!G230:G237)/COUNT('Training pairs'!F230:F237))/(SUM('Training pairs'!H230:H237)-SUM('Training pairs'!F230:F237)^2/COUNT('Training pairs'!F230:F237)) -> 0.60069365 | Q19: =AVERAGE('Training pairs'!G230:G237)-P19*AVERAGE('Training pairs'!F230:F237) -> -1.6931367 | R19: 1.6317086 | S19: =Q19+P19*R19 -> -0.7129797 | T19: =(H19+N19)/2 -> 0.026797337 | U19: 45499 | V19: 45401 | W19: https://alfred.stlouisfed.org/graph/alfredgraph.csv?id=PCENDC96&cosd=2021-01-01&coed=2026-04-01&vintage_date=2024-07-26
B20: 15 | C20: Health Care | D20: organic_volume_growth | E20: 45473 | F20: 45383 | G20: 0 | H20: =AVERAGE('PG facts'!D36,'PG facts'!D43,'PG facts'!D50,'PG facts'!D57) -> -1 | I20: ='PG facts'!D57 -> -4 | J20: =COUNT('Training pairs'!F238:F245) -> 8 | K20: =(SUM('Training pairs'!I238:I245)-SUM('Training pairs'!F238:F245)*SUM('Training pairs'!G238:G245)/COUNT('Training pairs'!F238:F245))/(SUM('Training pairs'!H238:H245)-SUM('Training pairs'!F238:F245)^2/COUNT('Training pairs'!F238:F245)) -> 1.4919507 | L20: =AVERAGE('Training pairs'!G238:G245)-K20*AVERAGE('Training pairs'!F238:F245) -> -0.97562448 | M20: =(SUM('Target months'!H48:H50)/SUM('Target months'!F48:F50)-1)*100 -> 1.6699249 | N20: =L20+K20*M20 -> 1.5158211 | O20: ="n.a." -> n.a. | P20: ="n.a." -> n.a. | Q20: ="n.a." -> n.a. | R20: n.a. | S20: ="n.a." -> n.a. | T20: =(H20+N20)/2 -> 0.25791056 | U20: 45383 | V20: 45314 | W20: https://alfred.stlouisfed.org/graph/alfredgraph.csv?id=PCENDC96&cosd=2021-01-01&coed=2026-04-01&vintage_date=2024-04-01
B21: 16 | C21: Health Care | D21: organic_volume_growth | E21: 45473 | F21: 45401 | G21: 0 | H21: =AVERAGE('PG facts'!D43,'PG facts'!D50,'PG facts'!D57,'PG facts'!D64) -> -2.25 | I21: ='PG facts'!D64 -> -4 | J21: =COUNT('Training pairs'!F253:F260) -> 8 | K21: =(SUM('Training pairs'!I253:I260)-SUM('Training pairs'!F253:F260)*SUM('Training pairs'!G253:G260)/COUNT('Training pairs'!F253:F260))/(SUM('Training pairs'!H253:H260)-SUM('Training pairs'!F253:F260)^2/COUNT('Training pairs'!F253:F260)) -> 1.4919507 | L21: =AVERAGE('Training pairs'!G253:G260)-K21*AVERAGE('Training pairs'!F253:F260) -> -0.97562448 | M21: =(SUM('Target months'!H51:H53)/SUM('Target months'!F51:F53)-1)*100 -> 1.6699249 | N21: =L21+K21*M21 -> 1.5158211 | O21: =COUNT('Training pairs'!F261:F268) -> 8 | P21: =(SUM('Training pairs'!I261:I268)-SUM('Training pairs'!F261:F268)*SUM('Training pairs'!G261:G268)/COUNT('Training pairs'!F261:F268))/(SUM('Training pairs'!H261:H268)-SUM('Training pairs'!F261:F268)^2/COUNT('Training pairs'!F261:F268)) -> -0.35458458 | Q21: =AVERAGE('Training pairs'!G261:G268)-P21*AVERAGE('Training pairs'!F261:F268) -> -1.11342 | R21: n.a. | S21: ="n.a." -> n.a. | T21: =(H21+N21)/2 -> -0.36708944 | U21: 45383 | V21: 45401 | W21: https://alfred.stlouisfed.org/graph/alfredgraph.csv?id=PCENDC96&cosd=2021-01-01&coed=2026-04-01&vintage_date=2024-04-01
B22: 17 | C22: Health Care | D22: organic_volume_growth | E22: 45473 | F22: 45408 | G22: 0 | H22: =AVERAGE('PG facts'!D43,'PG facts'!D50,'PG facts'!D57,'PG facts'!D64) -> -2.25 | I22: ='PG facts'!D64 -> -4 | J22: =COUNT('Training pairs'!F269:F277) -> 9 | K22: =(SUM('Training pairs'!I269:I277)-SUM('Training pairs'!F269:F277)*SUM('Training pairs'!G269:G277)/COUNT('Training pairs'!F269:F277))/(SUM('Training pairs'!H269:H277)-SUM('Training pairs'!F269:F277)^2/COUNT('Training pairs'!F269:F277)) -> 1.1606109 | L22: =AVERAGE('Training pairs'!G269:G277)-K22*AVERAGE('Training pairs'!F269:F277) -> -1.3398185 | M22: =(SUM('Target months'!H54:H56)/SUM('Target months'!F54:F56)-1)*100 -> 1.9054357 | N22: =L22+K22*M22 -> 0.87165099 | O22: =COUNT('Training pairs'!F278:F285) -> 8 | P22: =(SUM('Training pairs'!I278:I285)-SUM('Training pairs'!F278:F285)*SUM('Training pairs'!G278:G285)/COUNT('Training pairs'!F278:F285))/(SUM('Training pairs'!H278:H285)-SUM('Training pairs'!F278:F285)^2/COUNT('Training pairs'!F278:F285)) -> -0.35458458 | Q22: =AVERAGE('Training pairs'!G278:G285)-P22*AVERAGE('Training pairs'!F278:F285) -> -1.11342 | R22: 1.9031592 | S22: =Q22+P22*R22 -> -1.7882509 | T22: =(H22+N22)/2 -> -0.68917451 | U22: 45408 | V22: 45401 | W22: https://alfred.stlouisfed.org/graph/alfredgraph.csv?id=PCENDC96&cosd=2021-01-01&coed=2026-04-01&vintage_date=2024-04-26
B23: 18 | C23: Health Care | D23: organic_volume_growth | E23: 45473 | F23: 45443 | G23: 1 | H23: =AVERAGE('PG facts'!D43,'PG facts'!D50,'PG facts'!D57,'PG facts'!D64) -> -2.25 | I23: ='PG facts'!D64 -> -4 | J23: =COUNT('Training pairs'!F286:F294) -> 9 | K23: =(SUM('Training pairs'!I286:I294)-SUM('Training pairs'!F286:F294)*SUM('Training pairs'!G286:G294)/COUNT('Training pairs'!F286:F294))/(SUM('Training pairs'!H286:H294)-SUM('Training pairs'!F286:F294)^2/COUNT('Training pairs'!F286:F294)) -> 1.2128009 | L23: =AVERAGE('Training pairs'!G286:G294)-K23*AVERAGE('Training pairs'!F286:F294) -> -1.363616 | M23: =(SUM('Target months'!H57:H59)/SUM('Target months'!F57:F59)-1)*100 -> 1.7749528 | N23: =L23+K23*M23 -> 0.78904835 | O23: =COUNT('Training pairs'!F295:F302) -> 8 | P23: =(SUM('Training pairs'!I295:I302)-SUM('Training pairs'!F295:F302)*SUM('Training pairs'!G295:G302)/COUNT('Training pairs'!F295:F302))/(SUM('Training pairs'!H295:H302)-SUM('Training pairs'!F295:F302)^2/COUNT('Training pairs'!F295:F302)) -> -0.35458458 | Q23: =AVERAGE('Training pairs'!G295:G302)-P23*AVERAGE('Training pairs'!F295:F302) -> -1.11342 | R23: 1.7438949 | S23: =Q23+P23*R23 -> -1.7317782 | T23: =(H23+N23)/2 -> -0.73047582 | U23: 45443 | V23: 45401 | W23: https://alfred.stlouisfed.org/graph/alfredgraph.csv?id=PCENDC96&cosd=2021-01-01&coed=2026-04-01&vintage_date=2024-05-31
B24: 19 | C24: Health Care | D24: organic_volume_growth | E24: 45473 | F24: 45471 | G24: 2 | H24: =AVERAGE('PG facts'!D43,'PG facts'!D50,'PG facts'!D57,'PG facts'!D64) -> -2.25 | I24: ='PG facts'!D64 -> -4 | J24: =COUNT('Training pairs'!F303:F311) -> 9 | K24: =(SUM('Training pairs'!I303:I311)-SUM('Training pairs'!F303:F311)*SUM('Training pairs'!G303:G311)/COUNT('Training pairs'!F303:F311))/(SUM('Training pairs'!H303:H311)-SUM('Training pairs'!F303:F311)^2/COUNT('Training pairs'!F303:F311)) -> 1.2487472 | L24: =AVERAGE('Training pairs'!G303:G311)-K24*AVERAGE('Training pairs'!F303:F311) -> -1.3785868 | M24: =(SUM('Target months'!H60:H62)/SUM('Target months'!F60:F62)-1)*100 -> 1.5780382 | N24: =L24+K24*M24 -> 0.59198396 | O24: =COUNT('Training pairs'!F312:F319) -> 8 | P24: =(SUM('Training pairs'!I312:I319)-SUM('Training pairs'!F312:F319)*SUM('Training pairs'!G312:G319)/COUNT('Training pairs'!F312:F319))/(SUM('Training pairs'!H312:H319)-SUM('Training pairs'!F312:F319)^2/COUNT('Training pairs'!F312:F319)) -> -0.35458458 | Q24: =AVERAGE('Training pairs'!G312:G319)-P24*AVERAGE('Training pairs'!F312:F319) -> -1.11342 | R24: 1.6317086 | S24: =Q24+P24*R24 -> -1.6919987 | T24: =(H24+N24)/2 -> -0.82900802 | U24: 45471 | V24: 45401 | W24: https://alfred.stlouisfed.org/graph/alfredgraph.csv?id=PCENDC96&cosd=2021-01-01&coed=2026-04-01&vintage_date=2024-06-28
B25: 20 | C25: Health Care | D25: organic_volume_growth | E25: 45473 | F25: 45499 | G25: 3 | H25: =AVERAGE('PG facts'!D43,'PG facts'!D50,'PG facts'!D57,'PG facts'!D64) -> -2.25 | I25: ='PG facts'!D64 -> -4 | J25: =COUNT('Training pairs'!F320:F328) -> 9 | K25: =(SUM('Training pairs'!I320:I328)-SUM('Training pairs'!F320:F328)*SUM('Training pairs'!G320:G328)/COUNT('Training pairs'!F320:F328))/(SUM('Training pairs'!H320:H328)-SUM('Training pairs'!F320:F328)^2/COUNT('Training pairs'!F320:F328)) -> 1.2487472 | L25: =AVERAGE('Training pairs'!G320:G328)-K25*AVERAGE('Training pairs'!F320:F328) -> -1.3785868 | M25: =(SUM('Target months'!H63:H65)/SUM('Target months'!F63:F65)-1)*100 -> 1.7459001 | N25: =L25+K25*M25 -> 0.80160101 | O25: =COUNT('Training pairs'!F329:F336) -> 8 | P25: =(SUM('Training pairs'!I329:I336)-SUM('Training pairs'!F329:F336)*SUM('Training pairs'!G329:G336)/COUNT('Training pairs'!F329:F336))/(SUM('Training pairs'!H329:H336)-SUM('Training pairs'!F329:F336)^2/COUNT('Training pairs'!F329:F336)) -> -0.35458458 | Q25: =AVERAGE('Training pairs'!G329:G336)-P25*AVERAGE('Training pairs'!F329:F336) -> -1.11342 | R25: 1.6317086 | S25: =Q25+P25*R25 -> -1.6919987 | T25: =(H25+N25)/2 -> -0.72419949 | U25: 45499 | V25: 45401 | W25: https://alfred.stlouisfed.org/graph/alfredgraph.csv?id=PCENDC96&cosd=2021-01-01&coed=2026-04-01&vintage_date=2024-07-26
B26: 21 | C26: Health Care | D26: organic_volume_growth | E26: 45473 | F26: 45502 | G26: 3 | H26: =AVERAGE('PG facts'!D43,'PG facts'!D50,'PG facts'!D57,'PG facts'!D64) -> -2.25 | I26: ='PG facts'!D64 -> -4 | J26: =COUNT('Training pairs'!F337:F345) -> 9 | K26: =(SUM('Training pairs'!I337:I345)-SUM('Training pairs'!F337:F345)*SUM('Training pairs'!G337:G345)/COUNT('Training pairs'!F337:F345))/(SUM('Training pairs'!H337:H345)-SUM('Training pairs'!F337:F345)^2/COUNT('Training pairs'!F337:F345)) -> 1.2487472 | L26: =AVERAGE('Training pairs'!G337:G345)-K26*AVERAGE('Training pairs'!F337:F345) -> -1.3785868 | M26: =(SUM('Target months'!H66:H68)/SUM('Target months'!F66:F68)-1)*100 -> 1.7459001 | N26: =L26+K26*M26 -> 0.80160101 | O26: =COUNT('Training pairs'!F346:F353) -> 8 | P26: =(SUM('Training pairs'!I346:I353)-SUM('Training pairs'!F346:F353)*SUM('Training pairs'!G346:G353)/COUNT('Training pairs'!F346:F353))/(SUM('Training pairs'!H346:H353)-SUM('Training pairs'!F346:F353)^2/COUNT('Training pairs'!F346:F353)) -> -0.35458458 | Q26: =AVERAGE('Training pairs'!G346:G353)-P26*AVERAGE('Training pairs'!F346:F353) -> -1.11342 | R26: 1.6317086 | S26: =Q26+P26*R26 -> -1.6919987 | T26: =(H26+N26)/2 -> -0.72419949 | U26: 45499 | V26: 45401 | W26: https://alfred.stlouisfed.org/graph/alfredgraph.csv?id=PCENDC96&cosd=2021-01-01&coed=2026-04-01&vintage_date=2024-07-26
B27: 22 | C27: Fabric & Home Care | D27: organic_volume_growth | E27: 45473 | F27: 45383 | G27: 0 | H27: =AVERAGE('PG facts'!D37,'PG facts'!D44,'PG facts'!D51,'PG facts'!D58) -> -1.5 | I27: ='PG facts'!D58 -> 1 | J27: =COUNT('Training pairs'!F354:F361) -> 8 | K27: =(SUM('Training pairs'!I354:I361)-SUM('Training pairs'!F354:F361)*SUM('Training pairs'!G354:G361)/COUNT('Training pairs'!F354:F361))/(SUM('Training pairs'!H354:H361)-SUM('Training pairs'!F354:F361)^2/COUNT('Training pairs'!F354:F361)) -> 2.3065423 | L27: =AVERAGE('Training pairs'!G354:G361)-K27*AVERAGE('Training pairs'!F354:F361) -> -3.3265555 | M27: =(SUM('Target months'!H69:H71)/SUM('Target months'!F69:F71)-1)*100 -> 1.6699249 | N27: =L27+K27*M27 -> 0.52519685 | O27: ="n.a." -> n.a. | P27: ="n.a." -> n.a. | Q27: ="n.a." -> n.a. | R27: n.a. | S27: ="n.a." -> n.a. | T27: =(H27+N27)/2 -> -0.48740158 | U27: 45383 | V27: 45314 | W27: https://alfred.stlouisfed.org/graph/alfredgraph.csv?id=PCENDC96&cosd=2021-01-01&coed=2026-04-01&vintage_date=2024-04-01
B28: 23 | C28: Fabric & Home Care | D28: organic_volume_growth | E28: 45473 | F28: 45401 | G28: 0 | H28: =AVERAGE('PG facts'!D44,'PG facts'!D51,'PG facts'!D58,'PG facts'!D65) -> 0 | I28: ='PG facts'!D65 -> 1 | J28: =COUNT('Training pairs'!F369:F376) -> 8 | K28: =(SUM('Training pairs'!I369:I376)-SUM('Training pairs'!F369:F376)*SUM('Training pairs'!G369:G376)/COUNT('Training pairs'!F369:F376))/(SUM('Training pairs'!H369:H376)-SUM('Training pairs'!F369:F376)^2/COUNT('Training pairs'!F369:F376)) -> 2.3065423 | L28: =AVERAGE('Training pairs'!G369:G376)-K28*AVERAGE('Training pairs'!F369:F376) -> -3.3265555 | M28: =(SUM('Target months'!H72:H74)/SUM('Target months'!F72:F74)-1)*100 -> 1.6699249 | N28: =L28+K28*M28 -> 0.52519685 | O28: =COUNT('Training pairs'!F377:F384) -> 8 | P28: =(SUM('Training pairs'!I377:I384)-SUM('Training pairs'!F377:F384)*SUM('Training pairs'!G377:G384)/COUNT('Training pairs'!F377:F384))/(SUM('Training pairs'!H377:H384)-SUM('Training pairs'!F377:F384)^2/COUNT('Training pairs'!F377:F384)) -> 1.1542055 | Q28: =AVERAGE('Training pairs'!G377:G384)-P28*AVERAGE('Training pairs'!F377:F384) -> -2.9764671 | R28: n.a. | S28: ="n.a." -> n.a. | T28: =(H28+N28)/2 -> 0.26259842 | U28: 45383 | V28: 45401 | W28: https://alfred.stlouisfed.org/graph/alfredgraph.csv?id=PCENDC96&cosd=2021-01-01&coed=2026-04-01&vintage_date=2024-04-01
B29: 24 | C29: Fabric & Home Care | D29: organic_volume_growth | E29: 45473 | F29: 45408 | G29: 0 | H29: =AVERAGE('PG facts'!D44,'PG facts'!D51,'PG facts'!D58,'PG facts'!D65) -> 0 | I29: ='PG facts'!D65 -> 1 | J29: =COUNT('Training pairs'!F385:F393) -> 9 | K29: =(SUM('Training pairs'!I385:I393)-SUM('Training pairs'!F385:F393)*SUM('Training pairs'!G385:G393)/COUNT('Training pairs'!F385:F393))/(SUM('Training pairs'!H385:H393)-SUM('Training pairs'!F385:F393)^2/COUNT('Training pairs'!F385:F393)) -> 2.3029732 | L29: =AVERAGE('Training pairs'!G385:G393)-K29*AVERAGE('Training pairs'!F385:F393) -> -3.3304784 | M29: =(SUM('Target months'!H75:H77)/SUM('Target months'!F75:F77)-1)*100 -> 1.9054357 | N29: =L29+K29*M29 -> 1.057689 | O29: =COUNT('Training pairs'!F394:F401) -> 8 | P29: =(SUM('Training pairs'!I394:I401)-SUM('Training pairs'!F394:F401)*SUM('Training pairs'!G394:G401)/COUNT('Training pairs'!F394:F401))/(SUM('Training pairs'!H394:H401)-SUM('Training pairs'!F394:F401)^2/COUNT('Training pairs'!F394:F401)) -> 1.1542055 | Q29: =AVERAGE('Training pairs'!G394:G401)-P29*AVERAGE('Training pairs'!F394:F401) -> -2.9764671 | R29: 1.9031592 | S29: =Q29+P29*R29 -> -0.7798301 | T29: =(H29+N29)/2 -> 0.52884449 | U29: 45408 | V29: 45401 | W29: https://alfred.stlouisfed.org/graph/alfredgraph.csv?id=PCENDC96&cosd=2021-01-01&coed=2026-04-01&vintage_date=2024-04-26
B30: 25 | C30: Fabric & Home Care | D30: organic_volume_growth | E30: 45473 | F30: 45443 | G30: 1 | H30: =AVERAGE('PG facts'!D44,'PG facts'!D51,'PG facts'!D58,'PG facts'!D65) -> 0 | I30: ='PG facts'!D65 -> 1 | J30: =COUNT('Training pairs'!F402:F410) -> 9 | K30: =(SUM('Training pairs'!I402:I410)-SUM('Training pairs'!F402:F410)*SUM('Training pairs'!G402:G410)/COUNT('Training pairs'!F402:F410))/(SUM('Training pairs'!H402:H410)-SUM('Training pairs'!F402:F410)^2/COUNT('Training pairs'!F402:F410)) -> 2.3216349 | L30: =AVERAGE('Training pairs'!G402:G410)-K30*AVERAGE('Training pairs'!F402:F410) -> -3.3055781 | M30: =(SUM('Target months'!H78:H80)/SUM('Target months'!F78:F80)-1)*100 -> 1.7749528 | N30: =L30+K30*M30 -> 0.81521439 | O30: =COUNT('Training pairs'!F411:F418) -> 8 | P30: =(SUM('Training pairs'!I411:I418)-SUM('Training pairs'!F411:F418)*SUM('Training pairs'!G411:G418)/COUNT('Training pairs'!F411:F418))/(SUM('Training pairs'!H411:H418)-SUM('Training pairs'!F411:F418)^2/COUNT('Training pairs'!F411:F418)) -> 1.1542055 | Q30: =AVERAGE('Training pairs'!G411:G418)-P30*AVERAGE('Training pairs'!F411:F418) -> -2.9764671 | R30: 1.7438949 | S30: =Q30+P30*R30 -> -0.96365393 | T30: =(H30+N30)/2 -> 0.40760719 | U30: 45443 | V30: 45401 | W30: https://alfred.stlouisfed.org/graph/alfredgraph.csv?id=PCENDC96&cosd=2021-01-01&coed=2026-04-01&vintage_date=2024-05-31
B31: 26 | C31: Fabric & Home Care | D31: organic_volume_growth | E31: 45473 | F31: 45471 | G31: 2 | H31: =AVERAGE('PG facts'!D44,'PG facts'!D51,'PG facts'!D58,'PG facts'!D65) -> 0 | I31: ='PG facts'!D65 -> 1 | J31: =COUNT('Training pairs'!F419:F427) -> 9 | K31: =(SUM('Training pairs'!I419:I427)-SUM('Training pairs'!F419:F427)*SUM('Training pairs'!G419:G427)/COUNT('Training pairs'!F419:F427))/(SUM('Training pairs'!H419:H427)-SUM('Training pairs'!F419:F427)^2/COUNT('Training pairs'!F419:F427)) -> 2.3316231 | L31: =AVERAGE('Training pairs'!G419:G427)-K31*AVERAGE('Training pairs'!F419:F427) -> -3.2849991 | M31: =(SUM('Target months'!H81:H83)/SUM('Target months'!F81:F83)-1)*100 -> 1.5780382 | N31: =L31+K31*M31 -> 0.39439122 | O31: =COUNT('Training pairs'!F428:F435) -> 8 | P31: =(SUM('Training pairs'!I428:I435)-SUM('Training pairs'!F428:F435)*SUM('Training pairs'!G428:G435)/COUNT('Training pairs'!F428:F435))/(SUM('Training pairs'!H428:H435)-SUM('Training pairs'!F428:F435)^2/COUNT('Training pairs'!F428:F435)) -> 1.1542055 | Q31: =AVERAGE('Training pairs'!G428:G435)-P31*AVERAGE('Training pairs'!F428:F435) -> -2.9764671 | R31: 1.6317086 | S31: =Q31+P31*R31 -> -1.0931399 | T31: =(H31+N31)/2 -> 0.19719561 | U31: 45471 | V31: 45401 | W31: https://alfred.stlouisfed.org/graph/alfredgraph.csv?id=PCENDC96&cosd=2021-01-01&coed=2026-04-01&vintage_date=2024-06-28
B32: 27 | C32: Fabric & Home Care | D32: organic_volume_growth | E32: 45473 | F32: 45499 | G32: 3 | H32: =AVERAGE('PG facts'!D44,'PG facts'!D51,'PG facts'!D58,'PG facts'!D65) -> 0 | I32: ='PG facts'!D65 -> 1 | J32: =COUNT('Training pairs'!F436:F444) -> 9 | K32: =(SUM('Training pairs'!I436:I444)-SUM('Training pairs'!F436:F444)*SUM('Training pairs'!G436:G444)/COUNT('Training pairs'!F436:F444))/(SUM('Training pairs'!H436:H444)-SUM('Training pairs'!F436:F444)^2/COUNT('Training pairs'!F436:F444)) -> 2.3316231 | L32: =AVERAGE('Training pairs'!G436:G444)-K32*AVERAGE('Training pairs'!F436:F444) -> -3.2849991 | M32: =(SUM('Target months'!H84:H86)/SUM('Target months'!F84:F86)-1)*100 -> 1.7459001 | N32: =L32+K32*M32 -> 0.78578187 | O32: =COUNT('Training pairs'!F445:F452) -> 8 | P32: =(SUM('Training pairs'!I445:I452)-SUM('Training pairs'!F445:F452)*SUM('Training pairs'!G445:G452)/COUNT('Training pairs'!F445:F452))/(SUM('Training pairs'!H445:H452)-SUM('Training pairs'!F445:F452)^2/COUNT('Training pairs'!F445:F452)) -> 1.1542055 | Q32: =AVERAGE('Training pairs'!G445:G452)-P32*AVERAGE('Training pairs'!F445:F452) -> -2.9764671 | R32: 1.6317086 | S32: =Q32+P32*R32 -> -1.0931399 | T32: =(H32+N32)/2 -> 0.39289093 | U32: 45499 | V32: 45401 | W32: https://alfred.stlouisfed.org/graph/alfredgraph.csv?id=PCENDC96&cosd=2021-01-01&coed=2026-04-01&vintage_date=2024-07-26
B33: 28 | C33: Fabric & Home Care | D33: organic_volume_growth | E33: 45473 | F33: 45502 | G33: 3 | H33: =AVERAGE('PG facts'!D44,'PG facts'!D51,'PG facts'!D58,'PG facts'!D65) -> 0 | I33: ='PG facts'!D65 -> 1 | J33: =COUNT('Training pairs'!F453:F461) -> 9 | K33: =(SUM('Training pairs'!I453:I461)-SUM('Training pairs'!F453:F461)*SUM('Training pairs'!G453:G461)/COUNT('Training pairs'!F453:F461))/(SUM('Training pairs'!H453:H461)-SUM('Training pairs'!F453:F461)^2/COUNT('Training pairs'!F453:F461)) -> 2.3316231 | L33: =AVERAGE('Training pairs'!G453:G461)-K33*AVERAGE('Training pairs'!F453:F461) -> -3.2849991 | M33: =(SUM('Target months'!H87:H89)/SUM('Target months'!F87:F89)-1)*100 -> 1.7459001 | N33: =L33+K33*M33 -> 0.78578187 | O33: =COUNT('Training pairs'!F462:F469) -> 8 | P33: =(SUM('Training pairs'!I462:I469)-SUM('Training pairs'!F462:F469)*SUM('Training pairs'!G462:G469)/COUNT('Training pairs'!F462:F469))/(SUM('Training pairs'!H462:H469)-SUM('Training pairs'!F462:F469)^2/COUNT('Training pairs'!F462:F469)) -> 1.1542055 | Q33: =AVERAGE('Training pairs'!G462:G469)-P33*AVERAGE('Training pairs'!F462:F469) -> -2.9764671 | R33: 1.6317086 | S33: =Q33+P33*R33 -> -1.0931399 | T33: =(H33+N33)/2 -> 0.39289093 | U33: 45499 | V33: 45401 | W33: https://alfred.stlouisfed.org/graph/alfredgraph.csv?id=PCENDC96&cosd=2021-01-01&coed=2026-04-01&vintage_date=2024-07-26
B34: 29 | C34: Baby, Feminine & Family Care | D34: organic_volume_growth | E34: 45473 | F34: 45383 | G34: 0 | H34: =AVERAGE('PG facts'!D38,'PG facts'!D45,'PG facts'!D52,'PG facts'!D59) -> -2.25 | I34: ='PG facts'!D59 -> -2 | J34: =COUNT('Training pairs'!F470:F477) -> 8 | K34: =(SUM('Training pairs'!I470:I477)-SUM('Training pairs'!F470:F477)*SUM('Training pairs'!G470:G477)/COUNT('Training pairs'!F470:F477))/(SUM('Training pairs'!H470:H477)-SUM('Training pairs'!F470:F477)^2/COUNT('Training pairs'!F470:F477)) -> 1.0990266 | L34: =AVERAGE('Training pairs'!G470:G477)-K34*AVERAGE('Training pairs'!F470:F477) -> -2.8107611 | M34: =(SUM('Target months'!H90:H92)/SUM('Target months'!F90:F92)-1)*100 -> 1.6699249 | N34: =L34+K34*M34 -> -0.97546927 | O34: ="n.a." -> n.a. | P34: ="n.a." -> n.a. | Q34: ="n.a." -> n.a. | R34: n.a. | S34: ="n.a." -> n.a. | T34: =(H34+N34)/2 -> -1.6127346 | U34: 45383 | V34: 45314 | W34: https://alfred.stlouisfed.org/graph/alfredgraph.csv?id=PCENDC96&cosd=2021-01-01&coed=2026-04-01&vintage_date=2024-04-01
B35: 30 | C35: Baby, Feminine & Family Care | D35: organic_volume_growth | E35: 45473 | F35: 45401 | G35: 0 | H35: =AVERAGE('PG facts'!D45,'PG facts'!D52,'PG facts'!D59,'PG facts'!D66) -> -2 | I35: ='PG facts'!D66 -> -3 | J35: =COUNT('Training pairs'!F485:F492) -> 8 | K35: =(SUM('Training pairs'!I485:I492)-SUM('Training pairs'!F485:F492)*SUM('Training pairs'!G485:G492)/COUNT('Training pairs'!F485:F492))/(SUM('Training pairs'!H485:H492)-SUM('Training pairs'!F485:F492)^2/COUNT('Training pairs'!F485:F492)) -> 1.0990266 | L35: =AVERAGE('Training pairs'!G485:G492)-K35*AVERAGE('Training pairs'!F485:F492) -> -2.8107611 | M35: =(SUM('Target months'!H93:H95)/SUM('Target months'!F93:F95)-1)*100 -> 1.6699249 | N35: =L35+K35*M35 -> -0.97546927 | O35: =COUNT('Training pairs'!F493:F500) -> 8 | P35: =(SUM('Training pairs'!I493:I500)-SUM('Training pairs'!F493:F500)*SUM('Training pairs'!G493:G500)/COUNT('Training pairs'!F493:F500))/(SUM('Training pairs'!H493:H500)-SUM('Training pairs'!F493:F500)^2/COUNT('Training pairs'!F493:F500)) -> 0.71929975 | Q35: =AVERAGE('Training pairs'!G493:G500)-P35*AVERAGE('Training pairs'!F493:F500) -> -3.1556334 | R35: n.a. | S35: ="n.a." -> n.a. | T35: =(H35+N35)/2 -> -1.4877346 | U35: 45383 | V35: 45401 | W35: https://alfred.stlouisfed.org/graph/alfredgraph.csv?id=PCENDC96&cosd=2021-01-01&coed=2026-04-01&vintage_date=2024-04-01
B36: 31 | C36: Baby, Feminine & Family Care | D36: organic_volume_growth | E36: 45473 | F36: 45408 | G36: 0 | H36: =AVERAGE('PG facts'!D45,'PG facts'!D52,'PG facts'!D59,'PG facts'!D66) -> -2 | I36: ='PG facts'!D66 -> -3 | J36: =COUNT('Training pairs'!F501:F509) -> 9 | K36: =(SUM('Training pairs'!I501:I509)-SUM('Training pairs'!F501:F509)*SUM('Training pairs'!G501:G509)/COUNT('Training pairs'!F501:F509))/(SUM('Training pairs'!H501:H509)-SUM('Training pairs'!F501:F509)^2/COUNT('Training pairs'!F501:F509)) -> 0.97014414 | L36: =AVERAGE('Training pairs'!G501:G509)-K36*AVERAGE('Training pairs'!F501:F509) -> -2.9524229 | M36: =(SUM('Target months'!H96:H98)/SUM('Target months'!F96:F98)-1)*100 -> 1.9054357 | N36: =L36+K36*M36 -> -1.1038757 | O36: =COUNT('Training pairs'!F510:F517) -> 8 | P36: =(SUM('Training pairs'!I510:I517)-SUM('Training pairs'!F510:F517)*SUM('Training pairs'!G510:G517)/COUNT('Training pairs'!F510:F517))/(SUM('Training pairs'!H510:H517)-SUM('Training pairs'!F510:F517)^2/COUNT('Training pairs'!F510:F517)) -> 0.71929975 | Q36: =AVERAGE('Training pairs'!G510:G517)-P36*AVERAGE('Training pairs'!F510:F517) -> -3.1556334 | R36: 1.9031592 | S36: =Q36+P36*R36 -> -1.7866915 | T36: =(H36+N36)/2 -> -1.5519378 | U36: 45408 | V36: 45401 | W36: https://alfred.stlouisfed.org/graph/alfredgraph.csv?id=PCENDC96&cosd=2021-01-01&coed=2026-04-01&vintage_date=2024-04-26
B37: 32 | C37: Baby, Feminine & Family Care | D37: organic_volume_growth | E37: 45473 | F37: 45443 | G37: 1 | H37: =AVERAGE('PG facts'!D45,'PG facts'!D52,'PG facts'!D59,'PG facts'!D66) -> -2 | I37: ='PG facts'!D66 -> -3 | J37: =COUNT('Training pairs'!F518:F526) -> 9 | K37: =(SUM('Training pairs'!I518:I526)-SUM('Training pairs'!F518:F526)*SUM('Training pairs'!G518:G526)/COUNT('Training pairs'!F518:F526))/(SUM('Training pairs'!H518:H526)-SUM('Training pairs'!F518:F526)^2/COUNT('Training pairs'!F518:F526)) -> 0.99454343 | L37: =AVERAGE('Training pairs'!G518:G526)-K37*AVERAGE('Training pairs'!F518:F526) -> -2.9559826 | M37: =(SUM('Target months'!H99:H101)/SUM('Target months'!F99:F101)-1)*100 -> 1.7749528 | N37: =L37+K37*M37 -> -1.1907149 | O37: =COUNT('Training pairs'!F527:F534) -> 8 | P37: =(SUM('Training pairs'!I527:I534)-SUM('Training pairs'!F527:F534)*SUM('Training pairs'!G527:G534)/COUNT('Training pairs'!F527:F534))/(SUM('Training pairs'!H527:H534)-SUM('Training pairs'!F527:F534)^2/COUNT('Training pairs'!F527:F534)) -> 0.71929975 | Q37: =AVERAGE('Training pairs'!G527:G534)-P37*AVERAGE('Training pairs'!F527:F534) -> -3.1556334 | R37: 1.7438949 | S37: =Q37+P37*R37 -> -1.9012503 | T37: =(H37+N37)/2 -> -1.5953574 | U37: 45443 | V37: 45401 | W37: https://alfred.stlouisfed.org/graph/alfredgraph.csv?id=PCENDC96&cosd=2021-01-01&coed=2026-04-01&vintage_date=2024-05-31
B38: 33 | C38: Baby, Feminine & Family Care | D38: organic_volume_growth | E38: 45473 | F38: 45471 | G38: 2 | H38: =AVERAGE('PG facts'!D45,'PG facts'!D52,'PG facts'!D59,'PG facts'!D66) -> -2 | I38: ='PG facts'!D66 -> -3 | J38: =COUNT('Training pairs'!F535:F543) -> 9 | K38: =(SUM('Training pairs'!I535:I543)-SUM('Training pairs'!F535:F543)*SUM('Training pairs'!G535:G543)/COUNT('Training pairs'!F535:F543))/(SUM('Training pairs'!H535:H543)-SUM('Training pairs'!F535:F543)^2/COUNT('Training pairs'!F535:F543)) -> 1.0106998 | L38: =AVERAGE('Training pairs'!G535:G543)-K38*AVERAGE('Training pairs'!F535:F543) -> -2.957109 | M38: =(SUM('Target months'!H102:H104)/SUM('Target months'!F102:F104)-1)*100 -> 1.5780382 | N38: =L38+K38*M38 -> -1.3621861 | O38: =COUNT('Training pairs'!F544:F551) -> 8 | P38: =(SUM('Training pairs'!I544:I551)-SUM('Training pairs'!F544:F551)*SUM('Training pairs'!G544:G551)/COUNT('Training pairs'!F544:F551))/(SUM('Training pairs'!H544:H551)-SUM('Training pairs'!F544:F551)^2/COUNT('Training pairs'!F544:F551)) -> 0.71929975 | Q38: =AVERAGE('Training pairs'!G544:G551)-P38*AVERAGE('Training pairs'!F544:F551) -> -3.1556334 | R38: 1.6317086 | S38: =Q38+P38*R38 -> -1.9819458 | T38: =(H38+N38)/2 -> -1.681093 | U38: 45471 | V38: 45401 | W38: https://alfred.stlouisfed.org/graph/alfredgraph.csv?id=PCENDC96&cosd=2021-01-01&coed=2026-04-01&vintage_date=2024-06-28
B39: 34 | C39: Baby, Feminine & Family Care | D39: organic_volume_growth | E39: 45473 | F39: 45499 | G39: 3 | H39: =AVERAGE('PG facts'!D45,'PG facts'!D52,'PG facts'!D59,'PG facts'!D66) -> -2 | I39: ='PG facts'!D66 -> -3 | J39: =COUNT('Training pairs'!F552:F560) -> 9 | K39: =(SUM('Training pairs'!I552:I560)-SUM('Training pairs'!F552:F560)*SUM('Training pairs'!G552:G560)/COUNT('Training pairs'!F552:F560))/(SUM('Training pairs'!H552:H560)-SUM('Training pairs'!F552:F560)^2/COUNT('Training pairs'!F552:F560)) -> 1.0106998 | L39: =AVERAGE('Training pairs'!G552:G560)-K39*AVERAGE('Training pairs'!F552:F560) -> -2.957109 | M39: =(SUM('Target months'!H105:H107)/SUM('Target months'!F105:F107)-1)*100 -> 1.7459001 | N39: =L39+K39*M39 -> -1.1925281 | O39: =COUNT('Training pairs'!F561:F568) -> 8 | P39: =(SUM('Training pairs'!I561:I568)-SUM('Training pairs'!F561:F568)*SUM('Training pairs'!G561:G568)/COUNT('Training pairs'!F561:F568))/(SUM('Training pairs'!H561:H568)-SUM('Training pairs'!F561:F568)^2/COUNT('Training pairs'!F561:F568)) -> 0.71929975 | Q39: =AVERAGE('Training pairs'!G561:G568)-P39*AVERAGE('Training pairs'!F561:F568) -> -3.1556334 | R39: 1.6317086 | S39: =Q39+P39*R39 -> -1.9819458 | T39: =(H39+N39)/2 -> -1.5962641 | U39: 45499 | V39: 45401 | W39: https://alfred.stlouisfed.org/graph/alfredgraph.csv?id=PCENDC96&cosd=2021-01-01&coed=2026-04-01&vintage_date=2024-07-26
B40: 35 | C40: Baby, Feminine & Family Care | D40: organic_volume_growth | E40: 45473 | F40: 45502 | G40: 3 | H40: =AVERAGE('PG facts'!D45,'PG facts'!D52,'PG facts'!D59,'PG facts'!D66) -> -2 | I40: ='PG facts'!D66 -> -3 | J40: =COUNT('Training pairs'!F569:F577) -> 9 | K40: =(SUM('Training pairs'!I569:I577)-SUM('Training pairs'!F569:F577)*SUM('Training pairs'!G569:G577)/COUNT('Training pairs'!F569:F577))/(SUM('Training pairs'!H569:H577)-SUM('Training pairs'!F569:F577)^2/COUNT('Training pairs'!F569:F577)) -> 1.0106998 | L40: =AVERAGE('Training pairs'!G569:G577)-K40*AVERAGE('Training pairs'!F569:F577) -> -2.957109 | M40: =(SUM('Target months'!H108:H110)/SUM('Target months'!F108:F110)-1)*100 -> 1.7459001 | N40: =L40+K40*M40 -> -1.1925281 | O40: =COUNT('Training pairs'!F578:F585) -> 8 | P40: =(SUM('Training pairs'!I578:I585)-SUM('Training pairs'!F578:F585)*SUM('Training pairs'!G578:G585)/COUNT('Training pairs'!F578:F585))/(SUM('Training pairs'!H578:H585)-SUM('Training pairs'!F578:F585)^2/COUNT('Training pairs'!F578:F585)) -> 0.71929975 | Q40: =AVERAGE('Training pairs'!G578:G585)-P40*AVERAGE('Training pairs'!F578:F585) -> -3.1556334 | R40: 1.6317086 | S40: =Q40+P40*R40 -> -1.9819458 | T40: =(H40+N40)/2 -> -1.5962641 | U40: 45499 | V40: 45401 | W40: https://alfred.stlouisfed.org/graph/alfredgraph.csv?id=PCENDC96&cosd=2021-01-01&coed=2026-04-01&vintage_date=2024-07-26
B41: 36 | C41: Beauty | D41: price_contribution | E41: 45473 | F41: 45383 | G41: 0 | H41: =AVERAGE('PG facts'!E34,'PG facts'!E41,'PG facts'!E48,'PG facts'!E55) -> 6.75 | I41: ='PG facts'!E55 -> 4 | J41: =COUNT('Training pairs'!F586:F593) -> 8 | K41: =(SUM('Training pairs'!I586:I593)-SUM('Training pairs'!F586:F593)*SUM('Training pairs'!G586:G593)/COUNT('Training pairs'!F586:F593))/(SUM('Training pairs'!H586:H593)-SUM('Training pairs'!F586:F593)^2/COUNT('Training pairs'!F586:F593)) -> 0.73002167 | L41: =AVERAGE('Training pairs'!G586:G593)-K41*AVERAGE('Training pairs'!F586:F593) -> 2.92169 | M41: =(SUM('Target months'!H111:H113)/SUM('Target months'!F111:F113)-1)*100 -> 3.588559 | N41: =L41+K41*M41 -> 5.5414158 | O41: ="n.a." -> n.a. | P41: ="n.a." -> n.a. | Q41: ="n.a." -> n.a. | R41: n.a. | S41: ="n.a." -> n.a. | T41: =(H41+N41)/2 -> 6.1457079 | U41: 45383 | V41: 45314 | W41: https://alfred.stlouisfed.org/graph/alfredgraph.csv?id=CUUR0000SEGB&cosd=2021-01-01&coed=2026-04-01&vintage_date=2024-04-01
B42: 37 | C42: Beauty | D42: price_contribution | E42: 45473 | F42: 45392 | G42: 0 | H42: =AVERAGE('PG facts'!E34,'PG facts'!E41,'PG facts'!E48,'PG facts'!E55) -> 6.75 | I42: ='PG facts'!E55 -> 4 | J42: =COUNT('Training pairs'!F601:F608) -> 8 | K42: =(SUM('Training pairs'!I601:I608)-SUM('Training pairs'!F601:F608)*SUM('Training pairs'!G601:G608)/COUNT('Training pairs'!F601:F608))/(SUM('Training pairs'!H601:H608)-SUM('Training pairs'!F601:F608)^2/COUNT('Training pairs'!F601:F608)) -> 0.73002167 | L42: =AVERAGE('Training pairs'!G601:G608)-K42*AVERAGE('Training pairs'!F601:F608) -> 2.92169 | M42: =(SUM('Target months'!H114:H116)/SUM('Target months'!F114:F116)-1)*100 -> 3.6372374 | N42: =L42+K42*M42 -> 5.5769521 | O42: ="n.a." -> n.a. | P42: ="n.a." -> n.a. | Q42: ="n.a." -> n.a. | R42: 3.6368096 | S42: ="n.a." -> n.a. | T42: =(H42+N42)/2 -> 6.163476 | U42: 45392 | V42: 45314 | W42: https://alfred.stlouisfed.org/graph/alfredgraph.csv?id=CUUR0000SEGB&cosd=2021-01-01&coed=2026-04-01&vintage_date=2024-04-10
B43: 38 | C43: Beauty | D43: price_contribution | E43: 45473 | F43: 45401 | G43: 0 | H43: =AVERAGE('PG facts'!E41,'PG facts'!E48,'PG facts'!E55,'PG facts'!E62) -> 5.75 | I43: ='PG facts'!E62 -> 4 | J43: =COUNT('Training pairs'!F616:F624) -> 9 | K43: =(SUM('Training pairs'!I616:I624)-SUM('Training pairs'!F616:F624)*SUM('Training pairs'!G616:G624)/COUNT('Training pairs'!F616:F624))/(SUM('Training pairs'!H616:H624)-SUM('Training pairs'!F616:F624)^2/COUNT('Training pairs'!F616:F624)) -> 0.78595698 | L43: =AVERAGE('Training pairs'!G616:G624)-K43*AVERAGE('Training pairs'!F616:F624) -> 2.4716801 | M43: =(SUM('Target months'!H117:H119)/SUM('Target months'!F117:F119)-1)*100 -> 3.6372374 | N43: =L43+K43*M43 -> 5.3303922 | O43: =COUNT('Training pairs'!F625:F632) -> 8 | P43: =(SUM('Training pairs'!I625:I632)-SUM('Training pairs'!F625:F632)*SUM('Training pairs'!G625:G632)/COUNT('Training pairs'!F625:F632))/(SUM('Training pairs'!H625:H632)-SUM('Training pairs'!F625:F632)^2/COUNT('Training pairs'!F625:F632)) -> 0.31633921 | Q43: =AVERAGE('Training pairs'!G625:G632)-P43*AVERAGE('Training pairs'!F625:F632) -> 5.0202502 | R43: 3.6368096 | S43: =Q43+P43*R43 -> 6.1707157 | T43: =(H43+N43)/2 -> 5.5401961 | U43: 45392 | V43: 45401 | W43: https://alfred.stlouisfed.org/graph/alfredgraph.csv?id=CUUR0000SEGB&cosd=2021-01-01&coed=2026-04-01&vintage_date=2024-04-10
B44: 39 | C44: Beauty | D44: price_contribution | E44: 45473 | F44: 45427 | G44: 1 | H44: =AVERAGE('PG facts'!E41,'PG facts'!E48,'PG facts'!E55,'PG facts'!E62) -> 5.75 | I44: ='PG facts'!E62 -> 4 | J44: =COUNT('Training pairs'!F633:F641) -> 9 | K44: =(SUM('Training pairs'!I633:I641)-SUM('Training pairs'!F633:F641)*SUM('Training pairs'!G633:G641)/COUNT('Training pairs'!F633:F641))/(SUM('Training pairs'!H633:H641)-SUM('Training pairs'!F633:F641)^2/COUNT('Training pairs'!F633:F641)) -> 0.78595698 | L44: =AVERAGE('Training pairs'!G633:G641)-K44*AVERAGE('Training pairs'!F633:F641) -> 2.4716801 | M44: =(SUM('Target months'!H120:H122)/SUM('Target months'!F120:F122)-1)*100 -> 3.0970677 | N44: =L44+K44*M44 -> 4.905842 | O44: =COUNT('Training pairs'!F642:F649) -> 8 | P44: =(SUM('Training pairs'!I642:I649)-SUM('Training pairs'!F642:F649)*SUM('Training pairs'!G642:G649)/COUNT('Training pairs'!F642:F649))/(SUM('Training pairs'!H642:H649)-SUM('Training pairs'!F642:F649)^2/COUNT('Training pairs'!F642:F649)) -> 0.31633921 | Q44: =AVERAGE('Training pairs'!G642:G649)-P44*AVERAGE('Training pairs'!F642:F649) -> 5.0202502 | R44: 3.6368096 | S44: =Q44+P44*R44 -> 6.1707157 | T44: =(H44+N44)/2 -> 5.327921 | U44: 45427 | V44: 45401 | W44: https://alfred.stlouisfed.org/graph/alfredgraph.csv?id=CUUR0000SEGB&cosd=2021-01-01&coed=2026-04-01&vintage_date=2024-05-15
B45: 40 | C45: Beauty | D45: price_contribution | E45: 45473 | F45: 45455 | G45: 2 | H45: =AVERAGE('PG facts'!E41,'PG facts'!E48,'PG facts'!E55,'PG facts'!E62) -> 5.75 | I45: ='PG facts'!E62 -> 4 | J45: =COUNT('Training pairs'!F650:F658) -> 9 | K45: =(SUM('Training pairs'!I650:I658)-SUM('Training pairs'!F650:F658)*SUM('Training pairs'!G650:G658)/COUNT('Training pairs'!F650:F658))/(SUM('Training pairs'!H650:H658)-SUM('Training pairs'!F650:F658)^2/COUNT('Training pairs'!F650:F658)) -> 0.78595698 | L45: =AVERAGE('Training pairs'!G650:G658)-K45*AVERAGE('Training pairs'!F650:F658) -> 2.4716801 | M45: =(SUM('Target months'!H123:H125)/SUM('Target months'!F123:F125)-1)*100 -> 2.1258306 | N45: =L45+K45*M45 -> 4.1424914 | O45: =COUNT('Training pairs'!F659:F666) -> 8 | P45: =(SUM('Training pairs'!I659:I666)-SUM('Training pairs'!F659:F666)*SUM('Training pairs'!G659:G666)/COUNT('Training pairs'!F659:F666))/(SUM('Training pairs'!H659:H666)-SUM('Training pairs'!F659:F666)^2/COUNT('Training pairs'!F659:F666)) -> 0.31633921 | Q45: =AVERAGE('Training pairs'!G659:G666)-P45*AVERAGE('Training pairs'!F659:F666) -> 5.0202502 | R45: 3.6368096 | S45: =Q45+P45*R45 -> 6.1707157 | T45: =(H45+N45)/2 -> 4.9462457 | U45: 45455 | V45: 45401 | W45: https://alfred.stlouisfed.org/graph/alfredgraph.csv?id=CUUR0000SEGB&cosd=2021-01-01&coed=2026-04-01&vintage_date=2024-06-12
B46: 41 | C46: Beauty | D46: price_contribution | E46: 45473 | F46: 45484 | G46: 3 | H46: =AVERAGE('PG facts'!E41,'PG facts'!E48,'PG facts'!E55,'PG facts'!E62) -> 5.75 | I46: ='PG facts'!E62 -> 4 | J46: =COUNT('Training pairs'!F667:F675) -> 9 | K46: =(SUM('Training pairs'!I667:I675)-SUM('Training pairs'!F667:F675)*SUM('Training pairs'!G667:G675)/COUNT('Training pairs'!F667:F675))/(SUM('Training pairs'!H667:H675)-SUM('Training pairs'!F667:F675)^2/COUNT('Training pairs'!F667:F675)) -> 0.78595698 | L46: =AVERAGE('Training pairs'!G667:G675)-K46*AVERAGE('Training pairs'!F667:F675) -> 2.4716801 | M46: =(SUM('Target months'!H126:H128)/SUM('Target months'!F126:F128)-1)*100 -> 1.654755 | N46: =L46+K46*M46 -> 3.7722463 | O46: =COUNT('Training pairs'!F676:F683) -> 8 | P46: =(SUM('Training pairs'!I676:I683)-SUM('Training pairs'!F676:F683)*SUM('Training pairs'!G676:G683)/COUNT('Training pairs'!F676:F683))/(SUM('Training pairs'!H676:H683)-SUM('Training pairs'!F676:F683)^2/COUNT('Training pairs'!F676:F683)) -> 0.31633921 | Q46: =AVERAGE('Training pairs'!G676:G683)-P46*AVERAGE('Training pairs'!F676:F683) -> 5.0202502 | R46: 3.6368096 | S46: =Q46+P46*R46 -> 6.1707157 | T46: =(H46+N46)/2 -> 4.7611232 | U46: 45484 | V46: 45401 | W46: https://alfred.stlouisfed.org/graph/alfredgraph.csv?id=CUUR0000SEGB&cosd=2021-01-01&coed=2026-04-01&vintage_date=2024-07-11
B47: 42 | C47: Beauty | D47: price_contribution | E47: 45473 | F47: 45502 | G47: 3 | H47: =AVERAGE('PG facts'!E41,'PG facts'!E48,'PG facts'!E55,'PG facts'!E62) -> 5.75 | I47: ='PG facts'!E62 -> 4 | J47: =COUNT('Training pairs'!F684:F692) -> 9 | K47: =(SUM('Training pairs'!I684:I692)-SUM('Training pairs'!F684:F692)*SUM('Training pairs'!G684:G692)/COUNT('Training pairs'!F684:F692))/(SUM('Training pairs'!H684:H692)-SUM('Training pairs'!F684:F692)^2/COUNT('Training pairs'!F684:F692)) -> 0.78595698 | L47: =AVERAGE('Training pairs'!G684:G692)-K47*AVERAGE('Training pairs'!F684:F692) -> 2.4716801 | M47: =(SUM('Target months'!H129:H131)/SUM('Target months'!F129:F131)-1)*100 -> 1.654755 | N47: =L47+K47*M47 -> 3.7722463 | O47: =COUNT('Training pairs'!F693:F700) -> 8 | P47: =(SUM('Training pairs'!I693:I700)-SUM('Training pairs'!F693:F700)*SUM('Training pairs'!G693:G700)/COUNT('Training pairs'!F693:F700))/(SUM('Training pairs'!H693:H700)-SUM('Training pairs'!F693:F700)^2/COUNT('Training pairs'!F693:F700)) -> 0.31633921 | Q47: =AVERAGE('Training pairs'!G693:G700)-P47*AVERAGE('Training pairs'!F693:F700) -> 5.0202502 | R47: 3.6368096 | S47: =Q47+P47*R47 -> 6.1707157 | T47: =(H47+N47)/2 -> 4.7611232 | U47: 45484 | V47: 45401 | W47: https://alfred.stlouisfed.org/graph/alfredgraph.csv?id=CUUR0000SEGB&cosd=2021-01-01&coed=2026-04-01&vintage_date=2024-07-11
B48: 43 | C48: Grooming | D48: price_contribution | E48: 45473 | F48: 45383 | G48: 0 | H48: =AVERAGE('PG facts'!E35,'PG facts'!E42,'PG facts'!E49,'PG facts'!E56) -> 8.75 | I48: ='PG facts'!E56 -> 7 | J48: =COUNT('Training pairs'!F701:F708) -> 8 | K48: =(SUM('Training pairs'!I701:I708)-SUM('Training pairs'!F701:F708)*SUM('Training pairs'!G701:G708)/COUNT('Training pairs'!F701:F708))/(SUM('Training pairs'!H701:H708)-SUM('Training pairs'!F701:F708)^2/COUNT('Training pairs'!F701:F708)) -> 0.75045646 | L48: =AVERAGE('Training pairs'!G701:G708)-K48*AVERAGE('Training pairs'!F701:F708) -> 4.4430269 | M48: =(SUM('Target months'!H132:H134)/SUM('Target months'!F132:F134)-1)*100 -> 3.588559 | N48: =L48+K48*M48 -> 7.1360841 | O48: ="n.a." -> n.a. | P48: ="n.a." -> n.a. | Q48: ="n.a." -> n.a. | R48: n.a. | S48: ="n.a." -> n.a. | T48: =(H48+N48)/2 -> 7.943042 | U48: 45383 | V48: 45314 | W48: https://alfred.stlouisfed.org/graph/alfredgraph.csv?id=CUUR0000SEGB&cosd=2021-01-01&coed=2026-04-01&vintage_date=2024-04-01
B49: 44 | C49: Grooming | D49: price_contribution | E49: 45473 | F49: 45392 | G49: 0 | H49: =AVERAGE('PG facts'!E35,'PG facts'!E42,'PG facts'!E49,'PG facts'!E56) -> 8.75 | I49: ='PG facts'!E56 -> 7 | J49: =COUNT('Training pairs'!F716:F723) -> 8 | K49: =(SUM('Training pairs'!I716:I723)-SUM('Training pairs'!F716:F723)*SUM('Training pairs'!G716:G723)/COUNT('Training pairs'!F716:F723))/(SUM('Training pairs'!H716:H723)-SUM('Training pairs'!F716:F723)^2/COUNT('Training pairs'!F716:F723)) -> 0.75045646 | L49: =AVERAGE('Training pairs'!G716:G723)-K49*AVERAGE('Training pairs'!F716:F723) -> 4.4430269 | M49: =(SUM('Target months'!H135:H137)/SUM('Target months'!F135:F137)-1)*100 -> 3.6372374 | N49: =L49+K49*M49 -> 7.1726151 | O49: ="n.a." -> n.a. | P49: ="n.a." -> n.a. | Q49: ="n.a." -> n.a. | R49: 3.6368096 | S49: ="n.a." -> n.a. | T49: =(H49+N49)/2 -> 7.9613076 | U49: 45392 | V49: 45314 | W49: https://alfred.stlouisfed.org/graph/alfredgraph.csv?id=CUUR0000SEGB&cosd=2021-01-01&coed=2026-04-01&vintage_date=2024-04-10
B50: 45 | C50: Grooming | D50: price_contribution | E50: 45473 | F50: 45401 | G50: 0 | H50: =AVERAGE('PG facts'!E42,'PG facts'!E49,'PG facts'!E56,'PG facts'!E63) -> 8.75 | I50: ='PG facts'!E63 -> 10 | J50: =COUNT('Training pairs'!F731:F739) -> 9 | K50: =(SUM('Training pairs'!I731:I739)-SUM('Training pairs'!F731:F739)*SUM('Training pairs'!G731:G739)/COUNT('Training pairs'!F731:F739))/(SUM('Training pairs'!H731:H739)-SUM('Training pairs'!F731:F739)^2/COUNT('Training pairs'!F731:F739)) -> 0.65013638 | L50: =AVERAGE('Training pairs'!G731:G739)-K50*AVERAGE('Training pairs'!F731:F739) -> 5.2501204 | M50: =(SUM('Target months'!H138:H140)/SUM('Target months'!F138:F140)-1)*100 -> 3.6372374 | N50: =L50+K50*M50 -> 7.6148207 | O50: =COUNT('Training pairs'!F740:F747) -> 8 | P50: =(SUM('Training pairs'!I740:I747)-SUM('Training pairs'!F740:F747)*SUM('Training pairs'!G740:G747)/COUNT('Training pairs'!F740:F747))/(SUM('Training pairs'!H740:H747)-SUM('Training pairs'!F740:F747)^2/COUNT('Training pairs'!F740:F747)) -> 0.47825205 | Q50: =AVERAGE('Training pairs'!G740:G747)-P50*AVERAGE('Training pairs'!F740:F747) -> 6.3238863 | R50: 3.6368096 | S50: =Q50+P50*R50 -> 8.0631979 | T50: =(H50+N50)/2 -> 8.1824104 | U50: 45392 | V50: 45401 | W50: https://alfred.stlouisfed.org/graph/alfredgraph.csv?id=CUUR0000SEGB&cosd=2021-01-01&coed=2026-04-01&vintage_date=2024-04-10
B51: 46 | C51: Grooming | D51: price_contribution | E51: 45473 | F51: 45427 | G51: 1 | H51: =AVERAGE('PG facts'!E42,'PG facts'!E49,'PG facts'!E56,'PG facts'!E63) -> 8.75 | I51: ='PG facts'!E63 -> 10 | J51: =COUNT('Training pairs'!F748:F756) -> 9 | K51: =(SUM('Training pairs'!I748:I756)-SUM('Training pairs'!F748:F756)*SUM('Training pairs'!G748:G756)/COUNT('Training pairs'!F748:F756))/(SUM('Training pairs'!H748:H756)-SUM('Training pairs'!F748:F756)^2/COUNT('Training pairs'!F748:F756)) -> 0.65013638 | L51: =AVERAGE('Training pairs'!G748:G756)-K51*AVERAGE('Training pairs'!F748:F756) -> 5.2501204 | M51: =(SUM('Target months'!H141:H143)/SUM('Target months'!F141:F143)-1)*100 -> 3.0970677 | N51: =L51+K51*M51 -> 7.2636368 | O51: =COUNT('Training pairs'!F757:F764) -> 8 | P51: =(SUM('Training pairs'!I757:I764)-SUM('Training pairs'!F757:F764)*SUM('Training pairs'!G757:G764)/COUNT('Training pairs'!F757:F764))/(SUM('Training pairs'!H757:H764)-SUM('Training pairs'!F757:F764)^2/COUNT('Training pairs'!F757:F764)) -> 0.47825205 | Q51: =AVERAGE('Training pairs'!G757:G764)-P51*AVERAGE('Training pairs'!F757:F764) -> 6.3238863 | R51: 3.6368096 | S51: =Q51+P51*R51 -> 8.0631979 | T51: =(H51+N51)/2 -> 8.0068184 | U51: 45427 | V51: 45401 | W51: https://alfred.stlouisfed.org/graph/alfredgraph.csv?id=CUUR0000SEGB&cosd=2021-01-01&coed=2026-04-01&vintage_date=2024-05-15
B52: 47 | C52: Grooming | D52: price_contribution | E52: 45473 | F52: 45455 | G52: 2 | H52: =AVERAGE('PG facts'!E42,'PG facts'!E49,'PG facts'!E56,'PG facts'!E63) -> 8.75 | I52: ='PG facts'!E63 -> 10 | J52: =COUNT('Training pairs'!F765:F773) -> 9 | K52: =(SUM('Training pairs'!I765:I773)-SUM('Training pairs'!F765:F773)*SUM('Training pairs'!G765:G773)/COUNT('Training pairs'!F765:F773))/(SUM('Training pairs'!H765:H773)-SUM('Training pairs'!F765:F773)^2/COUNT('Training pairs'!F765:F773)) -> 0.65013638 | L52: =AVERAGE('Training pairs'!G765:G773)-K52*AVERAGE('Training pairs'!F765:F773) -> 5.2501204 | M52: =(SUM('Target months'!H144:H146)/SUM('Target months'!F144:F146)-1)*100 -> 2.1258306 | N52: =L52+K52*M52 -> 6.6322002 | O52: =COUNT('Training pairs'!F774:F781) -> 8 | P52: =(SUM('Training pairs'!I774:I781)-SUM('Training pairs'!F774:F781)*SUM('Training pairs'!G774:G781)/COUNT('Training pairs'!F774:F781))/(SUM('Training pairs'!H774:H781)-SUM('Training pairs'!F774:F781)^2/COUNT('Training pairs'!F774:F781)) -> 0.47825205 | Q52: =AVERAGE('Training pairs'!G774:G781)-P52*AVERAGE('Training pairs'!F774:F781) -> 6.3238863 | R52: 3.6368096 | S52: =Q52+P52*R52 -> 8.0631979 | T52: =(H52+N52)/2 -> 7.6911001 | U52: 45455 | V52: 45401 | W52: https://alfred.stlouisfed.org/graph/alfredgraph.csv?id=CUUR0000SEGB&cosd=2021-01-01&coed=2026-04-01&vintage_date=2024-06-12
B53: 48 | C53: Grooming | D53: price_contribution | E53: 45473 | F53: 45484 | G53: 3 | H53: =AVERAGE('PG facts'!E42,'PG facts'!E49,'PG facts'!E56,'PG facts'!E63) -> 8.75 | I53: ='PG facts'!E63 -> 10 | J53: =COUNT('Training pairs'!F782:F790) -> 9 | K53: =(SUM('Training pairs'!I782:I790)-SUM('Training pairs'!F782:F790)*SUM('Training pairs'!G782:G790)/COUNT('Training pairs'!F782:F790))/(SUM('Training pairs'!H782:H790)-SUM('Training pairs'!F782:F790)^2/COUNT('Training pairs'!F782:F790)) -> 0.65013638 | L53: =AVERAGE('Training pairs'!G782:G790)-K53*AVERAGE('Training pairs'!F782:F790) -> 5.2501204 | M53: =(SUM('Target months'!H147:H149)/SUM('Target months'!F147:F149)-1)*100 -> 1.654755 | N53: =L53+K53*M53 -> 6.3259368 | O53: =COUNT('Training pairs'!F791:F798) -> 8 | P53: =(SUM('Training pairs'!I791:I798)-SUM('Training pairs'!F791:F798)*SUM('Training pairs'!G791:G798)/COUNT('Training pairs'!F791:F798))/(SUM('Training pairs'!H791:H798)-SUM('Training pairs'!F791:F798)^2/COUNT('Training pairs'!F791:F798)) -> 0.47825205 | Q53: =AVERAGE('Training pairs'!G791:G798)-P53*AVERAGE('Training pairs'!F791:F798) -> 6.3238863 | R53: 3.6368096 | S53: =Q53+P53*R53 -> 8.0631979 | T53: =(H53+N53)/2 -> 7.5379684 | U53: 45484 | V53: 45401 | W53: https://alfred.stlouisfed.org/graph/alfredgraph.csv?id=CUUR0000SEGB&cosd=2021-01-01&coed=2026-04-01&vintage_date=2024-07-11
B54: 49 | C54: Grooming | D54: price_contribution | E54: 45473 | F54: 45502 | G54: 3 | H54: =AVERAGE('PG facts'!E42,'PG facts'!E49,'PG facts'!E56,'PG facts'!E63) -> 8.75 | I54: ='PG facts'!E63 -> 10 | J54: =COUNT('Training pairs'!F799:F807) -> 9 | K54: =(SUM('Training pairs'!I799:I807)-SUM('Training pairs'!F799:F807)*SUM('Training pairs'!G799:G807)/COUNT('Training pairs'!F799:F807))/(SUM('Training pairs'!H799:H807)-SUM('Training pairs'!F799:F807)^2/COUNT('Training pairs'!F799:F807)) -> 0.65013638 | L54: =AVERAGE('Training pairs'!G799:G807)-K54*AVERAGE('Training pairs'!F799:F807) -> 5.2501204 | M54: =(SUM('Target months'!H150:H152)/SUM('Target months'!F150:F152)-1)*100 -> 1.654755 | N54: =L54+K54*M54 -> 6.3259368 | O54: =COUNT('Training pairs'!F808:F815) -> 8 | P54: =(SUM('Training pairs'!I808:I815)-SUM('Training pairs'!F808:F815)*SUM('Training pairs'!G808:G815)/COUNT('Training pairs'!F808:F815))/(SUM('Training pairs'!H808:H815)-SUM('Training pairs'!F808:F815)^2/COUNT('Training pairs'!F808:F815)) -> 0.47825205 | Q54: =AVERAGE('Training pairs'!G808:G815)-P54*AVERAGE('Training pairs'!F808:F815) -> 6.3238863 | R54: 3.6368096 | S54: =Q54+P54*R54 -> 8.0631979 | T54: =(H54+N54)/2 -> 7.5379684 | U54: 45484 | V54: 45401 | W54: https://alfred.stlouisfed.org/graph/alfredgraph.csv?id=CUUR0000SEGB&cosd=2021-01-01&coed=2026-04-01&vintage_date=2024-07-11
B55: 50 | C55: Beauty | D55: organic_sales_growth | E55: 45473 | F55: 45383 | G55: 0 | H55: =AVERAGE('PG facts'!F34,'PG facts'!F41,'PG facts'!F48,'PG facts'!F55) -> 6 | I55: ='PG facts'!F55 -> 1 | J55: =COUNT('Training pairs'!F816:F823) -> 8 | K55: =(SUM('Training pairs'!I816:I823)-SUM('Training pairs'!F816:F823)*SUM('Training pairs'!G816:G823)/COUNT('Training pairs'!F816:F823))/(SUM('Training pairs'!H816:H823)-SUM('Training pairs'!F816:F823)^2/COUNT('Training pairs'!F816:F823)) -> 0.45754605 | L55: =AVERAGE('Training pairs'!G816:G823)-K55*AVERAGE('Training pairs'!F816:F823) -> 1.5252486 | M55: =(SUM('Target months'!H153:H155)/SUM('Target months'!F153:F155)-1)*100 -> 5.4048367 | N55: =L55+K55*M55 -> 3.9982103 | O55: ="n.a." -> n.a. | P55: ="n.a." -> n.a. | Q55: ="n.a." -> n.a. | R55: n.a. | S55: ="n.a." -> n.a. | T55: =(H55+N55)/2 -> 4.9991052 | U55: 45383 | V55: 45314 | W55: https://alfred.stlouisfed.org/graph/alfredgraph.csv?id=RSHPCS&cosd=2021-01-01&coed=2026-04-01&vintage_date=2024-04-01
B56: 51 | C56: Beauty | D56: organic_sales_growth | E56: 45473 | F56: 45397 | G56: 0 | H56: =AVERAGE('PG facts'!F34,'PG facts'!F41,'PG facts'!F48,'PG facts'!F55) -> 6 | I56: ='PG facts'!F55 -> 1 | J56: =COUNT('Training pairs'!F831:F838) -> 8 | K56: =(SUM('Training pairs'!I831:I838)-SUM('Training pairs'!F831:F838)*SUM('Training pairs'!G831:G838)/COUNT('Training pairs'!F831:F838))/(SUM('Training pairs'!H831:H838)-SUM('Training pairs'!F831:F838)^2/COUNT('Training pairs'!F831:F838)) -> 0.46096823 | L56: =AVERAGE('Training pairs'!G831:G838)-K56*AVERAGE('Training pairs'!F831:F838) -> 1.492499 | M56: =(SUM('Target months'!H156:H158)/SUM('Target months'!F156:F158)-1)*100 -> 2.7031812 | N56: =L56+K56*M56 -> 2.7385796 | O56: ="n.a." -> n.a. | P56: ="n.a." -> n.a. | Q56: ="n.a." -> n.a. | R56: 2.6947412 | S56: ="n.a." -> n.a. | T56: =(H56+N56)/2 -> 4.3692898 | U56: 45397 | V56: 45314 | W56: https://alfred.stlouisfed.org/graph/alfredgraph.csv?id=RSHPCS&cosd=2021-01-01&coed=2026-04-01&vintage_date=2024-04-15
B57: 52 | C57: Beauty | D57: organic_sales_growth | E57: 45473 | F57: 45401 | G57: 0 | H57: =AVERAGE('PG facts'!F41,'PG facts'!F48,'PG facts'!F55,'PG facts'!F62) -> 5 | I57: ='PG facts'!F62 -> 3 | J57: =COUNT('Training pairs'!F846:F854) -> 9 | K57: =(SUM('Training pairs'!I846:I854)-SUM('Training pairs'!F846:F854)*SUM('Training pairs'!G846:G854)/COUNT('Training pairs'!F846:F854))/(SUM('Training pairs'!H846:H854)-SUM('Training pairs'!F846:F854)^2/COUNT('Training pairs'!F846:F854)) -> 0.45073391 | L57: =AVERAGE('Training pairs'!G846:G854)-K57*AVERAGE('Training pairs'!F846:F854) -> 1.5794614 | M57: =(SUM('Target months'!H159:H161)/SUM('Target months'!F159:F161)-1)*100 -> 2.7031812 | N57: =L57+K57*M57 -> 2.7978768 | O57: =COUNT('Training pairs'!F855:F862) -> 8 | P57: =(SUM('Training pairs'!I855:I862)-SUM('Training pairs'!F855:F862)*SUM('Training pairs'!G855:G862)/COUNT('Training pairs'!F855:F862))/(SUM('Training pairs'!H855:H862)-SUM('Training pairs'!F855:F862)^2/COUNT('Training pairs'!F855:F862)) -> 0.027101416 | Q57: =AVERAGE('Training pairs'!G855:G862)-P57*AVERAGE('Training pairs'!F855:F862) -> 4.08788 | R57: 2.6947412 | S57: =Q57+P57*R57 -> 4.1609113 | T57: =(H57+N57)/2 -> 3.8989384 | U57: 45397 | V57: 45401 | W57: https://alfred.stlouisfed.org/graph/alfredgraph.csv?id=RSHPCS&cosd=2021-01-01&coed=2026-04-01&vintage_date=2024-04-15
B58: 53 | C58: Beauty | D58: organic_sales_growth | E58: 45473 | F58: 45405 | G58: 0 | H58: =AVERAGE('PG facts'!F41,'PG facts'!F48,'PG facts'!F55,'PG facts'!F62) -> 5 | I58: ='PG facts'!F62 -> 3 | J58: =COUNT('Training pairs'!F863:F871) -> 9 | K58: =(SUM('Training pairs'!I863:I871)-SUM('Training pairs'!F863:F871)*SUM('Training pairs'!G863:G871)/COUNT('Training pairs'!F863:F871))/(SUM('Training pairs'!H863:H871)-SUM('Training pairs'!F863:F871)^2/COUNT('Training pairs'!F863:F871)) -> 0.51472364 | L58: =AVERAGE('Training pairs'!G863:G871)-K58*AVERAGE('Training pairs'!F863:F871) -> 1.1029516 | M58: =(SUM('Target months'!H162:H164)/SUM('Target months'!F162:F164)-1)*100 -> 2.2798167 | N58: =L58+K58*M58 -> 2.2764271 | O58: =COUNT('Training pairs'!F872:F879) -> 8 | P58: =(SUM('Training pairs'!I872:I879)-SUM('Training pairs'!F872:F879)*SUM('Training pairs'!G872:G879)/COUNT('Training pairs'!F872:F879))/(SUM('Training pairs'!H872:H879)-SUM('Training pairs'!F872:F879)^2/COUNT('Training pairs'!F872:F879)) -> -0.060345979 | Q58: =AVERAGE('Training pairs'!G872:G879)-P58*AVERAGE('Training pairs'!F872:F879) -> 4.6296154 | R58: 2.2728128 | S58: =Q58+P58*R58 -> 4.4924603 | T58: =(H58+N58)/2 -> 3.6382136 | U58: 45405 | V58: 45401 | W58: https://alfred.stlouisfed.org/graph/alfredgraph.csv?id=RSHPCS&cosd=2021-01-01&coed=2026-04-01&vintage_date=2024-04-23
B59: 54 | C59: Beauty | D59: organic_sales_growth | E59: 45473 | F59: 45427 | G59: 1 | H59: =AVERAGE('PG facts'!F41,'PG facts'!F48,'PG facts'!F55,'PG facts'!F62) -> 5 | I59: ='PG facts'!F62 -> 3 | J59: =COUNT('Training pairs'!F880:F888) -> 9 | K59: =(SUM('Training pairs'!I880:I888)-SUM('Training pairs'!F880:F888)*SUM('Training pairs'!G880:G888)/COUNT('Training pairs'!F880:F888))/(SUM('Training pairs'!H880:H888)-SUM('Training pairs'!F880:F888)^2/COUNT('Training pairs'!F880:F888)) -> 0.51535306 | L59: =AVERAGE('Training pairs'!G880:G888)-K59*AVERAGE('Training pairs'!F880:F888) -> 1.1021914 | M59: =(SUM('Target months'!H165:H167)/SUM('Target months'!F165:F167)-1)*100 -> 0.52508752 | N59: =L59+K59*M59 -> 1.3727969 | O59: =COUNT('Training pairs'!F889:F896) -> 8 | P59: =(SUM('Training pairs'!I889:I896)-SUM('Training pairs'!F889:F896)*SUM('Training pairs'!G889:G896)/COUNT('Training pairs'!F889:F896))/(SUM('Training pairs'!H889:H896)-SUM('Training pairs'!F889:F896)^2/COUNT('Training pairs'!F889:F896)) -> -0.064383487 | Q59: =AVERAGE('Training pairs'!G889:G896)-P59*AVERAGE('Training pairs'!F889:F896) -> 4.6553477 | R59: 2.1803775 | S59: =Q59+P59*R59 -> 4.5149674 | T59: =(H59+N59)/2 -> 3.1863984 | U59: 45427 | V59: 45401 | W59: https://alfred.stlouisfed.org/graph/alfredgraph.csv?id=RSHPCS&cosd=2021-01-01&coed=2026-04-01&vintage_date=2024-05-15
B60: 55 | C60: Beauty | D60: organic_sales_growth | E60: 45473 | F60: 45461 | G60: 2 | H60: =AVERAGE('PG facts'!F41,'PG facts'!F48,'PG facts'!F55,'PG facts'!F62) -> 5 | I60: ='PG facts'!F62 -> 3 | J60: =COUNT('Training pairs'!F897:F905) -> 9 | K60: =(SUM('Training pairs'!I897:I905)-SUM('Training pairs'!F897:F905)*SUM('Training pairs'!G897:G905)/COUNT('Training pairs'!F897:F905))/(SUM('Training pairs'!H897:H905)-SUM('Training pairs'!F897:F905)^2/COUNT('Training pairs'!F897:F905)) -> 0.51664399 | L60: =AVERAGE('Training pairs'!G897:G905)-K60*AVERAGE('Training pairs'!F897:F905) -> 1.0941685 | M60: =(SUM('Target months'!H168:H170)/SUM('Target months'!F168:F170)-1)*100 -> -0.10738672 | N60: =L60+K60*M60 -> 1.0386878 | O60: =COUNT('Training pairs'!F906:F913) -> 8 | P60: =(SUM('Training pairs'!I906:I913)-SUM('Training pairs'!F906:F913)*SUM('Training pairs'!G906:G913)/COUNT('Training pairs'!F906:F913))/(SUM('Training pairs'!H906:H913)-SUM('Training pairs'!F906:F913)^2/COUNT('Training pairs'!F906:F913)) -> -0.063527926 | Q60: =AVERAGE('Training pairs'!G906:G913)-P60*AVERAGE('Training pairs'!F906:F913) -> 4.6502227 | R60: 2.1559106 | S60: =Q60+P60*R60 -> 4.5132621 | T60: =(H60+N60)/2 -> 3.0193439 | U60: 45461 | V60: 45401 | W60: https://alfred.stlouisfed.org/graph/alfredgraph.csv?id=RSHPCS&cosd=2021-01-01&coed=2026-04-01&vintage_date=2024-06-18
B61: 56 | C61: Beauty | D61: organic_sales_growth | E61: 45473 | F61: 45489 | G61: 3 | H61: =AVERAGE('PG facts'!F41,'PG facts'!F48,'PG facts'!F55,'PG facts'!F62) -> 5 | I61: ='PG facts'!F62 -> 3 | J61: =COUNT('Training pairs'!F914:F922) -> 9 | K61: =(SUM('Training pairs'!I914:I922)-SUM('Training pairs'!F914:F922)*SUM('Training pairs'!G914:G922)/COUNT('Training pairs'!F914:F922))/(SUM('Training pairs'!H914:H922)-SUM('Training pairs'!F914:F922)^2/COUNT('Training pairs'!F914:F922)) -> 0.51931253 | L61: =AVERAGE('Training pairs'!G914:G922)-K61*AVERAGE('Training pairs'!F914:F922) -> 1.0765128 | M61: =(SUM('Target months'!H171:H173)/SUM('Target months'!F171:F173)-1)*100 -> 0.089162607 | N61: =L61+K61*M61 -> 1.1228161 | O61: =COUNT('Training pairs'!F923:F930) -> 8 | P61: =(SUM('Training pairs'!I923:I930)-SUM('Training pairs'!F923:F930)*SUM('Training pairs'!G923:G930)/COUNT('Training pairs'!F923:F930))/(SUM('Training pairs'!H923:H930)-SUM('Training pairs'!F923:F930)^2/COUNT('Training pairs'!F923:F930)) -> -0.062598288 | Q61: =AVERAGE('Training pairs'!G923:G930)-P61*AVERAGE('Training pairs'!F923:F930) -> 4.6446471 | R61: 2.1559106 | S61: =Q61+P61*R61 -> 4.5096908 | T61: =(H61+N61)/2 -> 3.061408 | U61: 45489 | V61: 45401 | W61: https://alfred.stlouisfed.org/graph/alfredgraph.csv?id=RSHPCS&cosd=2021-01-01&coed=2026-04-01&vintage_date=2024-07-16
B62: 57 | C62: Beauty | D62: organic_sales_growth | E62: 45473 | F62: 45502 | G62: 3 | H62: =AVERAGE('PG facts'!F41,'PG facts'!F48,'PG facts'!F55,'PG facts'!F62) -> 5 | I62: ='PG facts'!F62 -> 3 | J62: =COUNT('Training pairs'!F931:F939) -> 9 | K62: =(SUM('Training pairs'!I931:I939)-SUM('Training pairs'!F931:F939)*SUM('Training pairs'!G931:G939)/COUNT('Training pairs'!F931:F939))/(SUM('Training pairs'!H931:H939)-SUM('Training pairs'!F931:F939)^2/COUNT('Training pairs'!F931:F939)) -> 0.51931253 | L62: =AVERAGE('Training pairs'!G931:G939)-K62*AVERAGE('Training pairs'!F931:F939) -> 1.0765128 | M62: =(SUM('Target months'!H174:H176)/SUM('Target months'!F174:F176)-1)*100 -> 0.089162607 | N62: =L62+K62*M62 -> 1.1228161 | O62: =COUNT('Training pairs'!F940:F947) -> 8 | P62: =(SUM('Training pairs'!I940:I947)-SUM('Training pairs'!F940:F947)*SUM('Training pairs'!G940:G947)/COUNT('Training pairs'!F940:F947))/(SUM('Training pairs'!H940:H947)-SUM('Training pairs'!F940:F947)^2/COUNT('Training pairs'!F940:F947)) -> -0.062598288 | Q62: =AVERAGE('Training pairs'!G940:G947)-P62*AVERAGE('Training pairs'!F940:F947) -> 4.6446471 | R62: 2.1559106 | S62: =Q62+P62*R62 -> 4.5096908 | T62: =(H62+N62)/2 -> 3.061408 | U62: 45489 | V62: 45401 | W62: https://alfred.stlouisfed.org/graph/alfredgraph.csv?id=RSHPCS&cosd=2021-01-01&coed=2026-04-01&vintage_date=2024-07-16
B63: 58 | C63: Health Care | D63: organic_sales_growth | E63: 45473 | F63: 45383 | G63: 0 | H63: =AVERAGE('PG facts'!F36,'PG facts'!F43,'PG facts'!F50,'PG facts'!F57) -> 6.5 | I63: ='PG facts'!F57 -> 2 | J63: =COUNT('Training pairs'!F948:F955) -> 8 | K63: =(SUM('Training pairs'!I948:I955)-SUM('Training pairs'!F948:F955)*SUM('Training pairs'!G948:G955)/COUNT('Training pairs'!F948:F955))/(SUM('Training pairs'!H948:H955)-SUM('Training pairs'!F948:F955)^2/COUNT('Training pairs'!F948:F955)) -> -0.54451855 | L63: =AVERAGE('Training pairs'!G948:G955)-K63*AVERAGE('Training pairs'!F948:F955) -> 11.617685 | M63: =(SUM('Target months'!H177:H179)/SUM('Target months'!F177:F179)-1)*100 -> 5.4048367 | N63: =L63+K63*M63 -> 8.674651 | O63: ="n.a." -> n.a. | P63: ="n.a." -> n.a. | Q63: ="n.a." -> n.a. | R63: n.a. | S63: ="n.a." -> n.a. | T63: =(H63+N63)/2 -> 7.5873255 | U63: 45383 | V63: 45314 | W63: https://alfred.stlouisfed.org/graph/alfredgraph.csv?id=RSHPCS&cosd=2021-01-01&coed=2026-04-01&vintage_date=2024-04-01
B64: 59 | C64: Health Care | D64: organic_sales_growth | E64: 45473 | F64: 45397 | G64: 0 | H64: =AVERAGE('PG facts'!F36,'PG facts'!F43,'PG facts'!F50,'PG facts'!F57) -> 6.5 | I64: ='PG facts'!F57 -> 2 | J64: =COUNT('Training pairs'!F963:F970) -> 8 | K64: =(SUM('Training pairs'!I963:I970)-SUM('Training pairs'!F963:F970)*SUM('Training pairs'!G963:G970)/COUNT('Training pairs'!F963:F970))/(SUM('Training pairs'!H963:H970)-SUM('Training pairs'!F963:F970)^2/COUNT('Training pairs'!F963:F970)) -> -0.53594044 | L64: =AVERAGE('Training pairs'!G963:G970)-K64*AVERAGE('Training pairs'!F963:F970) -> 11.580983 | M64: =(SUM('Target months'!H180:H182)/SUM('Target months'!F180:F182)-1)*100 -> 2.7031812 | N64: =L64+K64*M64 -> 10.132239 | O64: ="n.a." -> n.a. | P64: ="n.a." -> n.a. | Q64: ="n.a." -> n.a. | R64: 2.6947412 | S64: ="n.a." -> n.a. | T64: =(H64+N64)/2 -> 8.3161195 | U64: 45397 | V64: 45314 | W64: https://alfred.stlouisfed.org/graph/alfredgraph.csv?id=RSHPCS&cosd=2021-01-01&coed=2026-04-01&vintage_date=2024-04-15
B65: 60 | C65: Health Care | D65: organic_sales_growth | E65: 45473 | F65: 45401 | G65: 0 | H65: =AVERAGE('PG facts'!F43,'PG facts'!F50,'PG facts'!F57,'PG facts'!F64) -> 4.75 | I65: ='PG facts'!F64 -> 2 | J65: =COUNT('Training pairs'!F978:F986) -> 9 | K65: =(SUM('Training pairs'!I978:I986)-SUM('Training pairs'!F978:F986)*SUM('Training pairs'!G978:G986)/COUNT('Training pairs'!F978:F986))/(SUM('Training pairs'!H978:H986)-SUM('Training pairs'!F978:F986)^2/COUNT('Training pairs'!F978:F986)) -> -0.22206633 | L65: =AVERAGE('Training pairs'!G978:G986)-K65*AVERAGE('Training pairs'!F978:F986) -> 8.9139528 | M65: =(SUM('Target months'!H183:H185)/SUM('Target months'!F183:F185)-1)*100 -> 2.7031812 | N65: =L65+K65*M65 -> 8.3136673 | O65: =COUNT('Training pairs'!F987:F994) -> 8 | P65: =(SUM('Training pairs'!I987:I994)-SUM('Training pairs'!F987:F994)*SUM('Training pairs'!G987:G994)/COUNT('Training pairs'!F987:F994))/(SUM('Training pairs'!H987:H994)-SUM('Training pairs'!F987:F994)^2/COUNT('Training pairs'!F987:F994)) -> -0.66415308 | Q65: =AVERAGE('Training pairs'!G987:G994)-P65*AVERAGE('Training pairs'!F987:F994) -> 10.597948 | R65: 2.6947412 | S65: =Q65+P65*R65 -> 8.8082273 | T65: =(H65+N65)/2 -> 6.5318337 | U65: 45397 | V65: 45401 | W65: https://alfred.stlouisfed.org/graph/alfredgraph.csv?id=RSHPCS&cosd=2021-01-01&coed=2026-04-01&vintage_date=2024-04-15
B66: 61 | C66: Health Care | D66: organic_sales_growth | E66: 45473 | F66: 45405 | G66: 0 | H66: =AVERAGE('PG facts'!F43,'PG facts'!F50,'PG facts'!F57,'PG facts'!F64) -> 4.75 | I66: ='PG facts'!F64 -> 2 | J66: =COUNT('Training pairs'!F995:F1003) -> 9 | K66: =(SUM('Training pairs'!I995:I1003)-SUM('Training pairs'!F995:F1003)*SUM('Training pairs'!G995:G1003)/COUNT('Training pairs'!F995:F1003))/(SUM('Training pairs'!H995:H1003)-SUM('Training pairs'!F995:F1003)^2/COUNT('Training pairs'!F995:F1003)) -> -0.008182441 | L66: =AVERAGE('Training pairs'!G995:G1003)-K66*AVERAGE('Training pairs'!F995:F1003) -> 7.7144867 | M66: =(SUM('Target months'!H186:H188)/SUM('Target months'!F186:F188)-1)*100 -> 2.2798167 | N66: =L66+K66*M66 -> 7.6958322 | O66: =COUNT('Training pairs'!F1004:F1011) -> 8 | P66: =(SUM('Training pairs'!I1004:I1011)-SUM('Training pairs'!F1004:F1011)*SUM('Training pairs'!G1004:G1011)/COUNT('Training pairs'!F1004:F1011))/(SUM('Training pairs'!H1004:H1011)-SUM('Training pairs'!F1004:F1011)^2/COUNT('Training pairs'!F1004:F1011)) -> -0.68643393 | Q66: =AVERAGE('Training pairs'!G1004:G1011)-P66*AVERAGE('Training pairs'!F1004:F1011) -> 10.943115 | R66: 2.2728128 | S66: =Q66+P66*R66 -> 9.382979 | T66: =(H66+N66)/2 -> 6.2229161 | U66: 45405 | V66: 45401 | W66: https://alfred.stlouisfed.org/graph/alfredgraph.csv?id=RSHPCS&cosd=2021-01-01&coed=2026-04-01&vintage_date=2024-04-23
B67: 62 | C67: Health Care | D67: organic_sales_growth | E67: 45473 | F67: 45427 | G67: 1 | H67: =AVERAGE('PG facts'!F43,'PG facts'!F50,'PG facts'!F57,'PG facts'!F64) -> 4.75 | I67: ='PG facts'!F64 -> 2 | J67: =COUNT('Training pairs'!F1012:F1020) -> 9 | K67: =(SUM('Training pairs'!I1012:I1020)-SUM('Training pairs'!F1012:F1020)*SUM('Training pairs'!G1012:G1020)/COUNT('Training pairs'!F1012:F1020))/(SUM('Training pairs'!H1012:H1020)-SUM('Training pairs'!F1012:F1020)^2/COUNT('Training pairs'!F1012:F1020)) -> -0.0029984041 | L67: =AVERAGE('Training pairs'!G1012:G1020)-K67*AVERAGE('Training pairs'!F1012:F1020) -> 7.684173 | M67: =(SUM('Target months'!H189:H191)/SUM('Target months'!F189:F191)-1)*100 -> 0.52508752 | N67: =L67+K67*M67 -> 7.6825986 | O67: =COUNT('Training pairs'!F1021:F1028) -> 8 | P67: =(SUM('Training pairs'!I1021:I1028)-SUM('Training pairs'!F1021:F1028)*SUM('Training pairs'!G1021:G1028)/COUNT('Training pairs'!F1021:F1028))/(SUM('Training pairs'!H1021:H1028)-SUM('Training pairs'!F1021:F1028)^2/COUNT('Training pairs'!F1021:F1028)) -> -0.67425819 | Q67: =AVERAGE('Training pairs'!G1021:G1028)-P67*AVERAGE('Training pairs'!F1021:F1028) -> 10.870017 | R67: 2.1803775 | S67: =Q67+P67*R67 -> 9.3998793 | T67: =(H67+N67)/2 -> 6.2162993 | U67: 45427 | V67: 45401 | W67: https://alfred.stlouisfed.org/graph/alfredgraph.csv?id=RSHPCS&cosd=2021-01-01&coed=2026-04-01&vintage_date=2024-05-15
B68: 63 | C68: Health Care | D68: organic_sales_growth | E68: 45473 | F68: 45461 | G68: 2 | H68: =AVERAGE('PG facts'!F43,'PG facts'!F50,'PG facts'!F57,'PG facts'!F64) -> 4.75 | I68: ='PG facts'!F64 -> 2 | J68: =COUNT('Training pairs'!F1029:F1037) -> 9 | K68: =(SUM('Training pairs'!I1029:I1037)-SUM('Training pairs'!F1029:F1037)*SUM('Training pairs'!G1029:G1037)/COUNT('Training pairs'!F1029:F1037))/(SUM('Training pairs'!H1029:H1037)-SUM('Training pairs'!F1029:F1037)^2/COUNT('Training pairs'!F1029:F1037)) -> -0.0020556852 | L68: =AVERAGE('Training pairs'!G1029:G1037)-K68*AVERAGE('Training pairs'!F1029:F1037) -> 7.6786708 | M68: =(SUM('Target months'!H192:H194)/SUM('Target months'!F192:F194)-1)*100 -> -0.10738672 | N68: =L68+K68*M68 -> 7.6788916 | O68: =COUNT('Training pairs'!F1038:F1045) -> 8 | P68: =(SUM('Training pairs'!I1038:I1045)-SUM('Training pairs'!F1038:F1045)*SUM('Training pairs'!G1038:G1045)/COUNT('Training pairs'!F1038:F1045))/(SUM('Training pairs'!H1038:H1045)-SUM('Training pairs'!F1038:F1045)^2/COUNT('Training pairs'!F1038:F1045)) -> -0.66900532 | Q68: =AVERAGE('Training pairs'!G1038:G1045)-P68*AVERAGE('Training pairs'!F1038:F1045) -> 10.839699 | R68: 2.1559106 | S68: =Q68+P68*R68 -> 9.3973835 | T68: =(H68+N68)/2 -> 6.2144458 | U68: 45461 | V68: 45401 | W68: https://alfred.stlouisfed.org/graph/alfredgraph.csv?id=RSHPCS&cosd=2021-01-01&coed=2026-04-01&vintage_date=2024-06-18
B69: 64 | C69: Health Care | D69: organic_sales_growth | E69: 45473 | F69: 45489 | G69: 3 | H69: =AVERAGE('PG facts'!F43,'PG facts'!F50,'PG facts'!F57,'PG facts'!F64) -> 4.75 | I69: ='PG facts'!F64 -> 2 | J69: =COUNT('Training pairs'!F1046:F1054) -> 9 | K69: =(SUM('Training pairs'!I1046:I1054)-SUM('Training pairs'!F1046:F1054)*SUM('Training pairs'!G1046:G1054)/COUNT('Training pairs'!F1046:F1054))/(SUM('Training pairs'!H1046:H1054)-SUM('Training pairs'!F1046:F1054)^2/COUNT('Training pairs'!F1046:F1054)) -> -0.0037823382 | L69: =AVERAGE('Training pairs'!G1046:G1054)-K69*AVERAGE('Training pairs'!F1046:F1054) -> 7.6887687 | M69: =(SUM('Target months'!H195:H197)/SUM('Target months'!F195:F197)-1)*100 -> 0.089162607 | N69: =L69+K69*M69 -> 7.6884315 | O69: =COUNT('Training pairs'!F1055:F1062) -> 8 | P69: =(SUM('Training pairs'!I1055:I1062)-SUM('Training pairs'!F1055:F1062)*SUM('Training pairs'!G1055:G1062)/COUNT('Training pairs'!F1055:F1062))/(SUM('Training pairs'!H1055:H1062)-SUM('Training pairs'!F1055:F1062)^2/COUNT('Training pairs'!F1055:F1062)) -> -0.66328252 | Q69: =AVERAGE('Training pairs'!G1055:G1062)-P69*AVERAGE('Training pairs'!F1055:F1062) -> 10.806624 | R69: 2.1559106 | S69: =Q69+P69*R69 -> 9.3766463 | T69: =(H69+N69)/2 -> 6.2192157 | U69: 45489 | V69: 45401 | W69: https://alfred.stlouisfed.org/graph/alfredgraph.csv?id=RSHPCS&cosd=2021-01-01&coed=2026-04-01&vintage_date=2024-07-16
B70: 65 | C70: Health Care | D70: organic_sales_growth | E70: 45473 | F70: 45502 | G70: 3 | H70: =AVERAGE('PG facts'!F43,'PG facts'!F50,'PG facts'!F57,'PG facts'!F64) -> 4.75 | I70: ='PG facts'!F64 -> 2 | J70: =COUNT('Training pairs'!F1063:F1071) -> 9 | K70: =(SUM('Training pairs'!I1063:I1071)-SUM('Training pairs'!F1063:F1071)*SUM('Training pairs'!G1063:G1071)/COUNT('Training pairs'!F1063:F1071))/(SUM('Training pairs'!H1063:H1071)-SUM('Training pairs'!F1063:F1071)^2/COUNT('Training pairs'!F1063:F1071)) -> -0.0037823382 | L70: =AVERAGE('Training pairs'!G1063:G1071)-K70*AVERAGE('Training pairs'!F1063:F1071) -> 7.6887687 | M70: =(SUM('Target months'!H198:H200)/SUM('Target months'!F198:F200)-1)*100 -> 0.089162607 | N70: =L70+K70*M70 -> 7.6884315 | O70: =COUNT('Training pairs'!F1072:F1079) -> 8 | P70: =(SUM('Training pairs'!I1072:I1079)-SUM('Training pairs'!F1072:F1079)*SUM('Training pairs'!G1072:G1079)/COUNT('Training pairs'!F1072:F1079))/(SUM('Training pairs'!H1072:H1079)-SUM('Training pairs'!F1072:F1079)^2/COUNT('Training pairs'!F1072:F1079)) -> -0.66328252 | Q70: =AVERAGE('Training pairs'!G1072:G1079)-P70*AVERAGE('Training pairs'!F1072:F1079) -> 10.806624 | R70: 2.1559106 | S70: =Q70+P70*R70 -> 9.3766463 | T70: =(H70+N70)/2 -> 6.2192157 | U70: 45489 | V70: 45401 | W70: https://alfred.stlouisfed.org/graph/alfredgraph.csv?id=RSHPCS&cosd=2021-01-01&coed=2026-04-01&vintage_date=2024-07-16
B71: 66 | C71: Beauty | D71: organic_volume_growth | E71: 45565 | F71: 45474 | G71: 0 | H71: =AVERAGE('PG facts'!D41,'PG facts'!D48,'PG facts'!D55,'PG facts'!D62) -> -0.25 | I71: ='PG facts'!D62 -> 1 | J71: =COUNT('Training pairs'!F1080:F1088) -> 9 | K71: =(SUM('Training pairs'!I1080:I1088)-SUM('Training pairs'!F1080:F1088)*SUM('Training pairs'!G1080:G1088)/COUNT('Training pairs'!F1080:F1088))/(SUM('Training pairs'!H1080:H1088)-SUM('Training pairs'!F1080:F1088)^2/COUNT('Training pairs'!F1080:F1088)) -> 0.40471248 | L71: =AVERAGE('Training pairs'!G1080:G1088)-K71*AVERAGE('Training pairs'!F1080:F1088) -> -1.3387612 | M71: =(SUM('Target months'!H201:H203)/SUM('Target months'!F201:F203)-1)*100 -> 1.8076142 | N71: =L71+K71*M71 -> -0.6071972 | O71: =COUNT('Training pairs'!F1089:F1096) -> 8 | P71: =(SUM('Training pairs'!I1089:I1096)-SUM('Training pairs'!F1089:F1096)*SUM('Training pairs'!G1089:G1096)/COUNT('Training pairs'!F1089:F1096))/(SUM('Training pairs'!H1089:H1096)-SUM('Training pairs'!F1089:F1096)^2/COUNT('Training pairs'!F1089:F1096)) -> 0.045498424 | Q71: =AVERAGE('Training pairs'!G1089:G1096)-P71*AVERAGE('Training pairs'!F1089:F1096) -> -1.0335646 | R71: n.a. | S71: ="n.a." -> n.a. | T71: =(H71+N71)/2 -> -0.4285986 | U71: 45474 | V71: 45401 | W71: https://alfred.stlouisfed.org/graph/alfredgraph.csv?id=PCENDC96&cosd=2021-01-01&coed=2026-04-01&vintage_date=2024-07-01
B72: 67 | C72: Beauty | D72: organic_volume_growth | E72: 45565 | F72: 45499 | G72: 0 | H72: =AVERAGE('PG facts'!D41,'PG facts'!D48,'PG facts'!D55,'PG facts'!D62) -> -0.25 | I72: ='PG facts'!D62 -> 1 | J72: =COUNT('Training pairs'!F1097:F1105) -> 9 | K72: =(SUM('Training pairs'!I1097:I1105)-SUM('Training pairs'!F1097:F1105)*SUM('Training pairs'!G1097:G1105)/COUNT('Training pairs'!F1097:F1105))/(SUM('Training pairs'!H1097:H1105)-SUM('Training pairs'!F1097:F1105)^2/COUNT('Training pairs'!F1097:F1105)) -> 0.40471248 | L72: =AVERAGE('Training pairs'!G1097:G1105)-K72*AVERAGE('Training pairs'!F1097:F1105) -> -1.3387612 | M72: =(SUM('Target months'!H204:H206)/SUM('Target months'!F204:F206)-1)*100 -> 1.7457095 | N72: =L72+K72*M72 -> -0.63225081 | O72: =COUNT('Training pairs'!F1106:F1113) -> 8 | P72: =(SUM('Training pairs'!I1106:I1113)-SUM('Training pairs'!F1106:F1113)*SUM('Training pairs'!G1106:G1113)/COUNT('Training pairs'!F1106:F1113))/(SUM('Training pairs'!H1106:H1113)-SUM('Training pairs'!F1106:F1113)^2/COUNT('Training pairs'!F1106:F1113)) -> 0.045498424 | Q72: =AVERAGE('Training pairs'!G1106:G1113)-P72*AVERAGE('Training pairs'!F1106:F1113) -> -1.0335646 | R72: 1.7459001 | S72: =Q72+P72*R72 -> -0.95412886 | T72: =(H72+N72)/2 -> -0.44112541 | U72: 45499 | V72: 45401 | W72: https://alfred.stlouisfed.org/graph/alfredgraph.csv?id=PCENDC96&cosd=2021-01-01&coed=2026-04-01&vintage_date=2024-07-26
B73: 68 | C73: Beauty | D73: organic_volume_growth | E73: 45565 | F73: 45503 | G73: 0 | H73: =AVERAGE('PG facts'!D48,'PG facts'!D55,'PG facts'!D62,'PG facts'!D69) -> 0.25 | I73: ='PG facts'!D69 -> 1 | J73: =COUNT('Training pairs'!F1114:F1123) -> 10 | K73: =(SUM('Training pairs'!I1114:I1123)-SUM('Training pairs'!F1114:F1123)*SUM('Training pairs'!G1114:G1123)/COUNT('Training pairs'!F1114:F1123))/(SUM('Training pairs'!H1114:H1123)-SUM('Training pairs'!F1114:F1123)^2/COUNT('Training pairs'!F1114:F1123)) -> 0.47656766 | L73: =AVERAGE('Training pairs'!G1114:G1123)-K73*AVERAGE('Training pairs'!F1114:F1123) -> -1.2422203 | M73: =(SUM('Target months'!H207:H209)/SUM('Target months'!F207:F209)-1)*100 -> 1.7457095 | N73: =L73+K73*M73 -> -0.41027157 | O73: =COUNT('Training pairs'!F1124:F1132) -> 9 | P73: =(SUM('Training pairs'!I1124:I1132)-SUM('Training pairs'!F1124:F1132)*SUM('Training pairs'!G1124:G1132)/COUNT('Training pairs'!F1124:F1132))/(SUM('Training pairs'!H1124:H1132)-SUM('Training pairs'!F1124:F1132)^2/COUNT('Training pairs'!F1124:F1132)) -> 0.13279127 | Q73: =AVERAGE('Training pairs'!G1124:G1132)-P73*AVERAGE('Training pairs'!F1124:F1132) -> -0.88892961 | R73: 1.7459001 | S73: =Q73+P73*R73 -> -0.65708932 | T73: =(H73+N73)/2 -> -0.080135786 | U73: 45499 | V73: 45503 | W73: https://alfred.stlouisfed.org/graph/alfredgraph.csv?id=PCENDC96&cosd=2021-01-01&coed=2026-04-01&vintage_date=2024-07-26
B74: 69 | C74: Beauty | D74: organic_volume_growth | E74: 45565 | F74: 45534 | G74: 1 | H74: =AVERAGE('PG facts'!D48,'PG facts'!D55,'PG facts'!D62,'PG facts'!D69) -> 0.25 | I74: ='PG facts'!D69 -> 1 | J74: =COUNT('Training pairs'!F1133:F1142) -> 10 | K74: =(SUM('Training pairs'!I1133:I1142)-SUM('Training pairs'!F1133:F1142)*SUM('Training pairs'!G1133:G1142)/COUNT('Training pairs'!F1133:F1142))/(SUM('Training pairs'!H1133:H1142)-SUM('Training pairs'!F1133:F1142)^2/COUNT('Training pairs'!F1133:F1142)) -> 0.48431195 | L74: =AVERAGE('Training pairs'!G1133:G1142)-K74*AVERAGE('Training pairs'!F1133:F1142) -> -1.2568117 | M74: =(SUM('Target months'!H210:H212)/SUM('Target months'!F210:F212)-1)*100 -> 1.8769844 | N74: =L74+K74*M74 -> -0.34776572 | O74: =COUNT('Training pairs'!F1143:F1151) -> 9 | P74: =(SUM('Training pairs'!I1143:I1151)-SUM('Training pairs'!F1143:F1151)*SUM('Training pairs'!G1143:G1151)/COUNT('Training pairs'!F1143:F1151))/(SUM('Training pairs'!H1143:H1151)-SUM('Training pairs'!F1143:F1151)^2/COUNT('Training pairs'!F1143:F1151)) -> 0.13279127 | Q74: =AVERAGE('Training pairs'!G1143:G1151)-P74*AVERAGE('Training pairs'!F1143:F1151) -> -0.88892961 | R74: 1.8988038 | S74: =Q74+P74*R74 -> -0.63678505 | T74: =(H74+N74)/2 -> -0.048882858 | U74: 45534 | V74: 45503 | W74: https://alfred.stlouisfed.org/graph/alfredgraph.csv?id=PCENDC96&cosd=2021-01-01&coed=2026-04-01&vintage_date=2024-08-30
B75: 70 | C75: Beauty | D75: organic_volume_growth | E75: 45565 | F75: 45562 | G75: 2 | H75: =AVERAGE('PG facts'!D48,'PG facts'!D55,'PG facts'!D62,'PG facts'!D69) -> 0.25 | I75: ='PG facts'!D69 -> 1 | J75: =COUNT('Training pairs'!F1152:F1161) -> 10 | K75: =(SUM('Training pairs'!I1152:I1161)-SUM('Training pairs'!F1152:F1161)*SUM('Training pairs'!G1152:G1161)/COUNT('Training pairs'!F1152:F1161))/(SUM('Training pairs'!H1152:H1161)-SUM('Training pairs'!F1152:F1161)^2/COUNT('Training pairs'!F1152:F1161)) -> 0.49776242 | L75: =AVERAGE('Training pairs'!G1152:G1161)-K75*AVERAGE('Training pairs'!F1152:F1161) -> -1.1478675 | M75: =(SUM('Target months'!H213:H215)/SUM('Target months'!F213:F215)-1)*100 -> 2.2025959 | N75: =L75+K75*M75 -> -0.051498095 | O75: =COUNT('Training pairs'!F1162:F1170) -> 9 | P75: =(SUM('Training pairs'!I1162:I1170)-SUM('Training pairs'!F1162:F1170)*SUM('Training pairs'!G1162:G1170)/COUNT('Training pairs'!F1162:F1170))/(SUM('Training pairs'!H1162:H1170)-SUM('Training pairs'!F1162:F1170)^2/COUNT('Training pairs'!F1162:F1170)) -> 0.18790798 | Q75: =AVERAGE('Training pairs'!G1162:G1170)-P75*AVERAGE('Training pairs'!F1162:F1170) -> -0.88456451 | R75: 1.8739916 | S75: =Q75+P75*R75 -> -0.53242653 | T75: =(H75+N75)/2 -> 0.099250953 | U75: 45562 | V75: 45503 | W75: https://alfred.stlouisfed.org/graph/alfredgraph.csv?id=PCENDC96&cosd=2021-01-01&coed=2026-04-01&vintage_date=2024-09-27
B76: 71 | C76: Beauty | D76: organic_volume_growth | E76: 45565 | F76: 45582 | G76: 2 | H76: =AVERAGE('PG facts'!D48,'PG facts'!D55,'PG facts'!D62,'PG facts'!D69) -> 0.25 | I76: ='PG facts'!D69 -> 1 | J76: =COUNT('Training pairs'!F1171:F1180) -> 10 | K76: =(SUM('Training pairs'!I1171:I1180)-SUM('Training pairs'!F1171:F1180)*SUM('Training pairs'!G1171:G1180)/COUNT('Training pairs'!F1171:F1180))/(SUM('Training pairs'!H1171:H1180)-SUM('Training pairs'!F1171:F1180)^2/COUNT('Training pairs'!F1171:F1180)) -> 0.49776242 | L76: =AVERAGE('Training pairs'!G1171:G1180)-K76*AVERAGE('Training pairs'!F1171:F1180) -> -1.1478675 | M76: =(SUM('Target months'!H216:H218)/SUM('Target months'!F216:F218)-1)*100 -> 2.2025959 | N76: =L76+K76*M76 -> -0.051498095 | O76: =COUNT('Training pairs'!F1181:F1189) -> 9 | P76: =(SUM('Training pairs'!I1181:I1189)-SUM('Training pairs'!F1181:F1189)*SUM('Training pairs'!G1181:G1189)/COUNT('Training pairs'!F1181:F1189))/(SUM('Training pairs'!H1181:H1189)-SUM('Training pairs'!F1181:F1189)^2/COUNT('Training pairs'!F1181:F1189)) -> 0.18790798 | Q76: =AVERAGE('Training pairs'!G1181:G1189)-P76*AVERAGE('Training pairs'!F1181:F1189) -> -0.88456451 | R76: 1.8739916 | S76: =Q76+P76*R76 -> -0.53242653 | T76: =(H76+N76)/2 -> 0.099250953 | U76: 45566 | V76: 45503 | W76: https://alfred.stlouisfed.org/graph/alfredgraph.csv?id=PCENDC96&cosd=2021-01-01&coed=2026-04-01&vintage_date=2024-10-01
B77: 72 | C77: Grooming | D77: organic_volume_growth | E77: 45565 | F77: 45474 | G77: 0 | H77: =AVERAGE('PG facts'!D42,'PG facts'!D49,'PG facts'!D56,'PG facts'!D63) -> 0 | I77: ='PG facts'!D63 -> 2 | J77: =COUNT('Training pairs'!F1190:F1198) -> 9 | K77: =(SUM('Training pairs'!I1190:I1198)-SUM('Training pairs'!F1190:F1198)*SUM('Training pairs'!G1190:G1198)/COUNT('Training pairs'!F1190:F1198))/(SUM('Training pairs'!H1190:H1198)-SUM('Training pairs'!F1190:F1198)^2/COUNT('Training pairs'!F1190:F1198)) -> 1.1592507 | L77: =AVERAGE('Training pairs'!G1190:G1198)-K77*AVERAGE('Training pairs'!F1190:F1198) -> -1.9703412 | M77: =(SUM('Target months'!H219:H221)/SUM('Target months'!F219:F221)-1)*100 -> 1.8076142 | N77: =L77+K77*M77 -> 0.12513682 | O77: =COUNT('Training pairs'!F1199:F1206) -> 8 | P77: =(SUM('Training pairs'!I1199:I1206)-SUM('Training pairs'!F1199:F1206)*SUM('Training pairs'!G1199:G1206)/COUNT('Training pairs'!F1199:F1206))/(SUM('Training pairs'!H1199:H1206)-SUM('Training pairs'!F1199:F1206)^2/COUNT('Training pairs'!F1199:F1206)) -> 0.60069365 | Q77: =AVERAGE('Training pairs'!G1199:G1206)-P77*AVERAGE('Training pairs'!F1199:F1206) -> -1.6931367 | R77: n.a. | S77: ="n.a." -> n.a. | T77: =(H77+N77)/2 -> 0.062568409 | U77: 45474 | V77: 45401 | W77: https://alfred.stlouisfed.org/graph/alfredgraph.csv?id=PCENDC96&cosd=2021-01-01&coed=2026-04-01&vintage_date=2024-07-01
B78: 73 | C78: Grooming | D78: organic_volume_growth | E78: 45565 | F78: 45499 | G78: 0 | H78: =AVERAGE('PG facts'!D42,'PG facts'!D49,'PG facts'!D56,'PG facts'!D63) -> 0 | I78: ='PG facts'!D63 -> 2 | J78: =COUNT('Training pairs'!F1207:F1215) -> 9 | K78: =(SUM('Training pairs'!I1207:I1215)-SUM('Training pairs'!F1207:F1215)*SUM('Training pairs'!G1207:G1215)/COUNT('Training pairs'!F1207:F1215))/(SUM('Training pairs'!H1207:H1215)-SUM('Training pairs'!F1207:F1215)^2/COUNT('Training pairs'!F1207:F1215)) -> 1.1592507 | L78: =AVERAGE('Training pairs'!G1207:G1215)-K78*AVERAGE('Training pairs'!F1207:F1215) -> -1.9703412 | M78: =(SUM('Target months'!H222:H224)/SUM('Target months'!F222:F224)-1)*100 -> 1.7457095 | N78: =L78+K78*M78 -> 0.053373724 | O78: =COUNT('Training pairs'!F1216:F1223) -> 8 | P78: =(SUM('Training pairs'!I1216:I1223)-SUM('Training pairs'!F1216:F1223)*SUM('Training pairs'!G1216:G1223)/COUNT('Training pairs'!F1216:F1223))/(SUM('Training pairs'!H1216:H1223)-SUM('Training pairs'!F1216:F1223)^2/COUNT('Training pairs'!F1216:F1223)) -> 0.60069365 | Q78: =AVERAGE('Training pairs'!G1216:G1223)-P78*AVERAGE('Training pairs'!F1216:F1223) -> -1.6931367 | R78: 1.7459001 | S78: =Q78+P78*R78 -> -0.64438563 | T78: =(H78+N78)/2 -> 0.026686862 | U78: 45499 | V78: 45401 | W78: https://alfred.stlouisfed.org/graph/alfredgraph.csv?id=PCENDC96&cosd=2021-01-01&coed=2026-04-01&vintage_date=2024-07-26
B79: 74 | C79: Grooming | D79: organic_volume_growth | E79: 45565 | F79: 45503 | G79: 0 | H79: =AVERAGE('PG facts'!D49,'PG facts'!D56,'PG facts'!D63,'PG facts'!D70) -> 0.75 | I79: ='PG facts'!D70 -> 2 | J79: =COUNT('Training pairs'!F1224:F1233) -> 10 | K79: =(SUM('Training pairs'!I1224:I1233)-SUM('Training pairs'!F1224:F1233)*SUM('Training pairs'!G1224:G1233)/COUNT('Training pairs'!F1224:F1233))/(SUM('Training pairs'!H1224:H1233)-SUM('Training pairs'!F1224:F1233)^2/COUNT('Training pairs'!F1224:F1233)) -> 1.2449397 | L79: =AVERAGE('Training pairs'!G1224:G1233)-K79*AVERAGE('Training pairs'!F1224:F1233) -> -1.8552138 | M79: =(SUM('Target months'!H225:H227)/SUM('Target months'!F225:F227)-1)*100 -> 1.7457095 | N79: =L79+K79*M79 -> 0.31808917 | O79: =COUNT('Training pairs'!F1234:F1242) -> 9 | P79: =(SUM('Training pairs'!I1234:I1242)-SUM('Training pairs'!F1234:F1242)*SUM('Training pairs'!G1234:G1242)/COUNT('Training pairs'!F1234:F1242))/(SUM('Training pairs'!H1234:H1242)-SUM('Training pairs'!F1234:F1242)^2/COUNT('Training pairs'!F1234:F1242)) -> 0.72156373 | Q79: =AVERAGE('Training pairs'!G1234:G1242)-P79*AVERAGE('Training pairs'!F1234:F1242) -> -1.4928678 | R79: 1.7459001 | S79: =Q79+P79*R79 -> -0.23308965 | T79: =(H79+N79)/2 -> 0.53404458 | U79: 45499 | V79: 45503 | W79: https://alfred.stlouisfed.org/graph/alfredgraph.csv?id=PCENDC96&cosd=2021-01-01&coed=2026-04-01&vintage_date=2024-07-26
B80: 75 | C80: Grooming | D80: organic_volume_growth | E80: 45565 | F80: 45534 | G80: 1 | H80: =AVERAGE('PG facts'!D49,'PG facts'!D56,'PG facts'!D63,'PG facts'!D70) -> 0.75 | I80: ='PG facts'!D70 -> 2 | J80: =COUNT('Training pairs'!F1243:F1252) -> 10 | K80: =(SUM('Training pairs'!I1243:I1252)-SUM('Training pairs'!F1243:F1252)*SUM('Training pairs'!G1243:G1252)/COUNT('Training pairs'!F1243:F1252))/(SUM('Training pairs'!H1243:H1252)-SUM('Training pairs'!F1243:F1252)^2/COUNT('Training pairs'!F1243:F1252)) -> 1.2489305 | L80: =AVERAGE('Training pairs'!G1243:G1252)-K80*AVERAGE('Training pairs'!F1243:F1252) -> -1.8780136 | M80: =(SUM('Target months'!H228:H230)/SUM('Target months'!F228:F230)-1)*100 -> 1.8769844 | N80: =L80+K80*M80 -> 0.46620952 | O80: =COUNT('Training pairs'!F1253:F1261) -> 9 | P80: =(SUM('Training pairs'!I1253:I1261)-SUM('Training pairs'!F1253:F1261)*SUM('Training pairs'!G1253:G1261)/COUNT('Training pairs'!F1253:F1261))/(SUM('Training pairs'!H1253:H1261)-SUM('Training pairs'!F1253:F1261)^2/COUNT('Training pairs'!F1253:F1261)) -> 0.72156373 | Q80: =AVERAGE('Training pairs'!G1253:G1261)-P80*AVERAGE('Training pairs'!F1253:F1261) -> -1.4928678 | R80: 1.8988038 | S80: =Q80+P80*R80 -> -0.1227599 | T80: =(H80+N80)/2 -> 0.60810476 | U80: 45534 | V80: 45503 | W80: https://alfred.stlouisfed.org/graph/alfredgraph.csv?id=PCENDC96&cosd=2021-01-01&coed=2026-04-01&vintage_date=2024-08-30
B81: 76 | C81: Grooming | D81: organic_volume_growth | E81: 45565 | F81: 45562 | G81: 2 | H81: =AVERAGE('PG facts'!D49,'PG facts'!D56,'PG facts'!D63,'PG facts'!D70) -> 0.75 | I81: ='PG facts'!D70 -> 2 | J81: =COUNT('Training pairs'!F1262:F1271) -> 10 | K81: =(SUM('Training pairs'!I1262:I1271)-SUM('Training pairs'!F1262:F1271)*SUM('Training pairs'!G1262:G1271)/COUNT('Training pairs'!F1262:F1271))/(SUM('Training pairs'!H1262:H1271)-SUM('Training pairs'!F1262:F1271)^2/COUNT('Training pairs'!F1262:F1271)) -> 1.2043274 | L81: =AVERAGE('Training pairs'!G1262:G1271)-K81*AVERAGE('Training pairs'!F1262:F1271) -> -1.5416593 | M81: =(SUM('Target months'!H231:H233)/SUM('Target months'!F231:F233)-1)*100 -> 2.2025959 | N81: =L81+K81*M81 -> 1.1109871 | O81: =COUNT('Training pairs'!F1272:F1280) -> 9 | P81: =(SUM('Training pairs'!I1272:I1280)-SUM('Training pairs'!F1272:F1280)*SUM('Training pairs'!G1272:G1280)/COUNT('Training pairs'!F1272:F1280))/(SUM('Training pairs'!H1272:H1280)-SUM('Training pairs'!F1272:F1280)^2/COUNT('Training pairs'!F1272:F1280)) -> 0.76134549 | Q81: =AVERAGE('Training pairs'!G1272:G1280)-P81*AVERAGE('Training pairs'!F1272:F1280) -> -1.321556 | R81: 1.8739916 | S81: =Q81+P81*R81 -> 0.10519908 | T81: =(H81+N81)/2 -> 0.93049357 | U81: 45562 | V81: 45503 | W81: https://alfred.stlouisfed.org/graph/alfredgraph.csv?id=PCENDC96&cosd=2021-01-01&coed=2026-04-01&vintage_date=2024-09-27
B82: 77 | C82: Grooming | D82: organic_volume_growth | E82: 45565 | F82: 45582 | G82: 2 | H82: =AVERAGE('PG facts'!D49,'PG facts'!D56,'PG facts'!D63,'PG facts'!D70) -> 0.75 | I82: ='PG facts'!D70 -> 2 | J82: =COUNT('Training pairs'!F1281:F1290) -> 10 | K82: =(SUM('Training pairs'!I1281:I1290)-SUM('Training pairs'!F1281:F1290)*SUM('Training pairs'!G1281:G1290)/COUNT('Training pairs'!F1281:F1290))/(SUM('Training pairs'!H1281:H1290)-SUM('Training pairs'!F1281:F1290)^2/COUNT('Training pairs'!F1281:F1290)) -> 1.2043274 | L82: =AVERAGE('Training pairs'!G1281:G1290)-K82*AVERAGE('Training pairs'!F1281:F1290) -> -1.5416593 | M82: =(SUM('Target months'!H234:H236)/SUM('Target months'!F234:F236)-1)*100 -> 2.2025959 | N82: =L82+K82*M82 -> 1.1109871 | O82: =COUNT('Training pairs'!F1291:F1299) -> 9 | P82: =(SUM('Training pairs'!I1291:I1299)-SUM('Training pairs'!F1291:F1299)*SUM('Training pairs'!G1291:G1299)/COUNT('Training pairs'!F1291:F1299))/(SUM('Training pairs'!H1291:H1299)-SUM('Training pairs'!F1291:F1299)^2/COUNT('Training pairs'!F1291:F1299)) -> 0.76134549 | Q82: =AVERAGE('Training pairs'!G1291:G1299)-P82*AVERAGE('Training pairs'!F1291:F1299) -> -1.321556 | R82: 1.8739916 | S82: =Q82+P82*R82 -> 0.10519908 | T82: =(H82+N82)/2 -> 0.93049357 | U82: 45566 | V82: 45503 | W82: https://alfred.stlouisfed.org/graph/alfredgraph.csv?id=PCENDC96&cosd=2021-01-01&coed=2026-04-01&vintage_date=2024-10-01
B83: 78 | C83: Health Care | D83: organic_volume_growth | E83: 45565 | F83: 45474 | G83: 0 | H83: =AVERAGE('PG facts'!D43,'PG facts'!D50,'PG facts'!D57,'PG facts'!D64) -> -2.25 | I83: ='PG facts'!D64 -> -4 | J83: =COUNT('Training pairs'!F1300:F1308) -> 9 | K83: =(SUM('Training pairs'!I1300:I1308)-SUM('Training pairs'!F1300:F1308)*SUM('Training pairs'!G1300:G1308)/COUNT('Training pairs'!F1300:F1308))/(SUM('Training pairs'!H1300:H1308)-SUM('Training pairs'!F1300:F1308)^2/COUNT('Training pairs'!F1300:F1308)) -> 1.2487472 | L83: =AVERAGE('Training pairs'!G1300:G1308)-K83*AVERAGE('Training pairs'!F1300:F1308) -> -1.3785868 | M83: =(SUM('Target months'!H237:H239)/SUM('Target months'!F237:F239)-1)*100 -> 1.8076142 | N83: =L83+K83*M83 -> 0.87866636 | O83: =COUNT('Training pairs'!F1309:F1316) -> 8 | P83: =(SUM('Training pairs'!I1309:I1316)-SUM('Training pairs'!F1309:F1316)*SUM('Training pairs'!G1309:G1316)/COUNT('Training pairs'!F1309:F1316))/(SUM('Training pairs'!H1309:H1316)-SUM('Training pairs'!F1309:F1316)^2/COUNT('Training pairs'!F1309:F1316)) -> -0.35458458 | Q83: =AVERAGE('Training pairs'!G1309:G1316)-P83*AVERAGE('Training pairs'!F1309:F1316) -> -1.11342 | R83: n.a. | S83: ="n.a." -> n.a. | T83: =(H83+N83)/2 -> -0.68566682 | U83: 45474 | V83: 45401 | W83: https://alfred.stlouisfed.org/graph/alfredgraph.csv?id=PCENDC96&cosd=2021-01-01&coed=2026-04-01&vintage_date=2024-07-01
B84: 79 | C84: Health Care | D84: organic_volume_growth | E84: 45565 | F84: 45499 | G84: 0 | H84: =AVERAGE('PG facts'!D43,'PG facts'!D50,'PG facts'!D57,'PG facts'!D64) -> -2.25 | I84: ='PG facts'!D64 -> -4 | J84: =COUNT('Training pairs'!F1317:F1325) -> 9 | K84: =(SUM('Training pairs'!I1317:I1325)-SUM('Training pairs'!F1317:F1325)*SUM('Training pairs'!G1317:G1325)/COUNT('Training pairs'!F1317:F1325))/(SUM('Training pairs'!H1317:H1325)-SUM('Training pairs'!F1317:F1325)^2/COUNT('Training pairs'!F1317:F1325)) -> 1.2487472 | L84: =AVERAGE('Training pairs'!G1317:G1325)-K84*AVERAGE('Training pairs'!F1317:F1325) -> -1.3785868 | M84: =(SUM('Target months'!H240:H242)/SUM('Target months'!F240:F242)-1)*100 -> 1.7457095 | N84: =L84+K84*M84 -> 0.80136301 | O84: =COUNT('Training pairs'!F1326:F1333) -> 8 | P84: =(SUM('Training pairs'!I1326:I1333)-SUM('Training pairs'!F1326:F1333)*SUM('Training pairs'!G1326:G1333)/COUNT('Training pairs'!F1326:F1333))/(SUM('Training pairs'!H1326:H1333)-SUM('Training pairs'!F1326:F1333)^2/COUNT('Training pairs'!F1326:F1333)) -> -0.35458458 | Q84: =AVERAGE('Training pairs'!G1326:G1333)-P84*AVERAGE('Training pairs'!F1326:F1333) -> -1.11342 | R84: 1.7459001 | S84: =Q84+P84*R84 -> -1.7324892 | T84: =(H84+N84)/2 -> -0.7243185 | U84: 45499 | V84: 45401 | W84: https://alfred.stlouisfed.org/graph/alfredgraph.csv?id=PCENDC96&cosd=2021-01-01&coed=2026-04-01&vintage_date=2024-07-26
B85: 80 | C85: Health Care | D85: organic_volume_growth | E85: 45565 | F85: 45503 | G85: 0 | H85: =AVERAGE('PG facts'!D50,'PG facts'!D57,'PG facts'!D64,'PG facts'!D71) -> -1.25 | I85: ='PG facts'!D71 -> 1 | J85: =COUNT('Training pairs'!F1334:F1343) -> 10 | K85: =(SUM('Training pairs'!I1334:I1343)-SUM('Training pairs'!F1334:F1343)*SUM('Training pairs'!G1334:G1343)/COUNT('Training pairs'!F1334:F1343))/(SUM('Training pairs'!H1334:H1343)-SUM('Training pairs'!F1334:F1343)^2/COUNT('Training pairs'!F1334:F1343)) -> 1.2574816 | L85: =AVERAGE('Training pairs'!G1334:G1343)-K85*AVERAGE('Training pairs'!F1334:F1343) -> -1.3668518 | M85: =(SUM('Target months'!H243:H245)/SUM('Target months'!F243:F245)-1)*100 -> 1.7457095 | N85: =L85+K85*M85 -> 0.82834571 | O85: =COUNT('Training pairs'!F1344:F1352) -> 9 | P85: =(SUM('Training pairs'!I1344:I1352)-SUM('Training pairs'!F1344:F1352)*SUM('Training pairs'!G1344:G1352)/COUNT('Training pairs'!F1344:F1352))/(SUM('Training pairs'!H1344:H1352)-SUM('Training pairs'!F1344:F1352)^2/COUNT('Training pairs'!F1344:F1352)) -> -0.23464925 | Q85: =AVERAGE('Training pairs'!G1344:G1352)-P85*AVERAGE('Training pairs'!F1344:F1352) -> -0.9146999 | R85: 1.7459001 | S85: =Q85+P85*R85 -> -1.324374 | T85: =(H85+N85)/2 -> -0.21082715 | U85: 45499 | V85: 45503 | W85: https://alfred.stlouisfed.org/graph/alfredgraph.csv?id=PCENDC96&cosd=2021-01-01&coed=2026-04-01&vintage_date=2024-07-26
B86: 81 | C86: Health Care | D86: organic_volume_growth | E86: 45565 | F86: 45534 | G86: 1 | H86: =AVERAGE('PG facts'!D50,'PG facts'!D57,'PG facts'!D64,'PG facts'!D71) -> -1.25 | I86: ='PG facts'!D71 -> 1 | J86: =COUNT('Training pairs'!F1353:F1362) -> 10 | K86: =(SUM('Training pairs'!I1353:I1362)-SUM('Training pairs'!F1353:F1362)*SUM('Training pairs'!G1353:G1362)/COUNT('Training pairs'!F1353:F1362))/(SUM('Training pairs'!H1353:H1362)-SUM('Training pairs'!F1353:F1362)^2/COUNT('Training pairs'!F1353:F1362)) -> 1.2491254 | L86: =AVERAGE('Training pairs'!G1353:G1362)-K86*AVERAGE('Training pairs'!F1353:F1362) -> -1.3781975 | M86: =(SUM('Target months'!H246:H248)/SUM('Target months'!F246:F248)-1)*100 -> 1.8769844 | N86: =L86+K86*M86 -> 0.96639149 | O86: =COUNT('Training pairs'!F1363:F1371) -> 9 | P86: =(SUM('Training pairs'!I1363:I1371)-SUM('Training pairs'!F1363:F1371)*SUM('Training pairs'!G1363:G1371)/COUNT('Training pairs'!F1363:F1371))/(SUM('Training pairs'!H1363:H1371)-SUM('Training pairs'!F1363:F1371)^2/COUNT('Training pairs'!F1363:F1371)) -> -0.23464925 | Q86: =AVERAGE('Training pairs'!G1363:G1371)-P86*AVERAGE('Training pairs'!F1363:F1371) -> -0.9146999 | R86: 1.8988038 | S86: =Q86+P86*R86 -> -1.3602528 | T86: =(H86+N86)/2 -> -0.14180426 | U86: 45534 | V86: 45503 | W86: https://alfred.stlouisfed.org/graph/alfredgraph.csv?id=PCENDC96&cosd=2021-01-01&coed=2026-04-01&vintage_date=2024-08-30
B87: 82 | C87: Health Care | D87: organic_volume_growth | E87: 45565 | F87: 45562 | G87: 2 | H87: =AVERAGE('PG facts'!D50,'PG facts'!D57,'PG facts'!D64,'PG facts'!D71) -> -1.25 | I87: ='PG facts'!D71 -> 1 | J87: =COUNT('Training pairs'!F1372:F1381) -> 10 | K87: =(SUM('Training pairs'!I1372:I1381)-SUM('Training pairs'!F1372:F1381)*SUM('Training pairs'!G1372:G1381)/COUNT('Training pairs'!F1372:F1381))/(SUM('Training pairs'!H1372:H1381)-SUM('Training pairs'!F1372:F1381)^2/COUNT('Training pairs'!F1372:F1381)) -> 1.0064221 | L87: =AVERAGE('Training pairs'!G1372:G1381)-K87*AVERAGE('Training pairs'!F1372:F1381) -> -0.90335079 | M87: =(SUM('Target months'!H249:H251)/SUM('Target months'!F249:F251)-1)*100 -> 2.2025959 | N87: =L87+K87*M87 -> 1.3133905 | O87: =COUNT('Training pairs'!F1382:F1390) -> 9 | P87: =(SUM('Training pairs'!I1382:I1390)-SUM('Training pairs'!F1382:F1390)*SUM('Training pairs'!G1382:G1390)/COUNT('Training pairs'!F1382:F1390))/(SUM('Training pairs'!H1382:H1390)-SUM('Training pairs'!F1382:F1390)^2/COUNT('Training pairs'!F1382:F1390)) -> -0.30848067 | Q87: =AVERAGE('Training pairs'!G1382:G1390)-P87*AVERAGE('Training pairs'!F1382:F1390) -> -0.9358038 | R87: 1.8739916 | S87: =Q87+P87*R87 -> -1.513894 | T87: =(H87+N87)/2 -> 0.031695235 | U87: 45562 | V87: 45503 | W87: https://alfred.stlouisfed.org/graph/alfredgraph.csv?id=PCENDC96&cosd=2021-01-01&coed=2026-04-01&vintage_date=2024-09-27
B88: 83 | C88: Health Care | D88: organic_volume_growth | E88: 45565 | F88: 45582 | G88: 2 | H88: =AVERAGE('PG facts'!D50,'PG facts'!D57,'PG facts'!D64,'PG facts'!D71) -> -1.25 | I88: ='PG facts'!D71 -> 1 | J88: =COUNT('Training pairs'!F1391:F1400) -> 10 | K88: =(SUM('Training pairs'!I1391:I1400)-SUM('Training pairs'!F1391:F1400)*SUM('Training pairs'!G1391:G1400)/COUNT('Training pairs'!F1391:F1400))/(SUM('Training pairs'!H1391:H1400)-SUM('Training pairs'!F1391:F1400)^2/COUNT('Training pairs'!F1391:F1400)) -> 1.0064221 | L88: =AVERAGE('Training pairs'!G1391:G1400)-K88*AVERAGE('Training pairs'!F1391:F1400) -> -0.90335079 | M88: =(SUM('Target months'!H252:H254)/SUM('Target months'!F252:F254)-1)*100 -> 2.2025959 | N88: =L88+K88*M88 -> 1.3133905 | O88: =COUNT('Training pairs'!F1401:F1409) -> 9 | P88: =(SUM('Training pairs'!I1401:I1409)-SUM('Training pairs'!F1401:F1409)*SUM('Training pairs'!G1401:G1409)/COUNT('Training pairs'!F1401:F1409))/(SUM('Training pairs'!H1401:H1409)-SUM('Training pairs'!F1401:F1409)^2/COUNT('Training pairs'!F1401:F1409)) -> -0.30848067 | Q88: =AVERAGE('Training pairs'!G1401:G1409)-P88*AVERAGE('Training pairs'!F1401:F1409) -> -0.9358038 | R88: 1.8739916 | S88: =Q88+P88*R88 -> -1.513894 | T88: =(H88+N88)/2 -> 0.031695235 | U88: 45566 | V88: 45503 | W88: https://alfred.stlouisfed.org/graph/alfredgraph.csv?id=PCENDC96&cosd=2021-01-01&coed=2026-04-01&vintage_date=2024-10-01
B89: 84 | C89: Fabric & Home Care | D89: organic_volume_growth | E89: 45565 | F89: 45474 | G89: 0 | H89: =AVERAGE('PG facts'!D44,'PG facts'!D51,'PG facts'!D58,'PG facts'!D65) -> 0 | I89: ='PG facts'!D65 -> 1 | J89: =COUNT('Training pairs'!F1410:F1418) -> 9 | K89: =(SUM('Training pairs'!I1410:I1418)-SUM('Training pairs'!F1410:F1418)*SUM('Training pairs'!G1410:G1418)/COUNT('Training pairs'!F1410:F1418))/(SUM('Training pairs'!H1410:H1418)-SUM('Training pairs'!F1410:F1418)^2/COUNT('Training pairs'!F1410:F1418)) -> 2.3316231 | L89: =AVERAGE('Training pairs'!G1410:G1418)-K89*AVERAGE('Training pairs'!F1410:F1418) -> -3.2849991 | M89: =(SUM('Target months'!H255:H257)/SUM('Target months'!F255:F257)-1)*100 -> 1.8076142 | N89: =L89+K89*M89 -> 0.92967595 | O89: =COUNT('Training pairs'!F1419:F1426) -> 8 | P89: =(SUM('Training pairs'!I1419:I1426)-SUM('Training pairs'!F1419:F1426)*SUM('Training pairs'!G1419:G1426)/COUNT('Training pairs'!F1419:F1426))/(SUM('Training pairs'!H1419:H1426)-SUM('Training pairs'!F1419:F1426)^2/COUNT('Training pairs'!F1419:F1426)) -> 1.1542055 | Q89: =AVERAGE('Training pairs'!G1419:G1426)-P89*AVERAGE('Training pairs'!F1419:F1426) -> -2.9764671 | R89: n.a. | S89: ="n.a." -> n.a. | T89: =(H89+N89)/2 -> 0.46483798 | U89: 45474 | V89: 45401 | W89: https://alfred.stlouisfed.org/graph/alfredgraph.csv?id=PCENDC96&cosd=2021-01-01&coed=2026-04-01&vintage_date=2024-07-01
B90: 85 | C90: Fabric & Home Care | D90: organic_volume_growth | E90: 45565 | F90: 45499 | G90: 0 | H90: =AVERAGE('PG facts'!D44,'PG facts'!D51,'PG facts'!D58,'PG facts'!D65) -> 0 | I90: ='PG facts'!D65 -> 1 | J90: =COUNT('Training pairs'!F1427:F1435) -> 9 | K90: =(SUM('Training pairs'!I1427:I1435)-SUM('Training pairs'!F1427:F1435)*SUM('Training pairs'!G1427:G1435)/COUNT('Training pairs'!F1427:F1435))/(SUM('Training pairs'!H1427:H1435)-SUM('Training pairs'!F1427:F1435)^2/COUNT('Training pairs'!F1427:F1435)) -> 2.3316231 | L90: =AVERAGE('Training pairs'!G1427:G1435)-K90*AVERAGE('Training pairs'!F1427:F1435) -> -3.2849991 | M90: =(SUM('Target months'!H258:H260)/SUM('Target months'!F258:F260)-1)*100 -> 1.7457095 | N90: =L90+K90*M90 -> 0.78533746 | O90: =COUNT('Training pairs'!F1436:F1443) -> 8 | P90: =(SUM('Training pairs'!I1436:I1443)-SUM('Training pairs'!F1436:F1443)*SUM('Training pairs'!G1436:G1443)/COUNT('Training pairs'!F1436:F1443))/(SUM('Training pairs'!H1436:H1443)-SUM('Training pairs'!F1436:F1443)^2/COUNT('Training pairs'!F1436:F1443)) -> 1.1542055 | Q90: =AVERAGE('Training pairs'!G1436:G1443)-P90*AVERAGE('Training pairs'!F1436:F1443) -> -2.9764671 | R90: 1.7459001 | S90: =Q90+P90*R90 -> -0.9613395 | T90: =(H90+N90)/2 -> 0.39266873 | U90: 45499 | V90: 45401 | W90: https://alfred.stlouisfed.org/graph/alfredgraph.csv?id=PCENDC96&cosd=2021-01-01&coed=2026-04-01&vintage_date=2024-07-26
B91: 86 | C91: Fabric & Home Care | D91: organic_volume_growth | E91: 45565 | F91: 45503 | G91: 0 | H91: =AVERAGE('PG facts'!D51,'PG facts'!D58,'PG facts'!D65,'PG facts'!D72) -> 1.25 | I91: ='PG facts'!D72 -> 3 | J91: =COUNT('Training pairs'!F1444:F1453) -> 10 | K91: =(SUM('Training pairs'!I1444:I1453)-SUM('Training pairs'!F1444:F1453)*SUM('Training pairs'!G1444:G1453)/COUNT('Training pairs'!F1444:F1453))/(SUM('Training pairs'!H1444:H1453)-SUM('Training pairs'!F1444:F1453)^2/COUNT('Training pairs'!F1444:F1453)) -> 2.4291024 | L91: =AVERAGE('Training pairs'!G1444:G1453)-K91*AVERAGE('Training pairs'!F1444:F1453) -> -3.154031 | M91: =(SUM('Target months'!H261:H263)/SUM('Target months'!F261:F263)-1)*100 -> 1.7457095 | N91: =L91+K91*M91 -> 1.086476 | O91: =COUNT('Training pairs'!F1454:F1462) -> 9 | P91: =(SUM('Training pairs'!I1454:I1462)-SUM('Training pairs'!F1454:F1462)*SUM('Training pairs'!G1454:G1462)/COUNT('Training pairs'!F1454:F1462))/(SUM('Training pairs'!H1454:H1462)-SUM('Training pairs'!F1454:F1462)^2/COUNT('Training pairs'!F1454:F1462)) -> 1.3365652 | Q91: =AVERAGE('Training pairs'!G1454:G1462)-P91*AVERAGE('Training pairs'!F1454:F1462) -> -2.6743164 | R91: 1.7459001 | S91: =Q91+P91*R91 -> -0.34080704 | T91: =(H91+N91)/2 -> 1.168238 | U91: 45499 | V91: 45503 | W91: https://alfred.stlouisfed.org/graph/alfredgraph.csv?id=PCENDC96&cosd=2021-01-01&coed=2026-04-01&vintage_date=2024-07-26
B92: 87 | C92: Fabric & Home Care | D92: organic_volume_growth | E92: 45565 | F92: 45534 | G92: 1 | H92: =AVERAGE('PG facts'!D51,'PG facts'!D58,'PG facts'!D65,'PG facts'!D72) -> 1.25 | I92: ='PG facts'!D72 -> 3 | J92: =COUNT('Training pairs'!F1463:F1472) -> 10 | K92: =(SUM('Training pairs'!I1463:I1472)-SUM('Training pairs'!F1463:F1472)*SUM('Training pairs'!G1463:G1472)/COUNT('Training pairs'!F1463:F1472))/(SUM('Training pairs'!H1463:H1472)-SUM('Training pairs'!F1463:F1472)^2/COUNT('Training pairs'!F1463:F1472)) -> 2.4257918 | L92: =AVERAGE('Training pairs'!G1463:G1472)-K92*AVERAGE('Training pairs'!F1463:F1472) -> -3.1880503 | M92: =(SUM('Target months'!H264:H266)/SUM('Target months'!F264:F266)-1)*100 -> 1.8769844 | N92: =L92+K92*M92 -> 1.3651232 | O92: =COUNT('Training pairs'!F1473:F1481) -> 9 | P92: =(SUM('Training pairs'!I1473:I1481)-SUM('Training pairs'!F1473:F1481)*SUM('Training pairs'!G1473:G1481)/COUNT('Training pairs'!F1473:F1481))/(SUM('Training pairs'!H1473:H1481)-SUM('Training pairs'!F1473:F1481)^2/COUNT('Training pairs'!F1473:F1481)) -> 1.3365652 | Q92: =AVERAGE('Training pairs'!G1473:G1481)-P92*AVERAGE('Training pairs'!F1473:F1481) -> -2.6743164 | R92: 1.8988038 | S92: =Q92+P92*R92 -> -0.13644131 | T92: =(H92+N92)/2 -> 1.3075616 | U92: 45534 | V92: 45503 | W92: https://alfred.stlouisfed.org/graph/alfredgraph.csv?id=PCENDC96&cosd=2021-01-01&coed=2026-04-01&vintage_date=2024-08-30
B93: 88 | C93: Fabric & Home Care | D93: organic_volume_growth | E93: 45565 | F93: 45562 | G93: 2 | H93: =AVERAGE('PG facts'!D51,'PG facts'!D58,'PG facts'!D65,'PG facts'!D72) -> 1.25 | I93: ='PG facts'!D72 -> 3 | J93: =COUNT('Training pairs'!F1482:F1491) -> 10 | K93: =(SUM('Training pairs'!I1482:I1491)-SUM('Training pairs'!F1482:F1491)*SUM('Training pairs'!G1482:G1491)/COUNT('Training pairs'!F1482:F1491))/(SUM('Training pairs'!H1482:H1491)-SUM('Training pairs'!F1482:F1491)^2/COUNT('Training pairs'!F1482:F1491)) -> 2.2145813 | L93: =AVERAGE('Training pairs'!G1482:G1491)-K93*AVERAGE('Training pairs'!F1482:F1491) -> -2.447688 | M93: =(SUM('Target months'!H267:H269)/SUM('Target months'!F267:F269)-1)*100 -> 2.2025959 | N93: =L93+K93*M93 -> 2.4301395 | O93: =COUNT('Training pairs'!F1492:F1500) -> 9 | P93: =(SUM('Training pairs'!I1492:I1500)-SUM('Training pairs'!F1492:F1500)*SUM('Training pairs'!G1492:G1500)/COUNT('Training pairs'!F1492:F1500))/(SUM('Training pairs'!H1492:H1500)-SUM('Training pairs'!F1492:F1500)^2/COUNT('Training pairs'!F1492:F1500)) -> 1.3761046 | Q93: =AVERAGE('Training pairs'!G1492:G1500)-P93*AVERAGE('Training pairs'!F1492:F1500) -> -2.3375858 | R93: 1.8739916 | S93: =Q93+P93*R93 -> 0.24122271 | T93: =(H93+N93)/2 -> 1.8400698 | U93: 45562 | V93: 45503 | W93: https://alfred.stlouisfed.org/graph/alfredgraph.csv?id=PCENDC96&cosd=2021-01-01&coed=2026-04-01&vintage_date=2024-09-27
B94: 89 | C94: Fabric & Home Care | D94: organic_volume_growth | E94: 45565 | F94: 45582 | G94: 2 | H94: =AVERAGE('PG facts'!D51,'PG facts'!D58,'PG facts'!D65,'PG facts'!D72) -> 1.25 | I94: ='PG facts'!D72 -> 3 | J94: =COUNT('Training pairs'!F1501:F1510) -> 10 | K94: =(SUM('Training pairs'!I1501:I1510)-SUM('Training pairs'!F1501:F1510)*SUM('Training pairs'!G1501:G1510)/COUNT('Training pairs'!F1501:F1510))/(SUM('Training pairs'!H1501:H1510)-SUM('Training pairs'!F1501:F1510)^2/COUNT('Training pairs'!F1501:F1510)) -> 2.2145813 | L94: =AVERAGE('Training pairs'!G1501:G1510)-K94*AVERAGE('Training pairs'!F1501:F1510) -> -2.447688 | M94: =(SUM('Target months'!H270:H272)/SUM('Target months'!F270:F272)-1)*100 -> 2.2025959 | N94: =L94+K94*M94 -> 2.4301395 | O94: =COUNT('Training pairs'!F1511:F1519) -> 9 | P94: =(SUM('Training pairs'!I1511:I1519)-SUM('Training pairs'!F1511:F1519)*SUM('Training pairs'!G1511:G1519)/COUNT('Training pairs'!F1511:F1519))/(SUM('Training pairs'!H1511:H1519)-SUM('Training pairs'!F1511:F1519)^2/COUNT('Training pairs'!F1511:F1519)) -> 1.3761046 | Q94: =AVERAGE('Training pairs'!G1511:G1519)-P94*AVERAGE('Training pairs'!F1511:F1519) -> -2.3375858 | R94: 1.8739916 | S94: =Q94+P94*R94 -> 0.24122271 | T94: =(H94+N94)/2 -> 1.8400698 | U94: 45566 | V94: 45503 | W94: https://alfred.stlouisfed.org/graph/alfredgraph.csv?id=PCENDC96&cosd=2021-01-01&coed=2026-04-01&vintage_date=2024-10-01
B95: 90 | C95: Baby, Feminine & Family Care | D95: organic_volume_growth | E95: 45565 | F95: 45474 | G95: 0 | H95: =AVERAGE('PG facts'!D45,'PG facts'!D52,'PG facts'!D59,'PG facts'!D66) -> -2 | I95: ='PG facts'!D66 -> -3 | J95: =COUNT('Training pairs'!F1520:F1528) -> 9 | K95: =(SUM('Training pairs'!I1520:I1528)-SUM('Training pairs'!F1520:F1528)*SUM('Training pairs'!G1520:G1528)/COUNT('Training pairs'!F1520:F1528))/(SUM('Training pairs'!H1520:H1528)-SUM('Training pairs'!F1520:F1528)^2/COUNT('Training pairs'!F1520:F1528)) -> 1.0106998 | L95: =AVERAGE('Training pairs'!G1520:G1528)-K95*AVERAGE('Training pairs'!F1520:F1528) -> -2.957109 | M95: =(SUM('Target months'!H273:H275)/SUM('Target months'!F273:F275)-1)*100 -> 1.8076142 | N95: =L95+K95*M95 -> -1.1301536 | O95: =COUNT('Training pairs'!F1529:F1536) -> 8 | P95: =(SUM('Training pairs'!I1529:I1536)-SUM('Training pairs'!F1529:F1536)*SUM('Training pairs'!G1529:G1536)/COUNT('Training pairs'!F1529:F1536))/(SUM('Training pairs'!H1529:H1536)-SUM('Training pairs'!F1529:F1536)^2/COUNT('Training pairs'!F1529:F1536)) -> 0.71929975 | Q95: =AVERAGE('Training pairs'!G1529:G1536)-P95*AVERAGE('Training pairs'!F1529:F1536) -> -3.1556334 | R95: n.a. | S95: ="n.a." -> n.a. | T95: =(H95+N95)/2 -> -1.5650768 | U95: 45474 | V95: 45401 | W95: https://alfred.stlouisfed.org/graph/alfredgraph.csv?id=PCENDC96&cosd=2021-01-01&coed=2026-04-01&vintage_date=2024-07-01
B96: 91 | C96: Baby, Feminine & Family Care | D96: organic_volume_growth | E96: 45565 | F96: 45499 | G96: 0 | H96: =AVERAGE('PG facts'!D45,'PG facts'!D52,'PG facts'!D59,'PG facts'!D66) -> -2 | I96: ='PG facts'!D66 -> -3 | J96: =COUNT('Training pairs'!F1537:F1545) -> 9 | K96: =(SUM('Training pairs'!I1537:I1545)-SUM('Training pairs'!F1537:F1545)*SUM('Training pairs'!G1537:G1545)/COUNT('Training pairs'!F1537:F1545))/(SUM('Training pairs'!H1537:H1545)-SUM('Training pairs'!F1537:F1545)^2/COUNT('Training pairs'!F1537:F1545)) -> 1.0106998 | L96: =AVERAGE('Training pairs'!G1537:G1545)-K96*AVERAGE('Training pairs'!F1537:F1545) -> -2.957109 | M96: =(SUM('Target months'!H276:H278)/SUM('Target months'!F276:F278)-1)*100 -> 1.7457095 | N96: =L96+K96*M96 -> -1.1927207 | O96: =COUNT('Training pairs'!F1546:F1553) -> 8 | P96: =(SUM('Training pairs'!I1546:I1553)-SUM('Training pairs'!F1546:F1553)*SUM('Training pairs'!G1546:G1553)/COUNT('Training pairs'!F1546:F1553))/(SUM('Training pairs'!H1546:H1553)-SUM('Training pairs'!F1546:F1553)^2/COUNT('Training pairs'!F1546:F1553)) -> 0.71929975 | Q96: =AVERAGE('Training pairs'!G1546:G1553)-P96*AVERAGE('Training pairs'!F1546:F1553) -> -3.1556334 | R96: 1.7459001 | S96: =Q96+P96*R96 -> -1.8998079 | T96: =(H96+N96)/2 -> -1.5963604 | U96: 45499 | V96: 45401 | W96: https://alfred.stlouisfed.org/graph/alfredgraph.csv?id=PCENDC96&cosd=2021-01-01&coed=2026-04-01&vintage_date=2024-07-26
B97: 92 | C97: Baby, Feminine & Family Care | D97: organic_volume_growth | E97: 45565 | F97: 45503 | G97: 0 | H97: =AVERAGE('PG facts'!D52,'PG facts'!D59,'PG facts'!D66,'PG facts'!D73) -> -2.25 | I97: ='PG facts'!D73 -> -1 | J97: =COUNT('Training pairs'!F1554:F1563) -> 10 | K97: =(SUM('Training pairs'!I1554:I1563)-SUM('Training pairs'!F1554:F1563)*SUM('Training pairs'!G1554:G1563)/COUNT('Training pairs'!F1554:F1563))/(SUM('Training pairs'!H1554:H1563)-SUM('Training pairs'!F1554:F1563)^2/COUNT('Training pairs'!F1554:F1563)) -> 1.0191757 | L97: =AVERAGE('Training pairs'!G1554:G1563)-K97*AVERAGE('Training pairs'!F1554:F1563) -> -2.9457212 | M97: =(SUM('Target months'!H279:H281)/SUM('Target months'!F279:F281)-1)*100 -> 1.7457095 | N97: =L97+K97*M97 -> -1.1665365 | O97: =COUNT('Training pairs'!F1564:F1572) -> 9 | P97: =(SUM('Training pairs'!I1564:I1572)-SUM('Training pairs'!F1564:F1572)*SUM('Training pairs'!G1564:G1572)/COUNT('Training pairs'!F1564:F1572))/(SUM('Training pairs'!H1564:H1572)-SUM('Training pairs'!F1564:F1572)^2/COUNT('Training pairs'!F1564:F1572)) -> 0.76304791 | Q97: =AVERAGE('Training pairs'!G1564:G1572)-P97*AVERAGE('Training pairs'!F1564:F1572) -> -3.0831474 | R97: 1.7459001 | S97: =Q97+P97*R97 -> -1.750942 | T97: =(H97+N97)/2 -> -1.7082682 | U97: 45499 | V97: 45503 | W97: https://alfred.stlouisfed.org/graph/alfredgraph.csv?id=PCENDC96&cosd=2021-01-01&coed=2026-04-01&vintage_date=2024-07-26
B98: 93 | C98: Baby, Feminine & Family Care | D98: organic_volume_growth | E98: 45565 | F98: 45534 | G98: 1 | H98: =AVERAGE('PG facts'!D52,'PG facts'!D59,'PG facts'!D66,'PG facts'!D73) -> -2.25 | I98: ='PG facts'!D73 -> -1 | J98: =COUNT('Training pairs'!F1573:F1582) -> 10 | K98: =(SUM('Training pairs'!I1573:I1582)-SUM('Training pairs'!F1573:F1582)*SUM('Training pairs'!G1573:G1582)/COUNT('Training pairs'!F1573:F1582))/(SUM('Training pairs'!H1573:H1582)-SUM('Training pairs'!F1573:F1582)^2/COUNT('Training pairs'!F1573:F1582)) -> 1.0126255 | L98: =AVERAGE('Training pairs'!G1573:G1582)-K98*AVERAGE('Training pairs'!F1573:F1582) -> -2.9551265 | M98: =(SUM('Target months'!H282:H284)/SUM('Target months'!F282:F284)-1)*100 -> 1.8769844 | N98: =L98+K98*M98 -> -1.0544442 | O98: =COUNT('Training pairs'!F1583:F1591) -> 9 | P98: =(SUM('Training pairs'!I1583:I1591)-SUM('Training pairs'!F1583:F1591)*SUM('Training pairs'!G1583:G1591)/COUNT('Training pairs'!F1583:F1591))/(SUM('Training pairs'!H1583:H1591)-SUM('Training pairs'!F1583:F1591)^2/COUNT('Training pairs'!F1583:F1591)) -> 0.76304791 | Q98: =AVERAGE('Training pairs'!G1583:G1591)-P98*AVERAGE('Training pairs'!F1583:F1591) -> -3.0831474 | R98: 1.8988038 | S98: =Q98+P98*R98 -> -1.6342691 | T98: =(H98+N98)/2 -> -1.6522221 | U98: 45534 | V98: 45503 | W98: https://alfred.stlouisfed.org/graph/alfredgraph.csv?id=PCENDC96&cosd=2021-01-01&coed=2026-04-01&vintage_date=2024-08-30
B99: 94 | C99: Baby, Feminine & Family Care | D99: organic_volume_growth | E99: 45565 | F99: 45562 | G99: 2 | H99: =AVERAGE('PG facts'!D52,'PG facts'!D59,'PG facts'!D66,'PG facts'!D73) -> -2.25 | I99: ='PG facts'!D73 -> -1 | J99: =COUNT('Training pairs'!F1592:F1601) -> 10 | K99: =(SUM('Training pairs'!I1592:I1601)-SUM('Training pairs'!F1592:F1601)*SUM('Training pairs'!G1592:G1601)/COUNT('Training pairs'!F1592:F1601))/(SUM('Training pairs'!H1592:H1601)-SUM('Training pairs'!F1592:F1601)^2/COUNT('Training pairs'!F1592:F1601)) -> 0.8967705 | L99: =AVERAGE('Training pairs'!G1592:G1601)-K99*AVERAGE('Training pairs'!F1592:F1601) -> -2.6267194 | M99: =(SUM('Target months'!H285:H287)/SUM('Target months'!F285:F287)-1)*100 -> 2.2025959 | N99: =L99+K99*M99 -> -0.65149636 | O99: =COUNT('Training pairs'!F1602:F1610) -> 9 | P99: =(SUM('Training pairs'!I1602:I1610)-SUM('Training pairs'!F1602:F1610)*SUM('Training pairs'!G1602:G1610)/COUNT('Training pairs'!F1602:F1610))/(SUM('Training pairs'!H1602:H1610)-SUM('Training pairs'!F1602:F1610)^2/COUNT('Training pairs'!F1602:F1610)) -> 0.72826165 | Q99: =AVERAGE('Training pairs'!G1602:G1610)-P99*AVERAGE('Training pairs'!F1602:F1610) -> -2.8583102 | R99: 1.8739916 | S99: =Q99+P99*R99 -> -1.493554 | T99: =(H99+N99)/2 -> -1.4507482 | U99: 45562 | V99: 45503 | W99: https://alfred.stlouisfed.org/graph/alfredgraph.csv?id=PCENDC96&cosd=2021-01-01&coed=2026-04-01&vintage_date=2024-09-27
B100: 95 | C100: Baby, Feminine & Family Care | D100: organic_volume_growth | E100: 45565 | F100: 45582 | G100: 2 | H100: =AVERAGE('PG facts'!D52,'PG facts'!D59,'PG facts'!D66,'PG facts'!D73) -> -2.25 | I100: ='PG facts'!D73 -> -1 | J100: =COUNT('Training pairs'!F1611:F1620) -> 10 | K100: =(SUM('Training pairs'!I1611:I1620)-SUM('Training pairs'!F1611:F1620)*SUM('Training pairs'!G1611:G1620)/COUNT('Training pairs'!F1611:F1620))/(SUM('Training pairs'!H1611:H1620)-SUM('Training pairs'!F1611:F1620)^2/COUNT('Training pairs'!F1611:F1620)) -> 0.8967705 | L100: =AVERAGE('Training pairs'!G1611:G1620)-K100*AVERAGE('Training pairs'!F1611:F1620) -> -2.6267194 | M100: =(SUM('Target months'!H288:H290)/SUM('Target months'!F288:F290)-1)*100 -> 2.2025959 | N100: =L100+K100*M100 -> -0.65149636 | O100: =COUNT('Training pairs'!F1621:F1629) -> 9 | P100: =(SUM('Training pairs'!I1621:I1629)-SUM('Training pairs'!F1621:F1629)*SUM('Training pairs'!G1621:G1629)/COUNT('Training pairs'!F1621:F1629))/(SUM('Training pairs'!H1621:H1629)-SUM('Training pairs'!F1621:F1629)^2/COUNT('Training pairs'!F1621:F1629)) -> 0.72826165 | Q100: =AVERAGE('Training pairs'!G1621:G1629)-P100*AVERAGE('Training pairs'!F1621:F1629) -> -2.8583102 | R100: 1.8739916 | S100: =Q100+P100*R100 -> -1.493554 | T100: =(H100+N100)/2 -> -1.4507482 | U100: 45566 | V100: 45503 | W100: https://alfred.stlouisfed.org/graph/alfredgraph.csv?id=PCENDC96&cosd=2021-01-01&coed=2026-04-01&vintage_date=2024-10-01
B101: 96 | C101: Beauty | D101: price_contribution | E101: 45565 | F101: 45474 | G101: 0 | H101: =AVERAGE('PG facts'!E41,'PG facts'!E48,'PG facts'!E55,'PG facts'!E62) -> 5.75 | I101: ='PG facts'!E62 -> 4 | J101: =COUNT('Training pairs'!F1630:F1638) -> 9 | K101: =(SUM('Training pairs'!I1630:I1638)-SUM('Training pairs'!F1630:F1638)*SUM('Training pairs'!G1630:G1638)/COUNT('Training pairs'!F1630:F1638))/(SUM('Training pairs'!H1630:H1638)-SUM('Training pairs'!F1630:F1638)^2/COUNT('Training pairs'!F1630:F1638)) -> 0.78595698 | L101: =AVERAGE('Training pairs'!G1630:G1638)-K101*AVERAGE('Training pairs'!F1630:F1638) -> 2.4716801 | M101: =(SUM('Target months'!H291:H293)/SUM('Target months'!F291:F293)-1)*100 -> 2.4448013 | N101: =L101+K101*M101 -> 4.3931887 | O101: =COUNT('Training pairs'!F1639:F1646) -> 8 | P101: =(SUM('Training pairs'!I1639:I1646)-SUM('Training pairs'!F1639:F1646)*SUM('Training pairs'!G1639:G1646)/COUNT('Training pairs'!F1639:F1646))/(SUM('Training pairs'!H1639:H1646)-SUM('Training pairs'!F1639:F1646)^2/COUNT('Training pairs'!F1639:F1646)) -> 0.31633921 | Q101: =AVERAGE('Training pairs'!G1639:G1646)-P101*AVERAGE('Training pairs'!F1639:F1646) -> 5.0202502 | R101: n.a. | S101: ="n.a." -> n.a. | T101: =(H101+N101)/2 -> 5.0715944 | U101: 45474 | V101: 45401 | W101: https://alfred.stlouisfed.org/graph/alfredgraph.csv?id=CUUR0000SEGB&cosd=2021-01-01&coed=2026-04-01&vintage_date=2024-07-01
B102: 97 | C102: Beauty | D102: price_contribution | E102: 45565 | F102: 45484 | G102: 0 | H102: =AVERAGE('PG facts'!E41,'PG facts'!E48,'PG facts'!E55,'PG facts'!E62) -> 5.75 | I102: ='PG facts'!E62 -> 4 | J102: =COUNT('Training pairs'!F1647:F1655) -> 9 | K102: =(SUM('Training pairs'!I1647:I1655)-SUM('Training pairs'!F1647:F1655)*SUM('Training pairs'!G1647:G1655)/COUNT('Training pairs'!F1647:F1655))/(SUM('Training pairs'!H1647:H1655)-SUM('Training pairs'!F1647:F1655)^2/COUNT('Training pairs'!F1647:F1655)) -> 0.78595698 | L102: =AVERAGE('Training pairs'!G1647:G1655)-K102*AVERAGE('Training pairs'!F1647:F1655) -> 2.4716801 | M102: =(SUM('Target months'!H294:H296)/SUM('Target months'!F294:F296)-1)*100 -> 1.6583438 | N102: =L102+K102*M102 -> 3.775067 | O102: =COUNT('Training pairs'!F1656:F1663) -> 8 | P102: =(SUM('Training pairs'!I1656:I1663)-SUM('Training pairs'!F1656:F1663)*SUM('Training pairs'!G1656:G1663)/COUNT('Training pairs'!F1656:F1663))/(SUM('Training pairs'!H1656:H1663)-SUM('Training pairs'!F1656:F1663)^2/COUNT('Training pairs'!F1656:F1663)) -> 0.31633921 | Q102: =AVERAGE('Training pairs'!G1656:G1663)-P102*AVERAGE('Training pairs'!F1656:F1663) -> 5.0202502 | R102: 1.654755 | S102: =Q102+P102*R102 -> 5.5437141 | T102: =(H102+N102)/2 -> 4.7625335 | U102: 45484 | V102: 45401 | W102: https://alfred.stlouisfed.org/graph/alfredgraph.csv?id=CUUR0000SEGB&cosd=2021-01-01&coed=2026-04-01&vintage_date=2024-07-11
...

Sheet Training pairs
B2: Training pairs known at each forecast date
B5: Forecast ID | C5: Method | D5: Company quarter | E5: Published | F5: Market YoY % | G5: P&G result | H5: Market squared | I5: Cross product
B6: 1 | C6: bridge | D6: 44651 | E6: 44671 | F6: 3.7505058 | G6: ='PG facts'!D6 -> -1 | H6: =F6^2 -> 14.066294 | I6: =F6*G6 -> -3.7505058
B7: 1 | C7: bridge | D7: 44742 | E7: 44771 | F7: 0.22450064 | G7: ='PG facts'!D13 -> -2 | H7: =F7^2 -> 0.050400536 | I7: =F7*G7 -> -0.44900127
B8: 1 | C8: bridge | D8: 44834 | E8: 44853 | F8: -0.45976552 | G8: ='PG facts'!D20 -> -1 | H8: =F8^2 -> 0.21138433 | I8: =F8*G8 -> 0.45976552
B9: 1 | C9: bridge | D9: 44926 | E9: 44945 | F9: -0.97130769 | G9: ='PG facts'!D27 -> -4 | H9: =F9^2 -> 0.94343863 | I9: =F9*G9 -> 3.8852308
B10: 1 | C10: bridge | D10: 45016 | E10: 45037 | F10: -0.16799664 | G10: ='PG facts'!D34 -> 0 | H10: =F10^2 -> 0.028222871 | I10: =F10*G10 -> 0
B11: 1 | C11: bridge | D11: 45107 | E11: 45135 | F11: 0.06199938 | G11: ='PG facts'!D41 -> -1 | H11: =F11^2 -> 0.0038439231 | I11: =F11*G11 -> -0.06199938
B12: 1 | C12: bridge | D12: 45199 | E12: 45217 | F12: 1.4338645 | G12: ='PG facts'!D48 -> 0 | H12: =F12^2 -> 2.0559674 | I12: =F12*G12 -> 0
B13: 1 | C13: bridge | D13: 45291 | E13: 45314 | F13: 2.0298663 | G13: ='PG facts'!D55 -> -1 | H13: =F13^2 -> 4.1203573 | I13: =F13*G13 -> -2.0298663
B14: 1 | C14: lagged | D14: 44742 | E14: 44771 | F14: 3.7505058 | G14: ='PG facts'!D13 -> -2 | H14: =F14^2 -> 14.066294 | I14: =F14*G14 -> -7.5010115
B15: 1 | C15: lagged | D15: 44834 | E15: 44853 | F15: 0.22450064 | G15: ='PG facts'!D20 -> -1 | H15: =F15^2 -> 0.050400536 | I15: =F15*G15 -> -0.22450064
B16: 1 | C16: lagged | D16: 44926 | E16: 44945 | F16: -0.45976552 | G16: ='PG facts'!D27 -> -4 | H16: =F16^2 -> 0.21138433 | I16: =F16*G16 -> 1.8390621
B17: 1 | C17: lagged | D17: 45016 | E17: 45037 | F17: -0.97130769 | G17: ='PG facts'!D34 -> 0 | H17: =F17^2 -> 0.94343863 | I17: =F17*G17 -> 0
B18: 1 | C18: lagged | D18: 45107 | E18: 45135 | F18: -0.16799664 | G18: ='PG facts'!D41 -> -1 | H18: =F18^2 -> 0.028222871 | I18: =F18*G18 -> 0.16799664
B19: 1 | C19: lagged | D19: 45199 | E19: 45217 | F19: 0.06199938 | G19: ='PG facts'!D48 -> 0 | H19: =F19^2 -> 0.0038439231 | I19: =F19*G19 -> 0
B20: 1 | C20: lagged | D20: 45291 | E20: 45314 | F20: 1.4338645 | G20: ='PG facts'!D55 -> -1 | H20: =F20^2 -> 2.0559674 | I20: =F20*G20 -> -1.4338645
B21: 2 | C21: bridge | D21: 44651 | E21: 44671 | F21: 3.7505058 | G21: ='PG facts'!D6 -> -1 | H21: =F21^2 -> 14.066294 | I21: =F21*G21 -> -3.7505058
B22: 2 | C22: bridge | D22: 44742 | E22: 44771 | F22: 0.22450064 | G22: ='PG facts'!D13 -> -2 | H22: =F22^2 -> 0.050400536 | I22: =F22*G22 -> -0.44900127
B23: 2 | C23: bridge | D23: 44834 | E23: 44853 | F23: -0.45976552 | G23: ='PG facts'!D20 -> -1 | H23: =F23^2 -> 0.21138433 | I23: =F23*G23 -> 0.45976552
B24: 2 | C24: bridge | D24: 44926 | E24: 44945 | F24: -0.97130769 | G24: ='PG facts'!D27 -> -4 | H24: =F24^2 -> 0.94343863 | I24: =F24*G24 -> 3.8852308
B25: 2 | C25: bridge | D25: 45016 | E25: 45037 | F25: -0.16799664 | G25: ='PG facts'!D34 -> 0 | H25: =F25^2 -> 0.028222871 | I25: =F25*G25 -> 0
B26: 2 | C26: bridge | D26: 45107 | E26: 45135 | F26: 0.06199938 | G26: ='PG facts'!D41 -> -1 | H26: =F26^2 -> 0.0038439231 | I26: =F26*G26 -> -0.06199938
B27: 2 | C27: bridge | D27: 45199 | E27: 45217 | F27: 1.4338645 | G27: ='PG facts'!D48 -> 0 | H27: =F27^2 -> 2.0559674 | I27: =F27*G27 -> 0
B28: 2 | C28: bridge | D28: 45291 | E28: 45314 | F28: 2.0298663 | G28: ='PG facts'!D55 -> -1 | H28: =F28^2 -> 4.1203573 | I28: =F28*G28 -> -2.0298663
B29: 2 | C29: lagged | D29: 44742 | E29: 44771 | F29: 3.7505058 | G29: ='PG facts'!D13 -> -2 | H29: =F29^2 -> 14.066294 | I29: =F29*G29 -> -7.5010115
B30: 2 | C30: lagged | D30: 44834 | E30: 44853 | F30: 0.22450064 | G30: ='PG facts'!D20 -> -1 | H30: =F30^2 -> 0.050400536 | I30: =F30*G30 -> -0.22450064
B31: 2 | C31: lagged | D31: 44926 | E31: 44945 | F31: -0.45976552 | G31: ='PG facts'!D27 -> -4 | H31: =F31^2 -> 0.21138433 | I31: =F31*G31 -> 1.8390621
B32: 2 | C32: lagged | D32: 45016 | E32: 45037 | F32: -0.97130769 | G32: ='PG facts'!D34 -> 0 | H32: =F32^2 -> 0.94343863 | I32: =F32*G32 -> 0
B33: 2 | C33: lagged | D33: 45107 | E33: 45135 | F33: -0.16799664 | G33: ='PG facts'!D41 -> -1 | H33: =F33^2 -> 0.028222871 | I33: =F33*G33 -> 0.16799664
B34: 2 | C34: lagged | D34: 45199 | E34: 45217 | F34: 0.06199938 | G34: ='PG facts'!D48 -> 0 | H34: =F34^2 -> 0.0038439231 | I34: =F34*G34 -> 0
B35: 2 | C35: lagged | D35: 45291 | E35: 45314 | F35: 1.4338645 | G35: ='PG facts'!D55 -> -1 | H35: =F35^2 -> 2.0559674 | I35: =F35*G35 -> -1.4338645
B36: 2 | C36: lagged | D36: 45382 | E36: 45401 | F36: 2.0298663 | G36: ='PG facts'!D62 -> 1 | H36: =F36^2 -> 4.1203573 | I36: =F36*G36 -> 2.0298663
B37: 3 | C37: bridge | D37: 44651 | E37: 44671 | F37: 3.7505058 | G37: ='PG facts'!D6 -> -1 | H37: =F37^2 -> 14.066294 | I37: =F37*G37 -> -3.7505058
B38: 3 | C38: bridge | D38: 44742 | E38: 44771 | F38: 0.22450064 | G38: ='PG facts'!D13 -> -2 | H38: =F38^2 -> 0.050400536 | I38: =F38*G38 -> -0.44900127
B39: 3 | C39: bridge | D39: 44834 | E39: 44853 | F39: -0.45976552 | G39: ='PG facts'!D20 -> -1 | H39: =F39^2 -> 0.21138433 | I39: =F39*G39 -> 0.45976552
B40: 3 | C40: bridge | D40: 44926 | E40: 44945 | F40: -0.97130769 | G40: ='PG facts'!D27 -> -4 | H40: =F40^2 -> 0.94343863 | I40: =F40*G40 -> 3.8852308
B41: 3 | C41: bridge | D41: 45016 | E41: 45037 | F41: -0.16799664 | G41: ='PG facts'!D34 -> 0 | H41: =F41^2 -> 0.028222871 | I41: =F41*G41 -> 0
B42: 3 | C42: bridge | D42: 45107 | E42: 45135 | F42: 0.06199938 | G42: ='PG facts'!D41 -> -1 | H42: =F42^2 -> 0.0038439231 | I42: =F42*G42 -> -0.06199938
B43: 3 | C43: bridge | D43: 45199 | E43: 45217 | F43: 1.4338645 | G43: ='PG facts'!D48 -> 0 | H43: =F43^2 -> 2.0559674 | I43: =F43*G43 -> 0
B44: 3 | C44: bridge | D44: 45291 | E44: 45314 | F44: 2.0298663 | G44: ='PG facts'!D55 -> -1 | H44: =F44^2 -> 4.1203573 | I44: =F44*G44 -> -2.0298663
B45: 3 | C45: bridge | D45: 45382 | E45: 45401 | F45: 1.9031592 | G45: ='PG facts'!D62 -> 1 | H45: =F45^2 -> 3.6220151 | I45: =F45*G45 -> 1.9031592
B46: 3 | C46: lagged | D46: 44742 | E46: 44771 | F46: 3.7505058 | G46: ='PG facts'!D13 -> -2 | H46: =F46^2 -> 14.066294 | I46: =F46*G46 -> -7.5010115
B47: 3 | C47: lagged | D47: 44834 | E47: 44853 | F47: 0.22450064 | G47: ='PG facts'!D20 -> -1 | H47: =F47^2 -> 0.050400536 | I47: =F47*G47 -> -0.22450064
B48: 3 | C48: lagged | D48: 44926 | E48: 44945 | F48: -0.45976552 | G48: ='PG facts'!D27 -> -4 | H48: =F48^2 -> 0.21138433 | I48: =F48*G48 -> 1.8390621
B49: 3 | C49: lagged | D49: 45016 | E49: 45037 | F49: -0.97130769 | G49: ='PG facts'!D34 -> 0 | H49: =F49^2 -> 0.94343863 | I49: =F49*G49 -> 0
B50: 3 | C50: lagged | D50: 45107 | E50: 45135 | F50: -0.16799664 | G50: ='PG facts'!D41 -> -1 | H50: =F50^2 -> 0.028222871 | I50: =F50*G50 -> 0.16799664
B51: 3 | C51: lagged | D51: 45199 | E51: 45217 | F51: 0.06199938 | G51: ='PG facts'!D48 -> 0 | H51: =F51^2 -> 0.0038439231 | I51: =F51*G51 -> 0
B52: 3 | C52: lagged | D52: 45291 | E52: 45314 | F52: 1.4338645 | G52: ='PG facts'!D55 -> -1 | H52: =F52^2 -> 2.0559674 | I52: =F52*G52 -> -1.4338645
B53: 3 | C53: lagged | D53: 45382 | E53: 45401 | F53: 2.0298663 | G53: ='PG facts'!D62 -> 1 | H53: =F53^2 -> 4.1203573 | I53: =F53*G53 -> 2.0298663
B54: 4 | C54: bridge | D54: 44651 | E54: 44671 | F54: 3.7505058 | G54: ='PG facts'!D6 -> -1 | H54: =F54^2 -> 14.066294 | I54: =F54*G54 -> -3.7505058
B55: 4 | C55: bridge | D55: 44742 | E55: 44771 | F55: 0.22450064 | G55: ='PG facts'!D13 -> -2 | H55: =F55^2 -> 0.050400536 | I55: =F55*G55 -> -0.44900127
B56: 4 | C56: bridge | D56: 44834 | E56: 44853 | F56: -0.45976552 | G56: ='PG facts'!D20 -> -1 | H56: =F56^2 -> 0.21138433 | I56: =F56*G56 -> 0.45976552
B57: 4 | C57: bridge | D57: 44926 | E57: 44945 | F57: -0.97130769 | G57: ='PG facts'!D27 -> -4 | H57: =F57^2 -> 0.94343863 | I57: =F57*G57 -> 3.8852308
B58: 4 | C58: bridge | D58: 45016 | E58: 45037 | F58: -0.16799664 | G58: ='PG facts'!D34 -> 0 | H58: =F58^2 -> 0.028222871 | I58: =F58*G58 -> 0
B59: 4 | C59: bridge | D59: 45107 | E59: 45135 | F59: 0.06199938 | G59: ='PG facts'!D41 -> -1 | H59: =F59^2 -> 0.0038439231 | I59: =F59*G59 -> -0.06199938
B60: 4 | C60: bridge | D60: 45199 | E60: 45217 | F60: 1.4338645 | G60: ='PG facts'!D48 -> 0 | H60: =F60^2 -> 2.0559674 | I60: =F60*G60 -> 0
B61: 4 | C61: bridge | D61: 45291 | E61: 45314 | F61: 2.0298663 | G61: ='PG facts'!D55 -> -1 | H61: =F61^2 -> 4.1203573 | I61: =F61*G61 -> -2.0298663
B62: 4 | C62: bridge | D62: 45382 | E62: 45401 | F62: 1.7438949 | G62: ='PG facts'!D62 -> 1 | H62: =F62^2 -> 3.0411693 | I62: =F62*G62 -> 1.7438949
B63: 4 | C63: lagged | D63: 44742 | E63: 44771 | F63: 3.7505058 | G63: ='PG facts'!D13 -> -2 | H63: =F63^2 -> 14.066294 | I63: =F63*G63 -> -7.5010115
B64: 4 | C64: lagged | D64: 44834 | E64: 44853 | F64: 0.22450064 | G64: ='PG facts'!D20 -> -1 | H64: =F64^2 -> 0.050400536 | I64: =F64*G64 -> -0.22450064
B65: 4 | C65: lagged | D65: 44926 | E65: 44945 | F65: -0.45976552 | G65: ='PG facts'!D27 -> -4 | H65: =F65^2 -> 0.21138433 | I65: =F65*G65 -> 1.8390621
B66: 4 | C66: lagged | D66: 45016 | E66: 45037 | F66: -0.97130769 | G66: ='PG facts'!D34 -> 0 | H66: =F66^2 -> 0.94343863 | I66: =F66*G66 -> 0
B67: 4 | C67: lagged | D67: 45107 | E67: 45135 | F67: -0.16799664 | G67: ='PG facts'!D41 -> -1 | H67: =F67^2 -> 0.028222871 | I67: =F67*G67 -> 0.16799664
B68: 4 | C68: lagged | D68: 45199 | E68: 45217 | F68: 0.06199938 | G68: ='PG facts'!D48 -> 0 | H68: =F68^2 -> 0.0038439231 | I68: =F68*G68 -> 0
B69: 4 | C69: lagged | D69: 45291 | E69: 45314 | F69: 1.4338645 | G69: ='PG facts'!D55 -> -1 | H69: =F69^2 -> 2.0559674 | I69: =F69*G69 -> -1.4338645
